Workbook

Sheet 2026-1
B2: ='Monthly Report 2026 €'!D107 -> 46053
B4: CCY | C4: Rate | D4: Ester/SOFR | E4: BCE/Fed | F4: Amont EoM | G4: Interest Due | H4: Interest Paid | I4: Profit/NCA
F5: in Thousand | G5: in Thousand | H5: in Thousand | I5: in Thousand
B7: K€ | C7: =INDEX('Monthly Report 2026 €'!$I$107:$I$118,MATCH('2026-1'!$B$2,'Monthly Report 2026 €'!$D$107:$D$118,0)) -> 0.022007028 | D7: 0.0193 | E7: 0.02 | F7: =INDEX('Monthly Report 2026 €'!J$107:J$118,MATCH('2026-1'!$B$2,'Monthly Report 2026 €'!$D$107:$D$118,0)) -> 1.8793802e+08 | G7: =INDEX('Monthly Report 2026 €'!K$107:K$118,MATCH('2026-1'!$B$2,'Monthly Report 2026 €'!$D$107:$D$118,0)) -> 383920.66 | H7: =INDEX('Monthly Report 2026 €'!L$107:L$118,MATCH('2026-1'!$B$2,'Monthly Report 2026 €'!$D$107:$D$118,0)) -> 150003.47 | I7: =INDEX('Monthly Report 2026 €'!M$107:M$118,MATCH('2026-1'!$B$2,'Monthly Report 2026 €'!$D$107:$D$118,0)) -> 93246.038
B8: K$ | C8: =INDEX('Monthly Report 2026 $'!I$93:I$104,MATCH($B$2,'Monthly Report 2026 $'!$D$93:$D$104,0)) -> 0.036755514 | D8: 0.0367 | E8: 0.035 | F8: =INDEX('Monthly Report 2026 $'!J$93:J$104,MATCH($B$2,'Monthly Report 2026 $'!$D$93:$D$104,0)) -> 3.694326e+08 | G8: =INDEX('Monthly Report 2026 $'!K$93:K$104,MATCH($B$2,'Monthly Report 2026 $'!$D$93:$D$104,0)) -> 1183348.9 | H8: =INDEX('Monthly Report 2026 $'!L$93:L$104,MATCH($B$2,'Monthly Report 2026 $'!$D$93:$D$104,0)) -> 1095294.4 | I8: =INDEX('Monthly Report 2026 $'!M$93:M$104,MATCH($B$2,'Monthly Report 2026 $'!$D$93:$D$104,0)) -> 185126.47
B10: ="Total in K€eq at FX "&M10 -> Total in K€eq at FX 1,1919 | G10: =(G7+G8/$M$10)*10^-3 -> 1376.7463 | H10: =(H7+H8/$M$10)*10^-3 -> 1068.9517 | I10: =(I7+I8/$M$10)*10^-3 -> 248.56651 | M10: 1.1919
B12: ="Total in K€eq at FX "&M12 -> Total in K€eq at FX 1,1886 | G12: =(G7+G8/$M$12)*10^-3 -> 1379.5027 | H12: =(H7+H8/$M$12)*10^-3 -> 1071.5031 | I12: =(I7+I8/$M$12)*10^-3 -> 248.99774 | M12: 1.1886
B13: FX Gain/Loss- in thousand | G13: =G12-G10 -> 2.7564568 | H13: =H12-H10 -> 2.5513454 | I13: =I12-I10 -> 0.43122796
B15: YTD 2026
B17: CCY | C17: Rate | D17: Ester/SOFR | E17: BCE/Fed | F17: Amont EoM | G17: Interest Due | H17: Interest Paid | I17: Profit/NCA
F18: in Thousand | G18: in Thousand | H18: in Thousand | I18: in Thousand
B20: EUR | C20: ='Monthly Report 2026 €'!I119 -> 0.022007028 | D20: 0.0193 | E20: 0.02 | F20: ='Monthly Report 2026 €'!J119 -> 1.8793802e+08 | G20: ='Monthly Report 2026 €'!K119 -> 383920.66 | H20: ='Monthly Report 2026 €'!L119 -> 150003.47 | I20: ='Monthly Report 2026 €'!M119 -> 93246.038
B21: USD | C21: ='Monthly Report 2026 $'!I105 -> 0.036755514 | D21: 0.0367 | E21: 0.035 | F21: ='Monthly Report 2026 $'!J105 -> 3.694326e+08 | G21: ='Monthly Report 2026 $'!K105 -> 1183348.9 | H21: ='Monthly Report 2026 $'!L105 -> 1095294.4 | I21: ='Monthly Report 2026 $'!M105 -> 185126.47
B23: ="Total in K€eq at FX "&M23 -> Total in K€eq at FX 1,1919 | G23: =(G20+G21/M23)*10^-3 -> 1376.7463 | H23: =(H20+H21/$M$23)*10^-3 -> 1068.9517 | I23: =(I20+I21/$M$23)*10^-3 -> 248.56651 | M23: 1.1919
B25: ="Total in K€eq at FX "&M25 -> Total in K€eq at FX 1,1886 | G25: =(G20+G21/$M$25)*10^-3 -> 1379.5027 | H25: =(H20+H21/$M$25)*10^-3 -> 1071.5031 | I25: =(I20+I21/$M$25)*10^-3 -> 248.99774 | M25: =M12 -> 1.1886
B26: FX Gain/Loss- in thousand | G26: =G25-G23 -> 2.7564568 | H26: =H25-H23 -> 2.5513454 | I26: =I25-I23 -> 0.43122796

Sheet 2026-2
D3: Month | E3: Rate * | F3: Amount EoM | G3: Interest due | H3: Interest paid | I3: Profit/NCA
F4: in k€ | G4: in k€ | H4: in k€ | I4: in k€
D5: ='Monthly Report 2026 €'!D107 -> 46053 | E5: ='Monthly Report 2026 €'!I107 -> 0.022007028 | F5: ='Monthly Report 2026 €'!J107 -> 1.8793802e+08 | G5: ='Monthly Report 2026 €'!K107 -> 383920.66 | H5: ='Monthly Report 2026 €'!L107 -> 150003.47 | I5: ='Monthly Report 2026 €'!M107 -> 93246.038
A6: =CONCATENATE(MONTH(D6)," ",YEAR(D6)) -> 2 2026 | B6: =EOMONTH(D6,0) -> 46081 | D6: ='Monthly Report 2026 €'!D108 -> 46081 | E6: ='Monthly Report 2026 €'!I108 -> 0.022605121 | F6: ='Monthly Report 2026 €'!J108 -> 37210956 | G6: ='Monthly Report 2026 €'!K108 -> 67926.154 | H6: ='Monthly Report 2026 €'!L108 -> 0 | I6: ='Monthly Report 2026 €'!M108 -> 15322.769
A7: =CONCATENATE(MONTH(D7)," ",YEAR(D7)) -> 3 2026 | B7: =EOMONTH(D7,0) -> 46112 | D7: ='Monthly Report 2026 €'!D109 -> 46112 | E7: ='Monthly Report 2026 €'!I109 -> 0.02073427 | F7: ='Monthly Report 2026 €'!J109 -> 67260956 | G7: ='Monthly Report 2026 €'!K109 -> 112477.53 | H7: ='Monthly Report 2026 €'!L109 -> 0 | I7: ='Monthly Report 2026 €'!M109 -> 16964.495
A8: =CONCATENATE(MONTH(D8)," ",YEAR(D8)) -> 4 2026 | B8: =EOMONTH(D8,0) -> 46142 | D8: ='Monthly Report 2026 €'!D110 -> 46142 | E8: ='Monthly Report 2026 €'!I110 -> 0.020428995 | F8: ='Monthly Report 2026 €'!J110 -> 67260956 | G8: ='Monthly Report 2026 €'!K110 -> 114506.15 | H8: ='Monthly Report 2026 €'!L110 -> 0 | I8: ='Monthly Report 2026 €'!M110 -> 16417.253
A9: =CONCATENATE(MONTH(D9)," ",YEAR(D9)) -> 5 2026 | B9: =EOMONTH(D9,0) -> 46173 | D9: ='Monthly Report 2026 €'!D111 -> 46173 | E9: ='Monthly Report 2026 €'!I111 -> 0.020428995 | F9: ='Monthly Report 2026 €'!J111 -> 67260956 | G9: ='Monthly Report 2026 €'!K111 -> 118323.02 | H9: ='Monthly Report 2026 €'!L111 -> 0 | I9: ='Monthly Report 2026 €'!M111 -> 16964.495
A10: =CONCATENATE(MONTH(D10)," ",YEAR(D10)) -> 6 2026 | B10: =EOMONTH(D10,0) -> 46203 | D10: ='Monthly Report 2026 €'!D112 -> 46203 | E10: ='Monthly Report 2026 €'!I112 -> 0.020428995 | F10: ='Monthly Report 2026 €'!J112 -> 67260956 | G10: ='Monthly Report 2026 €'!K112 -> 114506.15 | H10: ='Monthly Report 2026 €'!L112 -> 0 | I10: ='Monthly Report 2026 €'!M112 -> 16417.253
A11: =CONCATENATE(MONTH(D11)," ",YEAR(D11)) -> 7 2026 | B11: =EOMONTH(D11,0) -> 46234 | D11: ='Monthly Report 2026 €'!D113 -> 46234 | E11: ='Monthly Report 2026 €'!I113 -> 0.020428995 | F11: ='Monthly Report 2026 €'!J113 -> 67260956 | G11: ='Monthly Report 2026 €'!K113 -> 118323.02 | H11: ='Monthly Report 2026 €'!L113 -> 0 | I11: ='Monthly Report 2026 €'!M113 -> 16964.495
A12: =CONCATENATE(MONTH(D12)," ",YEAR(D12)) -> 8 2026 | B12: =EOMONTH(D12,0) -> 46265 | D12: ='Monthly Report 2026 €'!D114 -> 46265 | E12: ='Monthly Report 2026 €'!I114 -> 0.020428995 | F12: ='Monthly Report 2026 €'!J114 -> 67260956 | G12: ='Monthly Report 2026 €'!K114 -> 118323.02 | H12: ='Monthly Report 2026 €'!L114 -> 0 | I12: ='Monthly Report 2026 €'!M114 -> 16964.495
A13: =CONCATENATE(MONTH(D13)," ",YEAR(D13)) -> 9 2026 | B13: =EOMONTH(D13,0) -> 46295 | D13: ='Monthly Report 2026 €'!D115 -> 46295 | E13: ='Monthly Report 2026 €'!I115 -> 0.020428995 | F13: ='Monthly Report 2026 €'!J115 -> 67260956 | G13: ='Monthly Report 2026 €'!K115 -> 114506.15 | H13: ='Monthly Report 2026 €'!L115 -> 0 | I13: ='Monthly Report 2026 €'!M115 -> 16417.253
A14: =CONCATENATE(MONTH(D14)," ",YEAR(D14)) -> 10 2026 | B14: =EOMONTH(D14,0) -> 46326 | D14: ='Monthly Report 2026 €'!D116 -> 46326 | E14: ='Monthly Report 2026 €'!I116 -> 0.020428995 | F14: ='Monthly Report 2026 €'!J116 -> 67260956 | G14: ='Monthly Report 2026 €'!K116 -> 118323.02 | H14: ='Monthly Report 2026 €'!L116 -> 0 | I14: ='Monthly Report 2026 €'!M116 -> 16964.495
A15: =CONCATENATE(MONTH(D15)," ",YEAR(D15)) -> 11 2026 | B15: =EOMONTH(D15,0) -> 46356 | D15: ='Monthly Report 2026 €'!D117 -> 46356 | E15: ='Monthly Report 2026 €'!I117 -> 0.019198018 | F15: ='Monthly Report 2026 €'!J117 -> 52260956 | G15: ='Monthly Report 2026 €'!K117 -> 88716.147 | H15: ='Monthly Report 2026 €'!L117 -> 0 | I15: ='Monthly Report 2026 €'!M117 -> 8127.253
A16: =CONCATENATE(MONTH(D16)," ",YEAR(D16)) -> 12 2026 | B16: =EOMONTH(D16,0) -> 46387 | D16: ='Monthly Report 2026 €'!D118 -> 46387 | E16: ='Monthly Report 2026 €'!I118 -> 0.018890274 | F16: ='Monthly Report 2026 €'!J118 -> 52260956 | G16: ='Monthly Report 2026 €'!K118 -> 85010.936 | H16: ='Monthly Report 2026 €'!L118 -> 0 | I16: ='Monthly Report 2026 €'!M118 -> 6256.5781
D17: ='Monthly Report 2026 €'!D119 -> Total 2026 | E17: ='Monthly Report 2026 €'!I119 -> 0.022007028 | F17: ='Monthly Report 2026 €'!J119 -> 1.8793802e+08 | G17: ='Monthly Report 2026 €'!K119 -> 383920.66 | H17: ='Monthly Report 2026 €'!L119 -> 150003.47 | I17: ='Monthly Report 2026 €'!M119 -> 93246.038
D20: Month | E20: Rate * | F20: Amount EoM | G20: Interest due | H20: Interest paid | I20: Profit/NCA
F21: in k$ | G21: in k$ | H21: in k$ | I21: in k$
D22: ='Monthly Report 2026 $'!D93 -> 46053 | E22: ='Monthly Report 2026 $'!I93 -> 0.036755514 | F22: ='Monthly Report 2026 $'!J93 -> 3.694326e+08 | G22: ='Monthly Report 2026 $'!K93 -> 1183348.9 | H22: ='Monthly Report 2026 $'!L93 -> 1095294.4 | I22: ='Monthly Report 2026 $'!M93 -> 185126.47
D23: ='Monthly Report 2026 $'!D94 -> 46081 | E23: ='Monthly Report 2026 $'!I94 -> 0.033400702 | F23: ='Monthly Report 2026 $'!J94 -> 22280000 | G23: ='Monthly Report 2026 $'!K94 -> 65861.444 | H23: ='Monthly Report 2026 $'!L94 -> 50983.33 | I23: ='Monthly Report 2026 $'!M94 -> 10834.444
D24: ='Monthly Report 2026 $'!D95 -> 46112 | E24: ='Monthly Report 2026 $'!I95 -> 0.037444946 | F24: ='Monthly Report 2026 $'!J95 -> 1450000 | G24: ='Monthly Report 2026 $'!K95 -> 3858.75 | H24: ='Monthly Report 2026 $'!L95 -> 0 | I24: ='Monthly Report 2026 $'!M95 -> 0
D25: ='Monthly Report 2026 $'!D96 -> 46142 | E25: ='Monthly Report 2026 $'!I96 -> 0.037437639 | F25: ='Monthly Report 2026 $'!J96 -> 1450000 | G25: ='Monthly Report 2026 $'!K96 -> 3806.25 | H25: ='Monthly Report 2026 $'!L96 -> 0 | I25: ='Monthly Report 2026 $'!M96 -> 0
D26: ='Monthly Report 2026 $'!D97 -> 46173 | E26: ='Monthly Report 2026 $'!I97 -> 0.036732483 | F26: ='Monthly Report 2026 $'!J97 -> 1450000 | G26: ='Monthly Report 2026 $'!K97 -> 3933.125 | H26: ='Monthly Report 2026 $'!L97 -> 0 | I26: ='Monthly Report 2026 $'!M97 -> 0
D27: ='Monthly Report 2026 $'!D98 -> 46203 | E27: ='Monthly Report 2026 $'!I98 -> 0.036932665 | F27: ='Monthly Report 2026 $'!J98 -> 1450000 | G27: ='Monthly Report 2026 $'!K98 -> 3806.25 | H27: ='Monthly Report 2026 $'!L98 -> 0 | I27: ='Monthly Report 2026 $'!M98 -> 0
D28: ='Monthly Report 2026 $'!D99 -> 46234 | E28: ='Monthly Report 2026 $'!I99 -> 0.036932665 | F28: ='Monthly Report 2026 $'!J99 -> 1450000 | G28: ='Monthly Report 2026 $'!K99 -> 3933.125 | H28: ='Monthly Report 2026 $'!L99 -> 0 | I28: ='Monthly Report 2026 $'!M99 -> 0
D29: ='Monthly Report 2026 $'!D100 -> 46265 | E29: ='Monthly Report 2026 $'!I100 -> 0.035600742 | F29: ='Monthly Report 2026 $'!J100 -> 1450000 | G29: ='Monthly Report 2026 $'!K100 -> 3933.125 | H29: ='Monthly Report 2026 $'!L100 -> 0 | I29: ='Monthly Report 2026 $'!M100 -> 0
D30: ='Monthly Report 2026 $'!D101 -> 46295 | E30: ='Monthly Report 2026 $'!I101 -> 0.036171141 | F30: ='Monthly Report 2026 $'!J101 -> 1450000 | G30: ='Monthly Report 2026 $'!K101 -> 3806.25 | H30: ='Monthly Report 2026 $'!L101 -> 0 | I30: ='Monthly Report 2026 $'!M101 -> 0
D31: ='Monthly Report 2026 $'!D102 -> 46326 | E31: ='Monthly Report 2026 $'!I102 -> 0.036171141 | F31: ='Monthly Report 2026 $'!J102 -> 1450000 | G31: ='Monthly Report 2026 $'!K102 -> 3933.125 | H31: ='Monthly Report 2026 $'!L102 -> 0 | I31: ='Monthly Report 2026 $'!M102 -> 0
D32: ='Monthly Report 2026 $'!D103 -> 46356 | E32: ='Monthly Report 2026 $'!I103 -> 0.031277181 | F32: ='Monthly Report 2026 $'!J103 -> 1450000 | G32: ='Monthly Report 2026 $'!K103 -> 3806.25 | H32: ='Monthly Report 2026 $'!L103 -> 0 | I32: ='Monthly Report 2026 $'!M103 -> 0
D33: ='Monthly Report 2026 $'!D104 -> 46387 | E33: ='Monthly Report 2026 $'!I104 -> 0.0315 | F33: ='Monthly Report 2026 $'!J104 -> 1450000 | G33: ='Monthly Report 2026 $'!K104 -> 3933.125 | H33: ='Monthly Report 2026 $'!L104 -> 0 | I33: ='Monthly Report 2026 $'!M104 -> 0
D34: Total 2026 | E34: ='Monthly Report 2026 $'!F105 -> 0 | F34: ='Monthly Report 2026 $'!J105 -> 3.694326e+08 | G34: ='Monthly Report 2026 $'!K105 -> 1183348.9 | H34: ='Monthly Report 2026 $'!L105 -> 1095294.4 | I34: ='Monthly Report 2026 $'!M105 -> 185126.47

Sheet Monthly Report 2026 €
L1: 46053
D6: ="€ Cash investments report as of "&TEXT(L1,"jj mm aaaa") -> € Cash investments report as of 31 01 2026
B7: Formule | D7: Month | E7: Bank | F7: Investment | G7: Opening Date | H7: Closing Date | I7: Rate * | J7: Amount EoM | K7: Interest due | L7: Interest paid | M7: Profit/NCA
D9: Deposit
A11: =CONCATENATE(MONTH(D11)," ",YEAR(D11)) -> 1 2026 | B11: 46053 | D11: 46053 | E11: SG | F11: NCA | G11: 45205 | I11: =INDEX('OverNight €'!$I$376:$I$737,MATCH(B11,'OverNight €'!$D$376:$D$737,0)) -> 0.0175 | J11: =INDEX('OverNight €'!$H$376:$H$737,MATCH(B11,'OverNight €'!$C$376:$C$737,0)) -> 7130000 | K11: =SUMIFS('OverNight €'!$J$373:$J$750,'OverNight €'!$B$373:$B$750,A11) -> 5285.9722 | L11: 4939.39 | M11: 0 | O11: OK
A12: =CONCATENATE(MONTH(D12)," ",YEAR(D12)) -> 2 2026 | B12: =EOMONTH(B11,1) -> 46081 | D12: =EOMONTH(D11,1) -> 46081 | E12: SG | F12: NCA | I12: =INDEX('OverNight €'!$I$376:$I$737,MATCH(B12,'OverNight €'!$D$376:$D$737,0)) -> 0.0175 | J12: =INDEX('OverNight €'!$H$376:$H$737,MATCH(B12,'OverNight €'!$C$376:$C$737,0)) -> 4200000 | K12: =SUMIFS('OverNight €'!$J$373:$J$750,'OverNight €'!$B$373:$B$750,A12) -> 7671.8056 | M12: 0
A13: =CONCATENATE(MONTH(D13)," ",YEAR(D13)) -> 3 2026 | B13: =EOMONTH(B12,1) -> 46112 | D13: =EOMONTH(D12,1) -> 46112 | E13: SG | F13: NCA | I13: =INDEX('OverNight €'!$I$376:$I$737,MATCH(B13,'OverNight €'!$D$376:$D$737,0)) -> 0.0175 | J13: =INDEX('OverNight €'!$H$376:$H$737,MATCH(B13,'OverNight €'!$C$376:$C$737,0)) -> 34250000 | K13: =SUMIFS('OverNight €'!$J$373:$J$750,'OverNight €'!$B$373:$B$750,A13) -> 45767.361 | M13: 0
A14: =CONCATENATE(MONTH(D14)," ",YEAR(D14)) -> 4 2026 | B14: =EOMONTH(B13,1) -> 46142 | D14: =EOMONTH(D13,1) -> 46142 | E14: SG | F14: NCA | I14: =INDEX('OverNight €'!$I$376:$I$737,MATCH(B14,'OverNight €'!$D$376:$D$737,0)) -> 0.0175 | J14: =INDEX('OverNight €'!$H$376:$H$737,MATCH(B14,'OverNight €'!$C$376:$C$737,0)) -> 34250000 | K14: =SUMIFS('OverNight €'!$J$373:$J$750,'OverNight €'!$B$373:$B$750,A14) -> 49947.917 | M14: 0
A15: =CONCATENATE(MONTH(D15)," ",YEAR(D15)) -> 5 2026 | B15: =EOMONTH(B14,1) -> 46173 | D15: =EOMONTH(D14,1) -> 46173 | E15: SG | F15: NCA | I15: =INDEX('OverNight €'!$I$376:$I$737,MATCH(B15,'OverNight €'!$D$376:$D$737,0)) -> 0.0175 | J15: =INDEX('OverNight €'!$H$376:$H$737,MATCH(B15,'OverNight €'!$C$376:$C$737,0)) -> 34250000 | K15: =SUMIFS('OverNight €'!$J$373:$J$750,'OverNight €'!$B$373:$B$750,A15) -> 51612.847 | M15: 0
A16: =CONCATENATE(MONTH(D16)," ",YEAR(D16)) -> 6 2026 | B16: =EOMONTH(B15,1) -> 46203 | D16: =EOMONTH(D15,1) -> 46203 | E16: SG | F16: NCA | I16: =INDEX('OverNight €'!$I$376:$I$737,MATCH(B16,'OverNight €'!$D$376:$D$737,0)) -> 0.0175 | J16: =INDEX('OverNight €'!$H$376:$H$737,MATCH(B16,'OverNight €'!$C$376:$C$737,0)) -> 34250000 | K16: =SUMIFS('OverNight €'!$J$373:$J$750,'OverNight €'!$B$373:$B$750,A16) -> 49947.917 | M16: 0
A17: =CONCATENATE(MONTH(D17)," ",YEAR(D17)) -> 7 2026 | B17: =EOMONTH(B16,1) -> 46234 | D17: =EOMONTH(D16,1) -> 46234 | E17: SG | F17: NCA | I17: =INDEX('OverNight €'!$I$376:$I$737,MATCH(B17,'OverNight €'!$D$376:$D$737,0)) -> 0.0175 | J17: =INDEX('OverNight €'!$H$376:$H$737,MATCH(B17,'OverNight €'!$C$376:$C$737,0)) -> 34250000 | K17: =SUMIFS('OverNight €'!$J$373:$J$750,'OverNight €'!$B$373:$B$750,A17) -> 51612.847 | M17: 0
A18: =CONCATENATE(MONTH(D18)," ",YEAR(D18)) -> 8 2026 | B18: =EOMONTH(B17,1) -> 46265 | D18: =EOMONTH(D17,1) -> 46265 | E18: SG | F18: NCA | I18: =INDEX('OverNight €'!$I$376:$I$737,MATCH(B18,'OverNight €'!$D$376:$D$737,0)) -> 0.0175 | J18: =INDEX('OverNight €'!$H$376:$H$737,MATCH(B18,'OverNight €'!$C$376:$C$737,0)) -> 34250000 | K18: =SUMIFS('OverNight €'!$J$373:$J$750,'OverNight €'!$B$373:$B$750,A18) -> 51612.847 | M18: 0
A19: =CONCATENATE(MONTH(D19)," ",YEAR(D19)) -> 9 2026 | B19: =EOMONTH(B18,1) -> 46295 | D19: =EOMONTH(D18,1) -> 46295 | E19: SG | F19: NCA | I19: =INDEX('OverNight €'!$I$376:$I$737,MATCH(B19,'OverNight €'!$D$376:$D$737,0)) -> 0.0175 | J19: =INDEX('OverNight €'!$H$376:$H$737,MATCH(B19,'OverNight €'!$C$376:$C$737,0)) -> 34250000 | K19: =SUMIFS('OverNight €'!$J$373:$J$750,'OverNight €'!$B$373:$B$750,A19) -> 49947.917 | M19: 0
A20: =CONCATENATE(MONTH(D20)," ",YEAR(D20)) -> 10 2026 | B20: =EOMONTH(B19,1) -> 46326 | D20: =EOMONTH(D19,1) -> 46326 | E20: SG | F20: NCA | I20: =INDEX('OverNight €'!$I$376:$I$737,MATCH(B20,'OverNight €'!$D$376:$D$737,0)) -> 0.0175 | J20: =INDEX('OverNight €'!$H$376:$H$737,MATCH(B20,'OverNight €'!$C$376:$C$737,0)) -> 34250000 | K20: =SUMIFS('OverNight €'!$J$373:$J$750,'OverNight €'!$B$373:$B$750,A20) -> 51612.847 | M20: 0
A21: =CONCATENATE(MONTH(D21)," ",YEAR(D21)) -> 11 2026 | B21: =EOMONTH(B20,1) -> 46356 | D21: =EOMONTH(D20,1) -> 46356 | E21: SG | F21: NCA | I21: =INDEX('OverNight €'!$I$376:$I$737,MATCH(B21,'OverNight €'!$D$376:$D$737,0)) -> 0.0175 | J21: =INDEX('OverNight €'!$H$376:$H$737,MATCH(B21,'OverNight €'!$C$376:$C$737,0)) -> 34250000 | K21: =SUMIFS('OverNight €'!$J$373:$J$750,'OverNight €'!$B$373:$B$750,A21) -> 49947.917 | M21: 0
A22: =CONCATENATE(MONTH(D22)," ",YEAR(D22)) -> 12 2026 | B22: =EOMONTH(B21,1) -> 46387 | D22: =EOMONTH(D21,1) -> 46387 | E22: SG | F22: NCA | I22: =INDEX('OverNight €'!$I$376:$I$737,MATCH(B22,'OverNight €'!$D$376:$D$737,0)) -> 0.0175 | J22: =INDEX('OverNight €'!$H$376:$H$750,MATCH(B22,'OverNight €'!$C$376:$C$750,0)) -> 34250000 | K22: =SUMIFS('OverNight €'!$J$373:$J$750,'OverNight €'!$B$373:$B$750,A22) -> 51612.847 | M22: 0
D23: Total 2026 NCA | I23: =AVERAGE(I11) -> 0.0175 | K23: =SUM(K11:K11) -> 5285.9722 | L23: =SUM(L11:L11) -> 4939.39 | M23: =SUM(M11:M11) -> 0 | O23: change all sums manually each month
A25: =CONCATENATE(MONTH(D25)," ",YEAR(D25)) -> 1 2026 | B25: 46053 | D25: 46053 | E25: SG | F25: CAT Tréso Plus | G25: 46027 | H25: =EDATE(G25,1) -> 46058 | I25: =INDEX('OverNight €'!$O$376:$O$750,MATCH($B25,'OverNight €'!$D$376:$D$750,0)) -> 0.02169863 | J25: =INDEX('OverNight €'!$N$376:$N$750,MATCH(B25,'OverNight €'!$C$376:$C$750,0)) -> 12000000 | K25: =SUMIFS('OverNight €'!$P$373:$P$750,'OverNight €'!$B$373:$B$750,A25) -> 22421.918 | L25: 22421.92 | M25: =SUMIFS('OverNight €'!$R$373:$R$750,'OverNight €'!$B$373:$B$750,A25) -> 4338.5845 | O25: OK
A26: =CONCATENATE(MONTH(D26)," ",YEAR(D26)) -> 2 2026 | B26: =EOMONTH(B25,1) -> 46081 | D26: =EOMONTH(D25,1) -> 46081 | E26: SG | F26: CAT Tréso Plus | G26: =H25 -> 46058 | H26: =EDATE(G26,1) -> 46086 | I26: =INDEX('OverNight €'!$O$376:$O$750,MATCH($B26,'OverNight €'!$D$376:$D$750,0)) -> 0.02169863 | J26: =INDEX('OverNight €'!$N$376:$N$750,MATCH(B26,'OverNight €'!$C$376:$C$750,0)) -> 12000000 | K26: =SUMIFS('OverNight €'!$P$373:$P$750,'OverNight €'!$B$373:$B$750,A26) -> 20252.055 | M26: =SUMIFS('OverNight €'!$R$373:$R$750,'OverNight €'!$B$373:$B$750,A26) -> 3918.7215
A27: =CONCATENATE(MONTH(D27)," ",YEAR(D27)) -> 3 2026 | B27: =EOMONTH(B26,1) -> 46112 | D27: =EOMONTH(D26,1) -> 46112 | E27: SG | F27: CAT Tréso Plus | G27: =H26 -> 46086 | H27: =EDATE(G27,1) -> 46117 | I27: =INDEX('OverNight €'!$O$376:$O$750,MATCH($B27,'OverNight €'!$D$376:$D$750,0)) -> 0.02169863 | J27: =INDEX('OverNight €'!$N$376:$N$750,MATCH(B27,'OverNight €'!$C$376:$C$750,0)) -> 12000000 | K27: =SUMIFS('OverNight €'!$P$373:$P$750,'OverNight €'!$B$373:$B$750,A27) -> 22421.918 | M27: =SUMIFS('OverNight €'!$R$373:$R$750,'OverNight €'!$B$373:$B$750,A27) -> 4338.5845
A28: =CONCATENATE(MONTH(D28)," ",YEAR(D28)) -> 4 2026 | B28: =EOMONTH(B27,1) -> 46142 | D28: =EOMONTH(D27,1) -> 46142 | E28: SG | F28: CAT Tréso Plus | G28: =H27 -> 46117 | H28: =EDATE(G28,1) -> 46147 | I28: =INDEX('OverNight €'!$O$376:$O$750,MATCH($B28,'OverNight €'!$D$376:$D$750,0)) -> 0.02169863 | J28: =INDEX('OverNight €'!$N$376:$N$750,MATCH(B28,'OverNight €'!$C$376:$C$750,0)) -> 12000000 | K28: =SUMIFS('OverNight €'!$P$373:$P$750,'OverNight €'!$B$373:$B$750,A28) -> 21698.63 | M28: =SUMIFS('OverNight €'!$R$373:$R$750,'OverNight €'!$B$373:$B$750,A28) -> 4198.6301
A29: =CONCATENATE(MONTH(D29)," ",YEAR(D29)) -> 5 2026 | B29: =EOMONTH(B28,1) -> 46173 | D29: =EOMONTH(D28,1) -> 46173 | E29: SG | F29: CAT Tréso Plus | G29: =H28 -> 46147 | H29: =EDATE(G29,1) -> 46178 | I29: =INDEX('OverNight €'!$O$376:$O$750,MATCH($B29,'OverNight €'!$D$376:$D$750,0)) -> 0.02169863 | J29: =INDEX('OverNight €'!$N$376:$N$750,MATCH(B29,'OverNight €'!$C$376:$C$750,0)) -> 12000000 | K29: =SUMIFS('OverNight €'!$P$373:$P$750,'OverNight €'!$B$373:$B$750,A29) -> 22421.918 | M29: =SUMIFS('OverNight €'!$R$373:$R$750,'OverNight €'!$B$373:$B$750,A29) -> 4338.5845
A30: =CONCATENATE(MONTH(D30)," ",YEAR(D30)) -> 6 2026 | B30: =EOMONTH(B29,1) -> 46203 | D30: =EOMONTH(D29,1) -> 46203 | E30: SG | F30: CAT Tréso Plus | G30: =H29 -> 46178 | H30: =EDATE(G30,1) -> 46208 | I30: =INDEX('OverNight €'!$O$376:$O$750,MATCH($B30,'OverNight €'!$D$376:$D$750,0)) -> 0.02169863 | J30: =INDEX('OverNight €'!$N$376:$N$750,MATCH(B30,'OverNight €'!$C$376:$C$750,0)) -> 12000000 | K30: =SUMIFS('OverNight €'!$P$373:$P$750,'OverNight €'!$B$373:$B$750,A30) -> 21698.63 | M30: =SUMIFS('OverNight €'!$R$373:$R$750,'OverNight €'!$B$373:$B$750,A30) -> 4198.6301
A31: =CONCATENATE(MONTH(D31)," ",YEAR(D31)) -> 7 2026 | B31: =EOMONTH(B30,1) -> 46234 | D31: =EOMONTH(D30,1) -> 46234 | E31: SG | F31: CAT Tréso Plus | G31: =H30 -> 46208 | H31: =EDATE(G31,1) -> 46239 | I31: =INDEX('OverNight €'!$O$376:$O$750,MATCH($B31,'OverNight €'!$D$376:$D$750,0)) -> 0.02169863 | J31: =INDEX('OverNight €'!$N$376:$N$750,MATCH(B31,'OverNight €'!$C$376:$C$750,0)) -> 12000000 | K31: =SUMIFS('OverNight €'!$P$373:$P$750,'OverNight €'!$B$373:$B$750,A31) -> 22421.918 | M31: =SUMIFS('OverNight €'!$R$373:$R$750,'OverNight €'!$B$373:$B$750,A31) -> 4338.5845
A32: =CONCATENATE(MONTH(D32)," ",YEAR(D32)) -> 8 2026 | B32: =EOMONTH(B31,1) -> 46265 | D32: =EOMONTH(D31,1) -> 46265 | E32: SG | F32: CAT Tréso Plus | G32: =H31 -> 46239 | H32: =EDATE(G32,1) -> 46270 | I32: =INDEX('OverNight €'!$O$376:$O$750,MATCH($B32,'OverNight €'!$D$376:$D$750,0)) -> 0.02169863 | J32: =INDEX('OverNight €'!$N$376:$N$750,MATCH(B32,'OverNight €'!$C$376:$C$750,0)) -> 12000000 | K32: =SUMIFS('OverNight €'!$P$373:$P$750,'OverNight €'!$B$373:$B$750,A32) -> 22421.918 | M32: =SUMIFS('OverNight €'!$R$373:$R$750,'OverNight €'!$B$373:$B$750,A32) -> 4338.5845
A33: =CONCATENATE(MONTH(D33)," ",YEAR(D33)) -> 9 2026 | B33: =EOMONTH(B32,1) -> 46295 | D33: =EOMONTH(D32,1) -> 46295 | E33: SG | F33: CAT Tréso Plus | G33: =H32 -> 46270 | H33: =EDATE(G33,1) -> 46300 | I33: =INDEX('OverNight €'!$O$376:$O$750,MATCH($B33,'OverNight €'!$D$376:$D$750,0)) -> 0.02169863 | J33: =INDEX('OverNight €'!$N$376:$N$750,MATCH(B33,'OverNight €'!$C$376:$C$750,0)) -> 12000000 | K33: =SUMIFS('OverNight €'!$P$373:$P$750,'OverNight €'!$B$373:$B$750,A33) -> 21698.63 | M33: =SUMIFS('OverNight €'!$R$373:$R$750,'OverNight €'!$B$373:$B$750,A33) -> 4198.6301
A34: =CONCATENATE(MONTH(D34)," ",YEAR(D34)) -> 10 2026 | B34: =EOMONTH(B33,1) -> 46326 | D34: =EOMONTH(D33,1) -> 46326 | E34: SG | F34: CAT Tréso Plus | G34: =H33 -> 46300 | H34: =EDATE(G34,1) -> 46331 | I34: =INDEX('OverNight €'!$O$376:$O$750,MATCH($B34,'OverNight €'!$D$376:$D$750,0)) -> 0.02169863 | J34: =INDEX('OverNight €'!$N$376:$N$750,MATCH(B34,'OverNight €'!$C$376:$C$750,0)) -> 12000000 | K34: =SUMIFS('OverNight €'!$P$373:$P$750,'OverNight €'!$B$373:$B$750,A34) -> 22421.918 | M34: =SUMIFS('OverNight €'!$R$373:$R$750,'OverNight €'!$B$373:$B$750,A34) -> 4338.5845
A35: =CONCATENATE(MONTH(D35)," ",YEAR(D35)) -> 11 2026 | B35: =EOMONTH(B34,1) -> 46356 | D35: =EOMONTH(D34,1) -> 46356 | E35: SG | F35: CAT Tréso Plus | G35: =H34 -> 46331 | H35: =EDATE(G35,1) -> 46361 | I35: =INDEX('OverNight €'!$O$376:$O$750,MATCH($B35,'OverNight €'!$D$376:$D$750,0)) -> 0.02169863 | J35: =INDEX('OverNight €'!$N$376:$N$750,MATCH(B35,'OverNight €'!$C$376:$C$750,0)) -> 12000000 | K35: =SUMIFS('OverNight €'!$P$373:$P$750,'OverNight €'!$B$373:$B$750,A35) -> 21698.63 | M35: =SUMIFS('OverNight €'!$R$373:$R$750,'OverNight €'!$B$373:$B$750,A35) -> 4198.6301
A36: =CONCATENATE(MONTH(D36)," ",YEAR(D36)) -> 12 2026 | B36: =EOMONTH(B35,1) -> 46387 | D36: =EOMONTH(D35,1) -> 46387 | E36: SG | F36: CAT Tréso Plus | G36: =H35 -> 46361 | H36: =EDATE(G36,1) -> 46392 | I36: =INDEX('OverNight €'!$O$376:$O$750,MATCH($B36,'OverNight €'!$D$376:$D$750,0)) -> 0.02169863 | J36: =INDEX('OverNight €'!$N$376:$N$750,MATCH(B36,'OverNight €'!$C$376:$C$750,0)) -> 12000000 | K36: =SUMIFS('OverNight €'!$P$373:$P$750,'OverNight €'!$B$373:$B$750,A36) -> 22421.918 | M36: =SUMIFS('OverNight €'!$R$373:$R$750,'OverNight €'!$B$373:$B$750,A36) -> 4338.5845
D37: Total 2026 CAT Tréso Plus | I37: =AVERAGE(I25) -> 0.02169863 | K37: =SUM(K25:K25) -> 22421.918 | L37: =SUM(L25:L25) -> 22421.92 | M37: =SUM(M25:M25) -> 4338.5845
A39: =CONCATENATE(MONTH(D39)," ",YEAR(D39)) -> 1 2026 | B39: 46053 | D39: 46053 | E39: SG | F39: CAT Tréso Plus n°2 | G39: 45668 | H39: =EDATE(G39,1) -> 45699 | I39: =INDEX('OverNight €'!$V$376:$V$750,MATCH($B39,'OverNight €'!$D$376:$D$750,0)) -> 0.021205479 | J39: =INDEX('OverNight €'!$U$376:$U$750,MATCH($B39,'OverNight €'!$D$376:$D$750,0)) -> 6010956.2 | K39: =SUMIFS('OverNight €'!$W$373:$W$750,'OverNight €'!$B$373:$B$750,$A39) -> 10969.072 | L39: 10956.16 | M39: =SUMIFS('OverNight €'!$Y$373:$Y$750,'OverNight €'!$B$373:$B$750,$A39) -> 1916.7532 | O39: OK
A40: =CONCATENATE(MONTH(D40)," ",YEAR(D40)) -> 2 2026 | B40: =EOMONTH(B39,1) -> 46081 | D40: =EOMONTH(D39,1) -> 46081 | E40: SG | F40: CAT Tréso Plus n°2 | G40: =H39 -> 45699 | H40: =EDATE(G40,1) -> 45727 | I40: =INDEX('OverNight €'!$V$376:$V$750,MATCH($B40,'OverNight €'!$D$376:$D$750,0)) -> 0.021205479 | J40: =INDEX('OverNight €'!$U$376:$U$750,MATCH($B40,'OverNight €'!$D$376:$D$750,0)) -> 6010956.2 | K40: =SUMIFS('OverNight €'!$W$373:$W$750,'OverNight €'!$B$373:$B$750,$A40) -> 9913.9606 | M40: =SUMIFS('OverNight €'!$Y$373:$Y$750,'OverNight €'!$B$373:$B$750,$A40) -> 1732.3814
A41: =CONCATENATE(MONTH(D41)," ",YEAR(D41)) -> 3 2026 | B41: =EOMONTH(B40,1) -> 46112 | D41: =EOMONTH(D40,1) -> 46112 | E41: SG | F41: CAT Tréso Plus n°2 | G41: =H40 -> 45727 | H41: =EDATE(G41,1) -> 45758 | I41: =INDEX('OverNight €'!$V$376:$V$750,MATCH($B41,'OverNight €'!$D$376:$D$750,0)) -> 0.021205479 | J41: =INDEX('OverNight €'!$U$376:$U$750,MATCH($B41,'OverNight €'!$D$376:$D$750,0)) -> 6010956.2 | K41: =SUMIFS('OverNight €'!$W$373:$W$750,'OverNight €'!$B$373:$B$750,$A41) -> 10976.171 | M41: =SUMIFS('OverNight €'!$Y$373:$Y$750,'OverNight €'!$B$373:$B$750,$A41) -> 1917.9936
A42: =CONCATENATE(MONTH(D42)," ",YEAR(D42)) -> 4 2026 | B42: =EOMONTH(B41,1) -> 46142 | D42: =EOMONTH(D41,1) -> 46142 | E42: SG | F42: CAT Tréso Plus n°2 | G42: =H41 -> 45758 | H42: =EDATE(G42,1) -> 45788 | I42: =INDEX('OverNight €'!$V$376:$V$750,MATCH($B42,'OverNight €'!$D$376:$D$750,0)) -> 0.021205479 | J42: =INDEX('OverNight €'!$U$376:$U$750,MATCH($B42,'OverNight €'!$D$376:$D$750,0)) -> 6010956.2 | K42: =SUMIFS('OverNight €'!$W$373:$W$750,'OverNight €'!$B$373:$B$750,$A42) -> 10622.101 | M42: =SUMIFS('OverNight €'!$Y$373:$Y$750,'OverNight €'!$B$373:$B$750,$A42) -> 1856.1229
A43: =CONCATENATE(MONTH(D43)," ",YEAR(D43)) -> 5 2026 | B43: =EOMONTH(B42,1) -> 46173 | D43: =EOMONTH(D42,1) -> 46173 | E43: SG | F43: CAT Tréso Plus n°2 | G43: =H42 -> 45788 | H43: =EDATE(G43,1) -> 45819 | I43: =INDEX('OverNight €'!$V$376:$V$750,MATCH($B43,'OverNight €'!$D$376:$D$750,0)) -> 0.021205479 | J43: =INDEX('OverNight €'!$U$376:$U$750,MATCH($B43,'OverNight €'!$D$376:$D$750,0)) -> 6010956.2 | K43: =SUMIFS('OverNight €'!$W$373:$W$750,'OverNight €'!$B$373:$B$750,$A43) -> 10976.171 | M43: =SUMIFS('OverNight €'!$Y$373:$Y$750,'OverNight €'!$B$373:$B$750,$A43) -> 1917.9936
A44: =CONCATENATE(MONTH(D44)," ",YEAR(D44)) -> 6 2026 | B44: =EOMONTH(B43,1) -> 46203 | D44: =EOMONTH(D43,1) -> 46203 | E44: SG | F44: CAT Tréso Plus n°2 | G44: =H43 -> 45819 | H44: =EDATE(G44,1) -> 45849 | I44: =INDEX('OverNight €'!$V$376:$V$750,MATCH($B44,'OverNight €'!$D$376:$D$750,0)) -> 0.021205479 | J44: =INDEX('OverNight €'!$U$376:$U$750,MATCH($B44,'OverNight €'!$D$376:$D$750,0)) -> 6010956.2 | K44: =SUMIFS('OverNight €'!$W$373:$W$750,'OverNight €'!$B$373:$B$750,$A44) -> 10622.101 | M44: =SUMIFS('OverNight €'!$Y$373:$Y$750,'OverNight €'!$B$373:$B$750,$A44) -> 1856.1229
A45: =CONCATENATE(MONTH(D45)," ",YEAR(D45)) -> 7 2026 | B45: =EOMONTH(B44,1) -> 46234 | D45: =EOMONTH(D44,1) -> 46234 | E45: SG | F45: CAT Tréso Plus n°2 | G45: =H44 -> 45849 | H45: =EDATE(G45,1) -> 45880 | I45: =INDEX('OverNight €'!$V$376:$V$750,MATCH($B45,'OverNight €'!$D$376:$D$750,0)) -> 0.021205479 | J45: =INDEX('OverNight €'!$U$376:$U$750,MATCH($B45,'OverNight €'!$D$376:$D$750,0)) -> 6010956.2 | K45: =SUMIFS('OverNight €'!$W$373:$W$750,'OverNight €'!$B$373:$B$750,$A45) -> 10976.171 | M45: =SUMIFS('OverNight €'!$Y$373:$Y$750,'OverNight €'!$B$373:$B$750,$A45) -> 1917.9936
A46: =CONCATENATE(MONTH(D46)," ",YEAR(D46)) -> 8 2026 | B46: =EOMONTH(B45,1) -> 46265 | D46: =EOMONTH(D45,1) -> 46265 | E46: SG | F46: CAT Tréso Plus n°2 | G46: =H45 -> 45880 | H46: =EDATE(G46,1) -> 45911 | I46: =INDEX('OverNight €'!$V$376:$V$750,MATCH($B46,'OverNight €'!$D$376:$D$750,0)) -> 0.021205479 | J46: =INDEX('OverNight €'!$U$376:$U$750,MATCH($B46,'OverNight €'!$D$376:$D$750,0)) -> 6010956.2 | K46: =SUMIFS('OverNight €'!$W$373:$W$750,'OverNight €'!$B$373:$B$750,$A46) -> 10976.171 | M46: =SUMIFS('OverNight €'!$Y$373:$Y$750,'OverNight €'!$B$373:$B$750,$A46) -> 1917.9936
A47: =CONCATENATE(MONTH(D47)," ",YEAR(D47)) -> 9 2026 | B47: =EOMONTH(B46,1) -> 46295 | D47: =EOMONTH(D46,1) -> 46295 | E47: SG | F47: CAT Tréso Plus n°2 | G47: =H46 -> 45911 | H47: =EDATE(G47,1) -> 45941 | I47: =INDEX('OverNight €'!$V$376:$V$750,MATCH($B47,'OverNight €'!$D$376:$D$750,0)) -> 0.021205479 | J47: =INDEX('OverNight €'!$U$376:$U$750,MATCH($B47,'OverNight €'!$D$376:$D$750,0)) -> 6010956.2 | K47: =SUMIFS('OverNight €'!$W$373:$W$750,'OverNight €'!$B$373:$B$750,$A47) -> 10622.101 | M47: =SUMIFS('OverNight €'!$Y$373:$Y$750,'OverNight €'!$B$373:$B$750,$A47) -> 1856.1229
A48: =CONCATENATE(MONTH(D48)," ",YEAR(D48)) -> 10 2026 | B48: =EOMONTH(B47,1) -> 46326 | D48: =EOMONTH(D47,1) -> 46326 | E48: SG | F48: CAT Tréso Plus n°2 | G48: =H47 -> 45941 | H48: =EDATE(G48,1) -> 45972 | I48: =INDEX('OverNight €'!$V$376:$V$750,MATCH($B48,'OverNight €'!$D$376:$D$750,0)) -> 0.021205479 | J48: =INDEX('OverNight €'!$U$376:$U$750,MATCH($B48,'OverNight €'!$D$376:$D$750,0)) -> 6010956.2 | K48: =SUMIFS('OverNight €'!$W$373:$W$750,'OverNight €'!$B$373:$B$750,$A48) -> 10976.171 | M48: =SUMIFS('OverNight €'!$Y$373:$Y$750,'OverNight €'!$B$373:$B$750,$A48) -> 1917.9936
A49: =CONCATENATE(MONTH(D49)," ",YEAR(D49)) -> 11 2026 | B49: =EOMONTH(B48,1) -> 46356 | D49: =EOMONTH(D48,1) -> 46356 | E49: SG | F49: CAT Tréso Plus n°2 | G49: =H48 -> 45972 | H49: =EDATE(G49,1) -> 46002 | I49: =INDEX('OverNight €'!$V$376:$V$750,MATCH($B49,'OverNight €'!$D$376:$D$750,0)) -> 0.021205479 | J49: =INDEX('OverNight €'!$U$376:$U$750,MATCH($B49,'OverNight €'!$D$376:$D$750,0)) -> 6010956.2 | K49: =SUMIFS('OverNight €'!$W$373:$W$750,'OverNight €'!$B$373:$B$750,$A49) -> 10622.101 | M49: =SUMIFS('OverNight €'!$Y$373:$Y$750,'OverNight €'!$B$373:$B$750,$A49) -> 1856.1229
A50: =CONCATENATE(MONTH(D50)," ",YEAR(D50)) -> 12 2026 | B50: =EOMONTH(B49,1) -> 46387 | D50: =EOMONTH(D49,1) -> 46387 | E50: SG | F50: CAT Tréso Plus n°2 | G50: =H49 -> 46002 | H50: =EDATE(G50,1) -> 46033 | I50: =INDEX('OverNight €'!$V$376:$V$750,MATCH($B50,'OverNight €'!$D$376:$D$750,0)) -> 0.021205479 | J50: =INDEX('OverNight €'!$U$376:$U$750,MATCH($B50,'OverNight €'!$D$376:$D$750,0)) -> 6010956.2 | K50: =SUMIFS('OverNight €'!$W$373:$W$750,'OverNight €'!$B$373:$B$750,$A50) -> 10976.171 | M50: =SUMIFS('OverNight €'!$Y$373:$Y$750,'OverNight €'!$B$373:$B$750,$A50) -> 1917.9936
D51: Total 2026 CAT Tréso Plus n°2 | I51: =AVERAGE(I39) -> 0.021205479 | K51: =SUM(K39:K39) -> 10969.072 | L51: =SUM(L39:L39) -> 10956.16 | M51: =SUM(M39:M39) -> 1916.7532
A53: =CONCATENATE(MONTH(D53)," ",YEAR(D53)) -> 11 2025 | B53: 45991 | D53: =B53 -> 45991 | E53: SG | F53: CAT Arkea 12m | G53: 45966 | I53: =INDEX('OverNight €'!$AC$5:$AC$369,MATCH($B53,'OverNight €'!$D$5:$D$369,0)) -> 0.02579 | J53: =INDEX('OverNight €'!$AB$5:$AB$369,MATCH($B53,'OverNight €'!$D$5:$D$369,0)) -> 15000000 | K53: =SUMIFS('OverNight €'!$AD$5:$AD$369,'OverNight €'!$B$5:$B$369,$A53) -> 26864.583 | M53: =SUMIFS('OverNight €'!$AF$5:$AF$369,'OverNight €'!$B$5:$B$369,$A53) -> 8635.4167
A54: =CONCATENATE(MONTH(D54)," ",YEAR(D54)) -> 12 2025 | B54: =EOMONTH(B53,1) -> 46022 | D54: =EOMONTH(D53,1) -> 46022 | E54: SG | F54: CAT Arkea 12m | I54: =INDEX('OverNight €'!$AC$5:$AC$369,MATCH($B54,'OverNight €'!$D$5:$D$369,0)) -> 0.02579 | J54: =INDEX('OverNight €'!$AB$5:$AB$369,MATCH($B54,'OverNight €'!$D$5:$D$369,0)) -> 15000000 | K54: =SUMIFS('OverNight €'!$AD$5:$AD$369,'OverNight €'!$B$5:$B$369,$A54) -> 33312.083 | M54: =SUMIFS('OverNight €'!$AF$5:$AF$369,'OverNight €'!$B$5:$B$369,$A54) -> 10707.917
D55: Total 2025 CAT ARKEA 12m | I55: =AVERAGE(I53:I54) -> 0.02579 | K55: =SUM(K53:K54) -> 60176.667 | L55: =SUM(L53:L54) -> 0 | M55: =SUM(M53:M54) -> 19343.333
A57: =CONCATENATE(MONTH(D57)," ",YEAR(D57)) -> 1 2026 | B57: 46053 | D57: 46053 | E57: SG | F57: CAT Arkea 12m | G57: 45966 | I57: =INDEX('OverNight €'!$AC$376:$AC$750,MATCH($B57,'OverNight €'!$D$376:$D$750,0)) -> 0.02579 | J57: =INDEX('OverNight €'!$AB$376:$AB$750,MATCH($B57,'OverNight €'!$D$376:$D$750,0)) -> 15000000 | K57: =SUMIFS('OverNight €'!$AD$373:$AD$750,'OverNight €'!$B$373:$B$750,$A57) -> 33312.083 | M57: =SUMIFS('OverNight €'!$AF$373:$AF$750,'OverNight €'!$B$373:$B$750,$A57) -> 10707.917
A58: =CONCATENATE(MONTH(D58)," ",YEAR(D58)) -> 2 2026 | B58: =EOMONTH(B57,1) -> 46081 | D58: =EOMONTH(D57,1) -> 46081 | E58: SG | F58: CAT Arkea 12m | I58: =INDEX('OverNight €'!$AC$376:$AC$750,MATCH($B58,'OverNight €'!$D$376:$D$750,0)) -> 0.02579 | J58: =INDEX('OverNight €'!$AB$376:$AB$750,MATCH($B58,'OverNight €'!$D$376:$D$750,0)) -> 15000000 | K58: =SUMIFS('OverNight €'!$AD$373:$AD$750,'OverNight €'!$B$373:$B$750,$A58) -> 30088.333 | M58: =SUMIFS('OverNight €'!$AF$373:$AF$750,'OverNight €'!$B$373:$B$750,$A58) -> 9671.6667
A59: =CONCATENATE(MONTH(D59)," ",YEAR(D59)) -> 3 2026 | B59: =EOMONTH(B58,1) -> 46112 | D59: =EOMONTH(D58,1) -> 46112 | E59: SG | F59: CAT Arkea 12m | I59: =INDEX('OverNight €'!$AC$376:$AC$750,MATCH($B59,'OverNight €'!$D$376:$D$750,0)) -> 0.02579 | J59: =INDEX('OverNight €'!$AB$376:$AB$750,MATCH($B59,'OverNight €'!$D$376:$D$750,0)) -> 15000000 | K59: =SUMIFS('OverNight €'!$AD$373:$AD$750,'OverNight €'!$B$373:$B$750,$A59) -> 33312.083 | M59: =SUMIFS('OverNight €'!$AF$373:$AF$750,'OverNight €'!$B$373:$B$750,$A59) -> 10707.917
A60: =CONCATENATE(MONTH(D60)," ",YEAR(D60)) -> 4 2026 | B60: =EOMONTH(B59,1) -> 46142 | D60: =EOMONTH(D59,1) -> 46142 | E60: SG | F60: CAT Arkea 12m | I60: =INDEX('OverNight €'!$AC$376:$AC$750,MATCH($B60,'OverNight €'!$D$376:$D$750,0)) -> 0.02579 | J60: =INDEX('OverNight €'!$AB$376:$AB$750,MATCH($B60,'OverNight €'!$D$376:$D$750,0)) -> 15000000 | K60: =SUMIFS('OverNight €'!$AD$373:$AD$750,'OverNight €'!$B$373:$B$750,$A60) -> 32237.5 | M60: =SUMIFS('OverNight €'!$AF$373:$AF$750,'OverNight €'!$B$373:$B$750,$A60) -> 10362.5
A61: =CONCATENATE(MONTH(D61)," ",YEAR(D61)) -> 5 2026 | B61: =EOMONTH(B60,1) -> 46173 | D61: =EOMONTH(D60,1) -> 46173 | E61: SG | F61: CAT Arkea 12m | I61: =INDEX('OverNight €'!$AC$376:$AC$750,MATCH($B61,'OverNight €'!$D$376:$D$750,0)) -> 0.02579 | J61: =INDEX('OverNight €'!$AB$376:$AB$750,MATCH($B61,'OverNight €'!$D$376:$D$750,0)) -> 15000000 | K61: =SUMIFS('OverNight €'!$AD$373:$AD$750,'OverNight €'!$B$373:$B$750,$A61) -> 33312.083 | M61: =SUMIFS('OverNight €'!$AF$373:$AF$750,'OverNight €'!$B$373:$B$750,$A61) -> 10707.917
A62: =CONCATENATE(MONTH(D62)," ",YEAR(D62)) -> 6 2026 | B62: =EOMONTH(B61,1) -> 46203 | D62: =EOMONTH(D61,1) -> 46203 | E62: SG | F62: CAT Arkea 12m | I62: =INDEX('OverNight €'!$AC$376:$AC$750,MATCH($B62,'OverNight €'!$D$376:$D$750,0)) -> 0.02579 | J62: =INDEX('OverNight €'!$AB$376:$AB$750,MATCH($B62,'OverNight €'!$D$376:$D$750,0)) -> 15000000 | K62: =SUMIFS('OverNight €'!$AD$373:$AD$750,'OverNight €'!$B$373:$B$750,$A62) -> 32237.5 | M62: =SUMIFS('OverNight €'!$AF$373:$AF$750,'OverNight €'!$B$373:$B$750,$A62) -> 10362.5
A63: =CONCATENATE(MONTH(D63)," ",YEAR(D63)) -> 7 2026 | B63: =EOMONTH(B62,1) -> 46234 | D63: =EOMONTH(D62,1) -> 46234 | E63: SG | F63: CAT Arkea 12m | I63: =INDEX('OverNight €'!$AC$376:$AC$750,MATCH($B63,'OverNight €'!$D$376:$D$750,0)) -> 0.02579 | J63: =INDEX('OverNight €'!$AB$376:$AB$750,MATCH($B63,'OverNight €'!$D$376:$D$750,0)) -> 15000000 | K63: =SUMIFS('OverNight €'!$AD$373:$AD$750,'OverNight €'!$B$373:$B$750,$A63) -> 33312.083 | M63: =SUMIFS('OverNight €'!$AF$373:$AF$750,'OverNight €'!$B$373:$B$750,$A63) -> 10707.917
A64: =CONCATENATE(MONTH(D64)," ",YEAR(D64)) -> 8 2026 | B64: =EOMONTH(B63,1) -> 46265 | D64: =EOMONTH(D63,1) -> 46265 | E64: SG | F64: CAT Arkea 12m | I64: =INDEX('OverNight €'!$AC$376:$AC$750,MATCH($B64,'OverNight €'!$D$376:$D$750,0)) -> 0.02579 | J64: =INDEX('OverNight €'!$AB$376:$AB$750,MATCH($B64,'OverNight €'!$D$376:$D$750,0)) -> 15000000 | K64: =SUMIFS('OverNight €'!$AD$373:$AD$750,'OverNight €'!$B$373:$B$750,$A64) -> 33312.083 | M64: =SUMIFS('OverNight €'!$AF$373:$AF$750,'OverNight €'!$B$373:$B$750,$A64) -> 10707.917
A65: =CONCATENATE(MONTH(D65)," ",YEAR(D65)) -> 9 2026 | B65: =EOMONTH(B64,1) -> 46295 | D65: =EOMONTH(D64,1) -> 46295 | E65: SG | F65: CAT Arkea 12m | I65: =INDEX('OverNight €'!$AC$376:$AC$750,MATCH($B65,'OverNight €'!$D$376:$D$750,0)) -> 0.02579 | J65: =INDEX('OverNight €'!$AB$376:$AB$750,MATCH($B65,'OverNight €'!$D$376:$D$750,0)) -> 15000000 | K65: =SUMIFS('OverNight €'!$AD$373:$AD$750,'OverNight €'!$B$373:$B$750,$A65) -> 32237.5 | M65: =SUMIFS('OverNight €'!$AF$373:$AF$750,'OverNight €'!$B$373:$B$750,$A65) -> 10362.5
A66: =CONCATENATE(MONTH(D66)," ",YEAR(D66)) -> 10 2026 | B66: =EOMONTH(B65,1) -> 46326 | D66: =EOMONTH(D65,1) -> 46326 | E66: SG | F66: CAT Arkea 12m | I66: =INDEX('OverNight €'!$AC$376:$AC$750,MATCH($B66,'OverNight €'!$D$376:$D$750,0)) -> 0.02579 | J66: =INDEX('OverNight €'!$AB$376:$AB$750,MATCH($B66,'OverNight €'!$D$376:$D$750,0)) -> 15000000 | K66: =SUMIFS('OverNight €'!$AD$373:$AD$750,'OverNight €'!$B$373:$B$750,$A66) -> 33312.083 | M66: =SUMIFS('OverNight €'!$AF$373:$AF$750,'OverNight €'!$B$373:$B$750,$A66) -> 10707.917
A67: =CONCATENATE(MONTH(D67)," ",YEAR(D67)) -> 11 2026 | B67: =EOMONTH(B66,1) -> 46356 | D67: =EOMONTH(D66,1) -> 46356 | E67: SG | F67: CAT Arkea 12m | H67: 46331 | I67: =INDEX('OverNight €'!$AC$376:$AC$750,MATCH($B67,'OverNight €'!$D$376:$D$750,0)) -> 0 | J67: =INDEX('OverNight €'!$AB$376:$AB$750,MATCH($B67,'OverNight €'!$D$376:$D$750,0)) -> 0 | K67: =SUMIFS('OverNight €'!$AD$373:$AD$750,'OverNight €'!$B$373:$B$750,$A67) -> 6447.5 | M67: =SUMIFS('OverNight €'!$AF$373:$AF$750,'OverNight €'!$B$373:$B$750,$A67) -> 2072.5
A68: =CONCATENATE(MONTH(D68)," ",YEAR(D68)) -> 12 2026 | B68: =EOMONTH(B67,1) -> 46387 | D68: =EOMONTH(D67,1) -> 46387 | E68: SG | F68: CAT Arkea 12m | I68: =INDEX('OverNight €'!$AC$376:$AC$750,MATCH($B68,'OverNight €'!$D$376:$D$750,0)) -> 0 | J68: =INDEX('OverNight €'!$AB$376:$AB$750,MATCH($B68,'OverNight €'!$D$376:$D$750,0)) -> 0 | K68: =SUMIFS('OverNight €'!$AD$373:$AD$750,'OverNight €'!$B$373:$B$750,$A68) -> 0 | M68: =SUMIFS('OverNight €'!$AF$373:$AF$750,'OverNight €'!$B$373:$B$750,$A68) -> 0
D69: Total 2026 CAT ARKEA 12m | I69: =AVERAGE(I57) -> 0.02579 | K69: =SUM(K57:K57) -> 33312.083 | L69: =SUM(L57:L57) -> 0 | M69: =SUM(M57:M57) -> 10707.917
D71: Total 2026 CAT | J71: =J11+J25+J39+J57 -> 40140956 | K71: =K69+K51+K37+K23 -> 71989.045 | L71: =L69+L51+L37+L23 -> 38317.47 | M71: =M69+M51+M37+M23 -> 16963.254 | O71: Change Amont end of month manually each month
D73: OPCVM - UCITS
A75: =CONCATENATE(MONTH(D75)," ",YEAR(D75)) -> 1 2026 | B75: =D75 -> 46053 | D75: 46053 | E75: SG | F75: codéis EUR | G75: 45940 | I75: ='codeis €'!AF403 -> 0.020819938 | J75: ='codeis €'!Z403 -> 47203973 | K75: ='codeis €'!AD403 -> 111686 | L75: =K75 -> 111686 | M75: =SUMIFS('codeis €'!$AI$373:$AI$750,'codeis €'!$B$373:$B$750,A75) -> 21969.048 | O75: Interets accrued are considered as paid
A76: =CONCATENATE(MONTH(D76)," ",YEAR(D76)) -> 2 2026 | B76: =D76 -> 46081 | D76: =EOMONTH(D75,1) -> 46081 | E76: SG | F76: codéis EUR
A77: =CONCATENATE(MONTH(D77)," ",YEAR(D77)) -> 3 2026 | B77: =EOMONTH(B76,1) -> 46112 | D77: =EOMONTH(D76,1) -> 46112 | E77: SG | F77: codéis EUR
A78: =CONCATENATE(MONTH(D78)," ",YEAR(D78)) -> 4 2026 | B78: =EOMONTH(B77,1) -> 46142 | D78: =EOMONTH(D77,1) -> 46142 | E78: SG | F78: codéis EUR
A79: =CONCATENATE(MONTH(D79)," ",YEAR(D79)) -> 5 2026 | B79: =EOMONTH(B78,1) -> 46173 | D79: =EOMONTH(D78,1) -> 46173 | E79: SG | F79: codéis EUR
A80: =CONCATENATE(MONTH(D80)," ",YEAR(D80)) -> 6 2026 | B80: =EOMONTH(B79,1) -> 46203 | D80: =EOMONTH(D79,1) -> 46203 | E80: SG | F80: codéis EUR
A81: =CONCATENATE(MONTH(D81)," ",YEAR(D81)) -> 7 2026 | B81: =EOMONTH(B80,1) -> 46234 | D81: =EOMONTH(D80,1) -> 46234 | E81: SG | F81: codéis EUR
A82: =CONCATENATE(MONTH(D82)," ",YEAR(D82)) -> 8 2026 | B82: =EOMONTH(B81,1) -> 46265 | D82: =EOMONTH(D81,1) -> 46265 | E82: SG | F82: codéis EUR
A83: =CONCATENATE(MONTH(D83)," ",YEAR(D83)) -> 9 2026 | B83: =EOMONTH(B82,1) -> 46295 | D83: =EOMONTH(D82,1) -> 46295 | E83: SG | F83: codéis EUR
A84: =CONCATENATE(MONTH(D84)," ",YEAR(D84)) -> 10 2026 | B84: =EOMONTH(B83,1) -> 46326 | D84: =EOMONTH(D83,1) -> 46326 | E84: SG | F84: codéis EUR
A85: =CONCATENATE(MONTH(D85)," ",YEAR(D85)) -> 11 2026 | B85: =EOMONTH(B84,1) -> 46356 | D85: =EOMONTH(D84,1) -> 46356 | E85: SG | F85: codéis EUR
A86: =CONCATENATE(MONTH(D86)," ",YEAR(D86)) -> 12 2026 | B86: =EOMONTH(B85,1) -> 46387 | D86: =EOMONTH(D85,1) -> 46387 | E86: SG | F86: codéis EUR
D87: Total 2026 Codéis | K87: =SUM(K75:K75) -> 111686 | L87: =SUM(L75:L75) -> 111686 | M87: =SUM(M75:M75) -> 21969.048
A89: =CONCATENATE(MONTH(D89)," ",YEAR(D89)) -> 1 2026 | B89: =D89 -> 46053 | D89: 46053 | E89: BNP/SG | F89: Ellipsis** (Ester +0,32%) | G89: 45959 | I89: ='CT- € Ellipsis BNP'!AA407 -> 0.022439479 | J89: ='CT- € Ellipsis BNP'!X407 -> 1.0059309e+08 | K89: =SUM('CT- € Ellipsis BNP'!W376:W407) -> 200245.61 | M89: =SUMIFS('CT- € Ellipsis BNP'!$AC$373:$AC$750,'CT- € Ellipsis BNP'!$B$373:$B$750,A89) -> 54313.736
A90: =CONCATENATE(MONTH(D90)," ",YEAR(D90)) -> 2 2026 | B90: =EOMONTH(B89,1) -> 46081 | D90: =EOMONTH(D89,1) -> 46081 | E90: =E89 -> BNP/SG | F90: =F89 -> Ellipsis** (Ester +0,32%)
A91: =CONCATENATE(MONTH(D91)," ",YEAR(D91)) -> 3 2026 | B91: =EOMONTH(B90,1) -> 46112 | D91: =EOMONTH(D90,1) -> 46112 | E91: =E90 -> BNP/SG | F91: =F90 -> Ellipsis** (Ester +0,32%)
A92: =CONCATENATE(MONTH(D92)," ",YEAR(D92)) -> 4 2026 | B92: =EOMONTH(B91,1) -> 46142 | D92: =EOMONTH(D91,1) -> 46142 | E92: =E91 -> BNP/SG | F92: =F91 -> Ellipsis** (Ester +0,32%)
A93: =CONCATENATE(MONTH(D93)," ",YEAR(D93)) -> 5 2026 | B93: =EOMONTH(B92,1) -> 46173 | D93: =EOMONTH(D92,1) -> 46173 | E93: =E92 -> BNP/SG | F93: =F92 -> Ellipsis** (Ester +0,32%)
A94: =CONCATENATE(MONTH(D94)," ",YEAR(D94)) -> 6 2026 | B94: =EOMONTH(B93,1) -> 46203 | D94: =EOMONTH(D93,1) -> 46203 | E94: =E93 -> BNP/SG | F94: =F93 -> Ellipsis** (Ester +0,32%)
A95: =CONCATENATE(MONTH(D95)," ",YEAR(D95)) -> 7 2026 | B95: =EOMONTH(B94,1) -> 46234 | D95: =EOMONTH(D94,1) -> 46234 | E95: =E94 -> BNP/SG | F95: =F94 -> Ellipsis** (Ester +0,32%)
A96: =CONCATENATE(MONTH(D96)," ",YEAR(D96)) -> 8 2026 | B96: =EOMONTH(B95,1) -> 46265 | D96: =EOMONTH(D95,1) -> 46265 | E96: =E95 -> BNP/SG | F96: =F95 -> Ellipsis** (Ester +0,32%)
A97: =CONCATENATE(MONTH(D97)," ",YEAR(D97)) -> 9 2026 | B97: =EOMONTH(B96,1) -> 46295 | D97: =EOMONTH(D96,1) -> 46295 | E97: =E96 -> BNP/SG | F97: =F96 -> Ellipsis** (Ester +0,32%) | H97: 18/09/206
A98: =CONCATENATE(MONTH(D98)," ",YEAR(D98)) -> 1 1900 | B98: =EOMONTH(B97,1) -> 46326
A99: =CONCATENATE(MONTH(D99)," ",YEAR(D99)) -> 1 1900 | B99: =EOMONTH(B98,1) -> 46356
A100: =CONCATENATE(MONTH(D100)," ",YEAR(D100)) -> 1 1900 | B100: =EOMONTH(B99,1) -> 46387
D101: Total 2026 Ellipsis (BNP) | I101: =AVERAGE(I89) -> 0.022439479 | K101: =SUM(K89:K89) -> 200245.61 | L101: =SUM(L89:L89) -> 0 | M101: =SUM(M89:M89) -> 54313.736 | O101: Interests are considered paid when cash out
D103: Total 2026 Note & Funds | J103: =J89+J75 -> 1.4779707e+08 | K103: =K101+K87+K68+K54 -> 345243.7 | L103: =L101+L87+L68+L54 -> 111686 | M103: =M101+M87+M68+M54 -> 86990.701 | O103: Change Amont end of month manually each month
D105: Month | E105: Bank | F105: Investment | G105: Opening Date | H105: Closing Date | I105: Rate * | J105: Amount EoM | K105: Interest due | L105: Interest paid | M105: Profit/NCA
J106: in k€ | K106: in k€ | L106: in k€ | M106: in k€
A107: =CONCATENATE(MONTH(D107)," ",YEAR(D107)) -> 1 2026 | B107: =EOMONTH(D107,0) -> 46053 | D107: 46053 | E107: Total | I107: =AVERAGEIFS('OverNight €'!$AT$373:$AT$750,'OverNight €'!$B$373:$B$750,$A107) -> 0.022007028 | J107: =SUMIFS(J$11:J$100,$D$11:$D$100,$D107) -> 1.8793802e+08 | K107: =SUMIFS(K$11:K$100,$D$11:$D$100,$D107) -> 383920.66 | L107: =SUMIFS(L$11:L$100,$D$11:$D$100,$D107) -> 150003.47 | M107: =SUMIFS(M$11:M$100,$D$11:$D$100,$D107) -> 93246.038 | O107: =L107-L75 -> 38317.47
A108: =CONCATENATE(MONTH(D108)," ",YEAR(D108)) -> 2 2026 | B108: =EOMONTH(D108,0) -> 46081 | D108: =EOMONTH(D107,1) -> 46081 | E108: Total | I108: =AVERAGEIFS('OverNight €'!$AT$373:$AT$750,'OverNight €'!$B$373:$B$750,$A108) -> 0.022605121 | J108: =SUMIFS(J$11:J$100,$D$11:$D$100,$D108) -> 37210956 | K108: =SUMIFS(K$11:K$100,$D$11:$D$100,$D108) -> 67926.154 | L108: =SUMIFS(L$11:L$100,$D$11:$D$100,$D108) -> 0 | M108: =SUMIFS(M$11:M$100,$D$11:$D$100,$D108) -> 15322.769
A109: =CONCATENATE(MONTH(D109)," ",YEAR(D109)) -> 3 2026 | B109: =EOMONTH(D109,0) -> 46112 | D109: =EOMONTH(D108,1) -> 46112 | E109: Total | I109: =AVERAGEIFS('OverNight €'!$AT$373:$AT$750,'OverNight €'!$B$373:$B$750,$A109) -> 0.02073427 | J109: =SUMIFS(J$11:J$100,$D$11:$D$100,$D109) -> 67260956 | K109: =SUMIFS(K$11:K$100,$D$11:$D$100,$D109) -> 112477.53 | L109: =SUMIFS(L$11:L$100,$D$11:$D$100,$D109) -> 0 | M109: =SUMIFS(M$11:M$100,$D$11:$D$100,$D109) -> 16964.495
A110: =CONCATENATE(MONTH(D110)," ",YEAR(D110)) -> 4 2026 | B110: =EOMONTH(D110,0) -> 46142 | D110: =EOMONTH(D109,1) -> 46142 | E110: Total | I110: =AVERAGEIFS('OverNight €'!$AT$373:$AT$750,'OverNight €'!$B$373:$B$750,$A110) -> 0.020428995 | J110: =SUMIFS(J$11:J$100,$D$11:$D$100,$D110) -> 67260956 | K110: =SUMIFS(K$11:K$100,$D$11:$D$100,$D110) -> 114506.15 | L110: =SUMIFS(L$11:L$100,$D$11:$D$100,$D110) -> 0 | M110: =SUMIFS(M$11:M$100,$D$11:$D$100,$D110) -> 16417.253
A111: =CONCATENATE(MONTH(D111)," ",YEAR(D111)) -> 5 2026 | B111: =EOMONTH(D111,0) -> 46173 | D111: =EOMONTH(D110,1) -> 46173 | E111: Total | I111: =AVERAGEIFS('OverNight €'!$AT$373:$AT$750,'OverNight €'!$B$373:$B$750,$A111) -> 0.020428995 | J111: =SUMIFS(J$11:J$100,$D$11:$D$100,$D111) -> 67260956 | K111: =SUMIFS(K$11:K$100,$D$11:$D$100,$D111) -> 118323.02 | L111: =SUMIFS(L$11:L$100,$D$11:$D$100,$D111) -> 0 | M111: =SUMIFS(M$11:M$100,$D$11:$D$100,$D111) -> 16964.495
A112: =CONCATENATE(MONTH(D112)," ",YEAR(D112)) -> 6 2026 | B112: =EOMONTH(D112,0) -> 46203 | D112: =EOMONTH(D111,1) -> 46203 | E112: Total | I112: =AVERAGEIFS('OverNight €'!$AT$373:$AT$750,'OverNight €'!$B$373:$B$750,$A112) -> 0.020428995 | J112: =SUMIFS(J$11:J$100,$D$11:$D$100,$D112) -> 67260956 | K112: =SUMIFS(K$11:K$100,$D$11:$D$100,$D112) -> 114506.15 | L112: =SUMIFS(L$11:L$100,$D$11:$D$100,$D112) -> 0 | M112: =SUMIFS(M$11:M$100,$D$11:$D$100,$D112) -> 16417.253
A113: =CONCATENATE(MONTH(D113)," ",YEAR(D113)) -> 7 2026 | B113: =EOMONTH(D113,0) -> 46234 | D113: =EOMONTH(D112,1) -> 46234 | E113: Total | I113: =AVERAGEIFS('OverNight €'!$AT$373:$AT$750,'OverNight €'!$B$373:$B$750,$A113) -> 0.020428995 | J113: =SUMIFS(J$11:J$100,$D$11:$D$100,$D113) -> 67260956 | K113: =SUMIFS(K$11:K$100,$D$11:$D$100,$D113) -> 118323.02 | L113: =SUMIFS(L$11:L$100,$D$11:$D$100,$D113) -> 0 | M113: =SUMIFS(M$11:M$100,$D$11:$D$100,$D113) -> 16964.495
A114: =CONCATENATE(MONTH(D114)," ",YEAR(D114)) -> 8 2026 | B114: =EOMONTH(D114,0) -> 46265 | D114: =EOMONTH(D113,1) -> 46265 | E114: Total | I114: =AVERAGEIFS('OverNight €'!$AT$373:$AT$750,'OverNight €'!$B$373:$B$750,$A114) -> 0.020428995 | J114: =SUMIFS(J$11:J$100,$D$11:$D$100,$D114) -> 67260956 | K114: =SUMIFS(K$11:K$100,$D$11:$D$100,$D114) -> 118323.02 | L114: =SUMIFS(L$11:L$100,$D$11:$D$100,$D114) -> 0 | M114: =SUMIFS(M$11:M$100,$D$11:$D$100,$D114) -> 16964.495
A115: =CONCATENATE(MONTH(D115)," ",YEAR(D115)) -> 9 2026 | B115: =EOMONTH(D115,0) -> 46295 | D115: =EOMONTH(D114,1) -> 46295 | E115: Total | I115: =AVERAGEIFS('OverNight €'!$AT$373:$AT$750,'OverNight €'!$B$373:$B$750,$A115) -> 0.020428995 | J115: =SUMIFS(J$11:J$100,$D$11:$D$100,$D115) -> 67260956 | K115: =SUMIFS(K$11:K$100,$D$11:$D$100,$D115) -> 114506.15 | L115: =SUMIFS(L$11:L$100,$D$11:$D$100,$D115) -> 0 | M115: =SUMIFS(M$11:M$100,$D$11:$D$100,$D115) -> 16417.253
A116: =CONCATENATE(MONTH(D116)," ",YEAR(D116)) -> 10 2026 | B116: =EOMONTH(D116,0) -> 46326 | D116: =EOMONTH(D115,1) -> 46326 | E116: Total | I116: =AVERAGEIFS('OverNight €'!$AT$373:$AT$750,'OverNight €'!$B$373:$B$750,$A116) -> 0.020428995 | J116: =SUMIFS(J$11:J$100,$D$11:$D$100,$D116) -> 67260956 | K116: =SUMIFS(K$11:K$100,$D$11:$D$100,$D116) -> 118323.02 | L116: =SUMIFS(L$11:L$100,$D$11:$D$100,$D116) -> 0 | M116: =SUMIFS(M$11:M$100,$D$11:$D$100,$D116) -> 16964.495
...

Sheet Monthly Report 2025 €
L1: 46022
D8: € Cash investments report as of 31 12 2025
B9: Formule | D9: Month | E9: Bank | F9: Investment | G9: Opening Date | H9: Closing Date | I9: Rate * | J9: Amount end of month | K9: Interest due | L9: Interest paid | M9: Profit/NCA
D11: Deposit
A13: 10 2023
A14: 11 2023 | B14: 45230 | D14: 45200 | E14: SG | F14: NCA | G14: 45205 | I14: 0.038 | J14: 150000000 | K14: 278983.33 | L14: 278983.33
A15: 12 2023 | B15: 45260 | D15: 45231 | E15: SG | F15: NCA | G15: 45205 | I15: 0.038 | J15: 191300000 | K15: 559423.33 | L15: 559423.35
B16: 45291 | D16: 45261 | E16: SG | F16: NCA | G16: 45205 | I16: 0.038 | J16: 191200000 | K16: 663965.56 | L16: 623601.11
D17: Total 2023 | K17: 1502372.2 | L17: 1462007.8
A19: 1 2024 | B19: 45322 | D19: 45292 | E19: SG | F19: NCA | G19: 45205 | I19: 0.038 | J19: 184300000 | K19: 614829.44 | L19: 655193.9
A20: 2 2024 | B20: 45351 | D20: 45323 | E20: SG | F20: NCA | I20: 0.038 | J20: 179700000 | K20: 561355 | L20: 561355
A21: 3 2024 | B21: 45382 | D21: 45352 | E21: SG | F21: NCA | I21: 0.038 | J21: 168900000 | K21: 575024.44 | L21: 521528.88
A22: 4 2024 | B22: 45412 | D22: 45383 | E22: SG | F22: NCA | I22: 0.038 | J22: 175300000 | K22: 557987.78 | L22: 611472.77
A23: 5 2024 | B23: 45443 | D23: 45413 | E23: SG | F23: NCA | I23: 0.038 | J23: 153100000 | K23: 536845 | L23: 539061.67
A24: 6 2024 | B24: 45473 | D24: 45444 | E24: SG | F24: NCA | I24: 0.0355 | J24: 169500000 | K24: 471724.44 | L24: 438295.27
A25: 7 2024 | B25: 45504 | D25: 45474 | E25: SG | F25: NCA | I25: 0.0355 | J25: 159950000 | K25: 509306.67 | L25: 542735.84
A26: 8 2024 | B26: 45535 | D26: 45505 | E26: SG | F26: NCA | I26: 0.0355 | J26: 142700000 | K26: 462777.01 | L26: 448705.21
A27: 9 2024 | B27: 45565 | D27: 45536 | E27: SG | F27: NCA | I27: 0.033 | J27: 134800000 | K27: 405311.39 | L27: 419383.19
A28: 10 2024 | B28: 45596 | D28: 45566 | E28: SG | F28: NCA | I28: 0.0305 | J28: 61250000 | K28: 234960.33 | L28: 234960.33
A29: 11 2024 | B29: 45626 | D29: 45597 | E29: SG | F29: NCA | I29: 0.0305 | J29: 61800000 | K29: 181072.57 | L29: 175836.75
A30: 12 2024 | B30: 45657 | D30: 45627 | E30: SG | F30: NCA | I30: 0.0275 | J30: 31100000 | K30: 120010 | L30: 125245.84
D31: Total 2024 NCA | K31: 5231204.1 | L31: 5273774.7
A35: 1 2025 | B35: 45688 | D35: 45688 | E35: SG | F35: NCA | G35: 45205 | I35: 0.0275 | J35: 12000000 | K35: 54071.875 | L35: 54071.89 | M35: 0
A36: 2 2025 | B36: 45716 | D36: 45716 | E36: SG | F36: NCA | I36: 0.025 | J36: 24350000 | K36: 49647.639 | L36: 49647.63 | M36: 0
A37: 3 2025 | B37: 45747 | D37: 45747 | E37: SG | F37: NCA | I37: 0.0225 | J37: 21820000 | K37: 56474.861 | L37: 56474.87 | M37: 0
A38: 4 2025 | B38: 45777 | D38: 45777 | E38: SG | F38: NCA | I38: 0.02 | J38: 11690000 | K38: 29334.236 | L38: 29334.24 | M38: 0
A39: 5 2025 | B39: 45808 | D39: 45808 | E39: SG | F39: NCA | I39: 0.02 | J39: 6430000 | K39: 15132.778 | L39: 14775.55 | M39: 0
A40: 6 2025 | B40: 45838 | D40: 45838 | E40: SG | F40: NCA | I40: 0.0175 | J40: 11530000 | K40: 14464.444 | L40: 14821.66 | M40: 0
A41: 7 2025 | B41: 45869 | D41: 45869 | E41: SG | F41: NCA | I41: 0.0175 | J41: 6120000 | K41: 14420.486 | L41: 14420.49 | M41: 0
A42: 8 2025 | B42: 45900 | D42: 45900 | E42: SG | F42: NCA | I42: 0.0175 | J42: 15800000 | K42: 88886.875 | L42: 87350.77 | M42: 0
A43: 9 2025 | B43: 45930 | D43: 45930 | E43: SG | F43: NCA | I43: 0.0175 | J43: 9445000 | K43: 28973.194 | L43: 30509.31 | M43: 0 | O43: OK fin septembre
A44: 10 2025 | B44: 45961 | D44: 45961 | E44: SG | F44: NCA | I44: 0.0175 | J44: 11244000 | K44: 33940.181 | L44: 33940.17 | M44: 0 | O44: OK fin octobre
A45: 11 2025 | B45: 45991 | D45: 45991 | E45: SG | F45: NCA | I45: 0.0175 | J45: 9710000 | K45: 18029.861 | L45: 17085.84 | M45: 0 | O45: OK au vendredi 26/11
A46: 12 2025 | B46: 46022 | D46: 46022 | E46: SG | F46: NCA | I46: 0.0175 | J46: 3940000 | K46: 14341.736 | L46: 15285.77 | M46: 0 | O46: OK au 31/12
D47: Total 2025 NCA | I47: 0.019791667 | K47: 417718.17 | L47: 417718.19 | M47: 0
A49: 1 2024 | B49: 45565 | D49: 45292 | E49: SG | F49: Dual deposit $ -> € | G49: 45288 | H49: 45320 | I49: 0.08 | J49: 9160025.6 | K49: 65137.962 | L49: 65137.962
A50: 10 2024 | B50: 45596 | D50: 45566 | E50: SG | F50: CAT Tréso Plus | G50: 45567 | H50: 45598 | I50: 0.033534247 | J50: 12000000 | K50: 32416.438 | L50: 0
A51: 10 2024 | B51: 45596 | D51: 45566 | E51: SG | F51: CAT €ster +0,25% n°1,2,3 | G51: 45575 | H51: 45606 | I51: 0.035268164 | J51: 45000000 | K51: 92578.932 | L51: 0 | P51: moyenne arithématique ester entre date blocage et veille de l'échéance de clôture
A52: 11 2024 | B52: 45626 | D52: 45597 | E52: SG | F52: CAT Tréso Plus | G52: 45598 | H52: 45628 | I52: 0.033534247 | J52: 12000000 | K52: 33534.247 | L52: 34652.05
A53: 11 2024 | B53: 45626 | D53: 45597 | E53: SG | F53: CAT €ster +0,25% | G53: 45606 | H53: 45636 | I53: 0.034148712 | J53: 45136664 | K53: 129716.26 | L53: 136664.13
A54: 12 2024 | B54: 45657 | D54: 45627 | E54: SG | F54: CAT Tréso Plus | G54: 45628 | H54: 45659 | I54: 0.02860274 | J54: 12000000 | K54: 29884.932 | L54: 33534.25
A55: 12 2024 | B55: 45657 | D55: 45627 | E55: SG | F55: CAT €ster +0,25% | G55: 45636 | H55: 45667 | I55: 0.032374356 | J55: 45265111 | K55: 128298.87 | L55: 128446.59
A56: 12 2024 | B56: 45657 | D56: 45627 | E56: BCP | F56: CAT Euribor 3 mois | G56: 45642 | H56: 45367 | I56: 0.03236 | J56: 30000000 | K56: 40450 | L56: 0
D57: Total 2024 CAT | K57: 552017.64 | L57: 398434.98
A59: 1 2025 | B59: 45688 | D59: 45688 | E59: SG | F59: CAT Tréso Plus | G59: 45659 | H59: 45690 | I59: 0.02860274 | J59: 12000000 | K59: 29556.164 | L59: 29556.16 | M59: 1139.4977
A60: 2 2025 | B60: 45716 | D60: 45716 | E60: SG | F60: CAT Tréso Plus | G60: 45659 | H60: 45690 | I60: - | J60: 0 | K60: 2860.274 | L60: 30509.59 | M60: 110.27397 | O60: 128252.05 | P60: 128252.05 | Q60: OK
A61: 8 2025 | B61: 45900 | D61: 45900 | E61: SG | F61: CAT Tréso Plus | G61: 45874 | H61: 45905 | I61: 0.02169863 | J61: 12000000 | K61: 18805.479 | M61: 3638.8128
A62: 9 2025 | B62: 45930 | D62: 45930 | E62: SG | F62: CAT Tréso Plus | G62: 45905 | H62: 45935 | I62: 0.02169863 | J62: 12000000 | K62: 21698.63 | L62: 22421.92 | M62: 4198.6301
A63: 10 2025 | B63: 45961 | D63: 45961 | E63: SG | F63: CAT Tréso Plus | G63: 45935 | H63: 45966 | I63: 0.02169863 | J63: 12000000 | K63: 22421.918 | L63: 21698.63 | M63: 4338.5845 | O63: OK 06/10
A64: 11 2025 | B64: 45991 | D64: 45991 | E64: SG | F64: CAT Tréso Plus | G64: 45966 | H64: 45996 | I64: 0.02169863 | J64: 12000000 | K64: 21698.63 | L64: 22421.92 | M64: 4198.6301 | O64: OK 05/11
A65: 12 2025 | B65: 46022 | D65: 46022 | E65: SG | F65: CAT Tréso Plus | G65: 45996 | H65: 46027 | I65: 0.02169863 | J65: 12000000 | K65: 22421.918 | L65: 21698.63 | M65: 4338.5845 | O65: OK 05/12
D66: Total 2025 CAT Tréso Plus | I66: 0.022849315 | K66: 139463.01 | L66: 148306.85 | M66: 17074.429
A68: 9 2025 | B68: 45930 | D68: 45930 | E68: SG | F68: CAT Tréso Plus n°2 | G68: 45911 | H68: 45941 | I68: 0.021205479 | J68: 20000000 | K68: 22383.562 | M68: 3911.3394
A69: 10 2025 | B69: 45961 | D69: 45961 | E69: SG | F69: CAT Tréso Plus n°2 | G69: 45941 | H69: 45972 | I69: 0.021205479 | J69: 20035342 | K69: 36562.184 | L69: 35342.47 | M69: 6388.9347
A70: 11 2025 | B70: 45991 | D70: 45991 | E70: SG | F70: CAT Tréso Plus n°2 | G70: 45972 | H70: 46002 | I70: 0.021205479 | J70: 20071928 | K70: 35445.865 | L70: 36585.08 | M70: 6193.8673 | O70: OK 11/11
A71: 12 2025 | B71: 46022 | D71: 46022 | E71: SG | F71: CAT Tréso Plus n°2 | G71: 46002 | H71: 46033 | I71: 0.021205479 | J71: 6000000 | K71: 20074.002 | L71: 35469.57 | M71: 3507.7633 | O71: OK fin décembre et OK montant reçus le 11/12 | P71: 107397.12 | Q71: 107397.12
D72: Total 2025 CAT Tréso Plus n°2 | I72: 0.021205479 | K72: 114465.61 | L72: 107397.12 | M72: 20001.905
A74: 1 2025 | B74: 45688 | D74: 45688 | E74: SG | F74: CAT €ster +0,25% | G74: 45667 | H74: 45698 | I74: 0.031366356 | J74: 45391300 | K74: 123759 | L74: 126189.69 | M74: 16366.279
A75: 2 2025 | B75: 45716 | D75: 45716 | E75: SG | F75: CAT €ster +0,20% | G75: 45667 | H75: 45698 | I75: 0.028647123 | J75: 40342601 | K75: 97333.854 | L75: 122601.54 | M75: 13807.779
A76: 3 2025 | B76: 45747 | D76: 45747 | E76: SG | F76: CAT €ster +0,20% | G76: 45698 | H76: 45726 | I76: 0.028647123 | J76: 0 | K76: 32102.763 | L76: 89887.74 | M76: 4087.0678 | O76: 603789.69 | P76: 603789.69 | Q76: OK
A77: 8 2025 | B77: 45900 | D77: 45900 | E77: SG | F77: CAT €ster +0,20% | G77: 45874 | H77: 45905 | I77: 0.021236055 | J77: 100000000 | K77: 153371.51 | M77: 26982.618
A78: 9 2025 | B78: 45930 | D78: 45930 | E78: SG | F78: CAT €ster +0,20% | G78: 45905 | H78: 45935 | I78: 0.021246904 | J78: 100000000 | K78: 177042.47 | L78: 182866.03 | M78: 31209.132
A79: 10 2025 | B79: 45961 | D79: 45961 | E79: SG | F79: CAT €ster +0,20% | G79: 45935 | H79: 45966 | I79: 0.021265644 | J79: 5000000 | K79: 37188.849 | L79: 177057.53 | M79: 6563.8493
A80: 11 2025 | B80: 45991 | D80: 45991 | E80: SG | F80: CAT €ster +0,20% | G80: 45966 | H80: 45966 | I80: 0.021265644 | J80: 0 | K80: 1476.7808 | L80: 9156.04 | M80: 261.50304 | O80: OK 05/11 et reconciliation
D81: Total 2025 CAT €ster + 20% | I81: 0.024810693 | K81: 622275.22 | L81: 707758.57 | M81: 99278.228
A83: 8 2025 | B83: 45900 | D83: 45900 | E83: SG | F83: CAT 1m | G83: 45880 | H83: 45911 | I83: 0.018443836 | J83: 90000000 | K83: 92219.178 | M83: 4719.1781
A84: 9 2025 | B84: 45930 | D84: 45930 | E84: SG | F84: CAT 1m | G84: 45880 | H84: 45911 | I84: 0.018443836 | J84: 0 | K84: 50720.548 | L84: 142939.73 | M84: 2595.5479
D85: Total 2025 CAT 1 m | I85: 0.018443836 | K85: 142939.73 | L85: 142939.73 | M85: 7314.726
A87: 1 2025 | B87: 45688 | D87: 45688 | E87: BCP | F87: CAT Euribor 3 mois | G87: 45642 | H87: 45732 | I87: 0.03236 | J87: 30000000 | K87: 83596.667 | L87: 0 | M87: 12555 | O87: réconciliation cloture CAT Tréso, ester et BCP
A88: 2 2025 | B88: 45716 | D88: 45716 | E88: BCP | F88: CAT Euribor 3 mois | G88: 45642 | H88: 45732 | I88: 0.03236 | J88: 30000000 | K88: 75506.667 | L88: 0 | M88: 16131.667
A89: 3 2025 | B89: 45747 | D89: 45747 | E89: BCP | F89: CAT Euribor 3 mois | G89: 45642 | H89: 45732 | I89: 0.03236 | J89: 0 | K89: 43146.667 | L89: 242700 | M89: 10646.667 | O89: 242700 | P89: 242700 | Q89: OK
D90: Total 2025 CAT Euribor 3 mois | I90: 0.03236 | K90: 202250 | L90: 242700 | M90: 39333.333
A92: 11 2025 | B92: 45991 | D92: 45991 | E92: SG | F92: CAT Arkea 12m | G92: 45966 | H92: 46361 | I92: 0.02579 | J92: 15000000 | K92: 26864.583 | M92: 8635.4167
A93: 12 2025 | B93: 46022 | D93: 46022 | E93: SG | F93: CAT Arkea 12m | G93: 46361 | H93: 46027 | I93: 0.02579 | J93: 15000000 | K93: 33312.083 | M93: 10707.917
D94: Total 2025 CAT ARKEA 12m | I94: 0.02579 | K94: 60176.667 | L94: 0 | M94: 19343.333
D96: Total 2025 CAT | K96: 1281570.2 | L96: 1349102.3 | M96: 202345.96
D99: OPCVM - UCITS
A101: 10 2025 | B101: 45961 | D101: 45961 | E101: SG | F101: codéis EUR | G101: 45940 | I101: 0.020776281 | J101: 51915241 | K101: 106697.5 | L101: 106697.5 | M101: 16053.304 | O101: Interets accrued are considered as paid
A102: 11 2025 | B102: 45991 | D102: 45991 | E102: SG | F102: codéis EUR | I102: 0.020810421 | J102: 36896168 | K102: 63988.9 | L102: 63988.9 | M102: 9234.119
A103: 12 2025 | B103: 46022 | D103: 46022 | E103: SG | F103: codéis EUR | I103: 0.02081446 | J103: 67027290 | K103: 91236 | L103: 91236 | M103: 15835.573
D104: Total 2025 Codéis | I104: 0.020800387 | K104: 261922.4 | L104: 261922.4 | M104: 41122.996
A106: 3 2025 | B106: 45747 | D106: 45747 | E106: Citi/SG | F106: Ellipsis** (Ester +0,28%) | G106: 45726 | I106: 0.027519979 | J106: 65087622 | K106: 87622.219 | L106: 0 | M106: 3280.4431
A107: 4 2025 | B107: 45777 | D107: 45777 | E107: Citi/SG | F107: Ellipsis** (Ester +0,28%) | I107: 0.026410448 | J107: 65245197 | K107: 157574.38 | L107: 0 | M107: 36669.679
A108: 5 2025 | B108: 45807 | D108: 45807 | E108: Citi/SG | F108: Ellipsis** (Ester +0,28%) | I108: 0.024442775 | J108: 65373664 | K108: 128467.88 | L108: 0 | M108: 25345.538
A109: 6 2025 | B109: 45838 | D109: 45838 | E109: Citi/SG | F109: Ellipsis** (Ester +0,28%) | I109: 0.02309858 | J109: 40462400 | K109: 88735.503 | L109: 162785.96 | M109: 16047.339
A110: 7 2025 | B110: 45869 | D110: 45869 | E110: Citi/SG | F110: Ellipsis** (Ester +0,28%) | I110: 0.02195573 | J110: 20514571 | K110: 52170.99 | L110: 161843.39 | M110: 16102.919
A111: 8 2025 | B111: 45898 | D111: 45900 | E111: Citi/SG | F111: Ellipsis** (Ester +0,28%) | I111: 0.02197401 | J111: 20550884 | K111: 36313.429 | M111: 6913.2344
A112: 9 2025 | B112: 45930 | D112: 45930 | E112: Citi/SG | F112: Ellipsis** (Ester +0,28%) | I112: 0.021956258 | J112: 63643589 | K112: 92704.31 | M112: 18815.475
A113: 10 2025 | B113: 45961 | D113: 45961 | E113: Citi/SG | F113: Ellipsis** (Ester +0,28%) | I113: 0.021967943 | J113: 0 | K113: 112626.23 | L113: 431585.59 | M113: 24915.361
D114: Total 2025 Ellipsis (Citi) | I114: 0.023665715 | K114: 756214.94 | L114: 756214.94 | M114: 148089.99 | O114: closed
A116: 10 2025 | B116: 45961 | D116: 45961 | E116: BNP/SG | F116: Ellipsis** (Ester +0,32%) | I116: 0.022461114 | J116: 1.0002496e+08 | K116: 24956.46 | M116: 0
A117: 11 2025 | B117: 45991 | D117: 45991 | E117: BNP/SG | F117: Ellipsis** (Ester +0,32%) | I117: 0.022425954 | J117: 1.001745e+08 | K117: 149543.67 | M117: 33527.911
A118: 12 2025 | B118: 46022 | D118: 46022 | E118: BNP/SG | F118: Ellipsis** (Ester +0,32%) | I118: 0.022419458 | J118: 1.0039285e+08 | K118: 218347.31 | M118: 42696.07
D119: Total 2025 Ellipsis (BNP) | I119: 0.022435509 | K119: 392847.44 | L119: 0 | M119: 76223.981 | O119: Interests are considered paid when cash out
A121: 1 2024 | B121: 45322 | D121: 45292 | E121: Total | K121: 679967.41 | L121: 720331.86
A122: 2 2024 | B122: 45351 | D122: 45323 | E122: Total | K122: 561355 | L122: 561355
A123: 3 2024 | B123: 45382 | D123: 45352 | E123: Total | K123: 575024.44 | L123: 521528.88
A124: 4 2024 | B124: 45412 | D124: 45383 | E124: Total | K124: 557987.78 | L124: 611472.77
A125: 5 2024 | B125: 45443 | D125: 45413 | E125: Total | K125: 536845 | L125: 539061.67
A126: 6 2024 | B126: 45473 | D126: 45444 | E126: Total | K126: 471724.44 | L126: 438295.27
...

Sheet OverNight €
C1: PLACEMENTS DE TRESORERIE AU JOUR LE JOUR | M1: € | T1: €
C2: Date de valeur pr mvt argent Date comptable pour solde | D2: Intérêts dû in fine ( à date d'échéance) | G2: Notice-Call Account Daily | M2: CAT Tréso plus (du 5 au 5) | T2: CAT Tréso plus n°2 (du 11 au 11) | AA2: CAT ARKEA 12m (du 05/11/25 au 05/11/26) | AH2: Ellipsis BNP | AM2: Codéis EUR
B3: mois | C3: Date départ | D3: Date échéance | E3: Nbj | G3: Emetteur | H3: Montant | I3: Taux | J3: Intérêts | K3: Cumul intérêts | M3: Emetteur | N3: Montant | O3: Taux | P3: Intérêts | Q3: Cumul intérêts | R3: Gain/NCA | T3: Emetteur | U3: Montant | V3: Taux | W3: Intérêts | X3: Cumul intérêts | Y3: Gain/NCA | AA3: Emetteur | AB3: Montant | AC3: Taux | AD3: Intérêts | AE3: Cumul intérêts | AF3: Gain/NCA | AH3: Valorisation | AI3: perf annuelle mensuelle annualisée | AJ3: +/- values quotidiennes | AK3: gain/NCA | AM3: Valorisation | AN3: Performance mensuelle annualisée | AO3: +/- values quotidiennes | AP3: gain/NCA | AR3: Total Montant | AS3: Taux BCE | AT3: Taux moyen | AU3: Total Interêts | AV3: Gain Placement/NCA
B5: 1 2025 | C5: 45657 | D5: 45658 | E5: 1 | G5: SG | H5: 31100000 | I5: 0.0275 | J5: =+H5*I5*E5/360 -> 2375.6944 | K5: =J5 -> 2375.6944 | M5: SG | N5: 12000000 | O5: =2.9%*360/365 -> 0.02860274 | P5: =+N5*O5*$E5/360 -> 953.42466 | Q5: =P5 -> 953.42466 | R5: =P5-(+N5*I5*$E5/360) -> 36.757991 | AR5: 1.1836511e+08 | AS5: 0.03 | AT5: 0.0307 | AU5: 10096.42 | AV5: 1054.64
B6: =CONCATENATE(MONTH(D6)," ",YEAR(D6)) -> 1 2025 | C6: =D5 -> 45658 | D6: =C6+1 -> 45659 | E6: =D6-C6 -> 1 | G6: SG | H6: =H5 -> 31100000 | I6: =I5 -> 0.0275 | J6: =+H6*I6*E6/360 -> 2375.6944 | K6: =J6+K5 -> 4751.3889 | M6: SG | N6: =N5 -> 12000000 | O6: =2.9%*360/365 -> 0.02860274 | P6: =+N6*O6*$E6/360 -> 953.42466 | Q6: =Q5+P6 -> 1906.8493 | R6: =P6-(+N6*I6*$E6/360) -> 36.757991 | AR6: 1.1836511e+08 | AS6: 0.03 | AT6: 0.0307 | AU6: 10096.42 | AV6: 1054.64
B7: =CONCATENATE(MONTH(D7)," ",YEAR(D7)) -> 1 2025 | C7: =D6 -> 45659 | D7: =D6+1 -> 45660 | E7: =D7-C7 -> 1 | G7: SG | H7: =H6-4900000 -> 26200000 | I7: =I6 -> 0.0275 | J7: =+H7*I7*E7/360 -> 2001.3889 | K7: =K6+J7 -> 6752.7778 | M7: SG | N7: =N6 -> 12000000 | O7: =2.9%*360/365 -> 0.02860274 | P7: =+N7*O7*$E7/360 -> 953.42466 | Q7: =Q6+P7 -> 2860.274 | R7: =P7-(+N7*I7*$E7/360) -> 36.757991 | AR7: 1.1346511e+08 | AS7: 0.03 | AT7: 0.0308 | AU7: 9722.12 | AV7: 1054.64
B8: =CONCATENATE(MONTH(D8)," ",YEAR(D8)) -> 1 2025 | C8: =D7 -> 45660 | D8: =D7+1 -> 45661 | E8: =D8-C8 -> 1 | G8: SG | H8: =H7-100000 -> 26100000 | I8: =I7 -> 0.0275 | J8: =+H8*I8*E8/360 -> 1993.75 | K8: =K7+J8 -> 8746.5278 | M8: SG | N8: =N7 -> 12000000 | O8: =2.9%*360/365 -> 0.02860274 | P8: =+N8*O8*$E8/360 -> 953.42466 | Q8: =Q7+P8 -> 3813.6986 | R8: =P8-(+N8*I8*$E8/360) -> 36.757991 | AR8: 1.1336511e+08 | AS8: 0.03 | AT8: 0.0308 | AU8: 9714.48 | AV8: 1054.64
B9: =CONCATENATE(MONTH(D9)," ",YEAR(D9)) -> 1 2025 | C9: =D8 -> 45661 | D9: =D8+1 -> 45662 | E9: =D9-C9 -> 1 | G9: SG | H9: =H8 -> 26100000 | I9: =I8 -> 0.0275 | J9: =+H9*I9*E9/360 -> 1993.75 | K9: =K8+J9 -> 10740.278 | M9: SG | N9: =N8 -> 12000000 | O9: =2.9%*360/365 -> 0.02860274 | P9: =+N9*O9*$E9/360 -> 953.42466 | Q9: =Q8+P9 -> 4767.1233 | R9: =P9-(+N9*I9*$E9/360) -> 36.757991 | AR9: 1.1336511e+08 | AS9: 0.03 | AT9: 0.0308 | AU9: 9714.48 | AV9: 1054.64
B10: =CONCATENATE(MONTH(D10)," ",YEAR(D10)) -> 1 2025 | C10: =D9 -> 45662 | D10: =D9+1 -> 45663 | E10: =D10-C10 -> 1 | G10: SG | H10: =H9 -> 26100000 | I10: =I9 -> 0.0275 | J10: =+H10*I10*E10/360 -> 1993.75 | K10: =K9+J10 -> 12734.028 | M10: SG | N10: =N9 -> 12000000 | O10: =2.9%*360/365 -> 0.02860274 | P10: =+N10*O10*$E10/360 -> 953.42466 | Q10: =Q9+P10 -> 5720.5479 | R10: =P10-(+N10*I10*$E10/360) -> 36.757991 | AR10: 1.1336511e+08 | AS10: 0.03 | AT10: 0.0308 | AU10: 9714.48 | AV10: 1054.64
B11: =CONCATENATE(MONTH(D11)," ",YEAR(D11)) -> 1 2025 | C11: =D10 -> 45663 | D11: =D10+1 -> 45664 | E11: =D11-C11 -> 1 | G11: SG | H11: =H10 -> 26100000 | I11: =I10 -> 0.0275 | J11: =+H11*I11*E11/360 -> 1993.75 | K11: =K10+J11 -> 14727.778 | M11: SG | N11: =N10 -> 12000000 | O11: =O10 -> 0.02860274 | P11: =+N11*O11*$E11/360 -> 953.42466 | Q11: =Q10+P11 -> 6673.9726 | R11: =P11-(+N11*I11*$E11/360) -> 36.757991 | AR11: 1.1336511e+08 | AS11: 0.03 | AT11: 0.0308 | AU11: 9714.48 | AV11: 1054.64
B12: =CONCATENATE(MONTH(D12)," ",YEAR(D12)) -> 1 2025 | C12: =D11 -> 45664 | D12: =D11+1 -> 45665 | E12: =D12-C12 -> 1 | G12: SG | H12: =H11 -> 26100000 | I12: =I11 -> 0.0275 | J12: =+H12*I12*E12/360 -> 1993.75 | K12: =K11+J12 -> 16721.528 | M12: SG | N12: =N11 -> 12000000 | O12: =O11 -> 0.02860274 | P12: =+N12*O12*$E12/360 -> 953.42466 | Q12: =Q11+P12 -> 7627.3973 | R12: =P12-(+N12*I12*$E12/360) -> 36.757991 | AR12: 1.1336511e+08 | AS12: 0.03 | AT12: 0.0308 | AU12: 9714.48 | AV12: 1054.64
B13: =CONCATENATE(MONTH(D13)," ",YEAR(D13)) -> 1 2025 | C13: =D12 -> 45665 | D13: =D12+1 -> 45666 | E13: =D13-C13 -> 1 | G13: SG | H13: =H12 -> 26100000 | I13: =I12 -> 0.0275 | J13: =+H13*I13*E13/360 -> 1993.75 | K13: =K12+J13 -> 18715.278 | M13: SG | N13: =N12 -> 12000000 | O13: =O12 -> 0.02860274 | P13: =+N13*O13*$E13/360 -> 953.42466 | Q13: =Q12+P13 -> 8580.8219 | R13: =P13-(+N13*I13*$E13/360) -> 36.757991 | AR13: 1.1336511e+08 | AS13: 0.03 | AT13: 0.0308 | AU13: 9714.48 | AV13: 1054.64
B14: =CONCATENATE(MONTH(D14)," ",YEAR(D14)) -> 1 2025 | C14: =D13 -> 45666 | D14: =D13+1 -> 45667 | E14: =D14-C14 -> 1 | G14: SG | H14: =H13+300000 -> 26400000 | I14: =I13 -> 0.0275 | J14: =+H14*I14*E14/360 -> 2016.6667 | K14: =K13+J14 -> 20731.944 | M14: SG | N14: =N13 -> 12000000 | O14: =O13 -> 0.02860274 | P14: =+N14*O14*$E14/360 -> 953.42466 | Q14: =Q13+P14 -> 9534.2466 | R14: =P14-(+N14*I14*$E14/360) -> 36.757991 | AR14: 1.1366511e+08 | AS14: 0.03 | AT14: 0.0308 | AU14: 9737.39 | AV14: 1054.64
B15: =CONCATENATE(MONTH(D15)," ",YEAR(D15)) -> 1 2025 | C15: =D14 -> 45667 | D15: =D14+1 -> 45668 | E15: =D15-C15 -> 1 | G15: SG | H15: =H14 -> 26400000 | I15: =I14 -> 0.0275 | J15: =+H15*I15*E15/360 -> 2016.6667 | K15: =K14+J15 -> 22748.611 | M15: SG | N15: =N14 -> 12000000 | O15: =O14 -> 0.02860274 | P15: =+N15*O15*$E15/360 -> 953.42466 | Q15: =Q14+P15 -> 10487.671 | R15: =P15-(+N15*I15*$E15/360) -> 36.757991 | AR15: 1.137913e+08 | AS15: 0.03 | AT15: 0.0304 | AU15: 9621.65 | AV15: 929.26
B16: =CONCATENATE(MONTH(D16)," ",YEAR(D16)) -> 1 2025 | C16: =D15 -> 45668 | D16: =D15+1 -> 45669 | E16: =D16-C16 -> 1 | G16: SG | H16: =H15 -> 26400000 | I16: =I15 -> 0.0275 | J16: =+H16*I16*E16/360 -> 2016.6667 | K16: =K15+J16 -> 24765.278 | M16: SG | N16: =N15 -> 12000000 | O16: =O15 -> 0.02860274 | P16: =+N16*O16*$E16/360 -> 953.42466 | Q16: =Q15+P16 -> 11441.096 | R16: =P16-(+N16*I16*$E16/360) -> 36.757991 | AR16: 1.137913e+08 | AS16: 0.03 | AT16: 0.0304 | AU16: 9621.65 | AV16: 929.26
B17: =CONCATENATE(MONTH(D17)," ",YEAR(D17)) -> 1 2025 | C17: =D16 -> 45669 | D17: =D16+1 -> 45670 | E17: =D17-C17 -> 1 | G17: SG | H17: =H16 -> 26400000 | I17: =I16 -> 0.0275 | J17: =+H17*I17*E17/360 -> 2016.6667 | K17: =K16+J17 -> 26781.944 | M17: SG | N17: =N16 -> 12000000 | O17: =O16 -> 0.02860274 | P17: =+N17*O17*$E17/360 -> 953.42466 | Q17: =Q16+P17 -> 12394.521 | R17: =P17-(+N17*I17*$E17/360) -> 36.757991 | AR17: 1.137913e+08 | AS17: 0.03 | AT17: 0.0304 | AU17: 9621.65 | AV17: 929.26
B18: =CONCATENATE(MONTH(D18)," ",YEAR(D18)) -> 1 2025 | C18: =D17 -> 45670 | D18: =D17+1 -> 45671 | E18: =D18-C18 -> 1 | G18: SG | H18: =H17-1700000 -> 24700000 | I18: =I17 -> 0.0275 | J18: =+H18*I18*E18/360 -> 1886.8056 | K18: =K17+J18 -> 28668.75 | M18: SG | N18: =N17 -> 12000000 | O18: =O17 -> 0.02860274 | P18: =+N18*O18*$E18/360 -> 953.42466 | Q18: =Q17+P18 -> 13347.945 | R18: =P18-(+N18*I18*$E18/360) -> 36.757991 | AR18: 1.120913e+08 | AS18: 0.03 | AT18: 0.0305 | AU18: 9491.78 | AV18: 929.26
B19: =CONCATENATE(MONTH(D19)," ",YEAR(D19)) -> 1 2025 | C19: =D18 -> 45671 | D19: =D18+1 -> 45672 | E19: =D19-C19 -> 1 | G19: SG | H19: =H18 -> 24700000 | I19: =I18 -> 0.0275 | J19: =+H19*I19*E19/360 -> 1886.8056 | K19: =K18+J19 -> 30555.556 | M19: SG | N19: =N18 -> 12000000 | O19: =O18 -> 0.02860274 | P19: =+N19*O19*$E19/360 -> 953.42466 | Q19: =Q18+P19 -> 14301.37 | R19: =P19-(+N19*I19*$E19/360) -> 36.757991 | AR19: 1.120913e+08 | AS19: 0.03 | AT19: 0.0305 | AU19: 9491.78 | AV19: 929.26
B20: =CONCATENATE(MONTH(D20)," ",YEAR(D20)) -> 1 2025 | C20: =D19 -> 45672 | D20: =D19+1 -> 45673 | E20: =D20-C20 -> 1 | G20: SG | H20: =H19 -> 24700000 | I20: =I19 -> 0.0275 | J20: =+H20*I20*E20/360 -> 1886.8056 | K20: =K19+J20 -> 32442.361 | M20: SG | N20: =N19 -> 12000000 | O20: =O19 -> 0.02860274 | P20: =+N20*O20*$E20/360 -> 953.42466 | Q20: =Q19+P20 -> 15254.795 | R20: =P20-(+N20*I20*$E20/360) -> 36.757991 | AR20: 1.120913e+08 | AS20: 0.03 | AT20: 0.0305 | AU20: 9491.78 | AV20: 929.26
B21: =CONCATENATE(MONTH(D21)," ",YEAR(D21)) -> 1 2025 | C21: =D20 -> 45673 | D21: =D20+1 -> 45674 | E21: =D21-C21 -> 1 | G21: SG | H21: =H20-450000 -> 24250000 | I21: =I20 -> 0.0275 | J21: =+H21*I21*E21/360 -> 1852.4306 | K21: =K20+J21 -> 34294.792 | M21: SG | N21: =N20 -> 12000000 | O21: =O20 -> 0.02860274 | P21: =+N21*O21*$E21/360 -> 953.42466 | Q21: =Q20+P21 -> 16208.219 | R21: =P21-(+N21*I21*$E21/360) -> 36.757991 | AR21: 1.116413e+08 | AS21: 0.03 | AT21: 0.0305 | AU21: 9457.41 | AV21: 929.26
B22: =CONCATENATE(MONTH(D22)," ",YEAR(D22)) -> 1 2025 | C22: =D21 -> 45674 | D22: =D21+1 -> 45675 | E22: =D22-C22 -> 1 | G22: SG | H22: =H21+50000 -> 24300000 | I22: =I21 -> 0.0275 | J22: =+H22*I22*E22/360 -> 1856.25 | K22: =K21+J22 -> 36151.042 | M22: SG | N22: =N21 -> 12000000 | O22: =O21 -> 0.02860274 | P22: =+N22*O22*$E22/360 -> 953.42466 | Q22: =Q21+P22 -> 17161.644 | R22: =P22-(+N22*I22*$E22/360) -> 36.757991 | AR22: 1.116913e+08 | AS22: 0.03 | AT22: 0.0305 | AU22: 9461.23 | AV22: 929.26
B23: =CONCATENATE(MONTH(D23)," ",YEAR(D23)) -> 1 2025 | C23: =D22 -> 45675 | D23: =D22+1 -> 45676 | E23: =D23-C23 -> 1 | G23: SG | H23: =H22 -> 24300000 | I23: =I22 -> 0.0275 | J23: =+H23*I23*E23/360 -> 1856.25 | K23: =K22+J23 -> 38007.292 | M23: SG | N23: =N22 -> 12000000 | O23: =O22 -> 0.02860274 | P23: =+N23*O23*$E23/360 -> 953.42466 | Q23: =Q22+P23 -> 18115.068 | R23: =P23-(+N23*I23*$E23/360) -> 36.757991 | AR23: 1.116913e+08 | AS23: 0.03 | AT23: 0.0305 | AU23: 9461.23 | AV23: 929.26
B24: =CONCATENATE(MONTH(D24)," ",YEAR(D24)) -> 1 2025 | C24: =D23 -> 45676 | D24: =D23+1 -> 45677 | E24: =D24-C24 -> 1 | G24: SG | H24: =H23 -> 24300000 | I24: =I23 -> 0.0275 | J24: =+H24*I24*E24/360 -> 1856.25 | K24: =K23+J24 -> 39863.542 | M24: SG | N24: =N23 -> 12000000 | O24: =O23 -> 0.02860274 | P24: =+N24*O24*$E24/360 -> 953.42466 | Q24: =Q23+P24 -> 19068.493 | R24: =P24-(+N24*I24*$E24/360) -> 36.757991 | AR24: 1.116913e+08 | AS24: 0.03 | AT24: 0.0305 | AU24: 9461.23 | AV24: 929.26
B25: =CONCATENATE(MONTH(D25)," ",YEAR(D25)) -> 1 2025 | C25: =D24 -> 45677 | D25: =D24+1 -> 45678 | E25: =D25-C25 -> 1 | G25: SG | H25: =H24 -> 24300000 | I25: =I24 -> 0.0275 | J25: =+H25*I25*E25/360 -> 1856.25 | K25: =K24+J25 -> 41719.792 | M25: SG | N25: =N24 -> 12000000 | O25: =O24 -> 0.02860274 | P25: =+N25*O25*$E25/360 -> 953.42466 | Q25: =Q24+P25 -> 20021.918 | R25: =P25-(+N25*I25*$E25/360) -> 36.757991 | AR25: 1.116913e+08 | AS25: 0.03 | AT25: 0.0305 | AU25: 9461.23 | AV25: 929.26
B26: =CONCATENATE(MONTH(D26)," ",YEAR(D26)) -> 1 2025 | C26: =D25 -> 45678 | D26: =D25+1 -> 45679 | E26: =D26-C26 -> 1 | G26: SG | H26: =H25-5350000 -> 18950000 | I26: =I25 -> 0.0275 | J26: =+H26*I26*E26/360 -> 1447.5694 | K26: =K25+J26 -> 43167.361 | M26: SG | N26: =N25 -> 12000000 | O26: =O25 -> 0.02860274 | P26: =+N26*O26*$E26/360 -> 953.42466 | Q26: =Q25+P26 -> 20975.342 | R26: =P26-(+N26*I26*$E26/360) -> 36.757991 | AR26: 1.063413e+08 | AS26: 0.03 | AT26: 0.0306 | AU26: 9052.55 | AV26: 929.26
B27: =CONCATENATE(MONTH(D27)," ",YEAR(D27)) -> 1 2025 | C27: =D26 -> 45679 | D27: =D26+1 -> 45680 | E27: =D27-C27 -> 1 | G27: SG | H27: =H26 -> 18950000 | I27: =I26 -> 0.0275 | J27: =+H27*I27*E27/360 -> 1447.5694 | K27: =K26+J27 -> 44614.931 | M27: SG | N27: =N26 -> 12000000 | O27: =O26 -> 0.02860274 | P27: =+N27*O27*$E27/360 -> 953.42466 | Q27: =Q26+P27 -> 21928.767 | R27: =P27-(+N27*I27*$E27/360) -> 36.757991 | AR27: 1.063413e+08 | AS27: 0.03 | AT27: 0.0306 | AU27: 9052.55 | AV27: 929.26
B28: =CONCATENATE(MONTH(D28)," ",YEAR(D28)) -> 1 2025 | C28: =D27 -> 45680 | D28: =D27+1 -> 45681 | E28: =D28-C28 -> 1 | G28: SG | H28: =H27 -> 18950000 | I28: =I27 -> 0.0275 | J28: =+H28*I28*E28/360 -> 1447.5694 | K28: =K27+J28 -> 46062.5 | M28: SG | N28: =N27 -> 12000000 | O28: =O27 -> 0.02860274 | P28: =+N28*O28*$E28/360 -> 953.42466 | Q28: =Q27+P28 -> 22882.192 | R28: =P28-(+N28*I28*$E28/360) -> 36.757991 | AR28: 1.063413e+08 | AS28: 0.03 | AT28: 0.0306 | AU28: 9052.55 | AV28: 929.26
B29: =CONCATENATE(MONTH(D29)," ",YEAR(D29)) -> 1 2025 | C29: =D28 -> 45681 | D29: =D28+1 -> 45682 | E29: =D29-C29 -> 1 | G29: SG | H29: =H28 -> 18950000 | I29: =I28 -> 0.0275 | J29: =+H29*I29*E29/360 -> 1447.5694 | K29: =K28+J29 -> 47510.069 | M29: SG | N29: =N28 -> 12000000 | O29: =O28 -> 0.02860274 | P29: =+N29*O29*$E29/360 -> 953.42466 | Q29: =Q28+P29 -> 23835.616 | R29: =P29-(+N29*I29*$E29/360) -> 36.757991 | AR29: 1.063413e+08 | AS29: 0.03 | AT29: 0.0306 | AU29: 9052.55 | AV29: 929.26
B30: =CONCATENATE(MONTH(D30)," ",YEAR(D30)) -> 1 2025 | C30: =D29 -> 45682 | D30: =D29+1 -> 45683 | E30: =D30-C30 -> 1 | G30: SG | H30: =H29 -> 18950000 | I30: =I29 -> 0.0275 | J30: =+H30*I30*E30/360 -> 1447.5694 | K30: =K29+J30 -> 48957.639 | M30: SG | N30: =N29 -> 12000000 | O30: =O29 -> 0.02860274 | P30: =+N30*O30*$E30/360 -> 953.42466 | Q30: =Q29+P30 -> 24789.041 | R30: =P30-(+N30*I30*$E30/360) -> 36.757991 | AR30: 1.063413e+08 | AS30: 0.03 | AT30: 0.0306 | AU30: 9052.55 | AV30: 929.26
B31: =CONCATENATE(MONTH(D31)," ",YEAR(D31)) -> 1 2025 | C31: =D30 -> 45683 | D31: =D30+1 -> 45684 | E31: =D31-C31 -> 1 | G31: SG | H31: =H30 -> 18950000 | I31: =I30 -> 0.0275 | J31: =+H31*I31*E31/360 -> 1447.5694 | K31: =K30+J31 -> 50405.208 | M31: SG | N31: =N30 -> 12000000 | O31: =O30 -> 0.02860274 | P31: =+N31*O31*$E31/360 -> 953.42466 | Q31: =Q30+P31 -> 25742.466 | R31: =P31-(+N31*I31*$E31/360) -> 36.757991 | AR31: 1.063413e+08 | AS31: 0.03 | AT31: 0.0306 | AU31: 9052.55 | AV31: 929.26
B32: =CONCATENATE(MONTH(D32)," ",YEAR(D32)) -> 1 2025 | C32: =D31 -> 45684 | D32: =D31+1 -> 45685 | E32: =D32-C32 -> 1 | G32: SG | H32: =H31-6700000 -> 12250000 | I32: =I31 -> 0.0275 | J32: =+H32*I32*E32/360 -> 935.76389 | K32: =K31+J32 -> 51340.972 | M32: SG | N32: =N31 -> 12000000 | O32: =O31 -> 0.02860274 | P32: =+N32*O32*$E32/360 -> 953.42466 | Q32: =Q31+P32 -> 26695.89 | R32: =P32-(+N32*I32*$E32/360) -> 36.757991 | AR32: 99641300 | AS32: 0.03 | AT32: 0.0309 | AU32: 8540.74 | AV32: 929.26
B33: =CONCATENATE(MONTH(D33)," ",YEAR(D33)) -> 1 2025 | C33: =D32 -> 45685 | D33: =D32+1 -> 45686 | E33: =D33-C33 -> 1 | G33: SG | H33: =H32-400000+50000 -> 11900000 | I33: =I32 -> 0.0275 | J33: =+H33*I33*E33/360 -> 909.02778 | K33: =K32+J33 -> 52250 | M33: SG | N33: =N32 -> 12000000 | O33: =O32 -> 0.02860274 | P33: =+N33*O33*$E33/360 -> 953.42466 | Q33: =Q32+P33 -> 27649.315 | R33: =P33-(+N33*I33*$E33/360) -> 36.757991 | AR33: 99291300 | AS33: 0.03 | AT33: 0.0309 | AU33: 8514.01 | AV33: 929.26
B34: =CONCATENATE(MONTH(D34)," ",YEAR(D34)) -> 1 2025 | C34: =D33 -> 45686 | D34: =D33+1 -> 45687 | E34: =D34-C34 -> 1 | G34: SG | H34: =H33 -> 11900000 | I34: =I33 -> 0.0275 | J34: =+H34*I34*E34/360 -> 909.02778 | K34: =K33+J34 -> 53159.028 | M34: SG | N34: =N33 -> 12000000 | O34: =O33 -> 0.02860274 | P34: =+N34*O34*$E34/360 -> 953.42466 | Q34: =Q33+P34 -> 28602.74 | R34: =P34-(+N34*I34*$E34/360) -> 36.757991 | AR34: 99291300 | AS34: 0.03 | AT34: 0.0309 | AU34: 8514.01 | AV34: 929.26
B35: =CONCATENATE(MONTH(D35)," ",YEAR(D35)) -> 1 2025 | C35: =D34 -> 45687 | D35: =D34+1 -> 45688 | E35: =D35-C35 -> 1 | G35: SG | H35: =H34+50000 -> 11950000 | I35: =I34 -> 0.0275 | J35: =+H35*I35*E35/360 -> 912.84722 | K35: =K34+J35 -> 54071.875 | M35: SG | N35: =N34 -> 12000000 | O35: =O34 -> 0.02860274 | P35: =+N35*O35*$E35/360 -> 953.42466 | Q35: =Q34+P35 -> 29556.164 | R35: =P35-(+N35*I35*$E35/360) -> 36.757991 | AR35: 99341300 | AS35: 0.03 | AT35: 0.0309 | AU35: 8517.83 | AV35: 929.26
B36: =CONCATENATE(MONTH(D36)," ",YEAR(D36)) -> 2 2025 | C36: =D35 -> 45688 | D36: =D35+1 -> 45689 | E36: =D36-C36 -> 1 | G36: SG | H36: =H35+50000 -> 12000000 | I36: =I35 -> 0.0275 | J36: =+H36*I36*E36/360 -> 916.66667 | K36: =K35+J36 -> 54988.542 | M36: SG | N36: =N35 -> 12000000 | O36: =O35 -> 0.02860274 | P36: =+N36*O36*$E36/360 -> 953.42466 | Q36: =Q35+P36 -> 30509.589 | R36: =P36-(+N36*I36*$E36/360) -> 36.757991 | AR36: 99391300 | AS36: 0.03 | AT36: 0.0309 | AU36: 8521.65 | AV36: 929.26
B37: =CONCATENATE(MONTH(D37)," ",YEAR(D37)) -> 2 2025 | C37: =D36 -> 45689 | D37: =D36+1 -> 45690 | E37: =D37-C37 -> 1 | G37: SG | H37: =H36 -> 12000000 | I37: =I36 -> 0.0275 | J37: =+H37*I37*E37/360 -> 916.66667 | K37: =K36+J37 -> 55905.208 | M37: SG | N37: =N36 -> 12000000 | O37: =O36 -> 0.02860274 | P37: =+N37*O37*$E37/360 -> 953.42466 | Q37: =Q36+P37 -> 31463.014 | R37: =P37-(+N37*I37*$E37/360) -> 36.757991 | AR37: 99391300 | AS37: 0.03 | AT37: 0.0309 | AU37: 8521.65 | AV37: 929.26
B38: =CONCATENATE(MONTH(D38)," ",YEAR(D38)) -> 2 2025 | C38: =D37 -> 45690 | D38: =D37+1 -> 45691 | E38: =D38-C38 -> 1 | G38: SG | H38: =H37 -> 12000000 | I38: =I37 -> 0.0275 | J38: =+H38*I38*E38/360 -> 916.66667 | K38: =K37+J38 -> 56821.875 | M38: SG | N38: =N37 -> 12000000 | O38: =O37 -> 0.02860274 | P38: =+N38*O38*$E38/360 -> 953.42466 | Q38: =Q37+P38 -> 32416.438 | R38: =P38-(+N38*I38*$E38/360) -> 36.757991 | AR38: 99391300 | AS38: 0.03 | AT38: 0.0309 | AU38: 8521.65 | AV38: 929.26
B39: =CONCATENATE(MONTH(D39)," ",YEAR(D39)) -> 2 2025 | C39: =D38 -> 45691 | D39: =D38+1 -> 45692 | E39: =D39-C39 -> 1 | G39: SG | H39: =H38+9820000 -> 21820000 | I39: =I38 -> 0.0275 | J39: =+H39*I39*E39/360 -> 1666.8056 | K39: =K38+J39 -> 58488.681 | M39: SG | AR39: 97211300 | AS39: 0.03 | AT39: 0.0308 | AU39: 8318.36 | AV39: 892.5
B40: =CONCATENATE(MONTH(D40)," ",YEAR(D40)) -> 2 2025 | C40: =D39 -> 45692 | D40: =D39+1 -> 45693 | E40: =D40-C40 -> 1 | G40: SG | H40: =H39+3120000 -> 24940000 | I40: =I39 -> 0.0275 | J40: =+H40*I40*E40/360 -> 1905.1389 | K40: =K39+J40 -> 60393.819 | M40: SG | AR40: 1.003313e+08 | AS40: 0.03 | AT40: 0.0307 | AU40: 8556.69 | AV40: 892.5
B41: =CONCATENATE(MONTH(D41)," ",YEAR(D41)) -> 2 2025 | C41: =D40 -> 45693 | D41: =D40+1 -> 45694 | E41: =D41-C41 -> 1 | G41: SG | H41: =H40 -> 24940000 | I41: 0.025 | J41: =+H41*I41*E41/360 -> 1731.9444 | K41: =K40+J41 -> 62125.764 | M41: SG | AR41: 1.003313e+08 | AS41: 0.0275 | AT41: 0.0301 | AU41: 8383.5 | AV41: 1416.05
B42: =CONCATENATE(MONTH(D42)," ",YEAR(D42)) -> 2 2025 | C42: =D41 -> 45694 | D42: =D41+1 -> 45695 | E42: =D42-C42 -> 1 | G42: SG | H42: =H41 -> 24940000 | I42: =I41 -> 0.025 | J42: =+H42*I42*E42/360 -> 1731.9444 | K42: =K41+J42 -> 63857.708 | M42: SG | AR42: 1.003313e+08 | AS42: 0.0275 | AT42: 0.0301 | AU42: 8383.5 | AV42: 1416.05
B43: =CONCATENATE(MONTH(D43)," ",YEAR(D43)) -> 2 2025 | C43: =D42 -> 45695 | D43: =D42+1 -> 45696 | E43: =D43-C43 -> 1 | G43: SG | H43: =H42 -> 24940000 | I43: =I42 -> 0.025 | J43: =+H43*I43*E43/360 -> 1731.9444 | K43: =K42+J43 -> 65589.653 | M43: SG | AR43: 1.003313e+08 | AS43: 0.0275 | AT43: 0.0301 | AU43: 8383.5 | AV43: 1416.05
B44: =CONCATENATE(MONTH(D44)," ",YEAR(D44)) -> 2 2025 | C44: =D43 -> 45696 | D44: =D43+1 -> 45697 | E44: =D44-C44 -> 1 | G44: SG | H44: =H43 -> 24940000 | I44: =I43 -> 0.025 | J44: =+H44*I44*E44/360 -> 1731.9444 | K44: =K43+J44 -> 67321.597 | M44: SG | AR44: 1.003313e+08 | AS44: 0.0275 | AT44: 0.0301 | AU44: 8383.5 | AV44: 1416.05
B45: =CONCATENATE(MONTH(D45)," ",YEAR(D45)) -> 2 2025 | C45: =D44 -> 45697 | D45: =D44+1 -> 45698 | E45: =D45-C45 -> 1 | G45: SG | H45: =H44 -> 24940000 | I45: =I44 -> 0.025 | J45: =+H45*I45*E45/360 -> 1731.9444 | K45: =K44+J45 -> 69053.542 | M45: SG | AR45: 1.003313e+08 | AS45: 0.0275 | AT45: 0.0301 | AU45: 8383.5 | AV45: 1416.05
B46: =CONCATENATE(MONTH(D46)," ",YEAR(D46)) -> 2 2025 | C46: =D45 -> 45698 | D46: =D45+1 -> 45699 | E46: =D46-C46 -> 1 | G46: SG | H46: =H45+5100000 -> 30040000 | I46: =I45 -> 0.025 | J46: =+H46*I46*E46/360 -> 2086.1111 | K46: =K45+J46 -> 71139.653 | M46: SG | AR46: 1.003826e+08 | AS46: 0.0275 | AT46: 0.0287 | AU46: 7993.05 | AV46: 1022.04
B47: =CONCATENATE(MONTH(D47)," ",YEAR(D47)) -> 2 2025 | C47: =D46 -> 45699 | D47: =D46+1 -> 45700 | E47: =D47-C47 -> 1 | G47: SG | H47: =H46-1800000 -> 28240000 | I47: =I46 -> 0.025 | J47: =+H47*I47*E47/360 -> 1961.1111 | K47: =K46+J47 -> 73100.764 | M47: SG | AR47: 98582601 | AS47: 0.0275 | AT47: 0.0287 | AU47: 7868.05 | AV47: 1022.04
B48: =CONCATENATE(MONTH(D48)," ",YEAR(D48)) -> 2 2025 | C48: =D47 -> 45700 | D48: =D47+1 -> 45701 | E48: =D48-C48 -> 1 | G48: SG | H48: =H47 -> 28240000 | I48: =I47 -> 0.025 | J48: =+H48*I48*E48/360 -> 1961.1111 | K48: =K47+J48 -> 75061.875 | M48: SG | AR48: 98582601 | AS48: 0.0275 | AT48: 0.0287 | AU48: 7868.05 | AV48: 1022.04
B49: =CONCATENATE(MONTH(D49)," ",YEAR(D49)) -> 2 2025 | C49: =D48 -> 45701 | D49: =D48+1 -> 45702 | E49: =D49-C49 -> 1 | G49: SG | H49: =H48+360000 -> 28600000 | I49: =I48 -> 0.025 | J49: =+H49*I49*E49/360 -> 1986.1111 | K49: =K48+J49 -> 77047.986 | M49: SG | AR49: 98942601 | AS49: 0.0275 | AT49: 0.0287 | AU49: 7893.05 | AV49: 1022.04
B50: =CONCATENATE(MONTH(D50)," ",YEAR(D50)) -> 2 2025 | C50: =D49 -> 45702 | D50: =D49+1 -> 45703 | E50: =D50-C50 -> 1 | G50: SG | H50: =H49 -> 28600000 | I50: =I49 -> 0.025 | J50: =+H50*I50*E50/360 -> 1986.1111 | K50: =K49+J50 -> 79034.097 | M50: SG | AR50: 98942601 | AS50: 0.0275 | AT50: 0.0287 | AU50: 7893.05 | AV50: 1022.04
B51: =CONCATENATE(MONTH(D51)," ",YEAR(D51)) -> 2 2025 | C51: =D50 -> 45703 | D51: =D50+1 -> 45704 | E51: =D51-C51 -> 1 | G51: SG | H51: =H50 -> 28600000 | I51: =I50 -> 0.025 | J51: =+H51*I51*E51/360 -> 1986.1111 | K51: =K50+J51 -> 81020.208 | M51: SG | AR51: 98942601 | AS51: 0.0275 | AT51: 0.0287 | AU51: 7893.05 | AV51: 1022.04
B52: =CONCATENATE(MONTH(D52)," ",YEAR(D52)) -> 2 2025 | C52: =D51 -> 45704 | D52: =D51+1 -> 45705 | E52: =D52-C52 -> 1 | G52: SG | H52: =H51 -> 28600000 | I52: =I51 -> 0.025 | J52: =+H52*I52*E52/360 -> 1986.1111 | K52: =K51+J52 -> 83006.319 | M52: SG | AR52: 98942601 | AS52: 0.0275 | AT52: 0.0287 | AU52: 7893.05 | AV52: 1022.04
B53: =CONCATENATE(MONTH(D53)," ",YEAR(D53)) -> 2 2025 | C53: =D52 -> 45705 | D53: =D52+1 -> 45706 | E53: =D53-C53 -> 1 | G53: SG | H53: =H52-240000 -> 28360000 | I53: =I52 -> 0.025 | J53: =+H53*I53*E53/360 -> 1969.4444 | K53: =K52+J53 -> 84975.764 | M53: SG | AR53: 98702601 | AS53: 0.0275 | AT53: 0.0287 | AU53: 7876.39 | AV53: 1022.04
B54: =CONCATENATE(MONTH(D54)," ",YEAR(D54)) -> 2 2025 | C54: =D53 -> 45706 | D54: =D53+1 -> 45707 | E54: =D54-C54 -> 1 | G54: SG | H54: =H53 -> 28360000 | I54: =I53 -> 0.025 | J54: =+H54*I54*E54/360 -> 1969.4444 | K54: =K53+J54 -> 86945.208 | M54: SG | AR54: 98702601 | AS54: 0.0275 | AT54: 0.0287 | AU54: 7876.39 | AV54: 1022.04
B55: =CONCATENATE(MONTH(D55)," ",YEAR(D55)) -> 2 2025 | C55: =D54 -> 45707 | D55: =D54+1 -> 45708 | E55: =D55-C55 -> 1 | G55: SG | H55: =H54 -> 28360000 | I55: =I54 -> 0.025 | J55: =+H55*I55*E55/360 -> 1969.4444 | K55: =K54+J55 -> 88914.653 | M55: SG | AR55: 98702601 | AS55: 0.0275 | AT55: 0.0287 | AU55: 7876.39 | AV55: 1022.04
B56: =CONCATENATE(MONTH(D56)," ",YEAR(D56)) -> 2 2025 | C56: =D55 -> 45708 | D56: =D55+1 -> 45709 | E56: =D56-C56 -> 1 | G56: SG | H56: =H55 -> 28360000 | I56: =I55 -> 0.025 | J56: =+H56*I56*E56/360 -> 1969.4444 | K56: =K55+J56 -> 90884.097 | M56: SG | AR56: 98702601 | AS56: 0.0275 | AT56: 0.0287 | AU56: 7876.39 | AV56: 1022.04
B57: =CONCATENATE(MONTH(D57)," ",YEAR(D57)) -> 2 2025 | C57: =D56 -> 45709 | D57: =D56+1 -> 45710 | E57: =D57-C57 -> 1 | G57: SG | H57: =H56 -> 28360000 | I57: =I56 -> 0.025 | J57: =+H57*I57*E57/360 -> 1969.4444 | K57: =K56+J57 -> 92853.542 | M57: SG | AR57: 98702601 | AS57: 0.0275 | AT57: 0.0287 | AU57: 7876.39 | AV57: 1022.04
B58: =CONCATENATE(MONTH(D58)," ",YEAR(D58)) -> 2 2025 | C58: =D57 -> 45710 | D58: =D57+1 -> 45711 | E58: =D58-C58 -> 1 | G58: SG | H58: =H57 -> 28360000 | I58: =I57 -> 0.025 | J58: =+H58*I58*E58/360 -> 1969.4444 | K58: =K57+J58 -> 94822.986 | M58: SG | AR58: 98702601 | AS58: 0.0275 | AT58: 0.0287 | AU58: 7876.39 | AV58: 1022.04
B59: =CONCATENATE(MONTH(D59)," ",YEAR(D59)) -> 2 2025 | C59: =D58 -> 45711 | D59: =D58+1 -> 45712 | E59: =D59-C59 -> 1 | G59: SG | H59: =H58 -> 28360000 | I59: =I58 -> 0.025 | J59: =+H59*I59*E59/360 -> 1969.4444 | K59: =K58+J59 -> 96792.431 | M59: SG | AR59: 98702601 | AS59: 0.0275 | AT59: 0.0287 | AU59: 7876.39 | AV59: 1022.04
B60: =CONCATENATE(MONTH(D60)," ",YEAR(D60)) -> 2 2025 | C60: =D59 -> 45712 | D60: =D59+1 -> 45713 | E60: =D60-C60 -> 1 | G60: SG | H60: =H59-2650000 -> 25710000 | I60: =I59 -> 0.025 | J60: =+H60*I60*E60/360 -> 1785.4167 | K60: =K59+J60 -> 98577.847 | M60: SG | AR60: 96052601 | AS60: 0.0275 | AT60: 0.0288 | AU60: 7692.36 | AV60: 1022.04
B61: =CONCATENATE(MONTH(D61)," ",YEAR(D61)) -> 2 2025 | C61: =D60 -> 45713 | D61: =D60+1 -> 45714 | E61: =D61-C61 -> 1 | G61: SG | H61: =H60-370000 -> 25340000 | I61: =I60 -> 0.025 | J61: =+H61*I61*E61/360 -> 1759.7222 | K61: =K60+J61 -> 100337.57 | M61: SG | AR61: 95682601 | AS61: 0.0275 | AT61: 0.0288 | AU61: 7666.67 | AV61: 1022.04
B62: =CONCATENATE(MONTH(D62)," ",YEAR(D62)) -> 2 2025 | C62: =D61 -> 45714 | D62: =D61+1 -> 45715 | E62: =D62-C62 -> 1 | G62: SG | H62: =H61-990000 -> 24350000 | I62: =I61 -> 0.025 | J62: =+H62*I62*E62/360 -> 1690.9722 | K62: =K61+J62 -> 102028.54 | M62: SG | AR62: 94692601 | AS62: 0.0275 | AT62: 0.0289 | AU62: 7597.92 | AV62: 1022.04
B63: =CONCATENATE(MONTH(D63)," ",YEAR(D63)) -> 2 2025 | C63: =D62 -> 45715 | D63: =D62+1 -> 45716 | E63: =D63-C63 -> 1 | G63: SG | H63: =H62 -> 24350000 | I63: =I62 -> 0.025 | J63: =+H63*I63*E63/360 -> 1690.9722 | K63: =K62+J63 -> 103719.51 | M63: SG | AR63: 94692601 | AS63: 0.0275 | AT63: 0.0289 | AU63: 7597.92 | AV63: 1022.04
B64: =CONCATENATE(MONTH(D64)," ",YEAR(D64)) -> 3 2025 | C64: =D63 -> 45716 | D64: =D63+1 -> 45717 | E64: =D64-C64 -> 1 | G64: SG | H64: =H63 -> 24350000 | I64: =I63 -> 0.025 | J64: =+H64*I64*E64/360 -> 1690.9722 | K64: =K63+J64 -> 105410.49 | M64: SG | AR64: 94692601 | AS64: 0.0275 | AT64: 0.0289 | AU64: 7597.92 | AV64: 1022.04
B65: =CONCATENATE(MONTH(D65)," ",YEAR(D65)) -> 3 2025 | C65: =D64 -> 45717 | D65: =D64+1 -> 45718 | E65: =D65-C65 -> 1 | G65: SG | H65: =H64 -> 24350000 | I65: =I64 -> 0.025 | J65: =+H65*I65*E65/360 -> 1690.9722 | K65: =K64+J65 -> 107101.46 | M65: SG | AR65: 94692601 | AS65: 0.0275 | AT65: 0.0289 | AU65: 7597.92 | AV65: 1022.04
B66: =CONCATENATE(MONTH(D66)," ",YEAR(D66)) -> 3 2025 | C66: =D65 -> 45718 | D66: =D65+1 -> 45719 | E66: =D66-C66 -> 1 | G66: SG | H66: =H65 -> 24350000 | I66: =I65 -> 0.025 | J66: =+H66*I66*E66/360 -> 1690.9722 | K66: =K65+J66 -> 108792.43 | M66: SG | AR66: 94692601 | AS66: 0.0275 | AT66: 0.0289 | AU66: 7597.92 | AV66: 1022.04
B67: =CONCATENATE(MONTH(D67)," ",YEAR(D67)) -> 3 2025 | C67: =D66 -> 45719 | D67: =D66+1 -> 45720 | E67: =D67-C67 -> 1 | G67: SG | H67: =H66-2080000 -> 22270000 | I67: =I66 -> 0.025 | J67: =+H67*I67*E67/360 -> 1546.5278 | K67: =K66+J67 -> 110338.96 | M67: SG | AR67: 92612601 | AS67: 0.0275 | AT67: 0.029 | AU67: 7453.47 | AV67: 1022.04
B68: =CONCATENATE(MONTH(D68)," ",YEAR(D68)) -> 3 2025 | C68: =D67 -> 45720 | D68: =D67+1 -> 45721 | E68: =D68-C68 -> 1 | G68: SG | H68: =H67 -> 22270000 | I68: =I67 -> 0.025 | J68: =+H68*I68*E68/360 -> 1546.5278 | K68: =K67+J68 -> 111885.49 | M68: SG | AR68: 92612601 | AS68: 0.0275 | AT68: 0.029 | AU68: 7453.47 | AV68: 1022.04
B69: =CONCATENATE(MONTH(D69)," ",YEAR(D69)) -> 3 2025 | C69: =D68 -> 45721 | D69: =D68+1 -> 45722 | E69: =D69-C69 -> 1 | G69: SG | H69: =H68 -> 22270000 | I69: =I68 -> 0.025 | J69: =+H69*I69*E69/360 -> 1546.5278 | K69: =K68+J69 -> 113432.01 | M69: SG | AR69: 92612601 | AS69: 0.0275 | AT69: 0.029 | AU69: 7453.47 | AV69: 1022.04
B70: =CONCATENATE(MONTH(D70)," ",YEAR(D70)) -> 3 2025 | C70: =D69 -> 45722 | D70: =D69+1 -> 45723 | E70: =D70-C70 -> 1 | G70: SG | H70: =H69 -> 22270000 | I70: =I69 -> 0.025 | J70: =+H70*I70*E70/360 -> 1546.5278 | K70: =K69+J70 -> 114978.54 | M70: SG | AR70: 92612601 | AS70: 0.0275 | AT70: 0.029 | AU70: 7453.47 | AV70: 1022.04
B71: =CONCATENATE(MONTH(D71)," ",YEAR(D71)) -> 3 2025 | C71: =D70 -> 45723 | D71: =D70+1 -> 45724 | E71: =D71-C71 -> 1 | G71: SG | H71: =H70 -> 22270000 | I71: =I70 -> 0.025 | J71: =+H71*I71*E71/360 -> 1546.5278 | K71: =K70+J71 -> 116525.07 | M71: SG | AR71: 92612601 | AS71: 0.0275 | AT71: 0.029 | AU71: 7453.47 | AV71: 1022.04
B72: =CONCATENATE(MONTH(D72)," ",YEAR(D72)) -> 3 2025 | C72: =D71 -> 45724 | D72: =D71+1 -> 45725 | E72: =D72-C72 -> 1 | G72: SG | H72: =H71 -> 22270000 | I72: =I71 -> 0.025 | J72: =+H72*I72*E72/360 -> 1546.5278 | K72: =K71+J72 -> 118071.6 | M72: SG | AR72: 92612601 | AS72: 0.0275 | AT72: 0.029 | AU72: 7453.47 | AV72: 1022.04
B73: =CONCATENATE(MONTH(D73)," ",YEAR(D73)) -> 3 2025 | C73: =D72 -> 45725 | D73: =D72+1 -> 45726 | E73: =D73-C73 -> 1 | G73: SG | H73: =H72 -> 22270000 | I73: =I72 -> 0.025 | J73: =+H73*I73*E73/360 -> 1546.5278 | K73: =K72+J73 -> 119618.12 | M73: SG | AR73: 92612601 | AS73: 0.0275 | AT73: 0.029 | AU73: 7453.47 | AV73: 1022.04
B74: =CONCATENATE(MONTH(D74)," ",YEAR(D74)) -> 3 2025 | C74: =D73 -> 45726 | D74: =D73+1 -> 45727 | E74: =D74-C74 -> 1 | G74: SG | H74: =H73+40430000 -> 62700000 | I74: =I73 -> 0.025 | J74: =+H74*I74*E74/360 -> 4354.1667 | K74: =K73+J74 -> 123972.29 | M74: SG | AR74: 92700000 | AS74: 0.0275 | AT74: 0.0274 | AU74: 7050.83 | AV74: 613.33
B75: =CONCATENATE(MONTH(D75)," ",YEAR(D75)) -> 3 2025 | C75: =D74 -> 45727 | D75: =D74+1 -> 45728 | E75: =D75-C75 -> 1 | G75: SG | H75: =H74-3090000 -> 59610000 | I75: =I74 -> 0.025 | J75: =+H75*I75*E75/360 -> 4139.5833 | K75: =K74+J75 -> 128111.87 | M75: SG | AR75: 89610000 | AS75: 0.0275 | AT75: 0.0275 | AU75: 6836.25 | AV75: 613.33
B76: =CONCATENATE(MONTH(D76)," ",YEAR(D76)) -> 3 2025 | C76: =D75 -> 45728 | D76: =D75+1 -> 45729 | E76: =D76-C76 -> 1 | G76: SG | H76: =H75-35000000 -> 24610000 | I76: 0.0225 | J76: =+H76*I76*E76/360 -> 1538.125 | K76: =K75+J76 -> 129650 | M76: SG | AR76: 89610000 | AS76: 0.025 | AT76: 0.0278 | AU76: 4235.29 | AV76: 821.67
B77: =CONCATENATE(MONTH(D77)," ",YEAR(D77)) -> 3 2025 | C77: =D76 -> 45729 | D77: =D76+1 -> 45730 | E77: =D77-C77 -> 1 | G77: SG | H77: =H76-250000 -> 24360000 | I77: =I76 -> 0.0225 | J77: =+H77*I77*E77/360 -> 1522.5 | K77: =K76+J77 -> 131172.5 | M77: SG | AR77: 89362845 | AS77: 0.025 | AT77: 0.0278 | AU77: 7063.18 | AV77: 1478.18
B78: =CONCATENATE(MONTH(D78)," ",YEAR(D78)) -> 3 2025 | C78: =D77 -> 45730 | D78: =D77+1 -> 45731 | E78: =D78-C78 -> 1 | G78: SG | H78: =H77 -> 24360000 | I78: =I77 -> 0.0225 | J78: =+H78*I78*E78/360 -> 1522.5 | K78: =K77+J78 -> 132695 | M78: SG | AR78: 89365689 | AS78: 0.025 | AT78: 0.0278 | AU78: 7063.18 | AV78: 1478.18
B79: =CONCATENATE(MONTH(D79)," ",YEAR(D79)) -> 3 2025 | C79: =D78 -> 45731 | D79: =D78+1 -> 45732 | E79: =D79-C79 -> 1 | G79: SG | H79: =H78 -> 24360000 | I79: =I78 -> 0.0225 | J79: =+H79*I79*E79/360 -> 1522.5 | K79: =K78+J79 -> 134217.5 | M79: SG | AR79: 89365689 | AS79: 0.025 | AT79: 0.0278 | AU79: 4219.17 | AV79: -1365.83
B80: =CONCATENATE(MONTH(D80)," ",YEAR(D80)) -> 3 2025 | C80: =D79 -> 45732 | D80: =D79+1 -> 45733 | E80: =D80-C80 -> 1 | G80: SG | H80: =H79 -> 24360000 | I80: =I79 -> 0.0225 | J80: =+H80*I80*E80/360 -> 1522.5 | K80: =K79+J80 -> 135740 | M80: SG | AR80: 89365689 | AS80: 0.025 | AT80: 0.0169 | AU80: 1522.5 | AV80: -2187.5
B81: =CONCATENATE(MONTH(D81)," ",YEAR(D81)) -> 3 2025 | C81: =D80 -> 45733 | D81: =D80+1 -> 45734 | E81: =D81-C81 -> 1 | G81: SG | H81: =H80+30220000 -> 54580000 | I81: =I80 -> 0.0225 | J81: =+H81*I81*E81/360 -> 3411.25 | K81: =K80+J81 -> 139151.25 | M81: SG | AR81: 89594290 | AS81: 0.025 | AT81: 0.0245 | AU81: 12012.66 | AV81: 6413.91
B82: =CONCATENATE(MONTH(D82)," ",YEAR(D82)) -> 3 2025 | C82: =D81 -> 45734 | D82: =D81+1 -> 45735 | E82: =D82-C82 -> 1 | G82: SG | H82: =H81-180000 -> 54400000 | I82: =I81 -> 0.0225 | J82: =+H82*I82*E82/360 -> 3400 | K82: =K81+J82 -> 142551.25 | M82: SG | AR82: 89416891 | AS82: 0.025 | AT82: 0.0245 | AU82: 6001.23 | AV82: 413.73
B83: =CONCATENATE(MONTH(D83)," ",YEAR(D83)) -> 3 2025 | C83: =D82 -> 45735 | D83: =D82+1 -> 45736 | E83: =D83-C83 -> 1 | G83: SG | H83: =H82-30000000 -> 24400000 | I83: =I82 -> 0.0225 | J83: =+H83*I83*E83/360 -> 1525 | K83: =K82+J83 -> 144076.25 | M83: SG | AR83: 89419492 | AS83: 0.025 | AT83: 0.0262 | AU83: 4126.22 | AV83: 413.72
B84: =CONCATENATE(MONTH(D84)," ",YEAR(D84)) -> 3 2025 | C84: =D83 -> 45736 | D84: =D83+1 -> 45737 | E84: =D84-C84 -> 1 | G84: SG | H84: =H83 -> 24400000 | I84: =I83 -> 0.0225 | J84: =+H84*I84*E84/360 -> 1525 | K84: =K83+J84 -> 145601.25 | M84: SG | AR84: 89424386 | AS84: 0.025 | AT84: 0.0262 | AU84: 6419.01 | AV84: 831.51
B85: =CONCATENATE(MONTH(D85)," ",YEAR(D85)) -> 3 2025 | C85: =D84 -> 45737 | D85: =D84+1 -> 45738 | E85: =D85-C85 -> 1 | G85: SG | H85: =H84 -> 24400000 | I85: =I84 -> 0.0225 | J85: =+H85*I85*E85/360 -> 1525 | K85: =K84+J85 -> 147126.25 | M85: SG | AR85: 89429216 | AS85: 0.025 | AT85: 0.0262 | AU85: 6354.62 | AV85: 767.12
B86: =CONCATENATE(MONTH(D86)," ",YEAR(D86)) -> 3 2025 | C86: =D85 -> 45738 | D86: =D85+1 -> 45739 | E86: =D86-C86 -> 1 | G86: SG | H86: =H85 -> 24400000 | I86: =I85 -> 0.0225 | J86: =+H86*I86*E86/360 -> 1525 | K86: =K85+J86 -> 148651.25 | M86: SG | AR86: 89429216 | AS86: 0.025 | AT86: 0.0262 | AU86: 1525 | AV86: -4062.5
B87: =CONCATENATE(MONTH(D87)," ",YEAR(D87)) -> 3 2025 | C87: =D86 -> 45739 | D87: =D86+1 -> 45740 | E87: =D87-C87 -> 1 | G87: SG | H87: =H86 -> 24400000 | I87: =I86 -> 0.0225 | J87: =+H87*I87*E87/360 -> 1525 | K87: =K86+J87 -> 150176.25 | M87: SG | AR87: 89429216 | AS87: 0.025 | AT87: 0.0262 | AU87: 1525 | AV87: -4062.5
B88: =CONCATENATE(MONTH(D88)," ",YEAR(D88)) -> 3 2025 | C88: =D87 -> 45740 | D88: =D87+1 -> 45741 | E88: =D88-C88 -> 1 | G88: SG | H88: =H87 -> 24400000 | I88: =I87 -> 0.0225 | J88: =+H88*I88*E88/360 -> 1525 | K88: =K87+J88 -> 151701.25 | M88: SG | AR88: 89443834 | AS88: 0.025 | AT88: 0.0262 | AU88: 16142.65 | AV88: 10555.15
B89: =CONCATENATE(MONTH(D89)," ",YEAR(D89)) -> 3 2025 | C89: =D88 -> 45741 | D89: =D88+1 -> 45742 | E89: =D89-C89 -> 1 | G89: SG | H89: =H88-80000 -> 24320000 | I89: =I88 -> 0.0225 | J89: =+H89*I89*E89/360 -> 1520 | K89: =K88+J89 -> 153221.25 | M89: SG | AR89: 89368663 | AS89: 0.025 | AT89: 0.0262 | AU89: 6349.62 | AV89: 767.12
B90: =CONCATENATE(MONTH(D90)," ",YEAR(D90)) -> 3 2025 | C90: =D89 -> 45742 | D90: =D89+1 -> 45743 | E90: =D90-C90 -> 1 | G90: SG | H90: =H89-30000 -> 24290000 | I90: =I89 -> 0.0225 | J90: =+H90*I90*E90/360 -> 1518.125 | K90: =K89+J90 -> 154739.37 | M90: SG | AR90: 89343557 | AS90: 0.025 | AT90: 0.0262 | AU90: 6412.14 | AV90: 831.51
B91: =CONCATENATE(MONTH(D91)," ",YEAR(D91)) -> 3 2025 | C91: =D90 -> 45743 | D91: =D90+1 -> 45744 | E91: =D91-C91 -> 1 | G91: SG | H91: =H90-2470000 -> 21820000 | I91: =I90 -> 0.0225 | J91: =+H91*I91*E91/360 -> 1363.75 | K91: =K90+J91 -> 156103.12 | M91: SG | AR91: 86878387 | AS91: 0.025 | AT91: 0.0263 | AU91: 6193.37 | AV91: 767.12
B92: =CONCATENATE(MONTH(D92)," ",YEAR(D92)) -> 3 2025 | C92: =D91 -> 45744 | D92: =D91+1 -> 45745 | E92: =D92-C92 -> 1 | G92: SG | H92: =H91 -> 21820000 | I92: =I91 -> 0.0225 | J92: =+H92*I92*E92/360 -> 1363.75 | K92: =K91+J92 -> 157466.87 | M92: SG | AR92: 86883281 | AS92: 0.025 | AT92: 0.0263 | AU92: 6257.76 | AV92: 831.51
B93: =CONCATENATE(MONTH(D93)," ",YEAR(D93)) -> 3 2025 | C93: =D92 -> 45745 | D93: =D92+1 -> 45746 | E93: =D93-C93 -> 1 | G93: SG | H93: =H92 -> 21820000 | I93: =I92 -> 0.0225 | J93: =+H93*I93*E93/360 -> 1363.75 | K93: =K92+J93 -> 158830.62 | M93: SG | AR93: 86883281 | AS93: 0.025 | AT93: 0.0263 | AU93: 1363.75 | AV93: -4062.5
B94: =CONCATENATE(MONTH(D94)," ",YEAR(D94)) -> 3 2025 | C94: =D93 -> 45746 | D94: =D93+1 -> 45747 | E94: =D94-C94 -> 1 | G94: SG | H94: =H93 -> 21820000 | I94: =I93 -> 0.0225 | J94: =+H94*I94*E94/360 -> 1363.75 | K94: =K93+J94 -> 160194.37 | M94: SG | AR94: 86883281 | AS94: 0.025 | AT94: 0.0263 | AU94: 1363.75 | AV94: -4062.5
B95: =CONCATENATE(MONTH(D95)," ",YEAR(D95)) -> 4 2025 | C95: =D94 -> 45747 | D95: =D94+1 -> 45748 | E95: =D95-C95 -> 1 | G95: SG | H95: =H94 -> 21820000 | I95: =I94 -> 0.0225 | J95: =+H95*I95*E95/360 -> 1363.75 | K95: =K94+J95 -> 161558.12 | M95: SG | AR95: 86897899 | AS95: 0.025 | AT95: 0.0263 | AU95: 15981.4 | AV95: 10555.15
B96: =CONCATENATE(MONTH(D96)," ",YEAR(D96)) -> 4 2025 | C96: =D95 -> 45748 | D96: =D95+1 -> 45749 | E96: =D96-C96 -> 1 | G96: SG | H96: =H95-2760000 -> 19060000 | I96: =I95 -> 0.0225 | J96: =+H96*I96*E96/360 -> 1191.25 | K96: =K95+J96 -> 162749.37 | M96: SG | AR96: 84142728 | AS96: 0.025 | AT96: 0.0264 | AU96: 6020.87 | AV96: 767.12
B97: =CONCATENATE(MONTH(D97)," ",YEAR(D97)) -> 4 2025 | C97: =D96 -> 45749 | D97: =D96+1 -> 45750 | E97: =D97-C97 -> 1 | G97: SG | H97: =H96-260000 -> 18800000 | I97: =I96 -> 0.0225 | J97: =+H97*I97*E97/360 -> 1175 | K97: =K96+J97 -> 163924.37 | M97: SG | AR97: 83887622 | AS97: 0.025 | AT97: 0.0264 | AU97: 6069.01 | AV97: 831.51
B98: =CONCATENATE(MONTH(D98)," ",YEAR(D98)) -> 4 2025 | C98: =D97 -> 45750 | D98: =D97+1 -> 45751 | E98: =D98-C98 -> 1 | G98: SG | H98: =H97-260000 -> 18540000 | I98: =I97 -> 0.0225 | J98: =+H98*I98*E98/360 -> 1158.75 | K98: =K97+J98 -> 165083.12 | M98: SG | AR98: 83632452 | AS98: 0.025 | AT98: 0.0255 | AU98: 5988.37 | AV98: 767.12
B99: =CONCATENATE(MONTH(D99)," ",YEAR(D99)) -> 4 2025 | C99: =D98 -> 45751 | D99: =D98+1 -> 45752 | E99: =D99-C99 -> 1 | G99: SG | H99: =H98 -> 18540000 | I99: =I98 -> 0.0225 | J99: =+H99*I99*E99/360 -> 1158.75 | K99: =K98+J99 -> 166241.87 | M99: SG | AR99: 83637346 | AS99: 0.025 | AT99: 0.0255 | AU99: 6052.76 | AV99: 831.51
B100: =CONCATENATE(MONTH(D100)," ",YEAR(D100)) -> 4 2025 | C100: =D99 -> 45752 | D100: =D99+1 -> 45753 | E100: =D100-C100 -> 1 | G100: SG | H100: =H99 -> 18540000 | I100: =I99 -> 0.0225 | J100: =+H100*I100*E100/360 -> 1158.75 | K100: =K99+J100 -> 167400.62 | M100: SG | AR100: 83637346 | AS100: 0.025 | AT100: 0.0255 | AU100: 1158.75 | AV100: -4062.5
B101: =CONCATENATE(MONTH(D101)," ",YEAR(D101)) -> 4 2025 | C101: =D100 -> 45753 | D101: =D100+1 -> 45754 | E101: =D101-C101 -> 1 | G101: SG | H101: =H100 -> 18540000 | I101: =I100 -> 0.0225 | J101: =+H101*I101*E101/360 -> 1158.75 | K101: =K100+J101 -> 168559.37 | M101: SG | AR101: 83637346 | AS101: 0.025 | AT101: 0.0255 | AU101: 1158.75 | AV101: -4062.5
...

Sheet codeis €
C2: Date de valeur pr mvt argent Date comptable pour solde | D2: Intérêts dû in fine ( à date d'échéance)
B3: Fin de mois | C3: Date départ | D3: Date échéance | E3: Nbj | F3: Emetteur | H3: Date de Valorisation Codéis | I3: VL (Date départ) | K3: Prix initial- 1 Part (EUR) | L3: Achat (Part) | M3: Valos achat | N3: Vente (Part) (31/10/2025) | O3: Part Restttes 31/10/2025 | P3: Vente 05/11/2025 | Q3: Parts Resttes 05/11/2025 | R3: Vente 26/01/2026 | S3: Part resttes 26/01/2026 | T3: Valos de la vente | U3: PV Vente | V3: Prinicpal ventes | X3: Part | Y3: Principal (EUR) | Z3: Valos (Date départ) | AB3: PV/MV depuis origine | AC3: PV quotidienne | AD3: PV mensuel | AF3: Performance mensuelle annualisée | AG3: Performance cumulée et annualisée | AI3: gain/NCA
B5: =CONCATENATE(MONTH(D5)," ",YEAR(D5)) -> 1 2025 | C5: ='OverNight €'!C5 -> 45657 | D5: ='OverNight €'!D5 -> 45658 | E5: =D5-C5 -> 1 | F5: SG | H5: =C5 -> 45657
B6: =CONCATENATE(MONTH(D6)," ",YEAR(D6)) -> 1 2025 | C6: =D5 -> 45658 | D6: =D5+1 -> 45659 | E6: =D6-C6 -> 1 | F6: SG | H6: =C6 -> 45658
B7: =CONCATENATE(MONTH(D7)," ",YEAR(D7)) -> 1 2025 | C7: =D6 -> 45659 | D7: =D6+1 -> 45660 | E7: =D7-C7 -> 1 | F7: SG | H7: =C7 -> 45659
B8: =CONCATENATE(MONTH(D8)," ",YEAR(D8)) -> 1 2025 | C8: =D7 -> 45660 | D8: =D7+1 -> 45661 | E8: =D8-C8 -> 1 | F8: SG | H8: =C8 -> 45660
B9: =CONCATENATE(MONTH(D9)," ",YEAR(D9)) -> 1 2025 | C9: =D8 -> 45661 | D9: =D8+1 -> 45662 | E9: =D9-C9 -> 1 | F9: SG | H9: =C9 -> 45661
B10: =CONCATENATE(MONTH(D10)," ",YEAR(D10)) -> 1 2025 | C10: =D9 -> 45662 | D10: =D9+1 -> 45663 | E10: =D10-C10 -> 1 | F10: SG | H10: =C10 -> 45662
B11: =CONCATENATE(MONTH(D11)," ",YEAR(D11)) -> 1 2025 | C11: =D10 -> 45663 | D11: =D10+1 -> 45664 | E11: =D11-C11 -> 1 | F11: SG | H11: =C11 -> 45663
B12: =CONCATENATE(MONTH(D12)," ",YEAR(D12)) -> 1 2025 | C12: =D11 -> 45664 | D12: =D11+1 -> 45665 | E12: =D12-C12 -> 1 | F12: SG | H12: =C12 -> 45664
B13: =CONCATENATE(MONTH(D13)," ",YEAR(D13)) -> 1 2025 | C13: =D12 -> 45665 | D13: =D12+1 -> 45666 | E13: =D13-C13 -> 1 | F13: SG | H13: =C13 -> 45665
B14: =CONCATENATE(MONTH(D14)," ",YEAR(D14)) -> 1 2025 | C14: =D13 -> 45666 | D14: =D13+1 -> 45667 | E14: =D14-C14 -> 1 | F14: SG | H14: =C14 -> 45666
B15: =CONCATENATE(MONTH(D15)," ",YEAR(D15)) -> 1 2025 | C15: =D14 -> 45667 | D15: =D14+1 -> 45668 | E15: =D15-C15 -> 1 | F15: SG | H15: =C15 -> 45667
B16: =CONCATENATE(MONTH(D16)," ",YEAR(D16)) -> 1 2025 | C16: =D15 -> 45668 | D16: =D15+1 -> 45669 | E16: =D16-C16 -> 1 | F16: SG | H16: =C16 -> 45668
B17: =CONCATENATE(MONTH(D17)," ",YEAR(D17)) -> 1 2025 | C17: =D16 -> 45669 | D17: =D16+1 -> 45670 | E17: =D17-C17 -> 1 | F17: SG | H17: =C17 -> 45669
... B192: =CONCATENATE(MONTH(D192)," ",YEAR(D192)) -> 7 2025 | C192: =D191 -> 45844 | D192: =D191+1 -> 45845 | E192: =D192-C192 -> 1 | F192: SG | H192: =C192 -> 45844
A193: recupérer argent CAT | B193: =CONCATENATE(MONTH(D193)," ",YEAR(D193)) -> 7 2025 | C193: =D192 -> 45845 | D193: =D192+1 -> 45846 | E193: =D193-C193 -> 1 | F193: SG | H193: =C193 -> 45845
B194: =CONCATENATE(MONTH(D194)," ",YEAR(D194)) -> 7 2025 | C194: =D193 -> 45846 | D194: =D193+1 -> 45847 | E194: =D194-C194 -> 1 | F194: SG | H194: =C194 -> 45846
B195: =CONCATENATE(MONTH(D195)," ",YEAR(D195)) -> 7 2025 | C195: =D194 -> 45847 | D195: =D194+1 -> 45848 | E195: =D195-C195 -> 1 | F195: SG | H195: =C195 -> 45847
B196: =CONCATENATE(MONTH(D196)," ",YEAR(D196)) -> 7 2025 | C196: =D195 -> 45848 | D196: =D195+1 -> 45849 | E196: =D196-C196 -> 1 | F196: SG | H196: =C196 -> 45848
B197: =CONCATENATE(MONTH(D197)," ",YEAR(D197)) -> 7 2025 | C197: =D196 -> 45849 | D197: =D196+1 -> 45850 | E197: =D197-C197 -> 1 | F197: SG | H197: =C197 -> 45849
B198: =CONCATENATE(MONTH(D198)," ",YEAR(D198)) -> 7 2025 | C198: =D197 -> 45850 | D198: =D197+1 -> 45851 | E198: =D198-C198 -> 1 | F198: SG | H198: =C198 -> 45850
B199: =CONCATENATE(MONTH(D199)," ",YEAR(D199)) -> 7 2025 | C199: =D198 -> 45851 | D199: =D198+1 -> 45852 | E199: =D199-C199 -> 1 | F199: SG | H199: =C199 -> 45851
B200: =CONCATENATE(MONTH(D200)," ",YEAR(D200)) -> 7 2025 | C200: =D199 -> 45852 | D200: =D199+1 -> 45853 | E200: =D200-C200 -> 1 | F200: SG | H200: =C200 -> 45852
B201: =CONCATENATE(MONTH(D201)," ",YEAR(D201)) -> 7 2025 | C201: =D200 -> 45853 | D201: =D200+1 -> 45854 | E201: =D201-C201 -> 1 | F201: SG | H201: =C201 -> 45853
B202: =CONCATENATE(MONTH(D202)," ",YEAR(D202)) -> 7 2025 | C202: =D201 -> 45854 | D202: =D201+1 -> 45855 | E202: =D202-C202 -> 1 | F202: SG | H202: =C202 -> 45854
B203: =CONCATENATE(MONTH(D203)," ",YEAR(D203)) -> 7 2025 | C203: =D202 -> 45855 | D203: =D202+1 -> 45856 | E203: =D203-C203 -> 1 | F203: SG | H203: =C203 -> 45855
B204: =CONCATENATE(MONTH(D204)," ",YEAR(D204)) -> 7 2025 | C204: =D203 -> 45856 | D204: =D203+1 -> 45857 | E204: =D204-C204 -> 1 | F204: SG | H204: =C204 -> 45856
B205: =CONCATENATE(MONTH(D205)," ",YEAR(D205)) -> 7 2025 | C205: =D204 -> 45857 | D205: =D204+1 -> 45858 | E205: =D205-C205 -> 1 | F205: SG | H205: =C205 -> 45857
... B277: =CONCATENATE(MONTH(D277)," ",YEAR(D277)) -> 9 2025 | C277: =D276 -> 45929 | D277: =D276+1 -> 45930 | E277: =D277-C277 -> 1 | F277: SG | H277: =C277 -> 45929
A278: Date VL | B278: =CONCATENATE(MONTH(D278)," ",YEAR(D278)) -> 10 2025 | C278: =D277 -> 45930 | D278: =D277+1 -> 45931 | E278: =D278-C278 -> 1 | F278: SG | H278: =C278 -> 45930
B279: =CONCATENATE(MONTH(D279)," ",YEAR(D279)) -> 10 2025 | C279: =D278 -> 45931 | D279: =D278+1 -> 45932 | E279: =D279-C279 -> 1 | F279: SG | H279: =C279 -> 45931
B280: =CONCATENATE(MONTH(D280)," ",YEAR(D280)) -> 10 2025 | C280: =D279 -> 45932 | D280: =D279+1 -> 45933 | E280: =D280-C280 -> 1 | F280: SG | H280: =C280 -> 45932
B281: =CONCATENATE(MONTH(D281)," ",YEAR(D281)) -> 10 2025 | C281: =D280 -> 45933 | D281: =D280+1 -> 45934 | E281: =D281-C281 -> 1 | F281: SG | H281: =C281 -> 45933
B282: =CONCATENATE(MONTH(D282)," ",YEAR(D282)) -> 10 2025 | C282: =D281 -> 45934 | D282: =D281+1 -> 45935 | E282: =D282-C282 -> 1 | F282: SG | H282: =C282 -> 45934
B283: =CONCATENATE(MONTH(D283)," ",YEAR(D283)) -> 10 2025 | C283: =D282 -> 45935 | D283: =D282+1 -> 45936 | E283: =D283-C283 -> 1 | F283: SG | H283: =C283 -> 45935
B284: =CONCATENATE(MONTH(D284)," ",YEAR(D284)) -> 10 2025 | C284: =D283 -> 45936 | D284: =D283+1 -> 45937 | E284: =D284-C284 -> 1 | F284: SG | H284: =C284 -> 45936
B285: =CONCATENATE(MONTH(D285)," ",YEAR(D285)) -> 10 2025 | C285: =D284 -> 45937 | D285: =D284+1 -> 45938 | E285: =D285-C285 -> 1 | F285: SG | H285: =C285 -> 45937
B286: =CONCATENATE(MONTH(D286)," ",YEAR(D286)) -> 10 2025 | C286: =D285 -> 45938 | D286: =D285+1 -> 45939 | E286: =D286-C286 -> 1 | F286: SG | H286: =C286 -> 45938
B287: =CONCATENATE(MONTH(D287)," ",YEAR(D287)) -> 10 2025 | C287: =D286 -> 45939 | D287: =D286+1 -> 45940 | E287: =D287-C287 -> 1 | F287: SG | H287: =C287 -> 45939
B288: =CONCATENATE(MONTH(D288)," ",YEAR(D288)) -> 10 2025 | C288: =D287 -> 45940 | D288: =D287+1 -> 45941 | E288: =D288-C288 -> 1 | F288: SG | H288: =C288 -> 45940 | I288: 101.0768 | K288: 100000 | L288: 871 | M288: =ROUND(L288*K288*ROUND(I288,4)%,2) -> 88037893 | N288: 358 | O288: =L288-N288 -> 513 | P288: 149 | Q288: =O288-P288 -> 364 | R288: 196 | S288: =Q288-R288 -> 168 | X288: =L288 -> 871 | Y288: =M288 -> 88037893 | Z288: =X288*K288*ROUND(I288,4)% -> 88037893 | AB288: =Z288-Y288 -> 0 | AC288: =Z288+T288-Z287-M288 -> 0 | AF288: =AF289 -> 0.020776281
B289: =CONCATENATE(MONTH(D289)," ",YEAR(D289)) -> 10 2025 | C289: =D288 -> 45941 | D289: =D288+1 -> 45942 | E289: =D289-C289 -> 1 | F289: SG | H289: =C289 -> 45941 | I289: 101.0768 | K289: 100000 | X289: =X288+L289-N289 -> 871 | Y289: =Y288 -> 88037893 | Z289: =X289*K289*ROUND(I289,4)% -> 88037893 | AB289: =Z289-Y289 -> 0 | AC289: =Z289+T289-Z288-M289 -> 0 | AF289: =AF290 -> 0.020776281 | AG289: =(I289/$I$288-1)*360/(D289-$D$288) -> 0 | AI289: =AC289-Y288*'OverNight €'!I289*E289/360 -> -4279.6198
B290: =CONCATENATE(MONTH(D290)," ",YEAR(D290)) -> 10 2025 | C290: =D289 -> 45942 | D290: =D289+1 -> 45943 | E290: =D290-C290 -> 1 | F290: SG | H290: =C290 -> 45942 | I290: 101.0768 | K290: 100000 | X290: =X289+L290-N290 -> 871 | Y290: =Y289 -> 88037893 | Z290: =X290*K290*ROUND(I290,4)% -> 88037893 | AB290: =Z290-Y290 -> 0 | AC290: =Z290+T290-Z289-M290 -> 0 | AF290: =AF291 -> 0.020776281 | AG290: =(I290/$I$288-1)*360/(D290-$D$288) -> 0 | AI290: =AC290-Y289*'OverNight €'!I290*E290/360 -> -4279.6198
B291: =CONCATENATE(MONTH(D291)," ",YEAR(D291)) -> 10 2025 | C291: =D290 -> 45943 | D291: =D290+1 -> 45944 | E291: =D291-C291 -> 1 | F291: SG | H291: =C291 -> 45943 | I291: 101.0943 | K291: 100000 | X291: =X290+L291-N291 -> 871 | Y291: =Y290 -> 88037893 | Z291: =X291*K291*ROUND(I291,4)% -> 88053135 | AB291: =Z291-Y291 -> 15242.5 | AC291: =Z291+T291-Z290-M291 -> 15242.5 | AF291: =AF292 -> 0.020776281 | AG291: =(I291/$I$288-1)*360/(D291-$D$288) -> 0.020776281 | AI291: =AC291-Y290*'OverNight €'!I291*E291/360 -> 10962.88
B292: =CONCATENATE(MONTH(D292)," ",YEAR(D292)) -> 10 2025 | C292: =D291 -> 45944 | D292: =D291+1 -> 45945 | E292: =D292-C292 -> 1 | F292: SG | H292: =C292 -> 45944 | I292: 101.1001 | K292: 100000 | X292: =X291+L292-N292 -> 871 | Y292: =Y291 -> 88037893 | Z292: =X292*K292*ROUND(I292,4)% -> 88058187 | AB292: =Z292-Y292 -> 20294.3 | AC292: =Z292+T292-Z291-M292 -> 5051.8 | AF292: =AF293 -> 0.020776281 | AG292: =(I292/$I$288-1)*360/(D292-$D$288) -> 0.020746601 | AI292: =AC292-Y291*'OverNight €'!I292*E292/360 -> 772.18021
B293: =CONCATENATE(MONTH(D293)," ",YEAR(D293)) -> 10 2025 | C293: =D292 -> 45945 | D293: =D292+1 -> 45946 | E293: =D293-C293 -> 1 | F293: SG | H293: =C293 -> 45945 | I293: 101.1059 | K293: 100000 | X293: =X292+L293-N293 -> 871 | Y293: =Y292 -> 88037893 | Z293: =X293*K293*ROUND(I293,4)% -> 88063239 | AB293: =Z293-Y293 -> 25346.1 | AC293: =Z293+T293-Z292-M293 -> 5051.8 | AF293: =AF294 -> 0.020776281 | AG293: =(I293/$I$288-1)*360/(D293-$D$288) -> 0.020728792 | AI293: =AC293-Y292*'OverNight €'!I293*E293/360 -> 772.18021
B294: =CONCATENATE(MONTH(D294)," ",YEAR(D294)) -> 10 2025 | C294: =D293 -> 45946 | D294: =D293+1 -> 45947 | E294: =D294-C294 -> 1 | F294: SG | H294: =C294 -> 45946 | I294: 101.1118 | K294: 100000 | X294: =X293+L294-N294 -> 871 | Y294: =Y293 -> 88037893 | Z294: =X294*K294*ROUND(I294,4)% -> 88068378 | AB294: =Z294-Y294 -> 30485 | AC294: =Z294+T294-Z293-M294 -> 5138.9 | AF294: =AF295 -> 0.020776281 | AG294: =(I294/$I$288-1)*360/(D294-$D$288) -> 0.020776281 | AI294: =AC294-Y293*'OverNight €'!I294*E294/360 -> 859.28021
B295: =CONCATENATE(MONTH(D295)," ",YEAR(D295)) -> 10 2025 | C295: =D294 -> 45947 | D295: =D294+1 -> 45948 | E295: =D295-C295 -> 1 | F295: SG | H295: =C295 -> 45947 | I295: 101.1176 | K295: 100000 | X295: =X294+L295-N295 -> 871 | Y295: =Y294 -> 88037893 | Z295: =X295*K295*ROUND(I295,4)% -> 88073430 | AB295: =Z295-Y295 -> 35536.8 | AC295: =Z295+T295-Z294-M295 -> 5051.8 | AF295: =AF296 -> 0.020776281 | AG295: =(I295/$I$288-1)*360/(D295-$D$288) -> 0.020759321 | AI295: =AC295-Y294*'OverNight €'!I295*E295/360 -> 772.18021
B296: =CONCATENATE(MONTH(D296)," ",YEAR(D296)) -> 10 2025 | C296: =D295 -> 45948 | D296: =D295+1 -> 45949 | E296: =D296-C296 -> 1 | F296: SG | H296: =C296 -> 45948 | I296: 101.1176 | K296: 100000 | X296: =X295+L296-N296 -> 871 | Y296: =Y295 -> 88037893 | Z296: =X296*K296*ROUND(I296,4)% -> 88073430 | AB296: =Z296-Y296 -> 35536.8 | AC296: =Z296+T296-Z295-M296 -> 0 | AF296: =AF297 -> 0.020776281 | AG296: =(I296/$I$288-1)*360/(D296-$D$288) -> 0.018164406 | AI296: =AC296-Y295*'OverNight €'!I296*E296/360 -> -4279.6198
B297: =CONCATENATE(MONTH(D297)," ",YEAR(D297)) -> 10 2025 | C297: =D296 -> 45949 | D297: =D296+1 -> 45950 | E297: =D297-C297 -> 1 | F297: SG | H297: =C297 -> 45949 | I297: 101.1176 | K297: 100000 | X297: =X296+L297-N297 -> 871 | Y297: =Y296 -> 88037893 | Z297: =X297*K297*ROUND(I297,4)% -> 88073430 | AB297: =Z297-Y297 -> 35536.8 | AC297: =Z297+T297-Z296-M297 -> 0 | AF297: =AF298 -> 0.020776281 | AG297: =(I297/$I$288-1)*360/(D297-$D$288) -> 0.016146138 | AI297: =AC297-Y296*'OverNight €'!I297*E297/360 -> -4279.6198
B298: =CONCATENATE(MONTH(D298)," ",YEAR(D298)) -> 10 2025 | C298: =D297 -> 45950 | D298: =D297+1 -> 45951 | E298: =D298-C298 -> 1 | F298: SG | H298: =C298 -> 45950 | I298: 101.1351 | K298: 100000 | X298: =X297+L298-N298 -> 871 | Y298: =Y297 -> 88037893 | Z298: =X298*K298*ROUND(I298,4)% -> 88088672 | AB298: =Z298-Y298 -> 50779.3 | AC298: =Z298+T298-Z297-M298 -> 15242.5 | AF298: =AF299 -> 0.020776281 | AG298: =(I298/$I$288-1)*360/(D298-$D$288) -> 0.020764409 | AI298: =AC298-Y297*'OverNight €'!I298*E298/360 -> 10962.88
B299: =CONCATENATE(MONTH(D299)," ",YEAR(D299)) -> 10 2025 | C299: =D298 -> 45951 | D299: =D298+1 -> 45952 | E299: =D299-C299 -> 1 | F299: SG | H299: =C299 -> 45951 | I299: 101.1409 | K299: 100000 | X299: =X298+L299-N299 -> 871 | Y299: =Y298 -> 88037893 | Z299: =X299*K299*ROUND(I299,4)% -> 88093724 | AB299: =Z299-Y299 -> 55831.1 | AC299: =Z299+T299-Z298-M299 -> 5051.8 | AF299: =AF300 -> 0.020776281 | AG299: =(I299/$I$288-1)*360/(D299-$D$288) -> 0.020754695 | AI299: =AC299-Y298*'OverNight €'!I299*E299/360 -> 772.18021
B300: =CONCATENATE(MONTH(D300)," ",YEAR(D300)) -> 10 2025 | C300: =D299 -> 45952 | D300: =D299+1 -> 45953 | E300: =D300-C300 -> 1 | F300: SG | H300: =C300 -> 45952 | I300: 101.1468 | K300: 100000 | X300: =X299+L300-N300 -> 871 | Y300: =Y299 -> 88037893 | Z300: =X300*K300*ROUND(I300,4)% -> 88098863 | AB300: =Z300-Y300 -> 60970 | AC300: =Z300+T300-Z299-M300 -> 5138.9 | AF300: =AF301 -> 0.020776281 | AG300: =(I300/$I$288-1)*360/(D300-$D$288) -> 0.020776281 | AI300: =AC300-Y299*'OverNight €'!I300*E300/360 -> 859.28021
... B308: =CONCATENATE(MONTH(D308)," ",YEAR(D308)) -> 10 2025 | C308: =D307 -> 45960 | D308: =D307+1 -> 45961 | E308: =D308-C308 -> 1 | F308: SG | H308: =C308 -> 45960 | I308: 101.1935 | K308: 100000 | X308: =X307+L308-N308 -> 871 | Y308: =Y307 -> 88037893 | Z308: =X308*K308*ROUND(I308,4)% -> 88139538 | AB308: =Z308-Y308 -> 101645.7 | AC308: =Z308+T308-Z307-M308 -> 5051.8 | AF308: =AF309 -> 0.020776281 | AG308: =(I308/$I$288-1)*360/(D308-$D$288) -> 0.020782217 | AI308: =AC308-Y307*'OverNight €'!I308*E308/360 -> 772.18021
B309: =CONCATENATE(MONTH(D309)," ",YEAR(D309)) -> 11 2025 | C309: =D308 -> 45961 | D309: =D308+1 -> 45962 | E309: =D309-C309 -> 1 | F309: SG | H309: =C309 -> 45961 | I309: 101.1993 | K309: 100000 | N309: 358 | T309: =N309*I309%*K309 -> 36229349 | U309: =N309*(I309-I288)%*K309 -> 43855 | V309: =T309-U309 -> 36185494 | X309: =X308+L309-N309 -> 513 | Y309: =Y308-V309 -> 51852398 | Z309: =X309*K309*ROUND(I309,4)% -> 51915241 | AB309: =Z309-Y309+U309 -> 106697.5 | AC309: =Z309+T309-Z308-M309 -> 5051.8 | AD309: =SUM(AC288:AC309) -> 106697.5 | AF309: =(I309/I288-1)*360/(H309-H288) -> 0.020776281 | AG309: =(I309/$I$288-1)*360/(D309-$D$288) -> 0.020776281 | AI309: =AC309-Y308*'OverNight €'!I309*E309/360 -> 772.18021
B310: =CONCATENATE(MONTH(D310)," ",YEAR(D310)) -> 11 2025 | C310: =D309 -> 45962 | D310: =D309+1 -> 45963 | E310: =D310-C310 -> 1 | F310: SG | H310: =C310 -> 45962 | I310: 101.1993 | K310: 100000 | X310: =X309+L310-N310 -> 513 | Y310: =Y309 -> 51852398 | Z310: =X310*K310*ROUND(I310,4)% -> 51915241 | AB310: =Z310-Y310 -> 62842.5 | AC310: =Z310+T310-Z309-M310 -> 0 | AF310: =AF311 -> 0.020810421 | AG310: =(I310/$I$288-1)*360/(D310-$D$288) -> 0.019831905 | AI310: =AC310-Y309*'OverNight €'!I310*E310/360 -> -2520.6027
B311: =CONCATENATE(MONTH(D311)," ",YEAR(D311)) -> 11 2025 | C311: =D310 -> 45963 | D311: =D310+1 -> 45964 | E311: =D311-C311 -> 1 | F311: SG | H311: =C311 -> 45963 | I311: 101.1993 | K311: 100000 | X311: =X310+L311-N311 -> 513 | Y311: =Y310 -> 51852398 | Z311: =X311*K311*ROUND(I311,4)% -> 51915241 | AB311: =Z311-Y311 -> 62842.5 | AC311: =Z311+T311-Z310-M311 -> 0 | AF311: =AF312 -> 0.020810421 | AG311: =(I311/$I$288-1)*360/(D311-$D$288) -> 0.018969648 | AI311: =AC311-Y310*'OverNight €'!I311*E311/360 -> -2520.6027
B312: =CONCATENATE(MONTH(D312)," ",YEAR(D312)) -> 11 2025 | C312: =D311 -> 45964 | D312: =D311+1 -> 45965 | E312: =D312-C312 -> 1 | F312: SG | H312: =C312 -> 45964 | I312: 101.2169 | K312: 100000 | X312: =X311+L312-N312 -> 513 | Y312: =Y311 -> 51852398 | Z312: =X312*K312*ROUND(I312,4)% -> 51924270 | AB312: =Z312-Y312 -> 71871.3 | AC312: =Z312+T312-Z311-M312 -> 9028.8 | AF312: =AF313 -> 0.020810421 | AG312: =(I312/$I$288-1)*360/(D312-$D$288) -> 0.020791121 | AI312: =AC312-Y311*'OverNight €'!I312*E312/360 -> 6508.1973
B313: =CONCATENATE(MONTH(D313)," ",YEAR(D313)) -> 11 2025 | C313: =D312 -> 45965 | D313: =D312+1 -> 45966 | E313: =D313-C313 -> 1 | F313: SG | H313: =C313 -> 45965 | I313: 101.2227 | K313: 100000 | X313: =X312+L313-N313 -> 513 | Y313: =Y312 -> 51852398 | Z313: =X313*K313*ROUND(I313,4)% -> 51927245 | AB313: =Z313-Y313 -> 74846.7 | AC313: =Z313+T313-Z312-M313 -> 2975.4 | AF313: =AF314 -> 0.020810421 | AG313: =(I313/$I$288-1)*360/(D313-$D$288) -> 0.020785779 | AI313: =AC313-Y312*'OverNight €'!I313*E313/360 -> 454.7973
B314: =CONCATENATE(MONTH(D314)," ",YEAR(D314)) -> 11 2025 | C314: =D313 -> 45966 | D314: =D313+1 -> 45967 | E314: =D314-C314 -> 1 | F314: SG | H314: =C314 -> 45966 | I314: 101.2286 | K314: 100000 | P314: 149 | T314: =P314*I314%*K314 -> 15083061 | U314: =P314*(I314-I288)%*K314 -> 22618.2 | V314: =T314-U314 -> 15060443 | X314: =X313+L314-P314 -> 364 | Y314: =Y313-V314 -> 36791955 | Z314: =X314*K314*ROUND(I314,4)% -> 36847210 | AB314: =Z314-Y314 -> 55255.2 | AC314: =Z314+T314-Z313-M314 -> 3026.7 | AF314: =AF315 -> 0.020810421 | AG314: =(I314/$I$288-1)*360/(D314-$D$288) -> 0.020794546 | AI314: =AC314-Y313*'OverNight €'!I314*E314/360 -> 506.0973
B315: =CONCATENATE(MONTH(D315)," ",YEAR(D315)) -> 11 2025 | C315: =D314 -> 45967 | D315: =D314+1 -> 45968 | E315: =D315-C315 -> 1 | F315: SG | H315: =C315 -> 45967 | I315: 101.2344 | K315: 100000 | X315: =X314+L315-N315 -> 364 | Y315: =Y314 -> 36791955 | Z315: =X315*K315*ROUND(I315,4)% -> 36849322 | AB315: =Z315-Y315 -> 57366.4 | AC315: =Z315+T315-Z314-M315 -> 2111.2 | AF315: =AF316 -> 0.020810421 | AG315: =(I315/$I$288-1)*360/(D315-$D$288) -> 0.020789472 | AI315: =AC315-Y314*'OverNight €'!I315*E315/360 -> 322.70218
B316: =CONCATENATE(MONTH(D316)," ",YEAR(D316)) -> 11 2025 | C316: =D315 -> 45968 | D316: =D315+1 -> 45969 | E316: =D316-C316 -> 1 | F316: SG | H316: =C316 -> 45968 | I316: 101.2403 | K316: 100000 | X316: =X315+L316-N316 -> 364 | Y316: =Y315 -> 36791955 | Z316: =X316*K316*ROUND(I316,4)% -> 36851469 | AB316: =Z316-Y316 -> 59514 | AC316: =Z316+T316-Z315-M316 -> 2147.6 | AF316: =AF317 -> 0.020810421 | AG316: =(I316/$I$288-1)*360/(D316-$D$288) -> 0.020797481 | AI316: =AC316-Y315*'OverNight €'!I316*E316/360 -> 359.10218
B317: =CONCATENATE(MONTH(D317)," ",YEAR(D317)) -> 11 2025 | C317: =D316 -> 45969 | D317: =D316+1 -> 45970 | E317: =D317-C317 -> 1 | F317: SG | H317: =C317 -> 45969 | I317: 101.2403 | K317: 100000 | X317: =X316+L317-N317 -> 364 | Y317: =Y316 -> 36791955 | Z317: =X317*K317*ROUND(I317,4)% -> 36851469 | AB317: =Z317-Y317 -> 59514 | AC317: =Z317+T317-Z316-M317 -> 0 | AF317: =AF318 -> 0.020810421 | AG317: =(I317/$I$288-1)*360/(D317-$D$288) -> 0.020080327 | AI317: =AC317-Y316*'OverNight €'!I317*E317/360 -> -1788.4978
B318: =CONCATENATE(MONTH(D318)," ",YEAR(D318)) -> 11 2025 | C318: =D317 -> 45970 | D318: =D317+1 -> 45971 | E318: =D318-C318 -> 1 | F318: SG | H318: =C318 -> 45970 | I318: 101.2403 | K318: 100000 | X318: =X317+L318-N318 -> 364 | Y318: =Y317 -> 36791955 | Z318: =X318*K318*ROUND(I318,4)% -> 36851469 | AB318: =Z318-Y318 -> 59514 | AC318: =Z318+T318-Z317-M318 -> 0 | AF318: =AF319 -> 0.020810421 | AG318: =(I318/$I$288-1)*360/(D318-$D$288) -> 0.019410983 | AI318: =AC318-Y317*'OverNight €'!I318*E318/360 -> -1788.4978
B319: =CONCATENATE(MONTH(D319)," ",YEAR(D319)) -> 11 2025 | C319: =D318 -> 45971 | D319: =D318+1 -> 45972 | E319: =D319-C319 -> 1 | F319: SG | H319: =C319 -> 45971 | I319: 101.2578 | K319: 100000 | X319: =X318+L319-N319 -> 364 | Y319: =Y318 -> 36791955 | Z319: =X319*K319*ROUND(I319,4)% -> 36857839 | AB319: =Z319-Y319 -> 65884 | AC319: =Z319+T319-Z318-M319 -> 6370 | AF319: =AF320 -> 0.020810421 | AG319: =(I319/$I$288-1)*360/(D319-$D$288) -> 0.02079543 | AI319: =AC319-Y318*'OverNight €'!I319*E319/360 -> 4581.5022
B320: =CONCATENATE(MONTH(D320)," ",YEAR(D320)) -> 11 2025 | C320: =D319 -> 45972 | D320: =D319+1 -> 45973 | E320: =D320-C320 -> 1 | F320: SG | H320: =C320 -> 45972 | I320: 101.2637 | K320: 100000 | X320: =X319+L320-N320 -> 364 | Y320: =Y319 -> 36791955 | Z320: =X320*K320*ROUND(I320,4)% -> 36859987 | AB320: =Z320-Y320 -> 68031.6 | AC320: =Z320+T320-Z319-M320 -> 2147.6 | AF320: =AF321 -> 0.020810421 | AG320: =(I320/$I$288-1)*360/(D320-$D$288) -> 0.020802251 | AI320: =AC320-Y319*'OverNight €'!I320*E320/360 -> 359.10218
B321: =CONCATENATE(MONTH(D321)," ",YEAR(D321)) -> 11 2025 | C321: =D320 -> 45973 | D321: =D320+1 -> 45974 | E321: =D321-C321 -> 1 | F321: SG | H321: =C321 -> 45973 | I321: 101.2695 | K321: 100000 | X321: =X320+L321-N321 -> 364 | Y321: =Y320 -> 36791955 | Z321: =X321*K321*ROUND(I321,4)% -> 36862098 | AB321: =Z321-Y321 -> 70142.8 | AC321: =Z321+T321-Z320-M321 -> 2111.2 | AF321: =AF322 -> 0.020810421 | AG321: =(I321/$I$288-1)*360/(D321-$D$288) -> 0.020797867 | AI321: =AC321-Y320*'OverNight €'!I321*E321/360 -> 322.70218
B322: =CONCATENATE(MONTH(D322)," ",YEAR(D322)) -> 11 2025 | C322: =D321 -> 45974 | D322: =D321+1 -> 45975 | E322: =D322-C322 -> 1 | F322: SG | H322: =C322 -> 45974 | I322: 101.2754 | K322: 100000 | X322: =X321+L322-N322 -> 364 | Y322: =Y321 -> 36791955 | Z322: =X322*K322*ROUND(I322,4)% -> 36864246 | AB322: =Z322-Y322 -> 72290.4 | AC322: =Z322+T322-Z321-M322 -> 2147.6 | AF322: =AF323 -> 0.020810421 | AG322: =(I322/$I$288-1)*360/(D322-$D$288) -> 0.020804216 | AI322: =AC322-Y321*'OverNight €'!I322*E322/360 -> 359.10218
B323: =CONCATENATE(MONTH(D323)," ",YEAR(D323)) -> 11 2025 | C323: =D322 -> 45975 | D323: =D322+1 -> 45976 | E323: =D323-C323 -> 1 | F323: SG | H323: =C323 -> 45975 | I323: 101.2812 | K323: 100000 | X323: =X322+L323-N323 -> 364 | Y323: =Y322 -> 36791955 | Z323: =X323*K323*ROUND(I323,4)% -> 36866357 | AB323: =Z323-Y323 -> 74401.6 | AC323: =Z323+T323-Z322-M323 -> 2111.2 | AF323: =AF324 -> 0.020810421 | AG323: =(I323/$I$288-1)*360/(D323-$D$288) -> 0.020800025 | AI323: =AC323-Y322*'OverNight €'!I323*E323/360 -> 322.70218
B324: =CONCATENATE(MONTH(D324)," ",YEAR(D324)) -> 11 2025 | C324: =D323 -> 45976 | D324: =D323+1 -> 45977 | E324: =D324-C324 -> 1 | F324: SG | H324: =C324 -> 45976 | I324: 101.2812 | K324: 100000 | X324: =X323+L324-N324 -> 364 | Y324: =Y323 -> 36791955 | Z324: =X324*K324*ROUND(I324,4)% -> 36866357 | AB324: =Z324-Y324 -> 74401.6 | AC324: =Z324+T324-Z323-M324 -> 0 | AF324: =AF325 -> 0.020810421 | AG324: =(I324/$I$288-1)*360/(D324-$D$288) -> 0.020222247 | AI324: =AC324-Y323*'OverNight €'!I324*E324/360 -> -1788.4978
B325: =CONCATENATE(MONTH(D325)," ",YEAR(D325)) -> 11 2025 | C325: =D324 -> 45977 | D325: =D324+1 -> 45978 | E325: =D325-C325 -> 1 | F325: SG | H325: =C325 -> 45977 | I325: 101.2812 | K325: 100000 | X325: =X324+L325-N325 -> 364 | Y325: =Y324 -> 36791955 | Z325: =X325*K325*ROUND(I325,4)% -> 36866357 | AB325: =Z325-Y325 -> 74401.6 | AC325: =Z325+T325-Z324-M325 -> 0 | AF325: =AF326 -> 0.020810421 | AG325: =(I325/$I$288-1)*360/(D325-$D$288) -> 0.0196757 | AI325: =AC325-Y324*'OverNight €'!I325*E325/360 -> -1788.4978
B326: =CONCATENATE(MONTH(D326)," ",YEAR(D326)) -> 11 2025 | C326: =D325 -> 45978 | D326: =D325+1 -> 45979 | E326: =D326-C326 -> 1 | F326: SG | H326: =C326 -> 45978 | I326: 101.2988 | K326: 100000 | X326: =X325+L326-N326 -> 364 | Y326: =Y325 -> 36791955 | Z326: =X326*K326*ROUND(I326,4)% -> 36872763 | AB326: =Z326-Y326 -> 80808 | AC326: =Z326+T326-Z325-M326 -> 6406.4 | AF326: =AF327 -> 0.020810421 | AG326: =(I326/$I$288-1)*360/(D326-$D$288) -> 0.020807524 | AI326: =AC326-Y325*'OverNight €'!I326*E326/360 -> 4617.9022
... B336: =CONCATENATE(MONTH(D336)," ",YEAR(D336)) -> 11 2025 | C336: =D335 -> 45988 | D336: =D335+1 -> 45989 | E336: =D336-C336 -> 1 | F336: SG | H336: =C336 -> 45988 | I336: 101.3573 | K336: 100000 | X336: =X335+L336-N336 -> 364 | Y336: =Y335 -> 36791955 | Z336: =X336*K336*ROUND(I336,4)% -> 36894057 | AB336: =Z336-Y336 -> 102102 | AC336: =Z336+T336-Z335-M336 -> 2147.6 | AF336: =AF337 -> 0.020810421 | AG336: =(I336/$I$288-1)*360/(D336-$D$288) -> 0.020813382 | AI336: =AC336-Y335*'OverNight €'!I336*E336/360 -> 359.10218
B337: =CONCATENATE(MONTH(D337)," ",YEAR(D337)) -> 11 2025 | C337: =D336 -> 45989 | D337: =D336+1 -> 45990 | E337: =D337-C337 -> 1 | F337: SG | H337: =C337 -> 45989 | I337: 101.3631 | K337: 100000 | X337: =X336+L337-N337 -> 364 | Y337: =Y336 -> 36791955 | Z337: =X337*K337*ROUND(I337,4)% -> 36896168 | AB337: =Z337-Y337 -> 104213.2 | AC337: =Z337+T337-Z336-M337 -> 2111.2 | AD337: =SUM(AC310:AC337) -> 63988.9 | AF337: =(I337/I309-1)*360/(H337-H309) -> 0.020810421 | AG337: =(I337/$I$288-1)*360/(D337-$D$288) -> 0.020810201 | AI337: =AC337-Y336*'OverNight €'!I337*E337/360 -> 322.70218
B338: =CONCATENATE(MONTH(D338)," ",YEAR(D338)) -> 11 2025 | C338: =D337 -> 45990 | D338: =D337+1 -> 45991 | E338: =D338-C338 -> 1 | F338: SG | H338: =C338 -> 45990 | I338: 101.3631 | K338: 100000 | X338: =X337+L338-N338 -> 364 | Y338: =Y337 -> 36791955 | Z338: =X338*K338*ROUND(I338,4)% -> 36896168 | AB338: =Z338-Y338 -> 104213.2 | AC338: =Z338+T338-Z337-M338 -> 0 | AF338: =AF339 -> 0.02081446 | AG338: =(I338/$I$288-1)*360/(D338-$D$288) -> 0.020393997 | AI338: =AC338-Y337*'OverNight €'!I338*E338/360 -> -1788.4978
B339: =CONCATENATE(MONTH(D339)," ",YEAR(D339)) -> 12 2025 | C339: =D338 -> 45991 | D339: =D338+1 -> 45992 | E339: =D339-C339 -> 1 | F339: SG | H339: =C339 -> 45991 | I339: 101.3631 | K339: 100000 | X339: =X338+L339-N339 -> 364 | Y339: =Y338 -> 36791955 | Z339: =X339*K339*ROUND(I339,4)% -> 36896168 | AB339: =Z339-Y339 -> 104213.2 | AC339: =Z339+T339-Z338-M339 -> 0 | AF339: =AF340 -> 0.02081446 | AG339: =(I339/$I$288-1)*360/(D339-$D$288) -> 0.019994115 | AI339: =AC339-Y338*'OverNight €'!I339*E339/360 -> -1788.4978
B340: =CONCATENATE(MONTH(D340)," ",YEAR(D340)) -> 12 2025 | C340: =D339 -> 45992 | D340: =D339+1 -> 45993 | E340: =D340-C340 -> 1 | F340: SG | H340: =C340 -> 45992 | I340: 101.3807 | K340: 100000 | X340: =X339+L340-N340 -> 364 | Y340: =Y339 -> 36791955 | Z340: =X340*K340*ROUND(I340,4)% -> 36902575 | AB340: =Z340-Y340 -> 110619.6 | AC340: =Z340+T340-Z339-M340 -> 6406.4 | AF340: =AF341 -> 0.02081446 | AG340: =(I340/$I$288-1)*360/(D340-$D$288) -> 0.020815094 | AI340: =AC340-Y339*'OverNight €'!I340*E340/360 -> 4617.9022
B341: =CONCATENATE(MONTH(D341)," ",YEAR(D341)) -> 12 2025 | C341: =D340 -> 45993 | D341: =D340+1 -> 45994 | E341: =D341-C341 -> 1 | F341: SG | H341: =C341 -> 45993 | I341: 101.3865 | K341: 100000 | X341: =X340+L341-N341 -> 364 | Y341: =Y340 -> 36791955 | Z341: =X341*K341*ROUND(I341,4)% -> 36904686 | AB341: =Z341-Y341 -> 112730.8 | AC341: =Z341+T341-Z340-M341 -> 2111.2 | AF341: =AF342 -> 0.02081446 | AG341: =(I341/$I$288-1)*360/(D341-$D$288) -> 0.020812121 | AI341: =AC341-Y340*'OverNight €'!I341*E341/360 -> 322.70218
B342: =CONCATENATE(MONTH(D342)," ",YEAR(D342)) -> 12 2025 | C342: =D341 -> 45994 | D342: =D341+1 -> 45995 | E342: =D342-C342 -> 1 | F342: SG | H342: =C342 -> 45994 | I342: 101.3924 | K342: 100000 | X342: =X341+L342-N342 -> 364 | Y342: =Y341 -> 36791955 | Z342: =X342*K342*ROUND(I342,4)% -> 36906834 | AB342: =Z342-Y342 -> 114878.4 | AC342: =Z342+T342-Z341-M342 -> 2147.6 | AF342: =AF343 -> 0.02081446 | AG342: =(I342/$I$288-1)*360/(D342-$D$288) -> 0.020815855 | AI342: =AC342-Y341*'OverNight €'!I342*E342/360 -> 359.10218
B343: =CONCATENATE(MONTH(D343)," ",YEAR(D343)) -> 12 2025 | C343: =D342 -> 45995 | D343: =D342+1 -> 45996 | E343: =D343-C343 -> 1 | F343: SG | H343: =C343 -> 45995 | I343: 101.3982 | K343: 100000 | X343: =X342+L343-N343 -> 364 | Y343: =Y342 -> 36791955 | Z343: =X343*K343*ROUND(I343,4)% -> 36908945 | AB343: =Z343-Y343 -> 116989.6 | AC343: =Z343+T343-Z342-M343 -> 2111.2 | AF343: =AF344 -> 0.02081446 | AG343: =(I343/$I$288-1)*360/(D343-$D$288) -> 0.020812977 | AI343: =AC343-Y342*'OverNight €'!I343*E343/360 -> 322.70218
B344: =CONCATENATE(MONTH(D344)," ",YEAR(D344)) -> 12 2025 | C344: =D343 -> 45996 | D344: =D343+1 -> 45997 | E344: =D344-C344 -> 1 | F344: SG | H344: =C344 -> 45996 | I344: 101.4041 | K344: 100000 | X344: =X343+L344-N344 -> 364 | Y344: =Y343 -> 36791955 | Z344: =X344*K344*ROUND(I344,4)% -> 36911092 | AB344: =Z344-Y344 -> 119137.2 | AC344: =Z344+T344-Z343-M344 -> 2147.6 | AF344: =AF345 -> 0.02081446 | AG344: =(I344/$I$288-1)*360/(D344-$D$288) -> 0.020816562 | AI344: =AC344-Y343*'OverNight €'!I344*E344/360 -> 359.10218
B345: =CONCATENATE(MONTH(D345)," ",YEAR(D345)) -> 12 2025 | C345: =D344 -> 45997 | D345: =D344+1 -> 45998 | E345: =D345-C345 -> 1 | F345: SG | H345: =C345 -> 45997 | I345: 101.4041 | K345: 100000 | X345: =X344+L345-N345 -> 364 | Y345: =Y344 -> 36791955 | Z345: =X345*K345*ROUND(I345,4)% -> 36911092 | AB345: =Z345-Y345 -> 119137.2 | AC345: =Z345+T345-Z344-M345 -> 0 | AF345: =AF346 -> 0.02081446 | AG345: =(I345/$I$288-1)*360/(D345-$D$288) -> 0.020451359 | AI345: =AC345-Y344*'OverNight €'!I345*E345/360 -> -1788.4978
B346: =CONCATENATE(MONTH(D346)," ",YEAR(D346)) -> 12 2025 | C346: =D345 -> 45998 | D346: =D345+1 -> 45999 | E346: =D346-C346 -> 1 | F346: SG | H346: =C346 -> 45998 | I346: 101.4041 | K346: 100000 | X346: =X345+L346-N346 -> 364 | Y346: =Y345 -> 36791955 | Z346: =X346*K346*ROUND(I346,4)% -> 36911092 | AB346: =Z346-Y346 -> 119137.2 | AC346: =Z346+T346-Z345-M346 -> 0 | AF346: =AF347 -> 0.02081446 | AG346: =(I346/$I$288-1)*360/(D346-$D$288) -> 0.020098749 | AI346: =AC346-Y345*'OverNight €'!I346*E346/360 -> -1788.4978
B347: =CONCATENATE(MONTH(D347)," ",YEAR(D347)) -> 12 2025 | C347: =D346 -> 45999 | D347: =D346+1 -> 46000 | E347: =D347-C347 -> 1 | F347: SG | H347: =C347 -> 45999 | I347: 101.4216 | K347: 100000 | X347: =X346+L347-N347 -> 364 | Y347: =Y346 -> 36791955 | Z347: =X347*K347*ROUND(I347,4)% -> 36917462 | AB347: =Z347-Y347 -> 125507.2 | AC347: =Z347+T347-Z346-M347 -> 6370 | AF347: =AF348 -> 0.02081446 | AG347: =(I347/$I$288-1)*360/(D347-$D$288) -> 0.020814513 | AI347: =AC347-Y346*'OverNight €'!I347*E347/360 -> 4581.5022
B348: =CONCATENATE(MONTH(D348)," ",YEAR(D348)) -> 12 2025 | C348: =D347 -> 46000 | D348: =D347+1 -> 46001 | E348: =D348-C348 -> 1 | F348: SG | H348: =C348 -> 46000 | I348: 101.4275 | K348: 100000 | X348: =X347+L348-N348 -> 364 | Y348: =Y347 -> 36791955 | Z348: =X348*K348*ROUND(I348,4)% -> 36919610 | AB348: =Z348-Y348 -> 127654.8 | AC348: =Z348+T348-Z347-M348 -> 2147.6 | AF348: =AF349 -> 0.02081446 | AG348: =(I348/$I$288-1)*360/(D348-$D$288) -> 0.020817834 | AI348: =AC348-Y347*'OverNight €'!I348*E348/360 -> 359.10218
B349: =CONCATENATE(MONTH(D349)," ",YEAR(D349)) -> 12 2025 | C349: =D348 -> 46001 | D349: =D348+1 -> 46002 | E349: =D349-C349 -> 1 | F349: SG | H349: =C349 -> 46001 | I349: 101.4334 | K349: 100000 | X349: =X348+L349-N349 -> 364 | Y349: =Y348 -> 36791955 | Z349: =X349*K349*ROUND(I349,4)% -> 36921758 | AB349: =Z349-Y349 -> 129802.4 | AC349: =Z349+T349-Z348-M349 -> 2147.6 | AF349: =AF350 -> 0.02081446 | AG349: =(I349/$I$288-1)*360/(D349-$D$288) -> 0.020821045 | AI349: =AC349-Y348*'OverNight €'!I349*E349/360 -> 359.10218
... B357: =CONCATENATE(MONTH(D357)," ",YEAR(D357)) -> 12 2025 | C357: =D356 -> 46009 | D357: =D356+1 -> 46010 | E357: =D357-C357 -> 1 | F357: SG | H357: =C357 -> 46009 | I357: 101.4803 | K357: 100000 | X357: =X356+L357-N357 -> 364 | Y357: =Y356 -> 36791955 | Z357: =X357*K357*ROUND(I357,4)% -> 36938829 | AB357: =Z357-Y357 -> 146874 | AC357: =Z357+T357-Z356-M357 -> 2147.6 | AF357: =AF358 -> 0.02081446 | AG357: =(I357/$I$288-1)*360/(D357-$D$288) -> 0.020827899 | AI357: =AC357-Y356*'OverNight €'!I357*E357/360 -> 359.10218
B358: =CONCATENATE(MONTH(D358)," ",YEAR(D358)) -> 12 2025 | C358: =D357 -> 46010 | D358: =D357+1 -> 46011 | E358: =D358-C358 -> 1 | F358: SG | H358: =C358 -> 46010 | I358: 101.4861 | K358: 100000 | L358: 296 | M358: =ROUND(L358*K358*ROUND(I358,4)%,2) -> 30039886 | X358: =X357+L358-N358 -> 660 | Y358: =Y357+M358 -> 66831841 | Z358: =X358*K358*ROUND(I358,4)% -> 66980826 | AB358: =Z358-Y358 -> 148985.2 | AC358: =Z358+T358-Z357-M358 -> 2111.2 | AF358: =AF359 -> 0.02081446 | AG358: =(I358/$I$288-1)*360/(D358-$D$288) -> 0.020825466 | AI358: =AC358-Y357*'OverNight €'!I358*E358/360 -> 322.70218
B359: =CONCATENATE(MONTH(D359)," ",YEAR(D359)) -> 12 2025 | C359: =D358 -> 46011 | D359: =D358+1 -> 46012 | E359: =D359-C359 -> 1 | F359: SG | H359: =C359 -> 46011 | I359: 101.4861 | K359: 100000 | X359: =X358+L359-N359 -> 660 | Y359: =Y358 -> 66831841 | Z359: =X359*K359*ROUND(I359,4)% -> 66980826 | AB359: =Z359-Y359 -> 148985.2 | AC359: =Z359+T359-Z358-M359 -> 0 | AF359: =AF360 -> 0.02081446 | AG359: =(I359/$I$288-1)*360/(D359-$D$288) -> 0.020532149 | AI359: =AC359-Y358*'OverNight €'!I359*E359/360 -> -3248.77
B360: =CONCATENATE(MONTH(D360)," ",YEAR(D360)) -> 12 2025 | C360: =D359 -> 46012 | D360: =D359+1 -> 46013 | E360: =D360-C360 -> 1 | F360: SG | H360: =C360 -> 46012 | I360: 101.4861 | K360: 100000 | X360: =X359+L360-N360 -> 660 | Y360: =Y359 -> 66831841 | Z360: =X360*K360*ROUND(I360,4)% -> 66980826 | AB360: =Z360-Y360 -> 148985.2 | AC360: =Z360+T360-Z359-M360 -> 0 | AF360: =AF361 -> 0.02081446 | AG360: =(I360/$I$288-1)*360/(D360-$D$288) -> 0.020246981 | AI360: =AC360-Y359*'OverNight €'!I360*E360/360 -> -3248.77
B361: =CONCATENATE(MONTH(D361)," ",YEAR(D361)) -> 12 2025 | C361: =D360 -> 46013 | D361: =D360+1 -> 46014 | E361: =D361-C361 -> 1 | F361: SG | H361: =C361 -> 46013 | I361: 101.5037 | K361: 100000 | X361: =X360+L361-N361 -> 660 | Y361: =Y360 -> 66831841 | Z361: =X361*K361*ROUND(I361,4)% -> 66992442 | AB361: =Z361-Y361 -> 160601.2 | AC361: =Z361+T361-Z360-M361 -> 11616 | AF361: =AF362 -> 0.02081446 | AG361: =(I361/$I$288-1)*360/(D361-$D$288) -> 0.020828323 | AI361: =AC361-Y360*'OverNight €'!I361*E361/360 -> 8367.23
B362: =CONCATENATE(MONTH(D362)," ",YEAR(D362)) -> 12 2025 | C362: =D361 -> 46014 | D362: =D361+1 -> 46015 | E362: =D362-C362 -> 1 | F362: SG | H362: =C362 -> 46014 | I362: 101.5096 | K362: 100000 | X362: =X361+L362-N362 -> 660 | Y362: =Y361 -> 66831841 | Z362: =X362*K362*ROUND(I362,4)% -> 66996336 | AB362: =Z362-Y362 -> 164495.2 | AC362: =Z362+T362-Z361-M362 -> 3894 | AF362: =AF363 -> 0.02081446 | AG362: =(I362/$I$288-1)*360/(D362-$D$288) -> 0.020830829 | AI362: =AC362-Y361*'OverNight €'!I362*E362/360 -> 645.22996
B363: =CONCATENATE(MONTH(D363)," ",YEAR(D363)) -> 12 2025 | C363: =D362 -> 46015 | D363: =D362+1 -> 46016 | E363: =D363-C363 -> 1 | F363: SG | H363: =C363 -> 46015 | I363: 101.5155 | K363: 100000 | X363: =X362+L363-N363 -> 660 | Y363: =Y362 -> 66831841 | Z363: =X363*K363*ROUND(I363,4)% -> 67000230 | AB363: =Z363-Y363 -> 168389.2 | AC363: =Z363+T363-Z362-M363 -> 3894 | AF363: =AF364 -> 0.02081446 | AG363: =(I363/$I$288-1)*360/(D363-$D$288) -> 0.020833267 | AI363: =AC363-Y362*'OverNight €'!I363*E363/360 -> 645.22996
B364: =CONCATENATE(MONTH(D364)," ",YEAR(D364)) -> 12 2025 | C364: =D363 -> 46016 | D364: =D363+1 -> 46017 | E364: =D364-C364 -> 1 | F364: SG | H364: =C364 -> 46016 | I364: 101.5155 | K364: 100000 | X364: =X363+L364-N364 -> 660 | Y364: =Y363 -> 66831841 | Z364: =X364*K364*ROUND(I364,4)% -> 67000230 | AB364: =Z364-Y364 -> 168389.2 | AC364: =Z364+T364-Z363-M364 -> 0 | AF364: =AF365 -> 0.02081446 | AG364: =(I364/$I$288-1)*360/(D364-$D$288) -> 0.020559145 | AI364: =AC364-Y363*'OverNight €'!I364*E364/360 -> -3248.77
B365: =CONCATENATE(MONTH(D365)," ",YEAR(D365)) -> 12 2025 | C365: =D364 -> 46017 | D365: =D364+1 -> 46018 | E365: =D365-C365 -> 1 | F365: SG | H365: =C365 -> 46017 | I365: 101.5155 | K365: 100000 | X365: =X364+L365-N365 -> 660 | Y365: =Y364 -> 66831841 | Z365: =X365*K365*ROUND(I365,4)% -> 67000230 | AB365: =Z365-Y365 -> 168389.2 | AC365: =Z365+T365-Z364-M365 -> 0 | AF365: =AF366 -> 0.02081446 | AG365: =(I365/$I$288-1)*360/(D365-$D$288) -> 0.020292144 | AI365: =AC365-Y364*'OverNight €'!I365*E365/360 -> -3248.77
B366: =CONCATENATE(MONTH(D366)," ",YEAR(D366)) -> 12 2025 | C366: =D365 -> 46018 | D366: =D365+1 -> 46019 | E366: =D366-C366 -> 1 | F366: SG | H366: =C366 -> 46018 | I366: 101.5155 | K366: 100000 | X366: =X365+L366-N366 -> 660 | Y366: =Y365 -> 66831841 | Z366: =X366*K366*ROUND(I366,4)% -> 67000230 | AB366: =Z366-Y366 -> 168389.2 | AC366: =Z366+T366-Z365-M366 -> 0 | AF366: =AF367 -> 0.02081446 | AG366: =(I366/$I$288-1)*360/(D366-$D$288) -> 0.020031988 | AI366: =AC366-Y365*'OverNight €'!I366*E366/360 -> -3248.77
B367: =CONCATENATE(MONTH(D367)," ",YEAR(D367)) -> 12 2025 | C367: =D366 -> 46019 | D367: =D366+1 -> 46020 | E367: =D367-C367 -> 1 | F367: SG | H367: =C367 -> 46019 | I367: 101.5155 | K367: 100000 | X367: =X366+L367-N367 -> 660 | Y367: =Y366 -> 66831841 | Z367: =X367*K367*ROUND(I367,4)% -> 67000230 | AB367: =Z367-Y367 -> 168389.2 | AC367: =Z367+T367-Z366-M367 -> 0 | AF367: =AF368 -> 0.02081446 | AG367: =(I367/$I$288-1)*360/(D367-$D$288) -> 0.019778418 | AI367: =AC367-Y366*'OverNight €'!I367*E367/360 -> -3248.77
B368: =CONCATENATE(MONTH(D368)," ",YEAR(D368)) -> 12 2025 | C368: =D367 -> 46020 | D368: =D367+1 -> 46021 | E368: =D368-C368 -> 1 | F368: SG | H368: =C368 -> 46020 | I368: 101.5447 | K368: 100000 | X368: =X367+L368-N368 -> 660 | Y368: =Y367 -> 66831841 | Z368: =X368*K368*ROUND(I368,4)% -> 67019502 | AB368: =Z368-Y368 -> 187661.2 | AC368: =Z368+T368-Z367-M368 -> 19272 | AF368: =AF369 -> 0.02081446 | AG368: =(I368/$I$288-1)*360/(D368-$D$288) -> 0.02083119 | AI368: =AC368-Y367*'OverNight €'!I368*E368/360 -> 16023.23
B369: =CONCATENATE(MONTH(D369)," ",YEAR(D369)) -> 12 2025 | C369: =D368 -> 46021 | D369: =D368+1 -> 46022 | E369: =D369-C369 -> 1 | F369: SG | H369: =C369 -> 46021 | I369: 101.5506 | K369: 100000 | X369: =X368+L369-N369 -> 660 | Y369: =Y368 -> 66831841 | Z369: =X369*K369*ROUND(I369,4)% -> 67023396 | AB369: =Z369-Y369 -> 191555.2 | AC369: =Z369+T369-Z368-M369 -> 3894 | AF369: =AF373 -> 0.02081446 | AG369: =(I369/$I$288-1)*360/(D369-$D$288) -> 0.020833443 | AI369: =AC369-Y368*'OverNight €'!I369*E369/360 -> 645.22996
B373: =CONCATENATE(MONTH(D373)," ",YEAR(D373)) -> 1 2026 | C373: =D369 -> 46022 | D373: =D369+1 -> 46023 | E373: =D373-C373 -> 1 | F373: SG | H373: =C373 -> 46022 | I373: 101.5565 | K373: 100000 | X373: =X369 -> 660 | Y373: =Y369 -> 66831841 | Z373: =X373*K373*ROUND(I373,4)% -> 67027290 | AB373: =Z373-Y373 -> 195449.2 | AC373: =Z373+T373-Z369-M373 -> 3894 | AD373: =SUM(AC338:AC369,AC373) -> 91236 | AF373: =(I373/I337-1)*360/(H373-H337) -> 0.02081446 | AG373: =(I373/$I$288-1)*360/(D373-$D$288) -> 0.020835642 | AI373: =AC373-Y372*'OverNight €'!I373*E373/360 -> 3894
...

Sheet CT- € Ellipsis BNP
C1: PLACEMENTS DE TRESORERIE AU JOUR LE JOUR
C2: Date de valeur pr mvt argent Date comptable pour solde | D2: Intérêts dû in fine ( à date d'échéance) | G2: Ellipsis | Z2: ce doit être les mêmes
B3: mois | C3: Date départ (Date de règlement) | D3: Date échéance | E3: Nbj | G3: Emetteur | H3: Date de Valorisation Fonds | K3: Achat (Parts) | L3: Valo achat | M3: Vente (Parts) | N3: vente | O3: FIFO-restant/total | P3: Valo Vente | Q3: Principal Vente | R3: PV Ventes | T3: Parts | U3: Principal | V3: PV | W3: PV quotidienne | X3: Valorisation (Date de départ) | Z3: Performance quotidienne | AA3: perf annuelle mensuelle annualisée | AB3: perf annuelle depuis le début (Formule linéaire) | AC3: gain/NCA
B5: =CONCATENATE(MONTH(D5)," ",YEAR(D5)) -> 1 2025 | C5: 45657 | D5: 45658 | E5: =D5-C5 -> 1
B6: =CONCATENATE(MONTH(D6)," ",YEAR(D6)) -> 1 2025 | C6: =D5 -> 45658 | D6: =C6+1 -> 45659 | E6: =D6-C6 -> 1
B7: =CONCATENATE(MONTH(D7)," ",YEAR(D7)) -> 1 2025 | C7: =D6 -> 45659 | D7: =D6+1 -> 45660 | E7: =D7-C7 -> 1
B8: =CONCATENATE(MONTH(D8)," ",YEAR(D8)) -> 1 2025 | C8: =D7 -> 45660 | D8: =D7+1 -> 45661 | E8: =D8-C8 -> 1
B9: =CONCATENATE(MONTH(D9)," ",YEAR(D9)) -> 1 2025 | C9: =D8 -> 45661 | D9: =D8+1 -> 45662 | E9: =D9-C9 -> 1
B10: =CONCATENATE(MONTH(D10)," ",YEAR(D10)) -> 1 2025 | C10: =D9 -> 45662 | D10: =D9+1 -> 45663 | E10: =D10-C10 -> 1
B11: =CONCATENATE(MONTH(D11)," ",YEAR(D11)) -> 1 2025 | C11: =D10 -> 45663 | D11: =D10+1 -> 45664 | E11: =D11-C11 -> 1
B12: =CONCATENATE(MONTH(D12)," ",YEAR(D12)) -> 1 2025 | C12: =D11 -> 45664 | D12: =D11+1 -> 45665 | E12: =D12-C12 -> 1
B13: =CONCATENATE(MONTH(D13)," ",YEAR(D13)) -> 1 2025 | C13: =D12 -> 45665 | D13: =D12+1 -> 45666 | E13: =D13-C13 -> 1
B14: =CONCATENATE(MONTH(D14)," ",YEAR(D14)) -> 1 2025 | C14: =D13 -> 45666 | D14: =D13+1 -> 45667 | E14: =D14-C14 -> 1
B15: =CONCATENATE(MONTH(D15)," ",YEAR(D15)) -> 1 2025 | C15: =D14 -> 45667 | D15: =D14+1 -> 45668 | E15: =D15-C15 -> 1
B16: =CONCATENATE(MONTH(D16)," ",YEAR(D16)) -> 1 2025 | C16: =D15 -> 45668 | D16: =D15+1 -> 45669 | E16: =D16-C16 -> 1
B17: =CONCATENATE(MONTH(D17)," ",YEAR(D17)) -> 1 2025 | C17: =D16 -> 45669 | D17: =D16+1 -> 45670 | E17: =D17-C17 -> 1
B18: =CONCATENATE(MONTH(D18)," ",YEAR(D18)) -> 1 2025 | C18: =D17 -> 45670 | D18: =D17+1 -> 45671 | E18: =D18-C18 -> 1
... B73: =CONCATENATE(MONTH(D73)," ",YEAR(D73)) -> 3 2025 | C73: =D72 -> 45725 | D73: =D72+1 -> 45726 | E73: =D73-C73 -> 1
A74: ICI | B74: =CONCATENATE(MONTH(D74)," ",YEAR(D74)) -> 3 2025 | C74: =D73 -> 45726 | D74: =D73+1 -> 45727 | E74: =D74-C74 -> 1
B75: =CONCATENATE(MONTH(D75)," ",YEAR(D75)) -> 3 2025 | C75: =D74 -> 45727 | D75: =D74+1 -> 45728 | E75: =D75-C75 -> 1
B76: =CONCATENATE(MONTH(D76)," ",YEAR(D76)) -> 3 2025 | C76: =D75 -> 45728 | D76: =D75+1 -> 45729 | E76: =D76-C76 -> 1 | V76: =X76-U76 -> 0 | W76: =V76-V75 -> 0 | X76: =T76*I76 -> 0
B77: =CONCATENATE(MONTH(D77)," ",YEAR(D77)) -> 3 2025 | C77: =D76 -> 45729 | D77: =D76+1 -> 45730 | E77: =D77-C77 -> 1 | V77: =X77-U77 -> 0 | W77: =V77-V76 -> 0 | X77: =T77*I77 -> 0 | Z77: =I77/I76-1 -> #DIV/0! | AB77: =(#REF!-1)*(360/(C77-$C$76)) -> #REF! | AC77: =W77-U76*'OverNight €'!I77*E77/360 -> 0
B78: =CONCATENATE(MONTH(D78)," ",YEAR(D78)) -> 3 2025 | C78: =D77 -> 45730 | D78: =D77+1 -> 45731 | E78: =D78-C78 -> 1 | V78: =X78-U78 -> 0 | W78: =V78-V77 -> 0 | X78: =T78*I78 -> 0 | Z78: =I78/I77-1 -> #DIV/0! | AB78: =(#REF!-1)*(360/(C78-$C$76)) -> #REF! | AC78: =W78-U77*'OverNight €'!I78*E78/360 -> 0
B79: =CONCATENATE(MONTH(D79)," ",YEAR(D79)) -> 3 2025 | C79: =D78 -> 45731 | D79: =D78+1 -> 45732 | E79: =D79-C79 -> 1 | V79: =X79-U79 -> 0 | W79: =V79-V78 -> 0 | X79: =T79*I79 -> 0 | Z79: =I79/I78-1 -> #DIV/0! | AB79: =(#REF!-1)*(360/(C79-$C$76)) -> #REF! | AC79: =W79-U78*'OverNight €'!I79*E79/360 -> 0
B80: =CONCATENATE(MONTH(D80)," ",YEAR(D80)) -> 3 2025 | C80: =D79 -> 45732 | D80: =D79+1 -> 45733 | E80: =D80-C80 -> 1 | V80: =X80-U80 -> 0 | W80: =V80-V79 -> 0 | X80: =T80*I80 -> 0 | Z80: =I80/I79-1 -> #DIV/0! | AB80: =(#REF!-1)*(360/(C80-$C$76)) -> #REF! | AC80: =W80-U79*'OverNight €'!I80*E80/360 -> 0
B81: =CONCATENATE(MONTH(D81)," ",YEAR(D81)) -> 3 2025 | C81: =D80 -> 45733 | D81: =D80+1 -> 45734 | E81: =D81-C81 -> 1 | V81: =X81-U81 -> 0 | W81: =V81-V80 -> 0 | X81: =T81*I81 -> 0 | Z81: =I81/I80-1 -> #DIV/0! | AB81: =(#REF!-1)*(360/(C81-$C$76)) -> #REF! | AC81: =W81-U80*'OverNight €'!I81*E81/360 -> 0
B82: =CONCATENATE(MONTH(D82)," ",YEAR(D82)) -> 3 2025 | C82: =D81 -> 45734 | D82: =D81+1 -> 45735 | E82: =D82-C82 -> 1 | V82: =X82-U82 -> 0 | W82: =V82-V81 -> 0 | X82: =T82*I82 -> 0 | Z82: =I82/I81-1 -> #DIV/0! | AB82: =(#REF!-1)*(360/(C82-$C$76)) -> #REF! | AC82: =W82-U81*'OverNight €'!I82*E82/360 -> 0
B83: =CONCATENATE(MONTH(D83)," ",YEAR(D83)) -> 3 2025 | C83: =D82 -> 45735 | D83: =D82+1 -> 45736 | E83: =D83-C83 -> 1 | V83: =X83-U83 -> 0 | W83: =V83-V82 -> 0 | X83: =T83*I83 -> 0 | Z83: =I83/I82-1 -> #DIV/0! | AB83: =(#REF!-1)*(360/(C83-$C$76)) -> #REF! | AC83: =W83-U82*'OverNight €'!I83*E83/360 -> 0
B84: =CONCATENATE(MONTH(D84)," ",YEAR(D84)) -> 3 2025 | C84: =D83 -> 45736 | D84: =D83+1 -> 45737 | E84: =D84-C84 -> 1 | V84: =X84-U84 -> 0 | W84: =V84-V83 -> 0 | X84: =T84*I84 -> 0 | Z84: =I84/I83-1 -> #DIV/0! | AB84: =(#REF!-1)*(360/(C84-$C$76)) -> #REF! | AC84: =W84-U83*'OverNight €'!I84*E84/360 -> 0
B85: =CONCATENATE(MONTH(D85)," ",YEAR(D85)) -> 3 2025 | C85: =D84 -> 45737 | D85: =D84+1 -> 45738 | E85: =D85-C85 -> 1 | V85: =X85-U85 -> 0 | W85: =V85-V84 -> 0 | X85: =T85*I85 -> 0 | Z85: =I85/I84-1 -> #DIV/0! | AB85: =(#REF!-1)*(360/(C85-$C$76)) -> #REF! | AC85: =W85-U84*'OverNight €'!I85*E85/360 -> 0
B86: =CONCATENATE(MONTH(D86)," ",YEAR(D86)) -> 3 2025 | C86: =D85 -> 45738 | D86: =D85+1 -> 45739 | E86: =D86-C86 -> 1 | V86: =X86-U86 -> 0 | W86: =V86-V85 -> 0 | X86: =T86*I86 -> 0 | Z86: =I86/I85-1 -> #DIV/0! | AB86: =(#REF!-1)*(360/(C86-$C$76)) -> #REF! | AC86: =W86-U85*'OverNight €'!I86*E86/360 -> 0
B87: =CONCATENATE(MONTH(D87)," ",YEAR(D87)) -> 3 2025 | C87: =D86 -> 45739 | D87: =D86+1 -> 45740 | E87: =D87-C87 -> 1 | V87: =X87-U87 -> 0 | W87: =V87-V86 -> 0 | X87: =T87*I87 -> 0 | Z87: =I87/I86-1 -> #DIV/0! | AB87: =(#REF!-1)*(360/(C87-$C$76)) -> #REF! | AC87: =W87-U86*'OverNight €'!I87*E87/360 -> 0
B88: =CONCATENATE(MONTH(D88)," ",YEAR(D88)) -> 3 2025 | C88: =D87 -> 45740 | D88: =D87+1 -> 45741 | E88: =D88-C88 -> 1 | V88: =X88-U88 -> 0 | W88: =V88-V87 -> 0 | X88: =T88*I88 -> 0 | Z88: =I88/I87-1 -> #DIV/0! | AB88: =(#REF!-1)*(360/(C88-$C$76)) -> #REF! | AC88: =W88-U87*'OverNight €'!I88*E88/360 -> 0
... B129: =CONCATENATE(MONTH(D129)," ",YEAR(D129)) -> 5 2025 | C129: =D128 -> 45781 | D129: =D128+1 -> 45782 | E129: =D129-C129 -> 1 | V129: =X129-U129 -> 0 | W129: =V129-V128 -> 0 | X129: =T129*I129 -> 0 | Z129: =I129/I128-1 -> #DIV/0! | AB129: =(#REF!-1)*(360/(C129-$C$76)) -> #REF! | AC129: =W129-U128*'OverNight €'!I129*E129/360 -> 0
B130: =CONCATENATE(MONTH(D130)," ",YEAR(D130)) -> 5 2025 | C130: =D129 -> 45782 | D130: =D129+1 -> 45783 | E130: =D130-C130 -> 1 | V130: =X130-U130 -> 0 | W130: =V130-V129 -> 0 | X130: =T130*I130 -> 0 | Z130: =I130/I129-1 -> #DIV/0! | AA130: =I130/I97-1 -> #DIV/0! | AB130: =(#REF!-1)*(360/(C130-$C$76)) -> #REF! | AC130: =W130-U129*'OverNight €'!I130*E130/360 -> 0
B131: =CONCATENATE(MONTH(D131)," ",YEAR(D131)) -> 5 2025 | C131: =D130 -> 45783 | D131: =D130+1 -> 45784 | E131: =D131-C131 -> 1 | V131: =X131-U131 -> 0 | W131: =V131-V130 -> 0 | X131: =T131*I131 -> 0 | Z131: =I131/I130-1 -> #DIV/0! | AB131: =(#REF!-1)*(360/(C131-$C$76)) -> #REF! | AC131: =W131-U130*'OverNight €'!I131*E131/360 -> 0
B132: =CONCATENATE(MONTH(D132)," ",YEAR(D132)) -> 5 2025 | C132: =D131 -> 45784 | D132: =D131+1 -> 45785 | E132: =D132-C132 -> 1 | V132: =X132-U132 -> 0 | W132: =V132-V131 -> 0 | X132: =T132*I132 -> 0 | Z132: =I132/I131-1 -> #DIV/0! | AB132: =(#REF!-1)*(360/(C132-$C$76)) -> #REF! | AC132: =W132-U131*'OverNight €'!I132*E132/360 -> 0
B133: =CONCATENATE(MONTH(D133)," ",YEAR(D133)) -> 5 2025 | C133: =D132 -> 45785 | D133: =D132+1 -> 45786 | E133: =D133-C133 -> 1 | V133: =X133-U133 -> 0 | W133: =V133-V132 -> 0 | X133: =T133*I133 -> 0 | Z133: =I133/I132-1 -> #DIV/0! | AB133: =(#REF!-1)*(360/(C133-$C$76)) -> #REF! | AC133: =W133-U132*'OverNight €'!I133*E133/360 -> 0
B134: =CONCATENATE(MONTH(D134)," ",YEAR(D134)) -> 5 2025 | C134: =D133 -> 45786 | D134: =D133+1 -> 45787 | E134: =D134-C134 -> 1 | V134: =X134-U134 -> 0 | W134: =V134-V133 -> 0 | X134: =T134*I134 -> 0 | Z134: =I134/I133-1 -> #DIV/0! | AB134: =(#REF!-1)*(360/(C134-$C$76)) -> #REF! | AC134: =W134-U133*'OverNight €'!I134*E134/360 -> 0
B135: =CONCATENATE(MONTH(D135)," ",YEAR(D135)) -> 5 2025 | C135: =D134 -> 45787 | D135: =D134+1 -> 45788 | E135: =D135-C135 -> 1 | V135: =X135-U135 -> 0 | W135: =V135-V134 -> 0 | X135: =T135*I135 -> 0 | Z135: =I135/I134-1 -> #DIV/0! | AB135: =(#REF!-1)*(360/(C135-$C$76)) -> #REF! | AC135: =W135-U134*'OverNight €'!I135*E135/360 -> 0
B136: =CONCATENATE(MONTH(D136)," ",YEAR(D136)) -> 5 2025 | C136: =D135 -> 45788 | D136: =D135+1 -> 45789 | E136: =D136-C136 -> 1 | V136: =X136-U136 -> 0 | W136: =V136-V135 -> 0 | X136: =T136*I136 -> 0 | Z136: =I136/I135-1 -> #DIV/0! | AB136: =(#REF!-1)*(360/(C136-$C$76)) -> #REF! | AC136: =W136-U135*'OverNight €'!I136*E136/360 -> 0
B137: =CONCATENATE(MONTH(D137)," ",YEAR(D137)) -> 5 2025 | C137: =D136 -> 45789 | D137: =D136+1 -> 45790 | E137: =D137-C137 -> 1 | V137: =X137-U137 -> 0 | W137: =V137-V136 -> 0 | X137: =T137*I137 -> 0 | Z137: =I137/I136-1 -> #DIV/0! | AB137: =(#REF!-1)*(360/(C137-$C$76)) -> #REF! | AC137: =W137-U136*'OverNight €'!I137*E137/360 -> 0
B138: =CONCATENATE(MONTH(D138)," ",YEAR(D138)) -> 5 2025 | C138: =D137 -> 45790 | D138: =D137+1 -> 45791 | E138: =D138-C138 -> 1 | V138: =X138-U138 -> 0 | W138: =V138-V137 -> 0 | X138: =T138*I138 -> 0 | Z138: =I138/I137-1 -> #DIV/0! | AB138: =(#REF!-1)*(360/(C138-$C$76)) -> #REF! | AC138: =W138-U137*'OverNight €'!I138*E138/360 -> 0
B139: =CONCATENATE(MONTH(D139)," ",YEAR(D139)) -> 5 2025 | C139: =D138 -> 45791 | D139: =D138+1 -> 45792 | E139: =D139-C139 -> 1 | V139: =X139-U139 -> 0 | W139: =V139-V138 -> 0 | X139: =T139*I139 -> 0 | Z139: =I139/I138-1 -> #DIV/0! | AB139: =(#REF!-1)*(360/(C139-$C$76)) -> #REF! | AC139: =W139-U138*'OverNight €'!I139*E139/360 -> 0
B140: =CONCATENATE(MONTH(D140)," ",YEAR(D140)) -> 5 2025 | C140: =D139 -> 45792 | D140: =D139+1 -> 45793 | E140: =D140-C140 -> 1 | V140: =X140-U140 -> 0 | W140: =V140-V139 -> 0 | X140: =T140*I140 -> 0 | Z140: =I140/I139-1 -> #DIV/0! | AB140: =(#REF!-1)*(360/(C140-$C$76)) -> #REF! | AC140: =W140-U139*'OverNight €'!I140*E140/360 -> 0
B141: =CONCATENATE(MONTH(D141)," ",YEAR(D141)) -> 5 2025 | C141: =D140 -> 45793 | D141: =D140+1 -> 45794 | E141: =D141-C141 -> 1 | V141: =X141-U141 -> 0 | W141: =V141-V140 -> 0 | X141: =T141*I141 -> 0 | Z141: =I141/I140-1 -> #DIV/0! | AB141: =(#REF!-1)*(360/(C141-$C$76)) -> #REF! | AC141: =W141-U140*'OverNight €'!I141*E141/360 -> 0
B142: =CONCATENATE(MONTH(D142)," ",YEAR(D142)) -> 5 2025 | C142: =D141 -> 45794 | D142: =D141+1 -> 45795 | E142: =D142-C142 -> 1 | V142: =X142-U142 -> 0 | W142: =V142-V141 -> 0 | X142: =T142*I142 -> 0 | Z142: =I142/I141-1 -> #DIV/0! | AB142: =(#REF!-1)*(360/(C142-$C$76)) -> #REF! | AC142: =W142-U141*'OverNight €'!I142*E142/360 -> 0
... B158: =CONCATENATE(MONTH(D158)," ",YEAR(D158)) -> 6 2025 | C158: =D157 -> 45810 | D158: =D157+1 -> 45811 | E158: =D158-C158 -> 1 | V158: =X158-U158 -> 0 | W158: =V158-V157 -> 0 | X158: =T158*I158 -> 0 | Z158: =I158/I157-1 -> #DIV/0! | AB158: =(#REF!-1)*(360/(C158-$C$76)) -> #REF! | AC158: =W158-U157*'OverNight €'!I158*E158/360 -> 0
B159: =CONCATENATE(MONTH(D159)," ",YEAR(D159)) -> 6 2025 | C159: =D158 -> 45811 | D159: =D158+1 -> 45812 | E159: =D159-C159 -> 1 | V159: =X159-U159 -> 0 | W159: =V159-V158 -> 0 | X159: =T159*I159 -> 0 | Z159: =I159/I158-1 -> #DIV/0! | AA159: =I159/I130-1 -> #DIV/0! | AB159: =(#REF!-1)*(360/(C159-$C$76)) -> #REF! | AC159: =W159-U158*'OverNight €'!I159*E159/360 -> 0
B160: =CONCATENATE(MONTH(D160)," ",YEAR(D160)) -> 6 2025 | C160: =D159 -> 45812 | D160: =D159+1 -> 45813 | E160: =D160-C160 -> 1 | V160: =X160-U160 -> 0 | W160: =V160-V159 -> 0 | X160: =T160*I160 -> 0 | Z160: =I160/I159-1 -> #DIV/0! | AB160: =(#REF!-1)*(360/(C160-$C$76)) -> #REF! | AC160: =W160-U159*'OverNight €'!I160*E160/360 -> 0
B161: =CONCATENATE(MONTH(D161)," ",YEAR(D161)) -> 6 2025 | C161: =D160 -> 45813 | D161: =D160+1 -> 45814 | E161: =D161-C161 -> 1 | V161: =X161-U161 -> 0 | W161: =V161-V160 -> 0 | X161: =T161*I161 -> 0 | Z161: =I161/I160-1 -> #DIV/0! | AB161: =(#REF!-1)*(360/(C161-$C$76)) -> #REF! | AC161: =W161-U160*'OverNight €'!I161*E161/360 -> 0
B162: =CONCATENATE(MONTH(D162)," ",YEAR(D162)) -> 6 2025 | C162: =D161 -> 45814 | D162: =D161+1 -> 45815 | E162: =D162-C162 -> 1 | V162: =X162-U162 -> 0 | W162: =V162-V161 -> 0 | X162: =T162*I162 -> 0 | Z162: =I162/I161-1 -> #DIV/0! | AB162: =(#REF!-1)*(360/(C162-$C$76)) -> #REF! | AC162: =W162-U161*'OverNight €'!I162*E162/360 -> 0
B163: =CONCATENATE(MONTH(D163)," ",YEAR(D163)) -> 6 2025 | C163: =D162 -> 45815 | D163: =D162+1 -> 45816 | E163: =D163-C163 -> 1 | V163: =X163-U163 -> 0 | W163: =V163-V162 -> 0 | X163: =T163*I163 -> 0 | Z163: =I163/I162-1 -> #DIV/0! | AB163: =(#REF!-1)*(360/(C163-$C$76)) -> #REF! | AC163: =W163-U162*'OverNight €'!I163*E163/360 -> 0
B164: =CONCATENATE(MONTH(D164)," ",YEAR(D164)) -> 6 2025 | C164: =D163 -> 45816 | D164: =D163+1 -> 45817 | E164: =D164-C164 -> 1 | V164: =X164-U164 -> 0 | W164: =V164-V163 -> 0 | X164: =T164*I164 -> 0 | Z164: =I164/I163-1 -> #DIV/0! | AB164: =(#REF!-1)*(360/(C164-$C$76)) -> #REF! | AC164: =W164-U163*'OverNight €'!I164*E164/360 -> 0
B165: =CONCATENATE(MONTH(D165)," ",YEAR(D165)) -> 6 2025 | C165: =D164 -> 45817 | D165: =D164+1 -> 45818 | E165: =D165-C165 -> 1 | V165: =X165-U165 -> 0 | W165: =V165-V164 -> 0 | X165: =T165*I165 -> 0 | Z165: =I165/I164-1 -> #DIV/0! | AB165: =(#REF!-1)*(360/(C165-$C$76)) -> #REF! | AC165: =W165-U164*'OverNight €'!I165*E165/360 -> 0
B166: =CONCATENATE(MONTH(D166)," ",YEAR(D166)) -> 6 2025 | C166: =D165 -> 45818 | D166: =D165+1 -> 45819 | E166: =D166-C166 -> 1 | V166: =X166-U166 -> 0 | W166: =V166-V165 -> 0 | X166: =T166*I166 -> 0 | Z166: =I166/I165-1 -> #DIV/0! | AB166: =(#REF!-1)*(360/(C166-$C$76)) -> #REF! | AC166: =W166-U165*'OverNight €'!I166*E166/360 -> 0
B167: =CONCATENATE(MONTH(D167)," ",YEAR(D167)) -> 6 2025 | C167: =D166 -> 45819 | D167: =D166+1 -> 45820 | E167: =D167-C167 -> 1 | V167: =X167-U167 -> 0 | W167: =V167+R167-V166 -> 0 | X167: =T167*I167 -> 0 | Z167: =I167/I166-1 -> #DIV/0! | AB167: =(#REF!-1)*(360/(C167-$C$76)) -> #REF! | AC167: =W167-U166*'OverNight €'!I167*E167/360 -> 0 | AD167: à valider avec Alan
B168: =CONCATENATE(MONTH(D168)," ",YEAR(D168)) -> 6 2025 | C168: =D167 -> 45820 | D168: =D167+1 -> 45821 | E168: =D168-C168 -> 1 | V168: =X168-U168 -> 0 | W168: =V168+R168-V167 -> 0 | X168: =T168*I168 -> 0 | Z168: =I168/I167-1 -> #DIV/0! | AB168: =(#REF!-1)*(360/(C168-$C$76)) -> #REF! | AC168: =W168-U167*'OverNight €'!I168*E168/360 -> 0
B169: =CONCATENATE(MONTH(D169)," ",YEAR(D169)) -> 6 2025 | C169: =D168 -> 45821 | D169: =D168+1 -> 45822 | E169: =D169-C169 -> 1 | V169: =X169-U169 -> 0 | W169: =V169+R169-V168 -> 0 | X169: =T169*I169 -> 0 | Z169: =I169/I168-1 -> #DIV/0! | AB169: =(#REF!-1)*(360/(C169-$C$76)) -> #REF! | AC169: =W169-U168*'OverNight €'!I169*E169/360 -> 0
B170: =CONCATENATE(MONTH(D170)," ",YEAR(D170)) -> 6 2025 | C170: =D169 -> 45822 | D170: =D169+1 -> 45823 | E170: =D170-C170 -> 1 | V170: =X170-U170 -> 0 | W170: =V170+R170-V169 -> 0 | X170: =T170*I170 -> 0 | Z170: =I170/I169-1 -> #DIV/0! | AB170: =(#REF!-1)*(360/(C170-$C$76)) -> #REF! | AC170: =W170-U169*'OverNight €'!I170*E170/360 -> 0
B171: =CONCATENATE(MONTH(D171)," ",YEAR(D171)) -> 6 2025 | C171: =D170 -> 45823 | D171: =D170+1 -> 45824 | E171: =D171-C171 -> 1 | V171: =X171-U171 -> 0 | W171: =V171+R171-V170 -> 0 | X171: =T171*I171 -> 0 | Z171: =I171/I170-1 -> #DIV/0! | AB171: =(#REF!-1)*(360/(C171-$C$76)) -> #REF! | AC171: =W171-U170*'OverNight €'!I171*E171/360 -> 0
B172: =CONCATENATE(MONTH(D172)," ",YEAR(D172)) -> 6 2025 | C172: =D171 -> 45824 | D172: =D171+1 -> 45825 | E172: =D172-C172 -> 1 | V172: =X172-U172 -> 0 | W172: =V172+R172-V171 -> 0 | X172: =T172*I172 -> 0 | Z172: =I172/I171-1 -> #DIV/0! | AB172: =(#REF!-1)*(360/(C172-$C$76)) -> #REF! | AC172: =W172-U171*'OverNight €'!I172*E172/360 -> 0
B173: =CONCATENATE(MONTH(D173)," ",YEAR(D173)) -> 6 2025 | C173: =D172 -> 45825 | D173: =D172+1 -> 45826 | E173: =D173-C173 -> 1 | V173: =X173-U173 -> 0 | W173: =V173+R173-V172 -> 0 | X173: =T173*I173 -> 0 | Z173: =I173/I172-1 -> #DIV/0! | AB173: =(#REF!-1)*(360/(C173-$C$76)) -> #REF! | AC173: =W173-U172*'OverNight €'!I173*E173/360 -> 0
B174: =CONCATENATE(MONTH(D174)," ",YEAR(D174)) -> 6 2025 | C174: =D173 -> 45826 | D174: =D173+1 -> 45827 | E174: =D174-C174 -> 1 | V174: =X174-U174 -> 0 | W174: =V174+R174-V173 -> 0 | X174: =T174*I174 -> 0 | Z174: =I174/I173-1 -> #DIV/0! | AB174: =(#REF!-1)*(360/(C174-$C$76)) -> #REF! | AC174: =W174-U173*'OverNight €'!I174*E174/360 -> 0
B175: =CONCATENATE(MONTH(D175)," ",YEAR(D175)) -> 6 2025 | C175: =D174 -> 45827 | D175: =D174+1 -> 45828 | E175: =D175-C175 -> 1 | V175: =X175-U175 -> 0 | W175: =V175+R175-V174 -> 0 | X175: =T175*I175 -> 0 | Z175: =I175/I174-1 -> #DIV/0! | AB175: =(#REF!-1)*(360/(C175-$C$76)) -> #REF! | AC175: =W175-U174*'OverNight €'!I175*E175/360 -> 0
B176: =CONCATENATE(MONTH(D176)," ",YEAR(D176)) -> 6 2025 | C176: =D175 -> 45828 | D176: =D175+1 -> 45829 | E176: =D176-C176 -> 1 | V176: =X176-U176 -> 0 | W176: =V176+R176-V175 -> 0 | X176: =T176*I176 -> 0 | Z176: =I176/I175-1 -> #DIV/0! | AB176: =(#REF!-1)*(360/(C176-$C$76)) -> #REF! | AC176: =W176-U175*'OverNight €'!I176*E176/360 -> 0
B177: =CONCATENATE(MONTH(D177)," ",YEAR(D177)) -> 6 2025 | C177: =D176 -> 45829 | D177: =D176+1 -> 45830 | E177: =D177-C177 -> 1 | V177: =X177-U177 -> 0 | W177: =V177+R177-V176 -> 0 | X177: =T177*I177 -> 0 | Z177: =I177/I176-1 -> #DIV/0! | AB177: =(#REF!-1)*(360/(C177-$C$76)) -> #REF! | AC177: =W177-U176*'OverNight €'!I177*E177/360 -> 0
B178: =CONCATENATE(MONTH(D178)," ",YEAR(D178)) -> 6 2025 | C178: =D177 -> 45830 | D178: =D177+1 -> 45831 | E178: =D178-C178 -> 1 | V178: =X178-U178 -> 0 | W178: =V178+R178-V177 -> 0 | X178: =T178*I178 -> 0 | Z178: =I178/I177-1 -> #DIV/0! | AB178: =(#REF!-1)*(360/(C178-$C$76)) -> #REF! | AC178: =W178-U177*'OverNight €'!I178*E178/360 -> 0
B179: =CONCATENATE(MONTH(D179)," ",YEAR(D179)) -> 6 2025 | C179: =D178 -> 45831 | D179: =D178+1 -> 45832 | E179: =D179-C179 -> 1 | V179: =X179-U179 -> 0 | W179: =V179+R179-V178 -> 0 | X179: =T179*I179 -> 0 | Z179: =I179/I178-1 -> #DIV/0! | AB179: =(#REF!-1)*(360/(C179-$C$76)) -> #REF! | AC179: =W179-U178*'OverNight €'!I179*E179/360 -> 0
... B187: =CONCATENATE(MONTH(D187)," ",YEAR(D187)) -> 7 2025 | C187: =D186 -> 45839 | D187: =D186+1 -> 45840 | E187: =D187-C187 -> 1 | V187: =X187-U187 -> 0 | W187: =V187+R187-V186 -> 0 | X187: =T187*I187 -> 0 | Z187: =I187/I186-1 -> #DIV/0! | AB187: =(#REF!-1)*(360/(C187-$C$76)) -> #REF! | AC187: =W187-U186*'OverNight €'!I187*E187/360 -> 0
B188: =CONCATENATE(MONTH(D188)," ",YEAR(D188)) -> 7 2025 | C188: =D187 -> 45840 | D188: =D187+1 -> 45841 | E188: =D188-C188 -> 1 | V188: =X188-U188 -> 0 | W188: =V188+R188-V187 -> 0 | X188: =T188*I188 -> 0 | Z188: =I188/I187-1 -> #DIV/0! | AA188: =I188/I159-1 -> #DIV/0! | AB188: =(#REF!-1)*(360/(C188-$C$76)) -> #REF! | AC188: =W188-U187*'OverNight €'!I188*E188/360 -> 0
B189: =CONCATENATE(MONTH(D189)," ",YEAR(D189)) -> 7 2025 | C189: =D188 -> 45841 | D189: =D188+1 -> 45842 | E189: =D189-C189 -> 1 | V189: =X189-U189 -> 0 | W189: =V189+R189-V188 -> 0 | X189: =T189*I189 -> 0 | Z189: =I189/I188-1 -> #DIV/0! | AB189: =(#REF!-1)*(360/(C189-$C$76)) -> #REF! | AC189: =W189-U188*'OverNight €'!I189*E189/360 -> 0
B190: =CONCATENATE(MONTH(D190)," ",YEAR(D190)) -> 7 2025 | C190: =D189 -> 45842 | D190: =D189+1 -> 45843 | E190: =D190-C190 -> 1 | V190: =X190-U190 -> 0 | W190: =V190+R190-V189 -> 0 | X190: =T190*I190 -> 0 | Z190: =I190/I189-1 -> #DIV/0! | AB190: =(#REF!-1)*(360/(C190-$C$76)) -> #REF! | AC190: =W190-U189*'OverNight €'!I190*E190/360 -> 0
B191: =CONCATENATE(MONTH(D191)," ",YEAR(D191)) -> 7 2025 | C191: =D190 -> 45843 | D191: =D190+1 -> 45844 | E191: =D191-C191 -> 1 | V191: =X191-U191 -> 0 | W191: =V191+R191-V190 -> 0 | X191: =T191*I191 -> 0 | Z191: =I191/I190-1 -> #DIV/0! | AB191: =(#REF!-1)*(360/(C191-$C$76)) -> #REF! | AC191: =W191-U190*'OverNight €'!I191*E191/360 -> 0
B192: =CONCATENATE(MONTH(D192)," ",YEAR(D192)) -> 7 2025 | C192: =D191 -> 45844 | D192: =D191+1 -> 45845 | E192: =D192-C192 -> 1 | V192: =X192-U192 -> 0 | W192: =V192+R192-V191 -> 0 | X192: =T192*I192 -> 0 | Z192: =I192/I191-1 -> #DIV/0! | AB192: =(#REF!-1)*(360/(C192-$C$76)) -> #REF! | AC192: =W192-U191*'OverNight €'!I192*E192/360 -> 0
B193: =CONCATENATE(MONTH(D193)," ",YEAR(D193)) -> 7 2025 | C193: =D192 -> 45845 | D193: =D192+1 -> 45846 | E193: =D193-C193 -> 1 | V193: =X193-U193 -> 0 | W193: =V193+R193-V192 -> 0 | X193: =T193*I193 -> 0 | Z193: =I193/I192-1 -> #DIV/0! | AB193: =(#REF!-1)*(360/(C193-$C$76)) -> #REF! | AC193: =W193-U192*'OverNight €'!I193*E193/360 -> 0
B194: =CONCATENATE(MONTH(D194)," ",YEAR(D194)) -> 7 2025 | C194: =D193 -> 45846 | D194: =D193+1 -> 45847 | E194: =D194-C194 -> 1 | V194: =X194-U194 -> 0 | W194: =V194+R194-V193 -> 0 | X194: =T194*I194 -> 0 | Z194: =I194/I193-1 -> #DIV/0! | AB194: =(#REF!-1)*(360/(C194-$C$76)) -> #REF! | AC194: =W194-U193*'OverNight €'!I194*E194/360 -> 0
B195: =CONCATENATE(MONTH(D195)," ",YEAR(D195)) -> 7 2025 | C195: =D194 -> 45847 | D195: =D194+1 -> 45848 | E195: =D195-C195 -> 1 | V195: =X195-U195 -> 0 | W195: =V195+R195-V194 -> 0 | X195: =T195*I195 -> 0 | Z195: =I195/I194-1 -> #DIV/0! | AB195: =(#REF!-1)*(360/(C195-$C$76)) -> #REF! | AC195: =W195-U194*'OverNight €'!I195*E195/360 -> 0
B196: =CONCATENATE(MONTH(D196)," ",YEAR(D196)) -> 7 2025 | C196: =D195 -> 45848 | D196: =D195+1 -> 45849 | E196: =D196-C196 -> 1 | V196: =X196-U196 -> 0 | W196: =V196+R196-V195 -> 0 | X196: =T196*I196 -> 0 | Z196: =I196/I195-1 -> #DIV/0! | AB196: =(#REF!-1)*(360/(C196-$C$76)) -> #REF! | AC196: =W196-U195*'OverNight €'!I196*E196/360 -> 0
B197: =CONCATENATE(MONTH(D197)," ",YEAR(D197)) -> 7 2025 | C197: =D196 -> 45849 | D197: =D196+1 -> 45850 | E197: =D197-C197 -> 1 | V197: =X197-U197 -> 0 | W197: =V197+R197-V196 -> 0 | X197: =T197*I197 -> 0 | Z197: =I197/I196-1 -> #DIV/0! | AB197: =(#REF!-1)*(360/(C197-$C$76)) -> #REF! | AC197: =W197-U196*'OverNight €'!I197*E197/360 -> 0
B198: =CONCATENATE(MONTH(D198)," ",YEAR(D198)) -> 7 2025 | C198: =D197 -> 45850 | D198: =D197+1 -> 45851 | E198: =D198-C198 -> 1 | V198: =X198-U198 -> 0 | W198: =V198+R198-V197 -> 0 | X198: =T198*I198 -> 0 | Z198: =I198/I197-1 -> #DIV/0! | AB198: =(#REF!-1)*(360/(C198-$C$76)) -> #REF! | AC198: =W198-U197*'OverNight €'!I198*E198/360 -> 0
B199: =CONCATENATE(MONTH(D199)," ",YEAR(D199)) -> 7 2025 | C199: =D198 -> 45851 | D199: =D198+1 -> 45852 | E199: =D199-C199 -> 1 | V199: =X199-U199 -> 0 | W199: =V199+R199-V198 -> 0 | X199: =T199*I199 -> 0 | Z199: =I199/I198-1 -> #DIV/0! | AB199: =(#REF!-1)*(360/(C199-$C$76)) -> #REF! | AC199: =W199-U198*'OverNight €'!I199*E199/360 -> 0
B200: =CONCATENATE(MONTH(D200)," ",YEAR(D200)) -> 7 2025 | C200: =D199 -> 45852 | D200: =D199+1 -> 45853 | E200: =D200-C200 -> 1 | V200: =X200-U200 -> 0 | W200: =V200+R200-V199 -> 0 | X200: =T200*I200 -> 0 | Z200: =I200/I199-1 -> #DIV/0! | AB200: =(#REF!-1)*(360/(C200-$C$76)) -> #REF! | AC200: =W200-U199*'OverNight €'!I200*E200/360 -> 0
... B220: =CONCATENATE(MONTH(D220)," ",YEAR(D220)) -> 8 2025 | C220: =D219 -> 45872 | D220: =D219+1 -> 45873 | E220: =D220-C220 -> 1 | V220: =X220-U220 -> 0 | W220: =V220+R220-V219 -> 0 | X220: =T220*I220 -> 0 | Z220: =I220/I219-1 -> #DIV/0! | AB220: =(#REF!-1)*(360/(C220-$C$76)) -> #REF! | AC220: =W220-U219*'OverNight €'!I220*E220/360 -> 0
B221: =CONCATENATE(MONTH(D221)," ",YEAR(D221)) -> 8 2025 | C221: =D220 -> 45873 | D221: =D220+1 -> 45874 | E221: =D221-C221 -> 1 | V221: =X221-U221 -> 0 | W221: =V221+R221-V220 -> 0 | X221: =T221*I221 -> 0 | Z221: =I221/I220-1 -> #DIV/0! | AA221: =I221/I188-1 -> #DIV/0! | AB221: =(#REF!-1)*(360/(C221-$C$76)) -> #REF! | AC221: =W221-U220*'OverNight €'!I221*E221/360 -> 0
B222: =CONCATENATE(MONTH(D222)," ",YEAR(D222)) -> 8 2025 | C222: =D221 -> 45874 | D222: =D221+1 -> 45875 | E222: =D222-C222 -> 1 | V222: =X222-U222 -> 0 | W222: =V222+R222-V221 -> 0 | X222: =T222*I222 -> 0 | Z222: =I222/I221-1 -> #DIV/0! | AB222: =(#REF!-1)*(360/(C222-$C$76)) -> #REF! | AC222: =W222-U221*'OverNight €'!I222*E222/360 -> 0
B223: =CONCATENATE(MONTH(D223)," ",YEAR(D223)) -> 8 2025 | C223: =D222 -> 45875 | D223: =D222+1 -> 45876 | E223: =D223-C223 -> 1 | V223: =X223-U223 -> 0 | W223: =V223+R223-V222 -> 0 | X223: =T223*I223 -> 0 | Z223: =I223/I222-1 -> #DIV/0! | AB223: =(#REF!-1)*(360/(C223-$C$76)) -> #REF! | AC223: =W223-U222*'OverNight €'!I223*E223/360 -> 0
B224: =CONCATENATE(MONTH(D224)," ",YEAR(D224)) -> 8 2025 | C224: =D223 -> 45876 | D224: =D223+1 -> 45877 | E224: =D224-C224 -> 1 | V224: =X224-U224 -> 0 | W224: =V224+R224-V223 -> 0 | X224: =T224*I224 -> 0 | Z224: =I224/I223-1 -> #DIV/0! | AB224: =(#REF!-1)*(360/(C224-$C$76)) -> #REF! | AC224: =W224-U223*'OverNight €'!I224*E224/360 -> 0
B225: =CONCATENATE(MONTH(D225)," ",YEAR(D225)) -> 8 2025 | C225: =D224 -> 45877 | D225: =D224+1 -> 45878 | E225: =D225-C225 -> 1 | V225: =X225-U225 -> 0 | W225: =V225+R225-V224 -> 0 | X225: =T225*I225 -> 0 | Z225: =I225/I224-1 -> #DIV/0! | AB225: =(#REF!-1)*(360/(C225-$C$76)) -> #REF! | AC225: =W225-U224*'OverNight €'!I225*E225/360 -> 0
B226: =CONCATENATE(MONTH(D226)," ",YEAR(D226)) -> 8 2025 | C226: =D225 -> 45878 | D226: =D225+1 -> 45879 | E226: =D226-C226 -> 1 | V226: =X226-U226 -> 0 | W226: =V226+R226-V225 -> 0 | X226: =T226*I226 -> 0 | Z226: =I226/I225-1 -> #DIV/0! | AB226: =(#REF!-1)*(360/(C226-$C$76)) -> #REF! | AC226: =W226-U225*'OverNight €'!I226*E226/360 -> 0
B227: =CONCATENATE(MONTH(D227)," ",YEAR(D227)) -> 8 2025 | C227: =D226 -> 45879 | D227: =D226+1 -> 45880 | E227: =D227-C227 -> 1 | V227: =X227-U227 -> 0 | W227: =V227+R227-V226 -> 0 | X227: =T227*I227 -> 0 | Z227: =I227/I226-1 -> #DIV/0! | AB227: =(#REF!-1)*(360/(C227-$C$76)) -> #REF! | AC227: =W227-U226*'OverNight €'!I227*E227/360 -> 0
B228: =CONCATENATE(MONTH(D228)," ",YEAR(D228)) -> 8 2025 | C228: =D227 -> 45880 | D228: =D227+1 -> 45881 | E228: =D228-C228 -> 1 | V228: =X228-U228 -> 0 | W228: =V228+R228-V227 -> 0 | X228: =T228*I228 -> 0 | Z228: =I228/I227-1 -> #DIV/0! | AB228: =(#REF!-1)*(360/(C228-$C$76)) -> #REF! | AC228: =W228-U227*'OverNight €'!I228*E228/360 -> 0
B229: =CONCATENATE(MONTH(D229)," ",YEAR(D229)) -> 8 2025 | C229: =D228 -> 45881 | D229: =D228+1 -> 45882 | E229: =D229-C229 -> 1 | V229: =X229-U229 -> 0 | W229: =V229+R229-V228 -> 0 | X229: =T229*I229 -> 0 | Z229: =I229/I228-1 -> #DIV/0! | AB229: =(#REF!-1)*(360/(C229-$C$76)) -> #REF! | AC229: =W229-U228*'OverNight €'!I229*E229/360 -> 0
B230: =CONCATENATE(MONTH(D230)," ",YEAR(D230)) -> 8 2025 | C230: =D229 -> 45882 | D230: =D229+1 -> 45883 | E230: =D230-C230 -> 1 | V230: =X230-U230 -> 0 | W230: =V230+R230-V229 -> 0 | X230: =T230*I230 -> 0 | Z230: =I230/I229-1 -> #DIV/0! | AB230: =(#REF!-1)*(360/(C230-$C$76)) -> #REF! | AC230: =W230-U229*'OverNight €'!I230*E230/360 -> 0
B231: =CONCATENATE(MONTH(D231)," ",YEAR(D231)) -> 8 2025 | C231: =D230 -> 45883 | D231: =D230+1 -> 45884 | E231: =D231-C231 -> 1 | V231: =X231-U231 -> 0 | W231: =V231+R231-V230 -> 0 | X231: =T231*I231 -> 0 | Z231: =I231/I230-1 -> #DIV/0! | AB231: =(#REF!-1)*(360/(C231-$C$76)) -> #REF! | AC231: =W231-U230*'OverNight €'!I231*E231/360 -> 0
B232: =CONCATENATE(MONTH(D232)," ",YEAR(D232)) -> 8 2025 | C232: =D231 -> 45884 | D232: =D231+1 -> 45885 | E232: =D232-C232 -> 1 | V232: =X232-U232 -> 0 | W232: =V232+R232-V231 -> 0 | X232: =T232*I232 -> 0 | Z232: =I232/I231-1 -> #DIV/0! | AB232: =(#REF!-1)*(360/(C232-$C$76)) -> #REF! | AC232: =W232-U231*'OverNight €'!I232*E232/360 -> 0
B233: =CONCATENATE(MONTH(D233)," ",YEAR(D233)) -> 8 2025 | C233: =D232 -> 45885 | D233: =D232+1 -> 45886 | E233: =D233-C233 -> 1 | V233: =X233-U233 -> 0 | W233: =V233+R233-V232 -> 0 | X233: =T233*I233 -> 0 | Z233: =I233/I232-1 -> #DIV/0! | AB233: =(#REF!-1)*(360/(C233-$C$76)) -> #REF! | AC233: =W233-U232*'OverNight €'!I233*E233/360 -> 0
... B249: =CONCATENATE(MONTH(D249)," ",YEAR(D249)) -> 9 2025 | C249: =D248 -> 45901 | D249: =D248+1 -> 45902 | E249: =D249-C249 -> 1 | V249: =X249-U249 -> 0 | W249: =V249+R249-V248 -> 0 | X249: =T249*I249 -> 0 | Z249: =I249/I248-1 -> #DIV/0! | AB249: =(#REF!-1)*(360/(C249-$C$76)) -> #REF! | AC249: =W249-U248*'OverNight €'!I249*E249/360 -> 0
B250: =CONCATENATE(MONTH(D250)," ",YEAR(D250)) -> 9 2025 | C250: =D249 -> 45902 | D250: =D249+1 -> 45903 | E250: =D250-C250 -> 1 | V250: =X250-U250 -> 0 | W250: =V250+R250-V249 -> 0 | X250: =T250*I250 -> 0 | Z250: =I250/I249-1 -> #DIV/0! | AA250: =I250/I221-1 -> #DIV/0! | AB250: =(#REF!-1)*(360/(C250-$C$76)) -> #REF! | AC250: =W250-U249*'OverNight €'!I250*E250/360 -> 0
B251: =CONCATENATE(MONTH(D251)," ",YEAR(D251)) -> 9 2025 | C251: =D250 -> 45903 | D251: =D250+1 -> 45904 | E251: =D251-C251 -> 1 | V251: =X251-U251 -> 0 | W251: =V251+R251-V250 -> 0 | X251: =T251*I251 -> 0 | Z251: =I251/I250-1 -> #DIV/0! | AB251: =(#REF!-1)*(360/(C251-$C$76)) -> #REF! | AC251: =W251-U250*'OverNight €'!I251*E251/360 -> 0
...

Sheet Préparation paiements
T2: =U52-X43 -> -10100000
C5: €URO | T5: U$ DOLLAR
B6: Date de valeur | C6: Mouvement | D6: solde | E6: Mouvement from NCA to CC | F6: Prélèvements / Ajustements | G6: Nouveau solde C/C | H6: Nouveau solde NCA | I6: CAT 1 mois | J6: CAT Tréso + n°2 (11) | K6: CAT Tréso + (5) | L6: CAT ester +0,20% (5) | M6: CAT Arkea | N6: Codéis EUR | O6: Ellipsis Principal | P6: CAT Tréso Plus | Q6: CAT Ester + 0,25% | R6: CAT Euribor 3 mois -BCP | S6: Date de valeur | T6: Mouvement | U6: solde | V6: Mouvement from NCA to CC | W6: Prélèvements / Ajustements | X6: Nouveau solde C/C | Y6: Nouveau solde NCA | Z6: Codéis | AA6: CAT BIL | AB6: DAT 29 Sep. 25 | AC6: DAT 17 Sept. 25 | AD6: LLC | AE6: ALLSPRING GOVT MM | AF6: GOLDMAN SACHS | AG6: Morgan Stanley | AH6: State Street | AJ6: EURUSD | AK6: Total- SA | AL6: Total- SA +LLC
B7: 45253 | C7: 0 | D7: 119506.65 | S7: 45253
B8: 45254 | C8: -2712000 | D8: =D7+C8 -> -2592493.4 | E8: 2700000 | G8: =E8+D8 -> 107506.65 | S8: 45254
B9: 45257 | C9: =-228200-696819.04 -> -925019.04 | D9: 296577 | E9: 1000000 | G9: =E9+D9 -> 1296577 | S9: 45257
B10: 45258 | C10: -1486780.1 | D10: =C10+G9 -> -190203.11 | E10: 1500000 | G10: =E10+D10 -> 1309796.9 | S10: 45258
D11: =C11+G10 -> 1309796.9 | G11: =E11+D11 -> 1309796.9
B12: 45260 | C12: =-1347260.4*2 -> -2694520.8 | D12: =C12+H11 -> -2694520.8 | G12: =E12+D12 -> -2694520.8 | S12: 45260
B13: 45260 | C13: 20000000 | D13: =C13+G12 -> 17305479 | E13: -17400000 | G13: 46722.9 | S13: 45260
B14: 45273 | D14: =C14+G13 -> 46722.9 | G14: 50019.8 | H14: 206500000 | S14: 45273
B15: 45275 | C15: -3792616.8 | D15: =C15+G14 -> -3742597 | E15: 3800000 | G15: =E15+D15 -> 57403 | H15: =H14-E15 -> 202700000 | S15: 45275
B16: 45278 | G16: -118513.69 | S16: 45278
B17: 45278 | D17: =C17+G16 -> -118513.69 | E17: 200000 | G17: =E17+D17 -> 81486.31 | H17: =H15-E17 -> 202500000 | S17: 45278
B18: 45280 | C18: -1407206.9 | D18: =C18+G15 -> -1349803.9 | E18: 1500000 | G18: =E18+D18 -> 150196.11 | H18: =H17-E18 -> 201000000 | S18: 45280
A19: =C19+C18 -> -2857548.8 | B19: 45281 | C19: -1450341.9 | D19: =C19+G18 -> -1300145.8 | E19: 1500000 | G19: =E19+D19 -> 199854.22 | H19: =H18-E19 -> 199500000 | S19: 45281
A20: 2892490 | B20: 45282 | C20: =-735428.49-718896.78 -> -1454325.3 | D20: =C20+G19 -> -1254471 | E20: 1300000 | G20: =E20+D20 -> 45528.95 | H20: =H19-E20 -> 198200000 | S20: 45282
A21: =SUM(A19:A20) -> 34941.2 | B21: 45286 | C21: =-4898998.8-1367589.14 -> -6266587.9 | D21: =C21+G20 -> -6221059 | E21: 6300000 | G21: =E21+D21 -> 78941.01 | H21: =H20-E21 -> 191900000 | S21: 45286
B22: 45300 | G22: 296577.04 | H22: 190800000 | S22: 45300
B23: 45301 | C23: -1050266 | D23: =C23+G22 -> -753688.96 | E23: 800000 | G23: =E23+D23 -> 46311.04 | H23: =H22-E23 -> 190000000 | S23: 45301
B24: 45302 | C24: =-701747-11898 -> -713645 | D24: =C24+G23 -> -667333.96 | E24: 800000 | G24: =E24+D24 -> 132666.04 | H24: =H23-E24 -> 189200000 | S24: 45302
B25: 45306 | G25: 95797.85 | H25: =H24-E25 -> 189200000 | S25: 45306
B26: 45307 | C26: =D26-G25 -> -300000 | D26: -204202.15 | E26: 300000 | G26: 95797.85 | H26: =H25-E26 -> 188900000 | S26: 45307
B27: 45308 | C27: 0 | D27: =C27+G24 -> 132666.04 | G27: 95797.85 | H27: =H26-E27 -> 188900000 | S27: 45308 | U27: =T27+X24 -> 0 | X27: 441011.92 | Y27: 44600000
B28: 45309 | C28: -3075813.8 | D28: =C28+G27 -> -2980016 | E28: 3100000 | G28: =E28+D28 -> 119984.01 | H28: =H27-E28 -> 185800000 | S28: 45309 | T28: -588673.18 | U28: =T28+X27 -> -147661.26 | V28: 200000 | X28: =V28+U28 -> 52338.74 | Y28: =Y27-V28 -> 44400000
B29: 45310 | D29: =C29+G28 -> 119984.01 | H29: =H28-E29 -> 185800000 | S29: 45310 | U29: =T29+X28 -> 52338.74 | X29: =V29+U29 -> 52338.74 | Y29: =Y28-V29 -> 44400000
B30: 45311 | D30: =C30+G29 -> 0 | H30: =H29-E30 -> 185800000 | S30: 45311 | U30: =T30+X29 -> 52338.74 | X30: =V30+U30 -> 52338.74 | Y30: =Y29-V30 -> 44400000
B31: 45312 | D31: =C31+G30 -> 0 | G31: 1228981.5 | H31: =H30-E31 -> 185800000 | S31: 45312 | U31: =T31+X30 -> 52338.74 | X31: =V31+U31 -> 52338.74 | Y31: =Y30-V31 -> 44400000
B32: 45313 | C32: =-1078382.16-1484348.85 -> -2562731 | D32: =C32+G31 -> -1333749.5 | E32: 1400000 | G32: =E32+D32 -> 66250.52 | H32: =H31-E32 -> 184400000 | S32: 45313 | U32: =T32+X31 -> 52338.74 | X32: =V32+U32 -> 52338.74 | Y32: =Y31-V32 -> 44400000
B33: 45345 | D33: =C33+G32+401311.72 -> 467562.24 | G33: =E33+D33 -> 467562.24 | H33: 183000000 | S33: 45345 | U33: =T33+X32 -> 52338.74 | X33: =V33+U33 -> 52338.74 | Y33: =Y32-V33 -> 44400000
B34: 45348 | C34: -2679687.5 | D34: =C34+G33 -> -2212125.3 | E34: 2400000 | G34: =E34+D34 -> 187874.74 | H34: =H33-E34 -> 180600000 | S34: 45348 | U34: =T34+X33 -> 52338.74 | X34: =V34+U34 -> 52338.74 | Y34: =Y33-V34 -> 44400000
B35: 45349 | D35: =C35+G34 -> 187874.74 | E35: 900000 | H35: =H34-E35 -> 179700000 | S35: 45349 | U35: =T35+X34 -> 52338.74 | X35: =V35+U35 -> 52338.74 | Y35: =Y34-V35 -> 44400000
B36: 45355 | D36: =C36+G35 -> 0 | G36: 147755.82 | H36: =H35-E36 -> 179700000 | S36: 45355 | U36: 106452.09 | X36: =V36+U36 -> 106452.09 | Y36: 18400000
A37: 1 554 623,97 | B37: 45356 | C37: -1554624 | D37: =C37+G36 -> -1406868.1 | E37: 1500000 | G37: =E37+D37 -> 93131.85 | H37: =H36 -> 179700000 | S37: 45356 | T37: -103387.45 | U37: =T37+X36 -> 3064.64 | V37: 100000 | X37: =V37+U37 -> 103064.64 | Y37: =Y36-V37 -> 18300000
B38: 45357 | D38: =C38+G37 -> 93131.85 | H38: 178700000 | S38: 45357 | U38: =T38+X37 -> 103064.64 | X38: =V38+U38 -> 103064.64 | Y38: =Y37-V38 -> 18300000
B39: 45358 | G39: =E39+D39 -> 0 | H39: =H38 -> 178700000 | S39: 45358 | U39: =T39+X38 -> 103064.64 | X39: =V39+U39 -> 103064.64 | Y39: =Y38-V39 -> 18300000
B40: 45359 | H40: 178600000 | S40: 45359 | U40: =T40+X39 -> 103064.64 | X40: =V40+U40 -> 103064.64 | Y40: =Y39-V40 -> 18300000
B41: 45360 | G41: =E41+D41 -> 0 | H41: =H40 -> 178600000 | S41: 45360 | U41: =T41+X40 -> 103064.64 | X41: =V41+U41 -> 103064.64 | Y41: =Y40-V41 -> 18300000
B42: 45361 | H42: =H41 -> 178600000 | S42: 45361 | U42: =T42+X41 -> 103064.64 | X42: =V42+U42 -> 103064.64 | Y42: =Y41-V42 -> 18300000
B43: 45362 | G43: =E43+D43 -> 0 | H43: =H42 -> 178600000 | S43: 45362 | T43: 10107084 | U43: =T43+X42 -> 10210149 | X43: =V43+U43 -> 10210149 | Y43: =Y42-V43 -> 18300000
B44: 45363 | H44: =H43 -> 178600000 | S44: 45363 | U44: =T44+X43 -> 10210149 | V44: -10100000 | X44: =V44+U44 -> 110148.76 | Y44: =Y43-V44 -> 28400000
B45: 45364 | D45: 105526.16 | G45: =E45+D45 -> 105526.16 | H45: =H44-E45 -> 178600000 | S45: 45364 | U45: =T45+X44 -> 110148.76 | X45: =V45+U45 -> 110148.76 | Y45: =Y44-V45 -> 28400000
B46: 45365 | C46: -1041948 | D46: =C46+G45 -> -936421.84 | E46: 1100000 | G46: =E46+D46 -> 163578.16 | H46: =H45-E46 -> 177500000 | S46: 45365 | U46: =T46+X45 -> 110148.76 | X46: =V46+U46 -> 110148.76 | Y46: =Y45-V46 -> 28400000
B47: 45366 | C47: -1329748 | D47: =C47+G46 -> -1166169.8 | E47: 1300000 | G47: =E47+D47 -> 133830.16 | H47: =H46-E47 -> 176200000 | S47: 45366 | U47: =T47+X46 -> 110148.76 | X47: =V47+U47 -> 110148.76 | Y47: =Y46-V47 -> 28400000
B48: 45367 | D48: =C48+G47 -> 133830.16 | G48: =E48+D48 -> 133830.16 | H48: =H47-E48 -> 176200000 | S48: 45367 | U48: =T48+X47 -> 110148.76 | X48: =V48+U48 -> 110148.76 | Y48: =Y47-V48 -> 28400000
B49: 45368 | D49: =C49+G48 -> 133830.16 | G49: =E49+D49 -> 133830.16 | H49: =H48-E49 -> 176200000 | S49: 45368 | U49: =T49+X48 -> 110148.76 | X49: =V49+U49 -> 110148.76 | Y49: =Y48-V49 -> 28400000
B50: 45369 | C50: =D52-E50-G47 -> -352492.49 | D50: =C50+G49 -> -218662.33 | E50: 200000 | G50: =E50+D50 -> -18662.33 | H50: =H49-E50 -> 176000000 | S50: 45369 | U50: =T50+X49 -> 110148.76 | X50: =V50+U50 -> 110148.76 | Y50: =Y49-V50 -> 28400000
B51: 45370 | D51: =C51+G50 -> -18662.33 | G51: 167123.87 | H51: =H50-E51 -> 176000000 | S51: 45370 | T51: -50000 | U51: =T51+X50 -> 60148.76 | V51: 50000 | X51: =V51+U51 -> 110148.76 | Y51: =Y50-V51 -> 28350000
B52: 45371 | C52: -185786.2 | D52: =C52+G51 -> -18662.33 | E52: 100000 | G52: =D52+E52 -> 81337.67 | H52: =H51-E52 -> 175900000 | S52: 45371 | U52: =T52+X51 -> 110148.76 | X52: =V52+U52 -> 110148.76 | Y52: =Y51-V52 -> 28350000
B53: 45372 | C53: -1684953.9 | D53: =C53+G52 -> -1603616.2 | E53: 1700000 | G53: =D53+E53 -> 96383.81 | H53: =H52-E53 -> 174200000 | S53: 45372 | T53: -248554.38 | U53: =T53+X52 -> -138405.62 | V53: 250000 | X53: =V53+U53 -> 111594.38 | Y53: =Y52-V53 -> 28100000
B54: 45373 | D54: =C54+G53 -> 96383.81 | E54: =2900000+100000 -> 3000000 | F54: -12009.72 | G54: =D54+E54+F54 -> 3084374.1 | H54: =H53-E54 -> 171200000 | S54: 45373 | U54: =T54+X53 -> 111594.38 | X54: =V54+U54 -> 111594.38 | Y54: =Y53-V54 -> 28100000
B55: 45374 | D55: =C55+G54 -> 3084374.1 | G55: =D55+E55+F55 -> 3084374.1 | H55: =H54-E55 -> 171200000 | S55: 45374 | U55: =T55+X54 -> 111594.38 | X55: =V55+U55 -> 111594.38 | Y55: =Y54-V55 -> 28100000
B56: 45375 | D56: =C56+G55 -> 3084374.1 | G56: =D56+E56+F56 -> 3084374.1 | H56: =H55-E56 -> 171200000 | S56: 45375 | U56: =T56+X55 -> 111594.38 | X56: =V56+U56 -> 111594.38 | Y56: =Y55-V56 -> 28100000
B57: 45376 | D57: =C57+G56 -> 3084374.1 | F57: -101138.97 | G57: =D57+E57+F57 -> 2983235.1 | H57: =H56-E57 -> 171200000 | S57: 45376 | U57: =T57+X56 -> 111594.38 | X57: =V57+U57 -> 111594.38 | Y57: =Y56-V57 -> 28100000
B58: 45377 | C58: =-83333.33-2845155.06 -> -2928488.4 | D58: =C58+G57 -> 54746.73 | E58: 300000 | G58: =D58+E58+F58 -> 354746.73 | H58: =H57-E58 -> 170900000 | S58: 45377 | U58: =T58+X57 -> 111594.38 | X58: =V58+U58 -> 111594.38 | Y58: =Y57-V58 -> 28100000
B59: 45378 | C59: -1429841.8 | D59: =C59+G58 -> -1075095.1 | E59: 2000000 | G59: =D59+E59+F59 -> 924904.93 | H59: =H58-E59 -> 168900000 | S59: 45378 | U59: =T59+X58 -> 111594.38 | X59: =V59+U59 -> 111594.38 | Y59: =Y58-V59 -> 28100000
B60: 45379 | C60: -25000 | D60: =C60+G59 -> 899904.93 | F60: 24053232 | G60: =D60+E60+F60 -> 24953137 | H60: =H59-E60 -> 168900000 | S60: 45379 | U60: =T60+X59 -> 111594.38 | X60: =V60+U60 -> 111594.38 | Y60: =Y59-V60 -> 28100000
B61: 45380 | D61: =C61+G60 -> 24953137 | G61: =D61+E61+F61 -> 24953137 | H61: =H60-E61 -> 168900000 | S61: 45380 | U61: =T61+X60 -> 111594.38 | X61: =V61+U61 -> 111594.38 | Y61: =Y60-V61 -> 28100000
B62: 45381 | D62: =C62+G61 -> 24953137 | G62: =D62+E62+F62 -> 24953137 | H62: =H61-E62 -> 168900000 | S62: 45381 | U62: =T62+X61 -> 111594.38 | X62: =V62+U62 -> 111594.38 | Y62: =Y61-V62 -> 28100000
B63: 45382 | D63: =C63+G62 -> 24953137 | G63: =D63+E63+F63 -> 24953137 | H63: =H62-E63 -> 168900000 | S63: 45382 | U63: =T63+X62 -> 111594.38 | X63: =V63+U63 -> 111594.38 | Y63: =Y62-V63 -> 28100000
B64: 45383 | D64: =C64+G63 -> 24953137 | G64: =D64+E64+F64 -> 24953137 | H64: =H63-E64 -> 168900000 | S64: 45383 | U64: =T64+X63 -> 111594.38 | X64: =V64+U64 -> 111594.38 | Y64: =Y63-V64 -> 28100000
B65: 45384 | D65: =C65+G64 -> 24953137 | G65: =D65+E65+F65 -> 24953137 | H65: =H64-E65 -> 168900000 | S65: 45384 | U65: =T65+X64 -> 111594.38 | X65: =V65+U65 -> 111594.38 | Y65: =Y64-V65 -> 28100000
B66: 45385 | D66: =C66+G65 -> 24953137 | G66: =D66+E66+F66 -> 24953137 | H66: =H65-E66 -> 168900000 | S66: 45385 | U66: =T66+X65 -> 111594.38 | X66: =V66+U66 -> 111594.38 | Y66: =Y65-V66 -> 28100000
B67: 45386 | D67: =C67+G66 -> 24953137 | G67: =D67+E67+F67 -> 24953137 | H67: =H66-E67 -> 168900000 | S67: 45386 | U67: =T67+X66 -> 111594.38 | X67: =V67+U67 -> 111594.38 | Y67: =Y66-V67 -> 28100000
B68: 45387 | D68: =C68+G67 -> 24953137 | G68: =D68+E68+F68 -> 24953137 | H68: =H67-E68 -> 168900000 | S68: 45387 | U68: =T68+X67 -> 111594.38 | X68: =V68+U68 -> 111594.38 | Y68: =Y67-V68 -> 28100000
B69: 45388 | D69: =C69+G68 -> 24953137 | G69: =D69+E69+F69 -> 24953137 | H69: =H68-E69 -> 168900000 | S69: 45388 | U69: =T69+X68 -> 111594.38 | X69: =V69+U69 -> 111594.38 | Y69: =Y68-V69 -> 28100000
B70: 45389 | D70: =C70+G69 -> 24953137 | G70: =D70+E70+F70 -> 24953137 | H70: =H69-E70 -> 168900000 | S70: 45389 | U70: =T70+X69 -> 111594.38 | X70: =V70+U70 -> 111594.38 | Y70: =Y69-V70 -> 28100000
B71: 45390 | D71: =C71+G70 -> 24953137 | G71: =D71+E71+F71 -> 24953137 | H71: =H70-E71 -> 168900000 | S71: 45390 | U71: =T71+X70 -> 111594.38 | X71: =V71+U71 -> 111594.38 | Y71: =Y70-V71 -> 28100000
B72: 45391 | D72: =C72+G71 -> 24953137 | G72: =D72+E72+F72 -> 24953137 | H72: =H71-E72 -> 168900000 | S72: 45391 | U72: =T72+X71 -> 111594.38 | X72: =V72+U72 -> 111594.38 | Y72: =Y71-V72 -> 28100000
B73: 45392 | D73: =C73+G72 -> 24953137 | G73: =D73+E73+F73 -> 24953137 | H73: =H72-E73 -> 168900000 | S73: 45392 | U73: =T73+X72 -> 111594.38 | X73: =V73+U73 -> 111594.38 | Y73: =Y72-V73-1000000 -> 27100000
B74: 45393 | D74: =C74+G73 -> 24953137 | G74: =D74+E74+F74 -> 24953137 | H74: =H73-E74 -> 168900000 | S74: 45393 | U74: =T74+X73 -> 111594.38 | X74: =V74+U74 -> 111594.38 | Y74: =Y73-V74 -> 27100000
B75: 45394 | D75: =C75+G74 -> 24953137 | G75: =D75+E75+F75 -> 24953137 | H75: =H74-E75 -> 168900000 | S75: 45394 | U75: =T75+X74 -> 111594.38 | X75: =V75+U75 -> 111594.38 | Y75: =Y74-V75 -> 27100000
B76: 45395 | D76: =C76+G75 -> 24953137 | G76: =D76+E76+F76 -> 24953137 | H76: =H75-E76 -> 168900000 | S76: 45395 | U76: =T76+X75 -> 111594.38 | X76: =V76+U76 -> 111594.38 | Y76: =Y75-V76 -> 27100000
B77: 45396 | D77: =C77+G76 -> 24953137 | G77: =D77+E77+F77 -> 24953137 | H77: =H76-E77 -> 168900000 | S77: 45396 | U77: =T77+X76 -> 111594.38 | X77: =V77+U77 -> 111594.38 | Y77: =Y76-V77 -> 27100000
B78: 45397 | D78: =C78+G77 -> 24953137 | G78: =D78+E78+F78 -> 24953137 | H78: =H77-E78 -> 168900000 | S78: 45397 | U78: =T78+X77 -> 111594.38 | X78: =V78+U78 -> 111594.38 | Y78: =Y77-V78 -> 27100000
B79: 45398 | D79: =C79+G78 -> 24953137 | G79: =D79+E79+F79 -> 24953137 | H79: =H78-E79 -> 168900000 | S79: 45398 | U79: =T79+X78 -> 111594.38 | X79: =V79+U79 -> 111594.38 | Y79: =Y78-V79 -> 27100000
B80: 45399 | D80: =C80+G79 -> 24953137 | G80: =D80+E80+F80 -> 24953137 | H80: =H79-E80 -> 168900000 | S80: 45399 | U80: =T80+X79 -> 111594.38 | X80: =V80+U80 -> 111594.38 | Y80: =Y79-V80 -> 27100000
B81: 45400 | D81: =C81+G80 -> 24953137 | G81: =D81+E81+F81 -> 24953137 | H81: =H80-E81 -> 168900000 | S81: 45400 | U81: =T81+X80 -> 111594.38 | X81: =V81+U81 -> 111594.38 | Y81: =Y80-V81 -> 27100000
B82: 45401 | D82: =C82+G81 -> 24953137 | G82: =D82+E82+F82 -> 24953137 | H82: =H81-E82 -> 168900000 | S82: 45401 | U82: =T82+X81 -> 111594.38 | X82: =V82+U82 -> 111594.38 | Y82: =Y81-V82 -> 27100000
B83: 45402 | D83: =C83+G82 -> 24953137 | G83: =D83+E83+F83 -> 24953137 | H83: =H82-E83 -> 168900000 | S83: 45402 | U83: =T83+X82 -> 111594.38 | X83: =V83+U83 -> 111594.38 | Y83: =Y82-V83 -> 27100000
B84: 45403 | D84: 115526.04 | G84: =D84+E84+F84 -> 115526.04 | H84: 178400000 | S84: 45403 | U84: =T84+X83 -> 111594.38 | X84: =V84+U84 -> 111594.38 | Y84: =Y83-V84 -> 27100000
B85: 45404 | C85: -604762 | D85: =C85+G84 -> -489235.96 | E85: 700000 | G85: =D85+E85+F85 -> 210764.04 | H85: =H84-E85 -> 177700000 | S85: 45404 | U85: =T85+X84 -> 111594.38 | X85: =V85+U85 -> 111594.38 | Y85: =Y84-V85 -> 27100000
B86: 45405 | D86: =C86+G85 -> 210764.04 | G86: =D86+E86+F86 -> 210764.04 | H86: =H85-E86 -> 177700000 | S86: 45405 | U86: =T86+X85 -> 111594.38 | X86: =V86+U86 -> 111594.38 | Y86: =Y85-V86 -> 27100000
B87: 45406 | D87: =C87+G86 -> 210764.04 | G87: =D87+E87+F87 -> 210764.04 | H87: =H86-E87 -> 177700000 | S87: 45406 | U87: =T87+X86 -> 111594.38 | X87: =V87+U87 -> 111594.38 | Y87: =Y86-V87 -> 27100000
B88: 45407 | C88: -1800000 | D88: =C88+G87 -> -1589236 | E88: 1800000 | G88: =D88+E88+F88 -> 210764.04 | H88: =H87-E88 -> 175900000 | S88: 45407 | U88: =T88+X87 -> 111594.38 | X88: =V88+U88 -> 111594.38 | Y88: =Y87-V88 -> 27100000
B89: 45408 | D89: =C89+G88 -> 210764.04 | G89: =D89+E89+F89 -> 210764.04 | H89: =H88-E89 -> 175900000 | S89: 45408 | U89: =T89+X88 -> 111594.38 | X89: =V89+U89 -> 111594.38 | Y89: =Y88-V89 -> 27100000
B90: 45409 | C90: -2275122 | D90: =C90+G89 -> -2064358 | E90: 2200000 | G90: =D90+E90+F90 -> 135642.04 | H90: =H89-E90 -> 173700000 | S90: 45409 | U90: =T90+X89 -> 111594.38 | X90: =V90+U90 -> 111594.38 | Y90: =Y89-V90 -> 27100000
B91: 45410 | D91: =C91+G90 -> 135642.04 | G91: =D91+E91+F91 -> 135642.04 | H91: =H90-E91 -> 173700000 | S91: 45410 | U91: =T91+X90 -> 111594.38 | X91: =V91+U91 -> 111594.38 | Y91: =Y90-V91 -> 27100000
B92: 45411 | D92: =C92+G91 -> 135642.04 | G92: =D92+E92+F92 -> 135642.04 | H92: =H91-E92 -> 173700000 | S92: 45411 | U92: =T92+X91 -> 111594.38 | X92: =V92+U92 -> 111594.38 | Y92: =Y91-V92 -> 27100000
B93: 45412 | D93: =C93+G92 -> 135642.04 | G93: =D93+E93+F93 -> 135642.04 | H93: =H92-E93 -> 173700000 | S93: 45412 | U93: =T93+X92 -> 111594.38 | X93: =V93+U93 -> 111594.38 | Y93: =Y92-V93 -> 27100000
B94: 45413 | D94: =C94+G93 -> 135642.04 | G94: =D94+E94+F94 -> 135642.04 | H94: =H93-E94 -> 173700000 | S94: 45413 | U94: =T94+X93 -> 111594.38 | X94: =V94+U94 -> 111594.38 | Y94: =Y93-V94 -> 27100000
B95: 45414 | D95: =C95+G94 -> 135642.04 | G95: =D95+E95+F95 -> 135642.04 | H95: =H94-E95 -> 173700000 | S95: 45414 | U95: =T95+X94 -> 111594.38 | X95: =V95+U95 -> 111594.38 | Y95: =Y94-V95 -> 27100000
B96: 45415 | D96: =C96+G95 -> 135642.04 | G96: =D96+E96+F96 -> 135642.04 | H96: =H95-E96 -> 173700000 | S96: 45415 | U96: =T96+X95 -> 111594.38 | X96: =V96+U96 -> 111594.38 | Y96: =Y95-V96 -> 27100000
B97: 45416 | D97: =C97+G96 -> 135642.04 | G97: =D97+E97+F97 -> 135642.04 | H97: =H96-E97 -> 173700000 | S97: 45416 | U97: =T97+X96 -> 111594.38 | X97: =V97+U97 -> 111594.38 | Y97: =Y96-V97 -> 27100000
B98: 45417 | D98: =C98+G97 -> 135642.04 | G98: =D98+E98+F98 -> 135642.04 | H98: =H97-E98 -> 173700000 | S98: 45417 | U98: =T98+X97 -> 111594.38 | X98: =V98+U98 -> 111594.38 | Y98: =Y97-V98 -> 27100000
B99: 45418 | D99: =C99+G98 -> 135642.04 | G99: =D99+E99+F99 -> 135642.04 | H99: =H98-E99 -> 173700000 | S99: 45418 | U99: =T99+X98 -> 111594.38 | X99: =V99+U99 -> 111594.38 | Y99: =Y98-V99 -> 27100000
B100: 45419 | D100: =C100+G99 -> 135642.04 | G100: =D100+E100+F100 -> 135642.04 | H100: =H99-E100 -> 173700000 | S100: 45419 | U100: =T100+X99 -> 111594.38 | X100: =V100+U100 -> 111594.38 | Y100: =Y99-V100 -> 27100000
B101: 45420 | D101: =C101+G100 -> 135642.04 | G101: =D101+E101+F101 -> 135642.04 | H101: =H100-E101 -> 173700000 | S101: 45420 | U101: =T101+X100 -> 111594.38 | X101: =V101+U101 -> 111594.38 | Y101: =Y100-V101 -> 27100000
B102: 45421 | D102: =C102+G101 -> 135642.04 | G102: =D102+E102+F102 -> 135642.04 | H102: =H101-E102 -> 173700000 | S102: 45421 | U102: =T102+X101 -> 111594.38 | X102: =V102+U102 -> 111594.38 | Y102: =Y101-V102 -> 27100000
... B105: 45424 | D105: =C105+G104 -> 135642.04 | G105: =D105+E105+F105 -> 135642.04 | H105: =H104-E105 -> 173700000 | S105: 45424 | U105: =T105+X104 -> 111594.38 | X105: =V105+U105 -> 111594.38 | Y105: =Y104-V105 -> 27100000
...

Sheet mouvement tréso & change
E5: mouvement intra-groupe 2025
G7: De SA -> LLC
E8: Date d'opération | F8: Date réglmt des fonds | G8: USD
E9: 45805 | F9: 45807 | G9: 1
E10: 45860 | F10: 45860 | G10: 1000000 | H10: urgent
E11: 45861 | F11: 45861 | G11: 1500000 | H11: urgent
E12: 45923 | F12: =E12 -> 45923 | G12: 4500000 | H12: urgent
E13: 45950 | F13: =E13 -> 45950 | G13: 193000000 | H13: urgent
G16: DE LLC à SA
E17: Date d'opération | F17: Date réglmt des fonds | G17: USD
E18: 45870 | F18: 45870 | G18: 1
E20: mouvement de change 2025
E22: Operation Date | F22: EURUSD FX | G22: EUR | H22: USD | I22: Value Date
E23: 45868 | F23: 1.1567 | G23: =H23/F23 -> 2.161321e+08 | H23: 250000000 | I23: 45870
E25: Operation Date | F25: EURUSD FX | G25: EUR | H25: USD | I25: Value Date
E26: 46008 | F26: 1.1756 | G26: =15*10^6 -> 15000000 | H26: =G26*F26 -> 17634000 | I26: 46010
E27: 46008 | F27: 1.1756 | G27: =15*10^6 -> 15000000 | H27: =G27*F27 -> 17634000 | I27: 46010
E28: 46009 | F28: 1.1728 | G28: =10*10^6 -> 10000000 | H28: =G28*F28 -> 11728000 | I28: 46013
E29: 46010 | F29: 1.1715 | G29: 20000000 | H29: =G29*F29 -> 23430000 | I29: 46014
E30: Total | F30: =H30/G30 -> 1.1737667 | G30: =SUM(G26:G29) -> 60000000 | H30: =SUM(H26:H29) -> 70426000
E32: mouvement de change 2026
E37: Operation Date | F37: EURUSD FX | G37: EUR | H37: USD | I37: Value Date
E38: 46083 | F38: 1.17 | G38: 15000000 | H38: =G38*F38 -> 17550000 | I38: 46085
E39: 46083 | F39: 1.175 | G39: 15000000 | H39: =G39*F39 -> 17625000 | I39: 46085
E40: Total | F40: =H40/G40 -> 1.1725 | G40: =SUM(G36:G39) -> 30000000 | H40: =SUM(H36:H39) -> 35175000

Sheet Monthly Report 2026 $
K1: ='Monthly Report 2026 €'!L1 -> 46053
D6: ="USD Cash Investments Report as of "&TEXT(K1,"jj mmm aaaa") -> USD Cash Investments Report as of 31 janv 2026
A7: Formule | B7: Formule | D7: Month | E7: Bank | F7: Investment | G7: Opening Date | H7: Closing Date | I7: Rate * | J7: Amount EoM | K7: Interest due | L7: Interest paid | M7: Profit/NCA
D9: Deposit
A11: =CONCATENATE(MONTH(D11)," ",YEAR(D11)) -> 1 2026 | B11: =D11 -> 46053 | D11: 46053 | E11: SG | F11: NCA | I11: =INDEX('OverNight $'!$H$376:$H$750,MATCH(B11,'OverNight $'!$D$376:$D$750,0)) -> 0.0315 | J11: =INDEX('OverNight $'!$G$373:$G$750,MATCH(B11,'OverNight $'!$C$373:$C$750,0)) -> 190000 | K11: =SUMIFS('OverNight $'!$I$373:$I$750,'OverNight $'!$B$373:$B$750,A11) -> 4324.25 | L11: 4307.63 | M11: 0 | O11: OK
A12: =CONCATENATE(MONTH(D12)," ",YEAR(D12)) -> 2 2026 | B12: =EOMONTH(B11,1) -> 46081 | D12: =EOMONTH(D11,1) -> 46081 | E12: SG | F12: NCA | I12: =INDEX('OverNight $'!$H$376:$H$750,MATCH(B12,'OverNight $'!$D$376:$D$750,0)) -> 0.0315 | J12: =INDEX('OverNight $'!$G$373:$G$750,MATCH(B12,'OverNight $'!$C$373:$C$750,0)) -> 1280000 | K12: =SUMIFS('OverNight $'!$I$373:$I$750,'OverNight $'!$B$373:$B$750,A12) -> 1827 | M12: 0
A13: =CONCATENATE(MONTH(D13)," ",YEAR(D13)) -> 3 2026 | B13: =EOMONTH(B12,1) -> 46112 | D13: =EOMONTH(D12,1) -> 46112 | E13: SG | F13: NCA | I13: =INDEX('OverNight $'!$H$376:$H$750,MATCH(B13,'OverNight $'!$D$376:$D$750,0)) -> 0.0315 | J13: =INDEX('OverNight $'!$G$373:$G$750,MATCH(B13,'OverNight $'!$C$373:$C$750,0)) -> 1450000 | K13: =SUMIFS('OverNight $'!$I$373:$I$750,'OverNight $'!$B$373:$B$750,A13) -> 3858.75 | M13: 0
A14: =CONCATENATE(MONTH(D14)," ",YEAR(D14)) -> 4 2026 | B14: =EOMONTH(B13,1) -> 46142 | D14: =EOMONTH(D13,1) -> 46142 | E14: SG | F14: NCA | I14: =INDEX('OverNight $'!$H$376:$H$750,MATCH(B14,'OverNight $'!$D$376:$D$750,0)) -> 0.0315 | J14: =INDEX('OverNight $'!$G$373:$G$750,MATCH(B14,'OverNight $'!$C$373:$C$750,0)) -> 1450000 | K14: =SUMIFS('OverNight $'!$I$373:$I$750,'OverNight $'!$B$373:$B$750,A14) -> 3806.25 | M14: 0
A15: =CONCATENATE(MONTH(D15)," ",YEAR(D15)) -> 5 2026 | B15: =EOMONTH(B14,1) -> 46173 | D15: =EOMONTH(D14,1) -> 46173 | E15: SG | F15: NCA | I15: =INDEX('OverNight $'!$H$376:$H$750,MATCH(B15,'OverNight $'!$D$376:$D$750,0)) -> 0.0315 | J15: =INDEX('OverNight $'!$G$373:$G$750,MATCH(B15,'OverNight $'!$C$373:$C$750,0)) -> 1450000 | K15: =SUMIFS('OverNight $'!$I$373:$I$750,'OverNight $'!$B$373:$B$750,A15) -> 3933.125 | M15: 0
A16: =CONCATENATE(MONTH(D16)," ",YEAR(D16)) -> 6 2026 | B16: =EOMONTH(B15,1) -> 46203 | D16: =EOMONTH(D15,1) -> 46203 | E16: SG | F16: NCA | I16: =INDEX('OverNight $'!$H$376:$H$750,MATCH(B16,'OverNight $'!$D$376:$D$750,0)) -> 0.0315 | J16: =INDEX('OverNight $'!$G$373:$G$750,MATCH(B16,'OverNight $'!$C$373:$C$750,0)) -> 1450000 | K16: =SUMIFS('OverNight $'!$I$373:$I$750,'OverNight $'!$B$373:$B$750,A16) -> 3806.25 | M16: 0
A17: =CONCATENATE(MONTH(D17)," ",YEAR(D17)) -> 7 2026 | B17: =EOMONTH(B16,1) -> 46234 | D17: =EOMONTH(D16,1) -> 46234 | E17: SG | F17: NCA | I17: =INDEX('OverNight $'!$H$376:$H$750,MATCH(B17,'OverNight $'!$D$376:$D$750,0)) -> 0.0315 | J17: =INDEX('OverNight $'!$G$373:$G$750,MATCH(B17,'OverNight $'!$C$373:$C$750,0)) -> 1450000 | K17: =SUMIFS('OverNight $'!$I$373:$I$750,'OverNight $'!$B$373:$B$750,A17) -> 3933.125 | M17: 0
A18: =CONCATENATE(MONTH(D18)," ",YEAR(D18)) -> 8 2026 | B18: =EOMONTH(B17,1) -> 46265 | D18: =EOMONTH(D17,1) -> 46265 | E18: SG | F18: NCA | I18: =INDEX('OverNight $'!$H$376:$H$750,MATCH(B18,'OverNight $'!$D$376:$D$750,0)) -> 0.0315 | J18: =INDEX('OverNight $'!$G$373:$G$750,MATCH(B18,'OverNight $'!$C$373:$C$750,0)) -> 1450000 | K18: =SUMIFS('OverNight $'!$I$373:$I$750,'OverNight $'!$B$373:$B$750,A18) -> 3933.125 | M18: 0
A19: =CONCATENATE(MONTH(D19)," ",YEAR(D19)) -> 9 2026 | B19: =EOMONTH(B18,1) -> 46295 | D19: =EOMONTH(D18,1) -> 46295 | E19: SG | F19: NCA | I19: =INDEX('OverNight $'!$H$376:$H$750,MATCH(B19,'OverNight $'!$D$376:$D$750,0)) -> 0.0315 | J19: =INDEX('OverNight $'!$G$373:$G$750,MATCH(B19,'OverNight $'!$C$373:$C$750,0)) -> 1450000 | K19: =SUMIFS('OverNight $'!$I$373:$I$750,'OverNight $'!$B$373:$B$750,A19) -> 3806.25 | M19: 0
A20: =CONCATENATE(MONTH(D20)," ",YEAR(D20)) -> 10 2026 | B20: =EOMONTH(B19,1) -> 46326 | D20: =EOMONTH(D19,1) -> 46326 | E20: SG | F20: NCA | I20: =INDEX('OverNight $'!$H$376:$H$750,MATCH(B20,'OverNight $'!$D$376:$D$750,0)) -> 0.0315 | J20: =INDEX('OverNight $'!$G$373:$G$750,MATCH(B20,'OverNight $'!$C$373:$C$750,0)) -> 1450000 | K20: =SUMIFS('OverNight $'!$I$373:$I$750,'OverNight $'!$B$373:$B$750,A20) -> 3933.125 | M20: 0
A21: =CONCATENATE(MONTH(D21)," ",YEAR(D21)) -> 11 2026 | B21: =EOMONTH(B20,1) -> 46356 | D21: =EOMONTH(D20,1) -> 46356 | E21: SG | F21: NCA | I21: =INDEX('OverNight $'!$H$376:$H$750,MATCH(B21,'OverNight $'!$D$376:$D$750,0)) -> 0.0315 | J21: =INDEX('OverNight $'!$G$373:$G$750,MATCH(B21,'OverNight $'!$C$373:$C$750,0)) -> 1450000 | K21: =SUMIFS('OverNight $'!$I$373:$I$750,'OverNight $'!$B$373:$B$750,A21) -> 3806.25 | M21: 0
A22: =CONCATENATE(MONTH(D22)," ",YEAR(D22)) -> 12 2026 | B22: =EOMONTH(B21,1) -> 46387 | D22: =EOMONTH(D21,1) -> 46387 | E22: SG | F22: NCA | I22: =INDEX('OverNight $'!$H$376:$H$750,MATCH(B22,'OverNight $'!$D$376:$D$750,0)) -> 0.0315 | J22: =INDEX('OverNight $'!$G$373:$G$750,MATCH(B22,'OverNight $'!$C$373:$C$750,0)) -> 1450000 | K22: =SUMIFS('OverNight $'!$I$373:$I$750,'OverNight $'!$B$373:$B$750,A22) -> 3933.125 | M22: 0
D23: Total NCA 2026 | I23: =AVERAGE(I11:I11) -> 0.0315 | K23: =SUM(K11:K11) -> 4324.25 | L23: =SUM(L11:L22) -> 4307.63 | M23: =SUM(M11:M22) -> 0 | O23: change all sums manually each month
A25: =CONCATENATE(MONTH(D25)," ",YEAR(D25)) -> 11 2025 | B25: 45991 | D25: =B25 -> 45991 | E25: BIL | F25: CAT 3m USD | G25: 45965 | H25: 46057 | I25: =INDEX('OverNight $'!$N$5:$N$750,MATCH(B25,'OverNight $'!$D$5:$D$750,0)) -> 0.0399 | J25: =INDEX('OverNight $'!$M$5:$M$750,MATCH(B25,'OverNight $'!$C$5:$C$750,0)) -> 5000000 | K25: =SUMIFS('OverNight $'!$O$5:$O$750,'OverNight $'!$B$5:$B$750,A25) -> 14408.333 | M25: =SUMIFS('OverNight $'!$Q$376:$Q$750,'OverNight $'!$B$376:$B$750,A25) -> 0
A26: =CONCATENATE(MONTH(D26)," ",YEAR(D26)) -> 12 2025 | B26: 46022 | D26: =B26 -> 46022 | E26: BIL | F26: CAT 3m USD | G26: 45965 | H26: 46057 | I26: =INDEX('OverNight $'!$N$5:$N$750,MATCH(B26,'OverNight $'!$D$5:$D$750,0)) -> 0.0399 | J26: =INDEX('OverNight $'!$M$5:$M$750,MATCH(B26,'OverNight $'!$C$5:$C$750,0)) -> 5000000 | K26: =SUMIFS('OverNight $'!$O$5:$O$750,'OverNight $'!$B$5:$B$750,A26) -> 17179.167 | M26: =SUMIFS('OverNight $'!$Q$376:$Q$750,'OverNight $'!$B$376:$B$750,A26) -> 0
D27: BIL 3 months | I27: =AVERAGE(I25:I26) -> 0.0399 | K27: =SUM(K25:K26) -> 31587.5 | L27: =SUM(L25:L26) -> 0 | M27: =SUM(M25:M26) -> 0
A29: =CONCATENATE(MONTH(D29)," ",YEAR(D29)) -> 11 2025 | B29: =B25 -> 45991 | D29: =D25 -> 45991 | E29: BIL | F29: CAT 6m USD | G29: =G25 -> 45965 | H29: 46146 | I29: =INDEX('OverNight $'!$U$5:$U$750,MATCH(B29,'OverNight $'!$D$5:$D$750,0)) -> 0.0392 | J29: =INDEX('OverNight $'!$T$5:$T$750,MATCH(B29,'OverNight $'!$C$5:$C$750,0)) -> 5000000 | K29: =SUMIFS('OverNight $'!$V$5:$V$750,'OverNight $'!$B$5:$B$750,A29) -> 14155.556 | M29: =SUMIFS('OverNight $'!$X$376:$X$750,'OverNight $'!$B$376:$B$750,A29) -> 0
A30: =CONCATENATE(MONTH(D30)," ",YEAR(D30)) -> 12 2025 | B30: =B26 -> 46022 | D30: =D26 -> 46022 | E30: BIL | F30: CAT 6m USD | G30: =G26 -> 45965 | H30: 46146 | I30: =INDEX('OverNight $'!$U$5:$U$750,MATCH(B30,'OverNight $'!$D$5:$D$750,0)) -> 0.0392 | J30: =INDEX('OverNight $'!$T$5:$T$750,MATCH(B30,'OverNight $'!$C$5:$C$750,0)) -> 5000000 | K30: =SUMIFS('OverNight $'!$V$5:$V$750,'OverNight $'!$B$5:$B$750,A30) -> 16877.778 | M30: =SUMIFS('OverNight $'!$X$376:$X$750,'OverNight $'!$B$376:$B$750,A30) -> 0
D31: BIL 6 months | I31: =AVERAGE(I29:I30) -> 0.0392 | K31: =SUM(K29:K30) -> 31033.333 | L31: =SUM(L29:L30) -> 0 | M31: =SUM(M29:M30) -> 0
A33: =CONCATENATE(MONTH(D33)," ",YEAR(D33)) -> 11 2025 | B33: =B29 -> 45991 | D33: =D29 -> 45991 | E33: BIL | F33: CAT 9m USD | G33: =G29 -> 45965 | H33: 46238 | I33: =INDEX('OverNight $'!$AB$5:$AB$750,MATCH(B33,'OverNight $'!$D$5:$D$750,0)) -> 0.0375 | J33: =INDEX('OverNight $'!$AA$5:$AA$750,MATCH(B33,'OverNight $'!$C$5:$C$750,0)) -> 10000000 | K33: =SUMIFS('OverNight $'!$AC$5:$AC$750,'OverNight $'!$B$5:$B$750,A33) -> 27083.333 | M33: =SUMIFS('OverNight $'!$AE$376:$AE$750,'OverNight $'!$B$376:$B$750,A33) -> 0
A34: =CONCATENATE(MONTH(D34)," ",YEAR(D34)) -> 12 2025 | B34: =B30 -> 46022 | D34: =D30 -> 46022 | E34: BIL | F34: CAT 9m USD | G34: =G30 -> 45965 | H34: 46238 | I34: =INDEX('OverNight $'!$AB$5:$AB$750,MATCH(B34,'OverNight $'!$D$5:$D$750,0)) -> 0.0375 | J34: =INDEX('OverNight $'!$AA$5:$AA$750,MATCH(B34,'OverNight $'!$C$5:$C$750,0)) -> 10000000 | K34: =SUMIFS('OverNight $'!$AC$5:$AC$750,'OverNight $'!$B$5:$B$750,A34) -> 32291.667 | M34: =SUMIFS('OverNight $'!$AE$376:$AE$750,'OverNight $'!$B$376:$B$750,A34) -> 0
D35: BIL 9 months | I35: =AVERAGE(I33:I34) -> 0.0375 | K35: =SUM(K33:K34) -> 59375 | L35: =SUM(L33:L34) -> 0 | M35: =SUM(M33:M34) -> 0
