Workbook

Sheet To do
C3: AGA US | G3: AGA Fr
C4: update % avec taux Matt | G4: DS et MM | H4: retirer des AGA et remplacer par le virement prévu
H5: retirer Saafa
C11: Verif
C13: 2027
C14: par quarter ???

Sheet Forecast    ->

Sheet Consolidated Forecast in €
B3: Abivax SA & LLC | E3: 2026 Cash Forecast
R5: if USDEUR 1,16 at 31/12/2026
R6: 3.0911801e+08 | S6: €
B7: Abivax SA + LLC | E7: 46023 | F7: =EDATE(E7,1) -> 46054 | G7: =EDATE(F7,1) -> 46082 | H7: =EDATE(G7,1) -> 46113 | I7: =EDATE(H7,1) -> 46143 | J7: =EDATE(I7,1) -> 46174 | K7: =EDATE(J7,1) -> 46204 | L7: =EDATE(K7,1) -> 46235 | M7: =EDATE(L7,1) -> 46266 | ... P7: =EDATE(O7,1) -> 46357 | R7: =R6-P10 -> 12621891 | S7: de plus si EURUSD a 1,16 car on rmaène tout en eur
A9: Forecast | B9: Balance SA + LLC -EUR+USD- begining of month | C9: k€ | E9: =E15+E19 -> 5.3015759e+08 | F9: =F15+F19 -> 5.0619075e+08 | G9: =G15+G19 -> 4.8497668e+08 | H9: =H15+H19 -> 4.7210148e+08 | I9: =I15+I19 -> 4.3911238e+08 | J9: =J15+J19 -> 4.147261e+08 | K9: =K15+K19 -> 4.0240552e+08 | L9: =L15+L19 -> 3.8323451e+08 | ... P9: =P15+P19 -> 3.0122866e+08 | R9: en USD
A10: Forecast | B10: Balance SA +LLC -EUR+USD- end of month | C10: k€ | E10: =E16+E20 -> 4.9767694e+08 | F10: =F16+F20 -> 4.8497668e+08 | G10: =G16+G20 -> 4.7210148e+08 | H10: =H16+H20 -> 4.3911238e+08 | I10: =I16+I20 -> 4.147261e+08 | J10: =J16+J20 -> 4.0240552e+08 | K10: =K16+K20 -> 3.8323451e+08 | L10: =L16+L20 -> 3.5508067e+08 | ... P10: =P16+P20 -> 2.9649612e+08 | R10: =P10*1.18 -> 3.4986542e+08
A12: Forecast | B12: Montly variance | C12: k€ | E12: =E10-E9 -> -32480653 | F12: =F10-F9 -> -21214077 | G12: =G10-G9 -> -12875195 | H12: =H10-H9 -> -32989102 | I12: =I10-I9 -> -24386281 | J12: =J10-J9 -> -12320576 | K12: =K10-K9 -> -19171010 | L12: =L10-L9 -> -28153839 | ... P12: =P10-P9 -> -4732544.2
B14: Abivax SA, EUR + USD | E14: 45658 | F14: =EDATE(E14,1) -> 45689 | G14: =EDATE(F14,1) -> 45717 | H14: =EDATE(G14,1) -> 45748 | I14: =EDATE(H14,1) -> 45778 | J14: =EDATE(I14,1) -> 45809 | K14: =EDATE(J14,1) -> 45839 | L14: =EDATE(K14,1) -> 45870 | M14: =EDATE(L14,1) -> 45901 | ... P14: =EDATE(O14,1) -> 45992
A15: Forecast | B15: Balance SA-EUR - begining of month | C15: k€ | E15: ='SA Reforecast'!E101 -> 3.6169533e+08 | F15: ='SA Reforecast'!F101 -> 3.4508643e+08 | G15: ='SA Reforecast'!G101 -> 3.3090059e+08 | H15: ='SA Reforecast'!H101 -> 3.1947064e+08 | I15: ='SA Reforecast'!I101 -> 2.8809606e+08 | J15: ='SA Reforecast'!J101 -> 2.6526307e+08 | K15: ='SA Reforecast'!K101 -> 2.5449966e+08 | L15: ='SA Reforecast'!L101 -> 2.3748713e+08 | ... P15: ='SA Reforecast'!P101 -> 1.7051297e+08
A16: Forecast | B16: Balance SA-EUR - end of month | C16: k€ | E16: ='SA Reforecast'!E102 -> 3.4088442e+08 | F16: ='SA Reforecast'!F102 -> 3.3090059e+08 | G16: ='SA Reforecast'!G102 -> 3.1947064e+08 | H16: ='SA Reforecast'!H102 -> 2.8809606e+08 | I16: ='SA Reforecast'!I102 -> 2.6526307e+08 | J16: ='SA Reforecast'!J102 -> 2.5449966e+08 | K16: ='SA Reforecast'!K102 -> 2.3748713e+08 | L16: ='SA Reforecast'!L102 -> 2.1242931e+08 | ... P16: ='SA Reforecast'!P102 -> 1.6944222e+08
B18: Abivax LLC, USD expressed in EUR
A19: Forecast | B19: Balance SA-USD - begining of month | C19: k€ | E19: ='LLC Reforecast'!E45 -> 1.6846226e+08 | F19: ='LLC Reforecast'!F45 -> 1.6110432e+08 | G19: ='LLC Reforecast'!G45 -> 1.5407609e+08 | H19: ='LLC Reforecast'!H45 -> 1.5263084e+08 | I19: ='LLC Reforecast'!I45 -> 1.5101632e+08 | J19: ='LLC Reforecast'!J45 -> 1.4946303e+08 | K19: ='LLC Reforecast'!K45 -> 1.4790586e+08 | L19: ='LLC Reforecast'!L45 -> 1.4574739e+08 | ... P19: ='LLC Reforecast'!P45 -> 1.3071569e+08
A20: Forecast | B20: Balance SA-USD - end of month | C20: k€ | E20: ='LLC Reforecast'!E46 -> 1.5679253e+08 | F20: ='LLC Reforecast'!F46 -> 1.5407609e+08 | G20: ='LLC Reforecast'!G46 -> 1.5263084e+08 | H20: ='LLC Reforecast'!H46 -> 1.5101632e+08 | I20: ='LLC Reforecast'!I46 -> 1.4946303e+08 | J20: ='LLC Reforecast'!J46 -> 1.4790586e+08 | K20: ='LLC Reforecast'!K46 -> 1.4574739e+08 | L20: ='LLC Reforecast'!L46 -> 1.4265136e+08 | ... P20: ='LLC Reforecast'!P46 -> 1.2705389e+08
E23: Budget
B26: Abivax SA + LLC | E26: 45658 | F26: =EDATE(E26,1) -> 45689 | G26: =EDATE(F26,1) -> 45717 | H26: =EDATE(G26,1) -> 45748 | I26: =EDATE(H26,1) -> 45778 | J26: =EDATE(I26,1) -> 45809 | K26: =EDATE(J26,1) -> 45839 | L26: =EDATE(K26,1) -> 45870 | M26: =EDATE(L26,1) -> 45901 | ... P26: =EDATE(O26,1) -> 45992
A27: Budget | B27: Balance SA -EUR+USD- begining of month | C27: k€ | E27: ='Consolidated Budget'!E8 -> 5.3015759e+08 | F27: ='Consolidated Budget'!F8 -> 5.1424281e+08 | G27: ='Consolidated Budget'!G8 -> 4.9302873e+08 | H27: ='Consolidated Budget'!H8 -> 4.8015354e+08 | I27: ='Consolidated Budget'!I8 -> 4.4716444e+08 | J27: ='Consolidated Budget'!J8 -> 4.2277816e+08 | K27: ='Consolidated Budget'!K8 -> 4.1045758e+08 | L27: ='Consolidated Budget'!L8 -> 3.9128657e+08 | ... P27: ='Consolidated Budget'!P8 -> 3.0928072e+08
A28: Budget | B28: Balance SA -EUR+USD- end of month | C28: k€ | E28: ='Consolidated Budget'!E9 -> 5.1424281e+08 | F28: ='Consolidated Budget'!F9 -> 4.9302873e+08 | G28: ='Consolidated Budget'!G9 -> 4.8015354e+08 | H28: ='Consolidated Budget'!H9 -> 4.4716444e+08 | I28: ='Consolidated Budget'!I9 -> 4.2277816e+08 | J28: ='Consolidated Budget'!J9 -> 4.1045758e+08 | K28: ='Consolidated Budget'!K9 -> 3.9128657e+08 | L28: ='Consolidated Budget'!L9 -> 3.6313273e+08 | ... P28: ='Consolidated Budget'!P9 -> 3.0454818e+08
A30: Budget | B30: Montly variance | E30: ='Consolidated Budget'!E11 -> -15914782 | F30: ='Consolidated Budget'!F11 -> -21214077 | G30: ='Consolidated Budget'!G11 -> -12875195 | H30: ='Consolidated Budget'!H11 -> -32989102 | I30: ='Consolidated Budget'!I11 -> -24386281 | J30: ='Consolidated Budget'!J11 -> -12320576 | K30: ='Consolidated Budget'!K11 -> -19171010 | L30: ='Consolidated Budget'!L11 -> -28153839 | ... P30: ='Consolidated Budget'!P11 -> -4732544.2
B33: Abivax SA, EUR + USD | E33: 45658 | F33: =EDATE(E33,1) -> 45689 | G33: =EDATE(F33,1) -> 45717 | H33: =EDATE(G33,1) -> 45748 | I33: =EDATE(H33,1) -> 45778 | J33: =EDATE(I33,1) -> 45809 | K33: =EDATE(J33,1) -> 45839 | L33: =EDATE(K33,1) -> 45870 | M33: =EDATE(L33,1) -> 45901 | ... P33: =EDATE(O33,1) -> 45992
A34: Budget | B34: Balance SA-EUR - begining of month | C34: k€ | E34: ='Consolidated Budget'!E15 -> 3.6169533e+08 | F34: ='Consolidated Budget'!F15 -> 3.4497937e+08 | G34: ='Consolidated Budget'!G15 -> 3.3079352e+08 | H34: ='Consolidated Budget'!H15 -> 3.1936358e+08 | I34: ='Consolidated Budget'!I15 -> 2.87989e+08 | J34: ='Consolidated Budget'!J15 -> 2.65156e+08 | K34: ='Consolidated Budget'!K15 -> 2.543926e+08 | L34: ='Consolidated Budget'!L15 -> 2.3738007e+08 | ... P34: ='Consolidated Budget'!P15 -> 1.7040591e+08
A35: Budget | B35: Balance SA-EUR - end of month | C35: k€ | E35: ='Consolidated Budget'!E16 -> 3.4497937e+08 | F35: ='Consolidated Budget'!F16 -> 3.3079352e+08 | G35: ='Consolidated Budget'!G16 -> 3.1936358e+08 | H35: ='Consolidated Budget'!H16 -> 2.87989e+08 | I35: ='Consolidated Budget'!I16 -> 2.65156e+08 | J35: ='Consolidated Budget'!J16 -> 2.543926e+08 | K35: ='Consolidated Budget'!K16 -> 2.3738007e+08 | L35: ='Consolidated Budget'!L16 -> 2.1232225e+08 | ... P35: ='Consolidated Budget'!P16 -> 1.6933516e+08
B37: Abivax LLC, USD expressed in EUR
A38: Budget | B38: Balance SA-USD - begining of month | C38: k€ | E38: ='Consolidated Budget'!E19 -> 1.6846226e+08 | F38: ='Consolidated Budget'!F19 -> 1.6926344e+08 | G38: ='Consolidated Budget'!G19 -> 1.6223521e+08 | H38: ='Consolidated Budget'!H19 -> 1.6078996e+08 | I38: ='Consolidated Budget'!I19 -> 1.5917544e+08 | J38: ='Consolidated Budget'!J19 -> 1.5762215e+08 | K38: ='Consolidated Budget'!K19 -> 1.5606498e+08 | L38: ='Consolidated Budget'!L19 -> 1.539065e+08 | ... P38: ='Consolidated Budget'!P19 -> 1.3887481e+08
A39: Budget | B39: Balance SA-USD - end of month | C39: k€ | E39: ='Consolidated Budget'!E20 -> 1.6926344e+08 | F39: ='Consolidated Budget'!F20 -> 1.6223521e+08 | G39: ='Consolidated Budget'!G20 -> 1.6078996e+08 | H39: ='Consolidated Budget'!H20 -> 1.5917544e+08 | I39: ='Consolidated Budget'!I20 -> 1.5762215e+08 | J39: ='Consolidated Budget'!J20 -> 1.5606498e+08 | K39: ='Consolidated Budget'!K20 -> 1.539065e+08 | L39: ='Consolidated Budget'!L20 -> 1.5081048e+08 | ... P39: ='Consolidated Budget'!P20 -> 1.3521301e+08
E43: Comparison with Budget (12 month, same methodology so diferent than Board)
B46: Abivax SA + LLC | E46: 45658 | F46: =EDATE(E46,1) -> 45689 | G46: =EDATE(F46,1) -> 45717 | H46: =EDATE(G46,1) -> 45748 | I46: =EDATE(H46,1) -> 45778 | J46: =EDATE(I46,1) -> 45809 | K46: =EDATE(J46,1) -> 45839 | L46: =EDATE(K46,1) -> 45870 | M46: =EDATE(L46,1) -> 45901 | ... P46: =EDATE(O46,1) -> 45992
A47: Comparison | B47: Balance SA -EUR+USD- begining of month | C47: k€ | E47: =E9-E27 -> 0 | F47: =F9-F27 -> -8052057.1 | G47: =G9-G27 -> -8052057.1 | H47: =H9-H27 -> -8052057.1 | I47: =I9-I27 -> -8052057.1 | J47: =J9-J27 -> -8052057.1 | K47: =K9-K27 -> -8052057.1 | L47: =L9-L27 -> -8052057.1 | ... P47: =P9-P27 -> -8052057.1
A48: Comparison | B48: Balance SA -EUR+USD- end of month | C48: k€ | E48: =E10-E28 -> -16565870 | F48: =F10-F28 -> -8052057.1 | G48: =G10-G28 -> -8052057.1 | H48: =H10-H28 -> -8052057.1 | I48: =I10-I28 -> -8052057.1 | J48: =J10-J28 -> -8052057.1 | K48: =K10-K28 -> -8052057.1 | L48: =L10-L28 -> -8052057.1 | ... P48: =P10-P28 -> -8052057.1
A50: Comparison | B50: Montly variance | E50: =E12-E30 -> -16565870 | F50: =F12-F30 -> 1.1920929e-07 | G50: =G12-G30 -> 0 | H50: =H12-H30 -> 0 | I50: =I12-I30 -> 0 | J50: =J12-J30 -> 0 | K50: =K12-K30 -> 0 | L50: =L12-L30 -> -5.9604645e-08 | ... P50: =P12-P30 -> 0
B53: Abivax SA, EUR + USD | E53: 45658 | F53: =EDATE(E53,1) -> 45689 | G53: =EDATE(F53,1) -> 45717 | H53: =EDATE(G53,1) -> 45748 | I53: =EDATE(H53,1) -> 45778 | J53: =EDATE(I53,1) -> 45809 | K53: =EDATE(J53,1) -> 45839 | L53: =EDATE(K53,1) -> 45870 | M53: =EDATE(L53,1) -> 45901 | ... P53: =EDATE(O53,1) -> 45992
A54: Comparison | B54: Balance SA-EUR - begining of month | C54: k€ | E54: =E15-'Consolidated Budget'!E15 -> 0 | F54: =F15-'Consolidated Budget'!F15 -> 107061.47 | G54: =G15-'Consolidated Budget'!G15 -> 107061.47 | H54: =H15-'Consolidated Budget'!H15 -> 107061.47 | I54: =I15-'Consolidated Budget'!I15 -> 107061.47 | J54: =J15-'Consolidated Budget'!J15 -> 107061.47 | K54: =K15-'Consolidated Budget'!K15 -> 107061.47 | L54: =L15-'Consolidated Budget'!L15 -> 107061.47 | ... P54: =P15-'Consolidated Budget'!P15 -> 107061.47
A55: Comparison | B55: Balance SA-EUR - end of month | C55: k€ | E55: =E16-'Consolidated Budget'!E16 -> -4094957.4 | F55: =F16-'Consolidated Budget'!F16 -> 107061.47 | G55: =G16-'Consolidated Budget'!G16 -> 107061.47 | H55: =H16-'Consolidated Budget'!H16 -> 107061.47 | I55: =I16-'Consolidated Budget'!I16 -> 107061.47 | J55: =J16-'Consolidated Budget'!J16 -> 107061.47 | K55: =K16-'Consolidated Budget'!K16 -> 107061.47 | L55: =L16-'Consolidated Budget'!L16 -> 107061.47 | ... P55: =P16-'Consolidated Budget'!P16 -> 107061.47
B57: Abivax LLC, USD expressed in EUR
A58: Comparison | B58: Balance SA-USD - begining of month | C58: k€ | E58: =E19-'Consolidated Budget'!E19 -> 0 | F58: =F19-'Consolidated Budget'!F19 -> -8159118.5 | G58: =G19-'Consolidated Budget'!G19 -> -8159118.5 | H58: =H19-'Consolidated Budget'!H19 -> -8159118.5 | I58: =I19-'Consolidated Budget'!I19 -> -8159118.5 | J58: =J19-'Consolidated Budget'!J19 -> -8159118.5 | K58: =K19-'Consolidated Budget'!K19 -> -8159118.5 | L58: =L19-'Consolidated Budget'!L19 -> -8159118.5 | ... P58: =P19-'Consolidated Budget'!P19 -> -8159118.5
A59: Comparison | B59: Balance SA-USD - end of month | C59: k€ | E59: =E20-'Consolidated Budget'!E20 -> -12470913 | F59: =F20-'Consolidated Budget'!F20 -> -8159118.5 | G59: =G20-'Consolidated Budget'!G20 -> -8159118.5 | H59: =H20-'Consolidated Budget'!H20 -> -8159118.5 | I59: =I20-'Consolidated Budget'!I20 -> -8159118.5 | J59: =J20-'Consolidated Budget'!J20 -> -8159118.5 | K59: =K20-'Consolidated Budget'!K20 -> -8159118.5 | L59: =L20-'Consolidated Budget'!L20 -> -8159118.5 | ... P59: =P20-'Consolidated Budget'!P20 -> -8159118.5
A60: check

Sheet SA Reforecast
B3: Abivax SA | E3: Cash Forecast - V budget | AA3: Comparison Forecast- Budget
B6: Abivax SA EUR | E6: Forecast-Budget | AA6: Forecast-Budget
E7: 46023 | F7: =EDATE(E7,1) -> 46054 | G7: =EDATE(F7,1) -> 46082 | H7: =EDATE(G7,1) -> 46113 | I7: =EDATE(H7,1) -> 46143 | J7: =EDATE(I7,1) -> 46174 | K7: =EDATE(J7,1) -> 46204 | L7: =EDATE(K7,1) -> 46235 | M7: =EDATE(L7,1) -> 46266 | ... P7: =EDATE(O7,1) -> 46357 | R7: 2026 | AA7: 46023 | AB7: =EDATE(AA7,1) -> 46054 | AC7: =EDATE(AB7,1) -> 46082 | AD7: =EDATE(AC7,1) -> 46113 | AE7: =EDATE(AD7,1) -> 46143 | AF7: =EDATE(AE7,1) -> 46174 | AG7: =EDATE(AF7,1) -> 46204 | AH7: =EDATE(AG7,1) -> 46235 | AI7: =EDATE(AH7,1) -> 46266 | ... AL7: =EDATE(AK7,1) -> 46357 | AN7: 2026
B9: Amount are VAT excluded
B10: IQVIA 105 milestone | C10: k€ | E10: ='SA Actual'!E10 -> 0 | F10: ='SA budget'!F10 -> 0 | G10: ='SA budget'!G10 -> 0 | H10: ='SA budget'!H10 -> 0 | I10: ='SA budget'!I10 -> 0 | J10: ='SA budget'!J10 -> 0 | K10: ='SA budget'!K10 -> 2363322 | L10: ='SA budget'!L10 -> 294998.69 | M10: ='SA budget'!M10 -> 0 | ... P10: ='SA budget'!P10 -> 0 | R10: =SUM(E10:P10) -> 2658320.7 | T10: 54 en cash versus 51 au budget : +3 m€ | AA10: =E10-'SA budget'!E10 -> 0 | AB10: =F10-'SA budget'!F10 -> 0 | AC10: =G10-'SA budget'!G10 -> 0 | AD10: =H10-'SA budget'!H10 -> 0 | AE10: =I10-'SA budget'!I10 -> 0 | AF10: =J10-'SA budget'!J10 -> 0 | AG10: =K10-'SA budget'!K10 -> 0 | AH10: =L10-'SA budget'!L10 -> 0 | ... AL10: =P10-'SA budget'!P10 -> 0 | AN10: =SUM(AA10:AL10) -> 0
B11: IQVIA 105 PTC & IF & Q2 | C11: k€ | E11: ='SA Actual'!E11 -> 599166.48 | F11: ='SA budget'!F11 -> 570621.62 | G11: ='SA budget'!G11 -> 612797.98 | H11: ='SA budget'!H11 -> 237810 | I11: ='SA budget'!I11 -> 0 | J11: ='SA budget'!J11 -> 0 | K11: ='SA budget'!K11 -> 0 | L11: ='SA budget'!L11 -> 0 | M11: ='SA budget'!M11 -> 0 | ... P11: ='SA budget'!P11 -> 0 | R11: =SUM(E11:P11) -> 2020396.1 | T11: milestone DBL 105 à ajouter au Reforecast : 2,4 m€ | AA11: =E11-'SA budget'!E11 -> 0 | AB11: =F11-'SA budget'!F11 -> 0 | AC11: =G11-'SA budget'!G11 -> 0 | AD11: =H11-'SA budget'!H11 -> 0 | AE11: =I11-'SA budget'!I11 -> 0 | AF11: =J11-'SA budget'!J11 -> 0 | AG11: =K11-'SA budget'!K11 -> 0 | AH11: =L11-'SA budget'!L11 -> 0 | ... AL11: =P11-'SA budget'!P11 -> 0 | AN11: =SUM(AA11:AL11) -> 0
B12: IQVIA 106 milestone | C12: k€ | E12: ='SA Actual'!E12 -> 0 | F12: ='SA budget'!F12 -> 0 | G12: ='SA budget'!G12 -> 0 | H12: ='SA budget'!H12 -> 0 | I12: ='SA budget'!I12 -> 0 | J12: ='SA budget'!J12 -> 0 | K12: ='SA budget'!K12 -> 756326 | L12: ='SA budget'!L12 -> 109002.94 | M12: ='SA budget'!M12 -> 0 | ... P12: ='SA budget'!P12 -> 0 | R12: =SUM(E12:P12) -> 865328.94 | T12: paiement janvier de facture de décembre 2025 + 10 m€ mais -9 m€ pour 107 (65% monitoring et PTC) | AA12: =E12-'SA budget'!E12 -> 0 | AB12: =F12-'SA budget'!F12 -> 0 | AC12: =G12-'SA budget'!G12 -> 0 | AD12: =H12-'SA budget'!H12 -> 0 | AE12: =I12-'SA budget'!I12 -> 0 | AF12: =J12-'SA budget'!J12 -> 0 | AG12: =K12-'SA budget'!K12 -> 0 | AH12: =L12-'SA budget'!L12 -> 0 | ... AL12: =P12-'SA budget'!P12 -> 0 | AN12: =SUM(AA12:AL12) -> 0
B13: IQVIA 106 PTC & IF & Q2 | C13: k€ | E13: ='SA Actual'!E13 -> 1246050.2 | F13: ='SA budget'!F13 -> 467517.53 | G13: ='SA budget'!G13 -> 619029.58 | H13: ='SA budget'!H13 -> 237306 | I13: ='SA budget'!I13 -> 224267 | J13: ='SA budget'!J13 -> 0 | K13: ='SA budget'!K13 -> 0 | L13: ='SA budget'!L13 -> 0 | M13: ='SA budget'!M13 -> 0 | ... P13: ='SA budget'!P13 -> 0 | R13: =SUM(E13:P13) -> 2794170.4 | AA13: =E13-'SA budget'!E13 -> 0 | AB13: =F13-'SA budget'!F13 -> 0 | AC13: =G13-'SA budget'!G13 -> 0 | AD13: =H13-'SA budget'!H13 -> 0 | AE13: =I13-'SA budget'!I13 -> 0 | AF13: =J13-'SA budget'!J13 -> 0 | AG13: =K13-'SA budget'!K13 -> 0 | AH13: =L13-'SA budget'!L13 -> 0 | ... AL13: =P13-'SA budget'!P13 -> 0 | AN13: =SUM(AA13:AL13) -> 0
B14: IQVIA 107 milestone | C14: k€ | E14: ='SA Actual'!E14 -> 4790962 | F14: ='SA budget'!F14 -> 0 | G14: ='SA budget'!G14 -> 0 | H14: ='SA budget'!H14 -> 0 | I14: ='SA budget'!I14 -> 7186443 | J14: ='SA budget'!J14 -> 0 | K14: ='SA budget'!K14 -> 0 | L14: ='SA budget'!L14 -> 9581924 | M14: ='SA budget'!M14 -> 0 | ... P14: ='SA budget'!P14 -> 0 | R14: =SUM(E14:P14) -> 28745772 | AA14: =E14-'SA budget'!E14 -> 0 | AB14: =F14-'SA budget'!F14 -> 0 | AC14: =G14-'SA budget'!G14 -> 0 | AD14: =H14-'SA budget'!H14 -> 0 | AE14: =I14-'SA budget'!I14 -> 0 | AF14: =J14-'SA budget'!J14 -> 0 | AG14: =K14-'SA budget'!K14 -> 0 | AH14: =L14-'SA budget'!L14 -> 0 | ... AL14: =P14-'SA budget'!P14 -> 0 | AN14: =SUM(AA14:AL14) -> 0
B15: IQVIA 107 PTC & IF & Q2 | C15: k€ | E15: ='SA Actual'!E15 -> 1814129.3 | F15: ='SA budget'!F15 -> 1542238.5 | G15: ='SA budget'!G15 -> 1125311.7 | H15: ='SA budget'!H15 -> 978890 | I15: ='SA budget'!I15 -> 650000 | J15: ='SA budget'!J15 -> 650000 | K15: ='SA budget'!K15 -> 0 | L15: ='SA budget'!L15 -> 0 | M15: ='SA budget'!M15 -> 0 | ... P15: ='SA budget'!P15 -> 0 | R15: =SUM(E15:P15) -> 6760569.5 | AA15: =E15-'SA budget'!E15 -> 0 | AB15: =F15-'SA budget'!F15 -> 0 | AC15: =G15-'SA budget'!G15 -> 0 | AD15: =H15-'SA budget'!H15 -> 0 | AE15: =I15-'SA budget'!I15 -> 0 | AF15: =J15-'SA budget'!J15 -> 0 | AG15: =K15-'SA budget'!K15 -> 0 | AH15: =L15-'SA budget'!L15 -> 0 | ... AL15: =P15-'SA budget'!P15 -> 0 | AN15: =SUM(AA15:AL15) -> 0
B16: IQVIA Ph3 - CO | C16: k€ | E16: ='SA Actual'!E16 -> 0 | F16: ='SA budget'!F16 -> 0 | G16: ='SA budget'!G16 -> 0 | H16: ='SA budget'!H16 -> 5000000 | I16: ='SA budget'!I16 -> 2000000 | J16: ='SA budget'!J16 -> 2000000 | K16: ='SA budget'!K16 -> 1000000 | L16: ='SA budget'!L16 -> 0 | M16: ='SA budget'!M16 -> 0 | ... P16: ='SA budget'!P16 -> 0 | R16: =SUM(E16:P16) -> 10000000 | T16: Budget : 10,5 me CO4 Ph3 sur 2026 | AA16: =E16-'SA budget'!E16 -> 0 | AB16: =F16-'SA budget'!F16 -> 0 | AC16: =G16-'SA budget'!G16 -> 0 | AD16: =H16-'SA budget'!H16 -> 0 | AE16: =I16-'SA budget'!I16 -> 0 | AF16: =J16-'SA budget'!J16 -> 0 | AG16: =K16-'SA budget'!K16 -> 0 | AH16: =L16-'SA budget'!L16 -> 0 | ... AL16: =P16-'SA budget'!P16 -> 0 | AN16: =SUM(AA16:AL16) -> 0
B17: IQVIA CD milestone | C17: k€ | E17: ='SA Actual'!E17 -> 1308382 | F17: ='SA budget'!F17 -> 0 | G17: ='SA budget'!G17 -> 1308382 | H17: ='SA budget'!H17 -> 1308381.9 | I17: ='SA budget'!I17 -> 1831734.7 | J17: ='SA budget'!J17 -> 0 | K17: ='SA budget'!K17 -> 2355087.5 | L17: ='SA budget'!L17 -> 1570058.3 | M17: ='SA budget'!M17 -> 1046705.6 | ... P17: ='SA budget'!P17 -> 0 | R17: =SUM(E17:P17) -> 11775438 | T17: pourquoi 14 m€ versus 10 m€ au budget et 14 m€ sur couts projets | AA17: =E17-'SA budget'!E17 -> 0 | AB17: =F17-'SA budget'!F17 -> 0 | AC17: =G17-'SA budget'!G17 -> 0 | AD17: =H17-'SA budget'!H17 -> 0 | AE17: =I17-'SA budget'!I17 -> 0 | AF17: =J17-'SA budget'!J17 -> 0 | AG17: =K17-'SA budget'!K17 -> 0 | AH17: =L17-'SA budget'!L17 -> 0 | ... AL17: =P17-'SA budget'!P17 -> 0 | AN17: =SUM(AA17:AL17) -> 0
B18: IQVIA CD PTC & IF & Q2 | C18: k€ | E18: ='SA Actual'!E18 -> 214041.3 | F18: ='SA budget'!F18 -> 301393.22 | G18: ='SA budget'!G18 -> 0 | H18: ='SA budget'!H18 -> 220000 | I18: ='SA budget'!I18 -> 220000 | J18: ='SA budget'!J18 -> 220000 | K18: ='SA budget'!K18 -> 220000 | L18: ='SA budget'!L18 -> 220000 | M18: ='SA budget'!M18 -> 220000 | ... P18: ='SA budget'!P18 -> 220000 | R18: =SUM(E18:P18) -> 2495434.5 | T18: réponse : -3m€ de FNP en janvier; +1 m€ de paiement jnvier et -1m€ factures dec 2026 | AA18: =E18-'SA budget'!E18 -> 0 | AB18: =F18-'SA budget'!F18 -> 0 | AC18: =G18-'SA budget'!G18 -> 0 | AD18: =H18-'SA budget'!H18 -> 0 | AE18: =I18-'SA budget'!I18 -> 0 | AF18: =J18-'SA budget'!J18 -> 0 | AG18: =K18-'SA budget'!K18 -> 0 | AH18: =L18-'SA budget'!L18 -> 0 | ... AL18: =P18-'SA budget'!P18 -> 0 | AN18: =SUM(AA18:AL18) -> 0
B19: IQVIA CD -CO | C19: k€ | E19: ='SA Actual'!E19 -> 0 | F19: ='SA budget'!F19 -> 0 | G19: ='SA budget'!G19 -> 0 | H19: ='SA budget'!H19 -> 3000000 | I19: ='SA budget'!I19 -> 375000 | J19: ='SA budget'!J19 -> 375000 | K19: ='SA budget'!K19 -> 375000 | L19: ='SA budget'!L19 -> 375000 | M19: ='SA budget'!M19 -> 375000 | ... P19: ='SA budget'!P19 -> 375000 | R19: =SUM(E19:P19) -> 6000000 | T19: CO2 ! 6 m€ ppour 2026 | AA19: =E19-'SA budget'!E19 -> 0 | AB19: =F19-'SA budget'!F19 -> 0 | AC19: =G19-'SA budget'!G19 -> 0 | AD19: =H19-'SA budget'!H19 -> 0 | AE19: =I19-'SA budget'!I19 -> 0 | AF19: =J19-'SA budget'!J19 -> 0 | AG19: =K19-'SA budget'!K19 -> 0 | AH19: =L19-'SA budget'!L19 -> 0 | ... AL19: =P19-'SA budget'!P19 -> 0 | AN19: =SUM(AA19:AL19) -> 0
B20: Total IQVIA | C20: k€ | E20: =SUM(E10:E19) -> 9972731.3 | F20: =SUM(F10:F19) -> 2881770.9 | G20: =SUM(G10:G19) -> 3665521.2 | H20: =SUM(H10:H19) -> 10982388 | I20: =SUM(I10:I19) -> 12487445 | J20: =SUM(J10:J19) -> 3245000 | K20: =SUM(K10:K19) -> 7069735.5 | L20: =SUM(L10:L19) -> 12150984 | ... P20: =SUM(P10:P19) -> 595000 | R20: =SUM(E20:P20) -> 74115430 | AA20: =SUM(AA10:AA19) -> 0 | AB20: =SUM(AB10:AB19) -> 0 | AC20: =SUM(AC10:AC19) -> 0 | AD20: =SUM(AD10:AD19) -> 0 | AE20: =SUM(AE10:AE19) -> 0 | AF20: =SUM(AF10:AF19) -> 0 | AG20: =SUM(AG10:AG19) -> 0 | AH20: =SUM(AH10:AH19) -> 0 | ... AL20: =SUM(AL10:AL19) -> 0 | AN20: =SUM(AA20:AL20) -> 0
B22: Other Suppliers € (HT) | C22: k€ | E22: ='SA Actual'!E22 -> 5117218.8 | F22: ='SA budget'!F22 -> 4718356.9 | G22: ='SA budget'!G22 -> 4718356.9 | H22: ='SA budget'!H22 -> 4718356.9 | I22: ='SA budget'!I22 -> 4596761.9 | J22: ='SA budget'!J22 -> 4596761.9 | K22: ='SA budget'!K22 -> 4596761.9 | L22: ='SA budget'!L22 -> 4858617.1 | M22: ='SA budget'!M22 -> 4858617.1 | ... P22: ='SA budget'!P22 -> 5128841.5 | R22: =SUM(E22:P22) -> 57896109 | AA22: =E22-'SA budget'!E22 -> 398861.87 | AB22: =F22-'SA budget'!F22 -> 0 | AC22: =G22-'SA budget'!G22 -> 0 | AD22: =H22-'SA budget'!H22 -> 0 | AE22: =I22-'SA budget'!I22 -> 0 | AF22: =J22-'SA budget'!J22 -> 0 | AG22: =K22-'SA budget'!K22 -> 0 | AH22: =L22-'SA budget'!L22 -> 0 | ... AL22: =P22-'SA budget'!P22 -> 0 | AN22: =SUM(AA22:AL22) -> 398861.87
B23: Contractor (HT) | C23: k€ | E23: ='SA Actual'!E23 -> 405647.09 | F23: ='SA budget'!F23 -> 416446.67 | G23: ='SA budget'!G23 -> 416446.67 | H23: ='SA budget'!H23 -> 416446.67 | I23: ='SA budget'!I23 -> 431846.67 | J23: ='SA budget'!J23 -> 431846.67 | K23: ='SA budget'!K23 -> 431846.67 | L23: ='SA budget'!L23 -> 431846.67 | M23: ='SA budget'!M23 -> 431846.67 | ... P23: ='SA budget'!P23 -> 420866.67 | R23: =SUM(E23:P23) -> 5087800.4 | AA23: =E23-'SA budget'!E23 -> -10799.575 | AB23: =F23-'SA budget'!F23 -> 0 | AC23: =G23-'SA budget'!G23 -> 0 | AD23: =H23-'SA budget'!H23 -> 0 | AE23: =I23-'SA budget'!I23 -> 0 | AF23: =J23-'SA budget'!J23 -> 0 | AG23: =K23-'SA budget'!K23 -> 0 | AH23: =L23-'SA budget'!L23 -> 0 | ... AL23: =P23-'SA budget'!P23 -> 0 | AN23: =SUM(AA23:AL23) -> -10799.575
B24: Bank fees | C24: k€ | E24: ='SA Actual'!E24 -> 17774.39 | F24: ='SA budget'!F24 -> 0 | G24: ='SA budget'!G24 -> 0 | H24: ='SA budget'!H24 -> 0 | I24: ='SA budget'!I24 -> 0 | J24: ='SA budget'!J24 -> 0 | K24: ='SA budget'!K24 -> 0 | L24: ='SA budget'!L24 -> 0 | M24: ='SA budget'!M24 -> 0 | ... P24: ='SA budget'!P24 -> 0 | AA24: =E24-'SA budget'!E24 -> 17774.39 | AB24: =F24-'SA budget'!F24 -> 0 | AC24: =G24-'SA budget'!G24 -> 0 | AD24: =H24-'SA budget'!H24 -> 0 | AE24: =I24-'SA budget'!I24 -> 0 | AF24: =J24-'SA budget'!J24 -> 0 | AG24: =K24-'SA budget'!K24 -> 0 | AH24: =L24-'SA budget'!L24 -> 0 | ... AL24: =P24-'SA budget'!P24 -> 0 | AN24: =SUM(AA24:AL24) -> 17774.39
B25: Suppliers + Contractos | C25: k€ | E25: =SUM(E22:E24) -> 5540640.2 | F25: =SUM(F22:F24) -> 5134803.5 | G25: =SUM(G22:G24) -> 5134803.5 | H25: =SUM(H22:H24) -> 5134803.5 | I25: =SUM(I22:I24) -> 5028608.5 | J25: =SUM(J22:J24) -> 5028608.5 | K25: =SUM(K22:K24) -> 5028608.5 | L25: =SUM(L22:L24) -> 5290463.8 | ... P25: =SUM(P22:P24) -> 5549708.2 | R25: =SUM(E25:P25) -> 63001684 | AA25: =SUM(AA22:AA24) -> 405836.68 | AB25: =SUM(AB22:AB24) -> 0 | AC25: =SUM(AC22:AC24) -> 0 | AD25: =SUM(AD22:AD24) -> 0 | AE25: =SUM(AE22:AE24) -> 0 | AF25: =SUM(AF22:AF24) -> 0 | AG25: =SUM(AG22:AG24) -> 0 | AH25: =SUM(AH22:AH24) -> 0 | ... AL25: =SUM(AL22:AL24) -> 0 | AN25: =SUM(AA25:AL25) -> 405836.68
B27: Capex | C27: k€ | E27: ='SA Actual'!E27 -> 0 | F27: ='SA budget'!F27 -> 0 | G27: ='SA budget'!G27 -> 0 | H27: ='SA budget'!H27 -> 200000 | I27: ='SA budget'!I27 -> 200000 | J27: ='SA budget'!J27 -> 200000 | K27: ='SA budget'!K27 -> 200000 | L27: ='SA budget'!L27 -> 200000 | M27: ='SA budget'!M27 -> 200000 | ... P27: ='SA budget'!P27 -> 200000 | R27: =SUM(E27:P27) -> 1800000 | AA27: =E27-'SA budget'!E27 -> 0 | AB27: =F27-'SA budget'!F27 -> 0 | AC27: =G27-'SA budget'!G27 -> 0 | AD27: =H27-'SA budget'!H27 -> 0 | AE27: =I27-'SA budget'!I27 -> 0 | AF27: =J27-'SA budget'!J27 -> 0 | AG27: =K27-'SA budget'!K27 -> 0 | AH27: =L27-'SA budget'!L27 -> 0 | ... AL27: =P27-'SA budget'!P27 -> 0 | AN27: =SUM(AA27:AL27) -> 0
B29: Salaire net aprés PAS | C29: k€ | E29: ='SA Actual'!E29 -> 309076.43 | F29: ='SA budget'!F29 -> 296854.81 | G29: ='SA budget'!G29 -> 296854.81 | H29: ='SA budget'!H29 -> 296854.81 | I29: ='SA budget'!I29 -> 296854.81 | J29: ='SA budget'!J29 -> 296854.81 | K29: ='SA budget'!K29 -> 296854.81 | L29: ='SA budget'!L29 -> 296854.81 | M29: ='SA budget'!M29 -> 296854.81 | ... P29: ='SA budget'!P29 -> 296854.81 | R29: =SUM(E29:P29) -> 3574479.3 | AA29: =E29-'SA budget'!E29 -> 12221.623 | AB29: =F29-'SA budget'!F29 -> 0 | AC29: =G29-'SA budget'!G29 -> 0 | AD29: =H29-'SA budget'!H29 -> 0 | AE29: =I29-'SA budget'!I29 -> 0 | AF29: =J29-'SA budget'!J29 -> 0 | AG29: =K29-'SA budget'!K29 -> 0 | AH29: =L29-'SA budget'!L29 -> 0 | ... AL29: =P29-'SA budget'!P29 -> 0 | AN29: =SUM(AA29:AL29) -> 12221.623
B30: Bonus net sans PAS | C30: k€ | E30: ='SA Actual'!E30 -> 0 | F30: ='SA budget'!F30 -> 662352.23 | G30: ='SA budget'!G30 -> 0 | H30: ='SA budget'!H30 -> 0 | I30: ='SA budget'!I30 -> 0 | J30: ='SA budget'!J30 -> 277342.06 | K30: ='SA budget'!K30 -> 0 | L30: ='SA budget'!L30 -> 0 | M30: ='SA budget'!M30 -> 0 | ... P30: ='SA budget'!P30 -> 0 | R30: =SUM(E30:P30) -> 939694.29 | AA30: =E30-'SA budget'!E30 -> 0 | AB30: =F30-'SA budget'!F30 -> 0 | AC30: =G30-'SA budget'!G30 -> 0 | AD30: =H30-'SA budget'!H30 -> 0 | AE30: =I30-'SA budget'!I30 -> 0 | AF30: =J30-'SA budget'!J30 -> 0 | AG30: =K30-'SA budget'!K30 -> 0 | AH30: =L30-'SA budget'!L30 -> 0 | ... AL30: =P30-'SA budget'!P30 -> 0 | AN30: =SUM(AA30:AL30) -> 0
B31: Urssaf | C31: k€ | E31: ='SA Actual'!E31 -> 175083 | F31: ='SA budget'!F31 -> 213251.39 | G31: ='SA budget'!G31 -> 689064.92 | H31: ='SA budget'!H31 -> 213251.39 | I31: ='SA budget'!I31 -> 213251.39 | J31: ='SA budget'!J31 -> 213251.39 | K31: ='SA budget'!K31 -> 412485.43 | L31: ='SA budget'!L31 -> 213251.39 | M31: ='SA budget'!M31 -> 213251.39 | ... P31: ='SA budget'!P31 -> 213251.39 | R31: =SUM(E31:P31) -> 3195895.9 | AA31: =E31-'SA budget'!E31 -> -38168.39 | AB31: =F31-'SA budget'!F31 -> 0 | AC31: =G31-'SA budget'!G31 -> 0 | AD31: =H31-'SA budget'!H31 -> 0 | AE31: =I31-'SA budget'!I31 -> 0 | AF31: =J31-'SA budget'!J31 -> 0 | AG31: =K31-'SA budget'!K31 -> 0 | AH31: =L31-'SA budget'!L31 -> 0 | ... AL31: =P31-'SA budget'!P31 -> 0 | AN31: =SUM(AA31:AL31) -> -38168.39
B32: Retraite | C32: k€ | E32: ='SA Actual'!E32 -> 70015.02 | F32: ='SA budget'!F32 -> 93053.399 | G32: ='SA budget'!G32 -> 300677.21 | H32: ='SA budget'!H32 -> 93053.399 | I32: ='SA budget'!I32 -> 93053.399 | J32: ='SA budget'!J32 -> 93053.399 | K32: ='SA budget'!K32 -> 179990.25 | L32: ='SA budget'!L32 -> 93053.399 | M32: ='SA budget'!M32 -> 93053.399 | ... P32: ='SA budget'!P32 -> 93053.399 | R32: =SUM(E32:P32) -> 1388163.1 | AA32: =E32-'SA budget'!E32 -> -23038.379 | AB32: =F32-'SA budget'!F32 -> 0 | AC32: =G32-'SA budget'!G32 -> 0 | AD32: =H32-'SA budget'!H32 -> 0 | AE32: =I32-'SA budget'!I32 -> 0 | AF32: =J32-'SA budget'!J32 -> 0 | AG32: =K32-'SA budget'!K32 -> 0 | AH32: =L32-'SA budget'!L32 -> 0 | ... AL32: =P32-'SA budget'!P32 -> 0 | AN32: =SUM(AA32:AL32) -> -23038.379
B33: Prévoyance | C33: k€ | E33: ='SA Actual'!E33 -> 0 | F33: ='SA budget'!F33 -> 0 | G33: ='SA budget'!G33 -> 0 | H33: ='SA budget'!H33 -> 44138.446 | I33: ='SA budget'!I33 -> 0 | J33: ='SA budget'!J33 -> 0 | K33: ='SA budget'!K33 -> 25312.453 | L33: ='SA budget'!L33 -> 0 | M33: ='SA budget'!M33 -> 0 | ... P33: ='SA budget'!P33 -> 0 | R33: =SUM(E33:P33) -> 94763.352 | AA33: =E33-'SA budget'!E33 -> -25312.453 | AB33: =F33-'SA budget'!F33 -> 0 | AC33: =G33-'SA budget'!G33 -> 0 | AD33: =H33-'SA budget'!H33 -> 0 | AE33: =I33-'SA budget'!I33 -> 0 | AF33: =J33-'SA budget'!J33 -> 0 | AG33: =K33-'SA budget'!K33 -> 0 | AH33: =L33-'SA budget'!L33 -> 0 | ... AL33: =P33-'SA budget'!P33 -> 0 | AN33: =SUM(AA33:AL33) -> -25312.453
B34: Mutuelle | C34: k€ | E34: ='SA Actual'!E34 -> 6151.49 | F34: ='SA budget'!F34 -> 0 | G34: ='SA budget'!G34 -> 0 | H34: ='SA budget'!H34 -> 38337.393 | I34: ='SA budget'!I34 -> 0 | J34: ='SA budget'!J34 -> 0 | K34: ='SA budget'!K34 -> 21985.674 | L34: ='SA budget'!L34 -> 0 | M34: ='SA budget'!M34 -> 0 | ... P34: ='SA budget'!P34 -> 0 | R34: =SUM(E34:P34) -> 88460.23 | AA34: =E34-'SA budget'!E34 -> -15834.184 | AB34: =F34-'SA budget'!F34 -> 0 | AC34: =G34-'SA budget'!G34 -> 0 | AD34: =H34-'SA budget'!H34 -> 0 | AE34: =I34-'SA budget'!I34 -> 0 | AF34: =J34-'SA budget'!J34 -> 0 | AG34: =K34-'SA budget'!K34 -> 0 | AH34: =L34-'SA budget'!L34 -> 0 | ... AL34: =P34-'SA budget'!P34 -> 0 | AN34: =SUM(AA34:AL34) -> -15834.184
B35: Dgfip (PAS) | C35: k€ | E35: ='SA Actual'!E35 -> 69813 | F35: ='SA budget'!F35 -> 80276.637 | G35: ='SA budget'!G35 -> 259392.52 | H35: ='SA budget'!H35 -> 80276.637 | I35: ='SA budget'!I35 -> 80276.637 | J35: ='SA budget'!J35 -> 80276.637 | K35: ='SA budget'!K35 -> 155276.56 | L35: ='SA budget'!L35 -> 80276.637 | M35: ='SA budget'!M35 -> 80276.637 | ... P35: ='SA budget'!P35 -> 80276.637 | R35: =SUM(E35:P35) -> 1206971.8 | AA35: =E35-'SA budget'!E35 -> -10463.637 | AB35: =F35-'SA budget'!F35 -> 0 | AC35: =G35-'SA budget'!G35 -> 0 | AD35: =H35-'SA budget'!H35 -> 0 | AE35: =I35-'SA budget'!I35 -> 0 | AF35: =J35-'SA budget'!J35 -> 0 | AG35: =K35-'SA budget'!K35 -> 0 | AH35: =L35-'SA budget'!L35 -> 0 | ... AL35: =P35-'SA budget'!P35 -> 0 | AN35: =SUM(AA35:AL35) -> -10463.637
B36: Total Salary & Social Charges | C36: k€ | E36: =SUM(E29:E35) -> 630138.94 | F36: =SUM(F29:F35) -> 1345788.5 | G36: =SUM(G29:G35) -> 1545989.5 | H36: =SUM(H29:H35) -> 765912.07 | I36: =SUM(I29:I35) -> 683436.23 | J36: =SUM(J29:J35) -> 960778.3 | K36: =SUM(K29:K35) -> 1091905.2 | L36: =SUM(L29:L35) -> 683436.23 | ... P36: =SUM(P29:P35) -> 683436.23 | R36: =SUM(E36:P36) -> 10488428 | AA36: =SUM(AA29:AA35) -> -100595.42 | AB36: =SUM(AB29:AB35) -> 0 | AC36: =SUM(AC29:AC35) -> 0 | AD36: =SUM(AD29:AD35) -> 0 | AE36: =SUM(AE29:AE35) -> 0 | AF36: =SUM(AF29:AF35) -> 0 | AG36: =SUM(AG29:AG35) -> 0 | AH36: =SUM(AH29:AH35) -> 0 | ... AL36: =SUM(AL29:AL35) -> 0 | AN36: =SUM(AA36:AL36) -> -100595.42
B38: Jetons de présence | C38: k€ | E38: ='SA Actual'!E38 -> 75500 | F38: ='SA budget'!F38 -> 0 | G38: ='SA budget'!G38 -> 0 | H38: ='SA budget'!H38 -> 0 | I38: ='SA budget'!I38 -> 0 | J38: ='SA budget'!J38 -> 385000 | K38: ='SA budget'!K38 -> 0 | L38: ='SA budget'!L38 -> 0 | M38: ='SA budget'!M38 -> 0 | ... P38: ='SA budget'!P38 -> 385000 | R38: =SUM(E38:P38) -> 845500 | AA38: =E38-'SA budget'!E38 -> 75500 | AB38: =F38-'SA budget'!F38 -> 0 | AC38: =G38-'SA budget'!G38 -> 0 | AD38: =H38-'SA budget'!H38 -> 0 | AE38: =I38-'SA budget'!I38 -> 0 | AF38: =J38-'SA budget'!J38 -> 0 | AG38: =K38-'SA budget'!K38 -> 0 | AH38: =L38-'SA budget'!L38 -> 0 | ... AL38: =P38-'SA budget'!P38 -> 0 | AN38: =SUM(AA38:AL38) -> 75500
B39: Forfait social jetons de présence (urssaf) | C39: k€ | E39: ='SA Actual'!E39 -> 0 | F39: ='SA budget'!F39 -> 0 | G39: ='SA budget'!G39 -> 0 | H39: ='SA budget'!H39 -> 0 | I39: ='SA budget'!I39 -> 0 | J39: ='SA budget'!J39 -> 0 | K39: ='SA budget'!K39 -> 90500 | L39: ='SA budget'!L39 -> 0 | M39: ='SA budget'!M39 -> 0 | ... P39: ='SA budget'!P39 -> 0 | R39: =SUM(E39:P39) -> 90500 | AA39: =E39-'SA budget'!E39 -> -77000 | AB39: =F39-'SA budget'!F39 -> 0 | AC39: =G39-'SA budget'!G39 -> 0 | AD39: =H39-'SA budget'!H39 -> 0 | AE39: =I39-'SA budget'!I39 -> 0 | AF39: =J39-'SA budget'!J39 -> 0 | AG39: =K39-'SA budget'!K39 -> 0 | AH39: =L39-'SA budget'!L39 -> 0 | ... AL39: =P39-'SA budget'!P39 -> 0 | AN39: =SUM(AA39:AL39) -> -77000
B40: Total jetons | C40: k€ | E40: =SUM(E38:E39) -> 75500 | F40: =SUM(F38:F39) -> 0 | G40: =SUM(G38:G39) -> 0 | H40: =SUM(H38:H39) -> 0 | I40: =SUM(I38:I39) -> 0 | J40: =SUM(J38:J39) -> 385000 | K40: =SUM(K38:K39) -> 90500 | L40: =SUM(L38:L39) -> 0 | ... P40: =SUM(P38:P39) -> 385000 | R40: =SUM(E40:P40) -> 936000 | AA40: =SUM(AA38:AA39) -> -1500 | AB40: =SUM(AB38:AB39) -> 0 | AC40: =SUM(AC38:AC39) -> 0 | AD40: =SUM(AD38:AD39) -> 0 | AE40: =SUM(AE38:AE39) -> 0 | AF40: =SUM(AF38:AF39) -> 0 | AG40: =SUM(AG38:AG39) -> 0 | AH40: =SUM(AH38:AH39) -> 0 | ... AL40: =SUM(AL38:AL39) -> 0 | AN40: =SUM(AA40:AL40) -> -1500
B42: AGA MdG - Part patronales | C42: k€ | E42: ='SA Actual'!E42 -> 0 | F42: ='SA budget'!F42 -> 274324.77 | G42: ='SA budget'!G42 -> 0 | H42: ='SA budget'!H42 -> 787709.15 | I42: ='SA budget'!I42 -> 0 | J42: ='SA budget'!J42 -> 0 | K42: ='SA budget'!K42 -> 787709.15 | L42: ='SA budget'!L42 -> 0 | M42: ='SA budget'!M42 -> 0 | ... P42: ='SA budget'!P42 -> 787709.15 | R42: =SUM(E42:P42) -> 3425161.4 | AA42: =E42-'SA budget'!E42 -> 0 | AB42: =F42-'SA budget'!F42 -> 0 | AC42: =G42-'SA budget'!G42 -> 0 | AD42: =H42-'SA budget'!H42 -> 0 | AE42: =I42-'SA budget'!I42 -> 0 | AF42: =J42-'SA budget'!J42 -> 0 | AG42: =K42-'SA budget'!K42 -> 0 | AH42: =L42-'SA budget'!L42 -> 0 | ... AL42: =P42-'SA budget'!P42 -> 0 | AN42: =SUM(AA42:AL42) -> 0
B43: AGA MdG - Part salariales | C43: k€ | E43: ='SA Actual'!E43 -> 0 | F43: ='SA budget'!F43 -> 274324.77 | G43: ='SA budget'!G43 -> 0 | H43: ='SA budget'!H43 -> 787709.15 | I43: ='SA budget'!I43 -> 0 | J43: ='SA budget'!J43 -> 0 | K43: ='SA budget'!K43 -> 787709.15 | L43: ='SA budget'!L43 -> 0 | M43: ='SA budget'!M43 -> 0 | ... P43: ='SA budget'!P43 -> 787709.15 | R43: =SUM(E43:P43) -> 3425161.4 | AA43: =E43-'SA budget'!E43 -> 0 | AB43: =F43-'SA budget'!F43 -> 0 | AC43: =G43-'SA budget'!G43 -> 0 | AD43: =H43-'SA budget'!H43 -> 0 | AE43: =I43-'SA budget'!I43 -> 0 | AF43: =J43-'SA budget'!J43 -> 0 | AG43: =K43-'SA budget'!K43 -> 0 | AH43: =L43-'SA budget'!L43 -> 0 | ... AL43: =P43-'SA budget'!P43 -> 0 | AN43: =SUM(AA43:AL43) -> 0
B44: AGA MdG -Remboursement MdG - Part salariales | C44: k€ | E44: ='SA Actual'!E44 -> -400704.4 | F44: ='SA budget'!F44 -> 0 | G44: ='SA budget'!G44 -> 0 | H44: ='SA budget'!H44 -> 0 | I44: ='SA budget'!I44 -> 0 | J44: ='SA budget'!J44 -> 0 | K44: ='SA budget'!K44 -> 0 | L44: ='SA budget'!L44 -> 0 | M44: ='SA budget'!M44 -> 0 | ... P44: ='SA budget'!P44 -> -3425161.4 | R44: =SUM(E44:P44) -> -3825865.8 | AA44: =E44-'SA budget'!E44 -> 0 | AB44: =F44-'SA budget'!F44 -> 0 | AC44: =G44-'SA budget'!G44 -> 0 | AD44: =H44-'SA budget'!H44 -> 0 | AE44: =I44-'SA budget'!I44 -> 0 | AF44: =J44-'SA budget'!J44 -> 0 | AG44: =K44-'SA budget'!K44 -> 0 | AH44: =L44-'SA budget'!L44 -> 0 | ... AL44: =P44-'SA budget'!P44 -> 0 | AN44: =SUM(AA44:AL44) -> 0
B45: AGA Abivax SA (French employee) | C45: k€ | E45: ='SA Actual'!E45 -> 353002 | F45: ='SA budget'!F45 -> 352350 | G45: ='SA budget'!G45 -> 0 | H45: ='SA budget'!H45 -> 8715600 | I45: ='SA budget'!I45 -> 210600 | J45: ='SA budget'!J45 -> 0 | K45: ='SA budget'!K45 -> 502200 | L45: ='SA budget'!L45 -> 0 | M45: ='SA budget'!M45 -> 252720 | ... P45: ='SA budget'!P45 -> 0 | R45: =SUM(E45:P45) -> 14383822 | AA45: =E45-'SA budget'!E45 -> 353002 | AB45: =F45-'SA budget'!F45 -> 0 | AC45: =G45-'SA budget'!G45 -> 0 | AD45: =H45-'SA budget'!H45 -> 0 | AE45: =I45-'SA budget'!I45 -> 0 | AF45: =J45-'SA budget'!J45 -> 0 | AG45: =K45-'SA budget'!K45 -> 0 | AH45: =L45-'SA budget'!L45 -> 0 | ... AL45: =P45-'SA budget'!P45 -> 0 | AN45: =SUM(AA45:AL45) -> 353002
B46: Total AGA | C46: k€ | E46: =SUM(E42:E45) -> -47702.4 | F46: =SUM(F42:F45) -> 900999.53 | G46: =SUM(G42:G45) -> 0 | H46: =SUM(H42:H45) -> 10291018 | I46: =SUM(I42:I45) -> 210600 | J46: =SUM(J42:J45) -> 0 | K46: =SUM(K42:K45) -> 2077618.3 | L46: =SUM(L42:L45) -> 0 | ... P46: =SUM(P42:P45) -> -1849743.1 | R46: =SUM(E46:P46) -> 17408279 | AA46: =SUM(AA42:AA45) -> 353002 | AB46: =SUM(AB42:AB45) -> 0 | AC46: =SUM(AC42:AC45) -> 0 | AD46: =SUM(AD42:AD45) -> 0 | AE46: =SUM(AE42:AE45) -> 0 | AF46: =SUM(AF42:AF45) -> 0 | AG46: =SUM(AG42:AG45) -> 0 | AH46: =SUM(AH42:AH45) -> 0 | ... AL46: =SUM(AL42:AL45) -> 0 | AN46: =SUM(AA46:AL46) -> 353002
B48: Total HR related | C48: k€ | E48: =E46+E40+E36 -> 657936.54 | F48: =F46+F40+F36 -> 2246788 | G48: =G46+G40+G36 -> 1545989.5 | H48: =H46+H40+H36 -> 11056930 | I48: =I46+I40+I36 -> 894036.23 | J48: =J46+J40+J36 -> 1345778.3 | K48: =K46+K40+K36 -> 3260023.5 | L48: =L46+L40+L36 -> 683436.23 | ... P48: =P46+P40+P36 -> -781306.84 | R48: =SUM(E48:P48) -> 28832707 | AA48: =AA46+AA40+AA36 -> 250906.58 | AB48: =AB46+AB40+AB36 -> 0 | AC48: =AC46+AC40+AC36 -> 0 | AD48: =AD46+AD40+AD36 -> 0 | AE48: =AE46+AE40+AE36 -> 0 | AF48: =AF46+AF40+AF36 -> 0 | AG48: =AG46+AG40+AG36 -> 0 | AH48: =AH46+AH40+AH36 -> 0 | ... AL48: =AL46+AL40+AL36 -> 0 | AN48: =SUM(AA48:AL48) -> 250906.58
B50: RTC | C50: k€ | E50: ='SA Actual'!E50 -> 0 | F50: ='SA budget'!F50 -> 0 | G50: ='SA budget'!G50 -> 0 | H50: ='SA budget'!H50 -> 0 | I50: ='SA budget'!I50 -> 0 | J50: ='SA budget'!J50 -> 0 | K50: ='SA budget'!K50 -> 0 | L50: ='SA budget'!L50 -> 0 | M50: ='SA budget'!M50 -> -5000000 | ... P50: ='SA budget'!P50 -> 0 | R50: =SUM(E50:P50) -> -5000000 | AA50: =E50-'SA budget'!E50 -> 0 | AB50: =F50-'SA budget'!F50 -> 0 | AC50: =G50-'SA budget'!G50 -> 0 | AD50: =H50-'SA budget'!H50 -> 0 | AE50: =I50-'SA budget'!I50 -> 0 | AF50: =J50-'SA budget'!J50 -> 0 | AG50: =K50-'SA budget'!K50 -> 0 | AH50: =L50-'SA budget'!L50 -> 0 | ... AL50: =P50-'SA budget'!P50 -> 0 | AN50: =SUM(AA50:AL50) -> 0
B51: IQVIA advances | C51: k€ | E51: ='SA Actual'!E51 -> 0 | F51: ='SA budget'!F51 -> 0 | G51: ='SA budget'!G51 -> 0 | H51: ='SA budget'!H51 -> 0 | I51: ='SA budget'!I51 -> 0 | J51: ='SA budget'!J51 -> 0 | K51: ='SA budget'!K51 -> 0 | L51: ='SA budget'!L51 -> 0 | M51: ='SA budget'!M51 -> 0 | ... P51: ='SA budget'!P51 -> -7739045.2 | AA51: =E51-'SA budget'!E51 -> 0 | AB51: =F51-'SA budget'!F51 -> 0 | AC51: =G51-'SA budget'!G51 -> 0 | AD51: =H51-'SA budget'!H51 -> 0 | AE51: =I51-'SA budget'!I51 -> 0 | AF51: =J51-'SA budget'!J51 -> 0 | AG51: =K51-'SA budget'!K51 -> 0 | AH51: =L51-'SA budget'!L51 -> 0 | ... AL51: =P51-'SA budget'!P51 -> 0 | AN51: =SUM(AA51:AL51) -> 0
B52: BSA/BCE cash in | C52: k€ | E52: ='SA Actual'!E52 -> -22758.4 | F52: ='SA budget'!F52 -> 0 | G52: ='SA budget'!G52 -> 0 | H52: ='SA budget'!H52 -> 0 | I52: ='SA budget'!I52 -> 0 | J52: ='SA budget'!J52 -> 0 | K52: ='SA budget'!K52 -> 0 | L52: ='SA budget'!L52 -> 0 | M52: ='SA budget'!M52 -> 0 | ... P52: ='SA budget'!P52 -> 0 | AA52: =E52-'SA budget'!E52 -> -22758.4 | AB52: =F52-'SA budget'!F52 -> 0 | AC52: =G52-'SA budget'!G52 -> 0 | AD52: =H52-'SA budget'!H52 -> 0 | AE52: =I52-'SA budget'!I52 -> 0 | AF52: =J52-'SA budget'!J52 -> 0 | AG52: =K52-'SA budget'!K52 -> 0 | AH52: =L52-'SA budget'!L52 -> 0 | ... AL52: =P52-'SA budget'!P52 -> 0 | AN52: =SUM(AA52:AL52) -> -22758.4
B53: Interets in | C53: k€ | E53: ='SA Actual'!E53 -> -38317.47 | F53: ='SA budget'!F53 -> -306069.94 | G53: ='SA budget'!G53 -> -286733.13 | H53: ='SA budget'!H53 -> -258046.4 | I53: ='SA budget'!I53 -> -217456.09 | J53: ='SA budget'!J53 -> -191222.05 | K53: ='SA budget'!K53 -> -173007.15 | L53: ='SA budget'!L53 -> -146865.35 | M53: ='SA budget'!M53 -> -122059.84 | ... P53: ='SA budget'!P53 -> -76608.913 | R53: =SUM(E53:P53) -> -2034598.2 | AA53: =E53-'SA budget'!E53 -> 290251.15 | AB53: =F53-'SA budget'!F53 -> 0 | AC53: =G53-'SA budget'!G53 -> 0 | AD53: =H53-'SA budget'!H53 -> 0 | AE53: =I53-'SA budget'!I53 -> 0 | AF53: =J53-'SA budget'!J53 -> 0 | AG53: =K53-'SA budget'!K53 -> 0 | AH53: =L53-'SA budget'!L53 -> 0 | ... AL53: =P53-'SA budget'!P53 -> 0 | AN53: =SUM(AA53:AL53) -> 290251.15
B54: Codéis interest in | C54: k€ | E54: ='SA Actual'!E54 -> -111686 | F54: ='SA budget'!F54 -> 0 | G54: ='SA budget'!G54 -> 0 | H54: ='SA budget'!H54 -> 0 | I54: ='SA budget'!I54 -> 0 | J54: ='SA budget'!J54 -> 0 | K54: ='SA budget'!K54 -> 0 | L54: ='SA budget'!L54 -> 0 | M54: ='SA budget'!M54 -> 0 | ... P54: ='SA budget'!P54 -> 0 | AA54: =E54-'SA budget'!E54 -> -111686 | AB54: =F54-'SA budget'!F54 -> 0 | AC54: =G54-'SA budget'!G54 -> 0 | AD54: =H54-'SA budget'!H54 -> 0 | AE54: =I54-'SA budget'!I54 -> 0 | AF54: =J54-'SA budget'!J54 -> 0 | AG54: =K54-'SA budget'!K54 -> 0 | AH54: =L54-'SA budget'!L54 -> 0 | ... AL54: =P54-'SA budget'!P54 -> 0 | AN54: =SUM(AA54:AL54) -> -111686
B55: monthly value variation FCP (Ellipsis) | C55: k€ | E55: ='SA Actual'!E55 -> -200245.61 | F55: ='SA budget'!F55 -> 0 | G55: ='SA budget'!G55 -> 0 | H55: ='SA budget'!H55 -> 0 | I55: ='SA budget'!I55 -> 0 | J55: ='SA budget'!J55 -> 0 | K55: ='SA budget'!K55 -> 0 | L55: ='SA budget'!L55 -> 0 | M55: ='SA budget'!M55 -> 0 | ... P55: ='SA budget'!P55 -> 0 | AA55: =E55-'SA budget'!E55 -> -200245.61 | AB55: =F55-'SA budget'!F55 -> 0 | AC55: =G55-'SA budget'!G55 -> 0 | AD55: =H55-'SA budget'!H55 -> 0 | AE55: =I55-'SA budget'!I55 -> 0 | AF55: =J55-'SA budget'!J55 -> 0 | AG55: =K55-'SA budget'!K55 -> 0 | AH55: =L55-'SA budget'!L55 -> 0 | ... AL55: =P55-'SA budget'!P55 -> 0 | AN55: =SUM(AA55:AL55) -> -200245.61
B59: Paid VAT | C59: k€ | E59: ='SA Actual'!E59 -> 3099119.4 | F59: ='SA budget'!F59 -> 1603314.9 | G59: ='SA budget'!G59 -> 1760065 | H59: ='SA budget'!H59 -> 3223438.3 | I59: ='SA budget'!I59 -> 3503210.7 | J59: ='SA budget'!J59 -> 1654721.7 | K59: ='SA budget'!K59 -> 2419668.8 | L59: ='SA budget'!L59 -> 3488289.5 | M59: ='SA budget'!M59 -> 1386433.9 | ... P59: ='SA budget'!P59 -> 1228941.6 | R59: =SUM(E59:P59) -> 27419868 | AA59: =E59-'SA budget'!E59 -> 77612.459 | AB59: =F59-'SA budget'!F59 -> 0 | AC59: =G59-'SA budget'!G59 -> 0 | AD59: =H59-'SA budget'!H59 -> 0 | AE59: =I59-'SA budget'!I59 -> 0 | AF59: =J59-'SA budget'!J59 -> 0 | AG59: =K59-'SA budget'!K59 -> 0 | AH59: =L59-'SA budget'!L59 -> 0 | ... AL59: =P59-'SA budget'!P59 -> 0 | AN59: =SUM(AA59:AL59) -> 77612.459
B60: received VAT | C60: k€ | E60: ='SA Actual'!E60 -> -2082692 | F60: ='SA budget'!F60 -> 0 | G60: ='SA budget'!G60 -> -3021507 | H60: ='SA budget'!H60 -> -1603314.9 | I60: ='SA budget'!I60 -> -1760065 | J60: ='SA budget'!J60 -> -3223438.3 | K60: ='SA budget'!K60 -> -3503210.7 | L60: ='SA budget'!L60 -> -1654721.7 | M60: ='SA budget'!M60 -> -2419668.8 | ... P60: ='SA budget'!P60 -> -1177092.8 | R60: =SUM(E60:P60) -> -25320434 | AA60: =E60-'SA budget'!E60 -> 0 | AB60: =F60-'SA budget'!F60 -> 0 | AC60: =G60-'SA budget'!G60 -> 0 | AD60: =H60-'SA budget'!H60 -> 0 | AE60: =I60-'SA budget'!I60 -> 0 | AF60: =J60-'SA budget'!J60 -> 0 | AG60: =K60-'SA budget'!K60 -> 0 | AH60: =L60-'SA budget'!L60 -> 0 | ... AL60: =P60-'SA budget'!P60 -> 0 | AN60: =SUM(AA60:AL60) -> 0
B62: Total | C62: k€ | E62: =+E48+E25+E20+SUM(E50:E55)+SUM(E59:E60)+E27 -> 16814728 | F62: =+F48+F25+F20+SUM(F50:F55)+SUM(F59:F60)+F27 -> 11560607 | G62: =+G48+G25+G20+SUM(G50:G55)+SUM(G59:G60)+G27 -> 8798139.1 | H62: =+H48+H25+H20+SUM(H50:H55)+SUM(H59:H60)+H27 -> 28736199 | I62: =+I48+I25+I20+SUM(I50:I55)+SUM(I59:I60)+I27 -> 20135779 | J62: =+J48+J25+J20+SUM(J50:J55)+SUM(J59:J60)+J27 -> 8059448.2 | K62: =+K48+K25+K20+SUM(K50:K55)+SUM(K59:K60)+K27 -> 14301819 | L62: =+L48+L25+L20+SUM(L50:L55)+SUM(L59:L60)+L27 -> 20011586 | ... P62: =+P48+P25+P20+SUM(P50:P55)+SUM(P59:P60)+P27 -> -2200403.9 | R62: =SUM(E62:P62) -> 1.5474092e+08 | AA62: =+AA48+AA25+AA20+SUM(AA50:AA55)+SUM(AA59:AA60)+AA27 -> 689916.87 | AB62: =+AB48+AB25+AB20+SUM(AB50:AB55)+SUM(AB59:AB60)+AB27 -> 0 | AC62: =+AC48+AC25+AC20+SUM(AC50:AC55)+SUM(AC59:AC60)+AC27 -> 0 | AD62: =+AD48+AD25+AD20+SUM(AD50:AD55)+SUM(AD59:AD60)+AD27 -> 0 | AE62: =+AE48+AE25+AE20+SUM(AE50:AE55)+SUM(AE59:AE60)+AE27 -> 0 | AF62: =+AF48+AF25+AF20+SUM(AF50:AF55)+SUM(AF59:AF60)+AF27 -> 0 | AG62: =+AG48+AG25+AG20+SUM(AG50:AG55)+SUM(AG59:AG60)+AG27 -> 0 | AH62: =+AH48+AH25+AH20+SUM(AH50:AH55)+SUM(AH59:AH60)+AH27 -> 0 | ... AL62: =+AL48+AL25+AL20+SUM(AL50:AL55)+SUM(AL59:AL60)+AL27 -> 0 | AN62: =SUM(AA62:AL62) -> 689916.87
R63: =R62/12 -> 12895077 | AN63: =AN62/12 -> 57493.072
B64: Balance SA-EUR - begining of month | C64: k€ | E64: ='SA Actual'!E64 -> 2.0489846e+08 | F64: =E65 -> 1.8808373e+08 | G64: =F65 -> 1.7652312e+08 | H64: =G65 -> 1.6772498e+08 | I64: =H65 -> 1.3898878e+08 | J64: =I65 -> 1.18853e+08 | K64: =J65 -> 1.1079356e+08 | L64: =K65 -> 96491737 | M64: =L65 -> 76480150 | ... P64: =O65 -> 47957131 | AA64: =E64-'SA budget'!E64 -> 0 | AB64: =F64-'SA budget'!F64 -> -689916.87 | AC64: =G64-'SA budget'!G64 -> -689916.87 | AD64: =H64-'SA budget'!H64 -> -689916.87 | AE64: =I64-'SA budget'!I64 -> -689916.87 | AF64: =J64-'SA budget'!J64 -> -689916.87 | AG64: =K64-'SA budget'!K64 -> -689916.87 | AH64: =L64-'SA budget'!L64 -> -689916.87 | ... AL64: =P64-'SA budget'!P64 -> -689916.87
B65: Balance SA-EUR - end of month | C65: k€ | E65: =E64-E62 -> 1.8808373e+08 | F65: =F64-F62 -> 1.7652312e+08 | G65: =G64-G62 -> 1.6772498e+08 | H65: =H64-H62 -> 1.3898878e+08 | I65: =I64-I62 -> 1.18853e+08 | J65: =J64-J62 -> 1.1079356e+08 | K65: =K64-K62 -> 96491737 | L65: =L64-L62 -> 76480150 | ... P65: =P64-P62 -> 50157535 | AA65: =E65-'SA budget'!E65 -> -689916.87 | AB65: =F65-'SA budget'!F65 -> -689916.87 | AC65: =G65-'SA budget'!G65 -> -689916.87 | AD65: =H65-'SA budget'!H65 -> -689916.87 | AE65: =I65-'SA budget'!I65 -> -689916.87 | AF65: =J65-'SA budget'!J65 -> -689916.87 | AG65: =K65-'SA budget'!K65 -> -689916.87 | AH65: =L65-'SA budget'!L65 -> -689916.87 | ... AL65: =P65-'SA budget'!P65 -> -689916.87
B70: Abivax SA USD | E70: 46023 | F70: =EDATE(E70,1) -> 46054 | G70: =EDATE(F70,1) -> 46082 | H70: =EDATE(G70,1) -> 46113 | I70: =EDATE(H70,1) -> 46143 | J70: =EDATE(I70,1) -> 46174 | K70: =EDATE(J70,1) -> 46204 | L70: =EDATE(K70,1) -> 46235 | M70: =EDATE(L70,1) -> 46266 | ... P70: =EDATE(O70,1) -> 46357 | R70: 2025 | AA70: 46023 | AB70: =EDATE(AA70,1) -> 46054 | AC70: =EDATE(AB70,1) -> 46082 | AD70: =EDATE(AC70,1) -> 46113 | AE70: =EDATE(AD70,1) -> 46143 | AF70: =EDATE(AE70,1) -> 46174 | AG70: =EDATE(AF70,1) -> 46204 | AH70: =EDATE(AG70,1) -> 46235 | AI70: =EDATE(AH70,1) -> 46266 | ... AL70: =EDATE(AK70,1) -> 46357 | AN70: 2025
B72: Other Suppliers (HT) | C72: k$ | E72: ='SA Actual'!E72 -> 1654185 | F72: ='SA budget'!F72 -> 2652656.2 | G72: ='SA budget'!G72 -> 2652656.2 | H72: ='SA budget'!H72 -> 2652656.2 | I72: ='SA budget'!I72 -> 2692903.8 | J72: ='SA budget'!J72 -> 2692903.8 | K72: ='SA budget'!K72 -> 2692903.8 | L72: ='SA budget'!L72 -> 5399665.4 | M72: ='SA budget'!M72 -> 5399665.4 | ... P72: ='SA budget'!P72 -> 3292479.8 | R72: =SUM(E72:P72) -> 40474821 | S72: usd | AA72: =E72-'SA budget'!E72 -> -998471.26 | AB72: =F72-'SA budget'!F72 -> 0 | AC72: =G72-'SA budget'!G72 -> 0 | AD72: =H72-'SA budget'!H72 -> 0 | AE72: =I72-'SA budget'!I72 -> 0 | AF72: =J72-'SA budget'!J72 -> 0 | AG72: =K72-'SA budget'!K72 -> 0 | AH72: =L72-'SA budget'!L72 -> 0 | ... AL72: =P72-'SA budget'!P72 -> 0 | AN72: =SUM(AA72:AL72) -> -998471.26
B73: Contractor (HT) | C73: k$ | E73: ='SA Actual'!E73 -> 462906.43 | F73: ='SA budget'!F73 -> 841253.33 | G73: ='SA budget'!G73 -> 841253.33 | H73: ='SA budget'!H73 -> 841253.33 | I73: ='SA budget'!I73 -> 861520 | J73: ='SA budget'!J73 -> 861520 | K73: ='SA budget'!K73 -> 861520 | L73: ='SA budget'!L73 -> 852720 | M73: ='SA budget'!M73 -> 852720 | ... P73: ='SA budget'!P73 -> 849973.33 | R73: =SUM(E73:P73) -> 9829333.1 | AA73: =E73-'SA budget'!E73 -> -378346.9 | AB73: =F73-'SA budget'!F73 -> 0 | AC73: =G73-'SA budget'!G73 -> 0 | AD73: =H73-'SA budget'!H73 -> 0 | AE73: =I73-'SA budget'!I73 -> 0 | AF73: =J73-'SA budget'!J73 -> 0 | AG73: =K73-'SA budget'!K73 -> 0 | AH73: =L73-'SA budget'!L73 -> 0 | ... AL73: =P73-'SA budget'!P73 -> 0 | AN73: =SUM(AA73:AL73) -> -378346.9
B74: Bank fees | C74: k$ | E74: ='SA Actual'!E74 -> 407.48 | F74: ='SA budget'!F74 -> 0 | G74: ='SA budget'!G74 -> 0 | H74: ='SA budget'!H74 -> 0 | I74: ='SA budget'!I74 -> 0 | J74: ='SA budget'!J74 -> 0 | K74: ='SA budget'!K74 -> 0 | L74: ='SA budget'!L74 -> 0 | M74: ='SA budget'!M74 -> 0 | ... P74: ='SA budget'!P74 -> 0 | AA74: =E74-'SA budget'!E74 -> 407.48 | AB74: =F74-'SA budget'!F74 -> 0 | AC74: =G74-'SA budget'!G74 -> 0 | AD74: =H74-'SA budget'!H74 -> 0 | AE74: =I74-'SA budget'!I74 -> 0 | AF74: =J74-'SA budget'!J74 -> 0 | AG74: =K74-'SA budget'!K74 -> 0 | AH74: =L74-'SA budget'!L74 -> 0 | ... AL74: =P74-'SA budget'!P74 -> 0 | AN74: =SUM(AA74:AL74) -> 407.48
B75: Citi cash in | C75: k$ | E75: ='SA Actual'!E75 -> 0 | F75: ='SA budget'!F75 -> 0 | G75: ='SA budget'!G75 -> 0 | H75: ='SA budget'!H75 -> 0 | I75: ='SA budget'!I75 -> 0 | J75: ='SA budget'!J75 -> 0 | K75: ='SA budget'!K75 -> 0 | L75: ='SA budget'!L75 -> 0 | M75: ='SA budget'!M75 -> 0 | ... P75: ='SA budget'!P75 -> 0 | AA75: =E75-'SA budget'!E75 -> 0 | AB75: =F75-'SA budget'!F75 -> 0 | AC75: =G75-'SA budget'!G75 -> 0 | AD75: =H75-'SA budget'!H75 -> 0 | AE75: =I75-'SA budget'!I75 -> 0 | AF75: =J75-'SA budget'!J75 -> 0 | AG75: =K75-'SA budget'!K75 -> 0 | AH75: =L75-'SA budget'!L75 -> 0 | ... AL75: =P75-'SA budget'!P75 -> 0 | AN75: =SUM(AA75:AL75) -> 0
B76: interests cash in | C76: k$ | E76: ='SA Actual'!E76 -> -4307.63 | F76: ='SA budget'!F76 -> -448629.22 | G76: ='SA budget'!G76 -> -441016.02 | H76: ='SA budget'!H76 -> -433383.79 | I76: ='SA budget'!I76 -> -425656.83 | J76: ='SA budget'!J76 -> -417834.91 | K76: ='SA budget'!K76 -> -409993.44 | L76: ='SA budget'!L76 -> -398759.91 | M76: ='SA budget'!M76 -> -384125.85 | ... P76: ='SA budget'!P76 -> -347922.62 | R76: =SUM(E76:P76) -> -4438470.7 | AA76: =E76-'SA budget'!E76 -> 451915.81 | AB76: =F76-'SA budget'!F76 -> 0 | AC76: =G76-'SA budget'!G76 -> 0 | AD76: =H76-'SA budget'!H76 -> 0 | AE76: =I76-'SA budget'!I76 -> 0 | AF76: =J76-'SA budget'!J76 -> 0 | AG76: =K76-'SA budget'!K76 -> 0 | AH76: =L76-'SA budget'!L76 -> 0 | ... AL76: =P76-'SA budget'!P76 -> 0 | AN76: =SUM(AA76:AL76) -> 451915.81
B77: Codéis interest in | C77: k$ | E77: ='SA Actual'!E77 -> -490769.4 | F77: ='SA budget'!F77 -> 0 | G77: ='SA budget'!G77 -> 0 | H77: ='SA budget'!H77 -> 0 | I77: ='SA budget'!I77 -> 0 | J77: ='SA budget'!J77 -> 0 | K77: ='SA budget'!K77 -> 0 | L77: ='SA budget'!L77 -> 0 | M77: ='SA budget'!M77 -> 0 | ... P77: ='SA budget'!P77 -> 0 | AA77: =E77-'SA budget'!E77 -> -490769.4 | AB77: =F77-'SA budget'!F77 -> 0 | AC77: =G77-'SA budget'!G77 -> 0 | AD77: =H77-'SA budget'!H77 -> 0 | AE77: =I77-'SA budget'!I77 -> 0 | AF77: =J77-'SA budget'!J77 -> 0 | AG77: =K77-'SA budget'!K77 -> 0 | AH77: =L77-'SA budget'!L77 -> 0 | ... AL77: =P77-'SA budget'!P77 -> 0 | AN77: =SUM(AA77:AL77) -> -490769.4
B78: Internal wire | C78: k$ | E78: ='SA Actual'!E78 -> 0 | F78: ='SA budget'!F78 -> 0 | G78: ='SA budget'!G78 -> 0 | H78: ='SA budget'!H78 -> 0 | I78: ='SA budget'!I78 -> 0 | J78: ='SA budget'!J78 -> 0 | K78: ='SA budget'!K78 -> 0 | L78: ='SA budget'!L78 -> 0 | M78: ='SA budget'!M78 -> 0 | ... P78: ='SA budget'!P78 -> 0 | AA78: =E78-'SA budget'!E78 -> 0 | AB78: =F78-'SA budget'!F78 -> 0 | AC78: =G78-'SA budget'!G78 -> 0 | AD78: =H78-'SA budget'!H78 -> 0 | AE78: =I78-'SA budget'!I78 -> 0 | AF78: =J78-'SA budget'!J78 -> 0 | AG78: =K78-'SA budget'!K78 -> 0 | AH78: =L78-'SA budget'!L78 -> 0 | ... AL78: =P78-'SA budget'!P78 -> 0 | AN78: =SUM(AA78:AL78) -> 0
B79: Capital Raised | C79: k$ | E79: ='SA Actual'!E79 -> 0 | F79: ='SA budget'!F79 -> 0 | G79: ='SA budget'!G79 -> 0 | H79: ='SA budget'!H79 -> 0 | I79: ='SA budget'!I79 -> 0 | J79: ='SA budget'!J79 -> 0 | K79: ='SA budget'!K79 -> 0 | L79: ='SA budget'!L79 -> 0 | M79: ='SA budget'!M79 -> 0 | ... P79: ='SA budget'!P79 -> 0 | AA79: =E79-'SA budget'!E79 -> 0 | AB79: =F79-'SA budget'!F79 -> 0 | AC79: =G79-'SA budget'!G79 -> 0 | AD79: =H79-'SA budget'!H79 -> 0 | AE79: =I79-'SA budget'!I79 -> 0 | AF79: =J79-'SA budget'!J79 -> 0 | AG79: =K79-'SA budget'!K79 -> 0 | AH79: =L79-'SA budget'!L79 -> 0 | ... AL79: =P79-'SA budget'!P79 -> 0 | AN79: =SUM(AA79:AL79) -> 0
B80: Change USD -> EUR | C80: k$ | E80: ='SA Actual'!E80 -> 0 | F80: ='SA budget'!F80 -> 0 | G80: ='SA budget'!G80 -> 0 | H80: ='SA budget'!H80 -> 0 | I80: ='SA budget'!I80 -> 0 | J80: ='SA budget'!J80 -> 0 | K80: ='SA budget'!K80 -> 0 | L80: ='SA budget'!L80 -> 0 | M80: ='SA budget'!M80 -> 0 | ... P80: ='SA budget'!P80 -> 0 | AA80: =E80-'SA budget'!E80 -> 0 | AB80: =F80-'SA budget'!F80 -> 0 | AC80: =G80-'SA budget'!G80 -> 0 | AD80: =H80-'SA budget'!H80 -> 0 | AE80: =I80-'SA budget'!I80 -> 0 | AF80: =J80-'SA budget'!J80 -> 0 | AG80: =K80-'SA budget'!K80 -> 0 | AH80: =L80-'SA budget'!L80 -> 0 | ... AL80: =P80-'SA budget'!P80 -> 0 | AN80: =SUM(AA80:AL80) -> 0
E81: =SUM(E72:E76) -> 2113191.2 | F81: =SUM(F72:F76) -> 3045280.3 | G81: =SUM(G72:G76) -> 3052893.5 | H81: =SUM(H72:H76) -> 3060525.8 | I81: =SUM(I72:I76) -> 3128767 | J81: =SUM(J72:J76) -> 3136588.9 | K81: =SUM(K72:K76) -> 3144430.4 | L81: =SUM(L72:L76) -> 5853625.5 | ... P81: =SUM(P72:P76) -> 3794530.6 | R81: =SUM(R72:R72) -> 40474821 | S81: eur | AA81: =SUM(AA72:AA76) -> -924494.87 | AB81: =SUM(AB72:AB76) -> 0 | AC81: =SUM(AC72:AC76) -> 0 | AD81: =SUM(AD72:AD76) -> 0 | AE81: =SUM(AE72:AE76) -> 0 | AF81: =SUM(AF72:AF76) -> 0 | AG81: =SUM(AG72:AG76) -> 0 | AH81: =SUM(AH72:AH76) -> 0 | ... AL81: =SUM(AL72:AL76) -> 0 | AN81: =SUM(AN72:AN72) -> -998471.26
B83: Abivax SA USD- Balance
B85: Balance SA-USD - begining of month | C85: k$ | E85: ='SA Actual'!E85 -> 1.8423633e+08 | F85: =E86 -> 1.8212314e+08 | G85: =F86 -> 1.7907786e+08 | H85: =G86 -> 1.7602497e+08 | I85: =H86 -> 1.7296444e+08 | J85: =I86 -> 1.6983567e+08 | K85: =J86 -> 1.6669908e+08 | L85: =K86 -> 1.6355465e+08 | M85: =L86 -> 1.5770103e+08 | ... P85: =O86 -> 1.4216477e+08 | AA85: =E85-'SA budget'!E85 -> 0 | AB85: =F85-'SA budget'!F85 -> 924494.87 | AC85: =G85-'SA budget'!G85 -> 924494.87 | AD85: =H85-'SA budget'!H85 -> 924494.87 | AE85: =I85-'SA budget'!I85 -> 924494.87 | AF85: =J85-'SA budget'!J85 -> 924494.87 | AG85: =K85-'SA budget'!K85 -> 924494.87 | AH85: =L85-'SA budget'!L85 -> 924494.87 | ... AL85: =P85-'SA budget'!P85 -> 924494.87
B86: Balance SA-USD - end of month | C86: k$ | E86: =E85-E81 -> 1.8212314e+08 | F86: =F85-F81 -> 1.7907786e+08 | G86: =G85-G81 -> 1.7602497e+08 | H86: =H85-H81 -> 1.7296444e+08 | I86: =I85-I81 -> 1.6983567e+08 | J86: =J85-J81 -> 1.6669908e+08 | K86: =K85-K81 -> 1.6355465e+08 | L86: =L85-L81 -> 1.5770103e+08 | ... P86: =P85-P81 -> 1.3837024e+08 | R86: =P86+'LLC Reforecast'!P38 -> 2.8575276e+08 | AA86: =E86-'SA budget'!E86 -> 924494.87 | AB86: =F86-'SA budget'!F86 -> 924494.87 | AC86: =G86-'SA budget'!G86 -> 924494.87 | AD86: =H86-'SA budget'!H86 -> 924494.87 | AE86: =I86-'SA budget'!I86 -> 924494.87 | AF86: =J86-'SA budget'!J86 -> 924494.87 | AG86: =K86-'SA budget'!K86 -> 924494.87 | AH86: =L86-'SA budget'!L86 -> 924494.87 | ... AL86: =P86-'SA budget'!P86 -> 924494.87 | AN86: =AL86+'LLC Reforecast'!AL38 -> -8540082.6
B88: EUR-USD m-1 | C88: k$ | E88: 1.175 | F88: 1.16 | G88: 1.16 | H88: 1.16 | I88: 1.16 | J88: 1.16 | K88: 1.16 | L88: 1.16 | M88: 1.16 | N88: 1.16 | O88: 1.16 | P88: 1.16 | AA88: =E88-'SA budget'!E88 -> 0 | AB88: =F88-'SA budget'!F88 -> 0 | AC88: =G88-'SA budget'!G88 -> 0 | AD88: =H88-'SA budget'!H88 -> 0 | AE88: =I88-'SA budget'!I88 -> 0 | AF88: =J88-'SA budget'!J88 -> 0 | AG88: =K88-'SA budget'!K88 -> 0 | AH88: =L88-'SA budget'!L88 -> 0 | ... AL88: =P88-'SA budget'!P88 -> 0
B89: EUR-USD m | C89: k$ | E89: 1.1919 | F89: 1.16 | G89: 1.16 | H89: 1.16 | I89: 1.16 | J89: 1.16 | K89: 1.16 | L89: 1.16 | M89: 1.16 | N89: 1.16 | O89: 1.16 | P89: 1.16 | AA89: =E89-'SA budget'!E89 -> 0.0319 | AB89: =F89-'SA budget'!F89 -> 0 | AC89: =G89-'SA budget'!G89 -> 0 | AD89: =H89-'SA budget'!H89 -> 0 | AE89: =I89-'SA budget'!I89 -> 0 | AF89: =J89-'SA budget'!J89 -> 0 | AG89: =K89-'SA budget'!K89 -> 0 | AH89: =L89-'SA budget'!L89 -> 0 | ... AL89: =P89-'SA budget'!P89 -> 0
B91: Balance SA-USD - begining of month | C91: k$ | E91: =E85/E88 -> 1.5679688e+08 | F91: =F85/F88 -> 1.5700271e+08 | G91: =G85/G88 -> 1.5437746e+08 | H91: =H85/H88 -> 1.5174566e+08 | I91: =I85/I88 -> 1.4910728e+08 | J91: =J85/J88 -> 1.4641006e+08 | K91: =K85/K88 -> 1.4370611e+08 | L91: =L85/L88 -> 1.4099539e+08 | ... P91: =P85/P88 -> 1.2255584e+08 | AA91: =E91-'SA budget'!E91 -> 0 | AB91: =F91-'SA budget'!F91 -> 796978.34 | AC91: =G91-'SA budget'!G91 -> 796978.34 | AD91: =H91-'SA budget'!H91 -> 796978.34 | AE91: =I91-'SA budget'!I91 -> 796978.34 | AF91: =J91-'SA budget'!J91 -> 796978.34 | AG91: =K91-'SA budget'!K91 -> 796978.34 | AH91: =L91-'SA budget'!L91 -> 796978.34 | ... AL91: =P91-'SA budget'!P91 -> 796978.34
B92: Balance SA-USD - end of month | C92: k$ | E92: =E86/E89 -> 1.5280069e+08 | F92: =F86/F89 -> 1.5437746e+08 | G92: =G86/G89 -> 1.5174566e+08 | H92: =H86/H89 -> 1.4910728e+08 | I92: =I86/I89 -> 1.4641006e+08 | J92: =J86/J89 -> 1.4370611e+08 | K92: =K86/K89 -> 1.4099539e+08 | L92: =L86/L89 -> 1.3594916e+08 | ... P92: =P86/P89 -> 1.1928469e+08 | AA92: =E92-'SA budget'!E92 -> -3405040.6 | AB92: =F92-'SA budget'!F92 -> 796978.34 | AC92: =G92-'SA budget'!G92 -> 796978.34 | AD92: =H92-'SA budget'!H92 -> 796978.34 | AE92: =I92-'SA budget'!I92 -> 796978.34 | AF92: =J92-'SA budget'!J92 -> 796978.34 | AG92: =K92-'SA budget'!K92 -> 796978.34 | AH92: =L92-'SA budget'!L92 -> 796978.34 | ... AL92: =P92-'SA budget'!P92 -> 796978.34
B99: Abivax SA EUR + USD
B101: Balance SA-USD - begining of month | C101: k€ | E101: =E91+E64 -> 3.6169533e+08 | F101: =F91+F64 -> 3.4508643e+08 | G101: =G91+G64 -> 3.3090059e+08 | H101: =H91+H64 -> 3.1947064e+08 | I101: =I91+I64 -> 2.8809606e+08 | J101: =J91+J64 -> 2.6526307e+08 | K101: =K91+K64 -> 2.5449966e+08 | L101: =L91+L64 -> 2.3748713e+08 | ... P101: =P91+P64 -> 1.7051297e+08 | AA101: =E101-'SA budget'!E101 -> 0 | AB101: =F101-'SA budget'!F101 -> 107061.47 | AC101: =G101-'SA budget'!G101 -> 107061.47 | AD101: =H101-'SA budget'!H101 -> 107061.47 | AE101: =I101-'SA budget'!I101 -> 107061.47 | AF101: =J101-'SA budget'!J101 -> 107061.47 | AG101: =K101-'SA budget'!K101 -> 107061.47 | AH101: =L101-'SA budget'!L101 -> 107061.47 | ... AL101: =P101-'SA budget'!P101 -> 107061.47
B102: Balance SA-USD - end of month | C102: k€ | E102: =E92+E65 -> 3.4088442e+08 | F102: =F92+F65 -> 3.3090059e+08 | G102: =G92+G65 -> 3.1947064e+08 | H102: =H92+H65 -> 2.8809606e+08 | I102: =I92+I65 -> 2.6526307e+08 | J102: =J92+J65 -> 2.5449966e+08 | K102: =K92+K65 -> 2.3748713e+08 | L102: =L92+L65 -> 2.1242931e+08 | ... P102: =P92+P65 -> 1.6944222e+08 | AA102: =E102-'SA budget'!E102 -> -4094957.4 | AB102: =F102-'SA budget'!F102 -> 107061.47 | AC102: =G102-'SA budget'!G102 -> 107061.47 | AD102: =H102-'SA budget'!H102 -> 107061.47 | AE102: =I102-'SA budget'!I102 -> 107061.47 | AF102: =J102-'SA budget'!J102 -> 107061.47 | AG102: =K102-'SA budget'!K102 -> 107061.47 | AH102: =L102-'SA budget'!L102 -> 107061.47 | ... AL102: =P102-'SA budget'!P102 -> 107061.47

Sheet LLC Reforecast
E3: Cash Forecast - V budget | AA3: Cash Forecast - V budget
B6: Abivax LLC USD
E7: 46023 | F7: =EDATE(E7,1) -> 46054 | G7: =EDATE(F7,1) -> 46082 | H7: =EDATE(G7,1) -> 46113 | I7: =EDATE(H7,1) -> 46143 | J7: =EDATE(I7,1) -> 46174 | K7: =EDATE(J7,1) -> 46204 | L7: =EDATE(K7,1) -> 46235 | M7: =EDATE(L7,1) -> 46266 | ... P7: =EDATE(O7,1) -> 46357 | R7: 2026 | AA7: 46023 | AB7: =EDATE(AA7,1) -> 46054 | AC7: =EDATE(AB7,1) -> 46082 | AD7: =EDATE(AC7,1) -> 46113 | AE7: =EDATE(AD7,1) -> 46143 | AF7: =EDATE(AE7,1) -> 46174 | AG7: =EDATE(AF7,1) -> 46204 | AH7: =EDATE(AG7,1) -> 46235 | AI7: =EDATE(AH7,1) -> 46266 | ... AL7: =EDATE(AK7,1) -> 46357 | AN7: 2026
B9: Amount are VAT excluded
B10: Other Suppliers € (HT) | C10: k$ | E10: ='LLC actual'!E10 -> 615407.3 | F10: ='LLC Budget'!F10 -> 945918.42 | G10: ='LLC Budget'!G10 -> 945918.42 | H10: ='LLC Budget'!H10 -> 945918.42 | I10: ='LLC Budget'!I10 -> 870303.42 | J10: ='LLC Budget'!J10 -> 870303.42 | K10: ='LLC Budget'!K10 -> 870303.42 | L10: ='LLC Budget'!L10 -> 2552403.4 | M10: ='LLC Budget'!M10 -> 2552403.4 | ... P10: ='LLC Budget'!P10 -> 2666531.4 | R10: =SUM(E10:P10) -> 19054346 | AA10: =E10-'LLC Budget'!E10 -> -330511.12 | AB10: =F10-'LLC Budget'!F10 -> 0 | AC10: =G10-'LLC Budget'!G10 -> 0 | AD10: =H10-'LLC Budget'!H10 -> 0 | AE10: =I10-'LLC Budget'!I10 -> 0 | AF10: =J10-'LLC Budget'!J10 -> 0 | AG10: =K10-'LLC Budget'!K10 -> 0 | AH10: =L10-'LLC Budget'!L10 -> 0 | ... AL10: =P10-'LLC Budget'!P10 -> 0 | AN10: =SUM(AA10:AL10) -> -330511.12
B11: Contractor (HT) | C11: k$ | E11: ='LLC actual'!E11 -> 0 | F11: ='LLC Budget'!F11 -> 112000 | G11: ='LLC Budget'!G11 -> 112000 | H11: ='LLC Budget'!H11 -> 112000 | I11: ='LLC Budget'!I11 -> 112000 | J11: ='LLC Budget'!J11 -> 112000 | K11: ='LLC Budget'!K11 -> 112000 | L11: ='LLC Budget'!L11 -> 112000 | M11: ='LLC Budget'!M11 -> 112000 | ... P11: ='LLC Budget'!P11 -> 112000 | R11: =SUM(E11:P11) -> 1232000 | AA11: =E11-'LLC Budget'!E11 -> -112000 | AB11: =F11-'LLC Budget'!F11 -> 0 | AC11: =G11-'LLC Budget'!G11 -> 0 | AD11: =H11-'LLC Budget'!H11 -> 0 | AE11: =I11-'LLC Budget'!I11 -> 0 | AF11: =J11-'LLC Budget'!J11 -> 0 | AG11: =K11-'LLC Budget'!K11 -> 0 | AH11: =L11-'LLC Budget'!L11 -> 0 | ... AL11: =P11-'LLC Budget'!P11 -> 0 | AN11: =SUM(AA11:AL11) -> -112000
B12: Bank fees | C12: k$ | E12: ='LLC actual'!E12 -> 1825.81 | F12: ='LLC Budget'!F12 -> 0 | G12: ='LLC Budget'!G12 -> 0 | H12: ='LLC Budget'!H12 -> 0 | I12: ='LLC Budget'!I12 -> 0 | J12: ='LLC Budget'!J12 -> 0 | K12: ='LLC Budget'!K12 -> 0 | L12: ='LLC Budget'!L12 -> 0 | M12: ='LLC Budget'!M12 -> 0 | ... P12: ='LLC Budget'!P12 -> 0 | AA12: =E12-'LLC Budget'!E12 -> 1825.81 | AB12: =F12-'LLC Budget'!F12 -> 0 | AC12: =G12-'LLC Budget'!G12 -> 0 | AD12: =H12-'LLC Budget'!H12 -> 0 | AE12: =I12-'LLC Budget'!I12 -> 0 | AF12: =J12-'LLC Budget'!J12 -> 0 | AG12: =K12-'LLC Budget'!K12 -> 0 | AH12: =L12-'LLC Budget'!L12 -> 0 | ... AL12: =P12-'LLC Budget'!P12 -> 0
B13: Suppliers + Contractos | C13: k$ | E13: =E11+E10 -> 615407.3 | F13: =F11+F10 -> 1057918.4 | G13: =G11+G10 -> 1057918.4 | H13: =H11+H10 -> 1057918.4 | I13: =I11+I10 -> 982303.42 | J13: =J11+J10 -> 982303.42 | K13: =K11+K10 -> 982303.42 | L13: =L11+L10 -> 2664403.4 | ... P13: =P11+P10 -> 2778531.4 | R13: =SUM(E13:P13) -> 20286346 | AA13: =AA11+AA10 -> -442511.12 | AB13: =AB11+AB10 -> 0 | AC13: =AC11+AC10 -> 0 | AD13: =AD11+AD10 -> 0 | AE13: =AE11+AE10 -> 0 | AF13: =AF11+AF10 -> 0 | AG13: =AG11+AG10 -> 0 | AH13: =AH11+AH10 -> 0 | ... AL13: =AL11+AL10 -> 0 | AN13: =SUM(AA13:AL13) -> -442511.12
B15: Payroll LLC (Salary) | C15: k$ | E15: ='LLC actual'!E15 -> 853284.16 | F15: ='LLC Budget'!F15 -> 893415.14 | G15: ='LLC Budget'!G15 -> 893415.14 | H15: ='LLC Budget'!H15 -> 1106748.5 | I15: ='LLC Budget'!I15 -> 1106748.5 | J15: ='LLC Budget'!J15 -> 1106748.5 | K15: ='LLC Budget'!K15 -> 1184650.9 | L15: ='LLC Budget'!L15 -> 1184650.9 | M15: ='LLC Budget'!M15 -> 1184650.9 | ... P15: ='LLC Budget'!P15 -> 1495900.9 | R15: =SUM(E15:P15) -> 14002015 | AA15: =E15-'LLC Budget'!E15 -> -40130.979 | AB15: =F15-'LLC Budget'!F15 -> 0 | AC15: =G15-'LLC Budget'!G15 -> 0 | AD15: =H15-'LLC Budget'!H15 -> 0 | AE15: =I15-'LLC Budget'!I15 -> 0 | AF15: =J15-'LLC Budget'!J15 -> 0 | AG15: =K15-'LLC Budget'!K15 -> 0 | AH15: =L15-'LLC Budget'!L15 -> 0 | ... AL15: =P15-'LLC Budget'!P15 -> 0 | AN15: =SUM(AA15:AL15) -> -40130.979
B16: Payroll LLC (Charges) | C16: k$ | E16: ='LLC actual'!E16 -> 0 | F16: ='LLC Budget'!F16 -> 138479.35 | G16: ='LLC Budget'!G16 -> 138479.35 | H16: ='LLC Budget'!H16 -> 171546.01 | I16: ='LLC Budget'!I16 -> 171546.01 | J16: ='LLC Budget'!J16 -> 171546.01 | K16: ='LLC Budget'!K16 -> 183620.89 | L16: ='LLC Budget'!L16 -> 183620.89 | M16: ='LLC Budget'!M16 -> 183620.89 | ... P16: ='LLC Budget'!P16 -> 231864.64 | R16: =SUM(E16:P16) -> 2038053.3 | AA16: =E16-'LLC Budget'!E16 -> -138479.35 | AB16: =F16-'LLC Budget'!F16 -> 0 | AC16: =G16-'LLC Budget'!G16 -> 0 | AD16: =H16-'LLC Budget'!H16 -> 0 | AE16: =I16-'LLC Budget'!I16 -> 0 | AF16: =J16-'LLC Budget'!J16 -> 0 | AG16: =K16-'LLC Budget'!K16 -> 0 | AH16: =L16-'LLC Budget'!L16 -> 0 | ... AL16: =P16-'LLC Budget'!P16 -> 0 | AN16: =SUM(AA16:AL16) -> -138479.35
B17: Bonus LLC (Gross) | C17: k$ | E17: ='LLC actual'!E17 -> 0 | F17: ='LLC Budget'!F17 -> 3740926.2 | G17: ='LLC Budget'!G17 -> 0 | H17: ='LLC Budget'!H17 -> 0 | I17: ='LLC Budget'!I17 -> 0 | J17: ='LLC Budget'!J17 -> 0 | K17: ='LLC Budget'!K17 -> 0 | L17: ='LLC Budget'!L17 -> 0 | M17: ='LLC Budget'!M17 -> 0 | ... P17: ='LLC Budget'!P17 -> 0 | R17: =SUM(E17:P17) -> 3740926.2 | AA17: =E17-'LLC Budget'!E17 -> 0 | AB17: =F17-'LLC Budget'!F17 -> 0 | AC17: =G17-'LLC Budget'!G17 -> 0 | AD17: =H17-'LLC Budget'!H17 -> 0 | AE17: =I17-'LLC Budget'!I17 -> 0 | AF17: =J17-'LLC Budget'!J17 -> 0 | AG17: =K17-'LLC Budget'!K17 -> 0 | AH17: =L17-'LLC Budget'!L17 -> 0 | ... AL17: =P17-'LLC Budget'!P17 -> 0 | AN17: =SUM(AA17:AL17) -> 0
B18: Bonus LLC (Charges) | C18: k$ | E18: ='LLC actual'!E18 -> 0 | F18: ='LLC Budget'!F18 -> 579843.56 | G18: ='LLC Budget'!G18 -> 0 | H18: ='LLC Budget'!H18 -> 0 | I18: ='LLC Budget'!I18 -> 0 | J18: ='LLC Budget'!J18 -> 0 | K18: ='LLC Budget'!K18 -> 0 | L18: ='LLC Budget'!L18 -> 0 | M18: ='LLC Budget'!M18 -> 0 | ... P18: ='LLC Budget'!P18 -> 0 | R18: =SUM(E18:P18) -> 579843.56 | AA18: =E18-'LLC Budget'!E18 -> 0 | AB18: =F18-'LLC Budget'!F18 -> 0 | AC18: =G18-'LLC Budget'!G18 -> 0 | AD18: =H18-'LLC Budget'!H18 -> 0 | AE18: =I18-'LLC Budget'!I18 -> 0 | AF18: =J18-'LLC Budget'!J18 -> 0 | AG18: =K18-'LLC Budget'!K18 -> 0 | AH18: =L18-'LLC Budget'!L18 -> 0 | ... AL18: =P18-'LLC Budget'!P18 -> 0 | AN18: =SUM(AA18:AL18) -> 0
B19: Total Salary & Social Charges | C19: k$ | E19: =SUM(E15:E18) -> 853284.16 | F19: =SUM(F15:F18) -> 5352664.2 | G19: =SUM(G15:G18) -> 1031894.5 | H19: =SUM(H15:H18) -> 1278294.5 | I19: =SUM(I15:I18) -> 1278294.5 | J19: =SUM(J15:J18) -> 1278294.5 | K19: =SUM(K15:K18) -> 1368271.8 | L19: =SUM(L15:L18) -> 1368271.8 | ... P19: =SUM(P15:P18) -> 1727765.5 | R19: =SUM(E19:P19) -> 20360838 | AA19: =SUM(AA15:AA18) -> -178610.33 | AB19: =SUM(AB15:AB18) -> 0 | AC19: =SUM(AC15:AC18) -> 0 | AD19: =SUM(AD15:AD18) -> 0 | AE19: =SUM(AE15:AE18) -> 0 | AF19: =SUM(AF15:AF18) -> 0 | AG19: =SUM(AG15:AG18) -> 0 | AH19: =SUM(AH15:AH18) -> 0 | ... AL19: =SUM(AL15:AL18) -> 0 | AN19: =SUM(AA19:AL19) -> -178610.33
B22: AGA charges LLC | C22: k$ | E22: ='LLC actual'!E22 -> 10193888 | F22: ='LLC Budget'!F22 -> 2222235 | G22: ='LLC Budget'!G22 -> 54480.6 | H22: ='LLC Budget'!H22 -> 0 | I22: ='LLC Budget'!I22 -> 0 | J22: ='LLC Budget'!J22 -> 0 | K22: ='LLC Budget'!K22 -> 602154 | L22: ='LLC Budget'!L22 -> 0 | M22: ='LLC Budget'!M22 -> 2168614.6 | ... P22: ='LLC Budget'!P22 -> 138323.38 | R22: =SUM(E22:P22) -> 15379696 | AA22: =E22-'LLC Budget'!E22 -> 10193888 | AB22: =F22-'LLC Budget'!F22 -> 0 | AC22: =G22-'LLC Budget'!G22 -> 0 | AD22: =H22-'LLC Budget'!H22 -> 0 | AE22: =I22-'LLC Budget'!I22 -> 0 | AF22: =J22-'LLC Budget'!J22 -> 0 | AG22: =K22-'LLC Budget'!K22 -> 0 | AH22: =L22-'LLC Budget'!L22 -> 0 | ... AL22: =P22-'LLC Budget'!P22 -> 0 | AN22: =SUM(AA22:AL22) -> 10193888
B23: AGA Uptevia STC | E23: ='LLC actual'!E23 -> 0 | F23: ='LLC Budget'!F23 -> 0 | G23: ='LLC Budget'!G23 -> 0 | H23: ='LLC Budget'!H23 -> 0 | I23: ='LLC Budget'!I23 -> 0 | J23: ='LLC Budget'!J23 -> 0 | K23: ='LLC Budget'!K23 -> 0 | L23: ='LLC Budget'!L23 -> 0 | M23: ='LLC Budget'!M23 -> 0 | ... P23: ='LLC Budget'!P23 -> 0 | AA23: =E23-'LLC Budget'!E23 -> 0 | AB23: =F23-'LLC Budget'!F23 -> 0 | AC23: =G23-'LLC Budget'!G23 -> 0 | AD23: =H23-'LLC Budget'!H23 -> 0 | AE23: =I23-'LLC Budget'!I23 -> 0 | AF23: =J23-'LLC Budget'!J23 -> 0 | AG23: =K23-'LLC Budget'!K23 -> 0 | AH23: =L23-'LLC Budget'!L23 -> 0 | ... AL23: =P23-'LLC Budget'!P23 -> 0
B24: Total AGA | C24: k$ | E24: =SUM(E22:E22) -> 10193888 | F24: =SUM(F22:F22) -> 2222235 | G24: =SUM(G22:G22) -> 54480.6 | H24: =SUM(H22:H22) -> 0 | I24: =SUM(I22:I22) -> 0 | J24: =SUM(J22:J22) -> 0 | K24: =SUM(K22:K22) -> 602154 | L24: =SUM(L22:L22) -> 0 | ... P24: =SUM(P22:P22) -> 138323.38 | R24: =SUM(E24:P24) -> 15379696 | AA24: =SUM(AA22:AA22) -> 10193888 | AB24: =SUM(AB22:AB22) -> 0 | AC24: =SUM(AC22:AC22) -> 0 | AD24: =SUM(AD22:AD22) -> 0 | AE24: =SUM(AE22:AE22) -> 0 | AF24: =SUM(AF22:AF22) -> 0 | AG24: =SUM(AG22:AG22) -> 0 | AH24: =SUM(AH22:AH22) -> 0 | ... AL24: =SUM(AL22:AL22) -> 0 | AN24: =SUM(AA24:AL24) -> 10193888
B26: Total HR related | C26: k$ | E26: =E24+E19 -> 11047172 | F26: =F24+F19 -> 7574899.2 | G26: =G24+G19 -> 1086375.1 | H26: =H24+H19 -> 1278294.5 | I26: =I24+I19 -> 1278294.5 | J26: =J24+J19 -> 1278294.5 | K26: =K24+K19 -> 1970425.8 | L26: =L24+L19 -> 1368271.8 | ... P26: =P24+P19 -> 1866088.9 | R26: =SUM(E26:P26) -> 35740534 | AA26: =AA24+AA19 -> 10015278 | AB26: =AB24+AB19 -> 0 | AC26: =AC24+AC19 -> 0 | AD26: =AD24+AD19 -> 0 | AE26: =AE24+AE19 -> 0 | AF26: =AF24+AF19 -> 0 | AG26: =AG24+AG19 -> 0 | AH26: =AH24+AH19 -> 0 | ... AL26: =AL24+AL19 -> 0 | AN26: =SUM(AA26:AL26) -> 10015278
B28: Interets in | C28: k$ | E28: ='LLC actual'!E28 -> -600434.79 | F28: ='LLC Budget'!F28 -> -480072.95 | G28: ='LLC Budget'!G28 -> -467801.74 | H28: ='LLC Budget'!H28 -> -463370.62 | I28: ='LLC Budget'!I28 -> -458783.03 | J28: ='LLC Budget'!J28 -> -454278.49 | K28: ='LLC Budget'!K28 -> -448897.53 | L28: ='LLC Budget'!L28 -> -441288.02 | M28: ='LLC Budget'!M28 -> -429598.78 | ... P28: ='LLC Budget'!P28 -> -396931.18 | R28: =SUM(E28:P28) -> -5466239.5 | AA28: =E28-'LLC Budget'!E28 -> -108189.17 | AB28: =F28-'LLC Budget'!F28 -> 0 | AC28: =G28-'LLC Budget'!G28 -> 0 | AD28: =H28-'LLC Budget'!H28 -> 0 | AE28: =I28-'LLC Budget'!I28 -> 0 | AF28: =J28-'LLC Budget'!J28 -> 0 | AG28: =K28-'LLC Budget'!K28 -> 0 | AH28: =L28-'LLC Budget'!L28 -> 0 | ... AL28: =P28-'LLC Budget'!P28 -> 0 | AN28: =SUM(AA28:AL28) -> -108189.17
B29: Internal wire | C29: k$ | E29: ='LLC actual'!E29 -> 0 | F29: ='LLC Budget'!F29 -> 0 | G29: ='LLC Budget'!G29 -> 0 | H29: ='LLC Budget'!H29 -> 0 | I29: ='LLC Budget'!I29 -> 0 | J29: ='LLC Budget'!J29 -> 0 | K29: ='LLC Budget'!K29 -> 0 | L29: ='LLC Budget'!L29 -> 0 | M29: ='LLC Budget'!M29 -> 0 | ... P29: ='LLC Budget'!P29 -> 0 | R29: =SUM(E29:P29) -> 0 | AA29: =E29-'LLC Budget'!E29 -> 0 | AB29: =F29-'LLC Budget'!F29 -> 0 | AC29: =G29-'LLC Budget'!G29 -> 0 | AD29: =H29-'LLC Budget'!H29 -> 0 | AE29: =I29-'LLC Budget'!I29 -> 0 | AF29: =J29-'LLC Budget'!J29 -> 0 | AG29: =K29-'LLC Budget'!K29 -> 0 | AH29: =L29-'LLC Budget'!L29 -> 0 | ... AL29: =P29-'LLC Budget'!P29 -> 0 | AN29: =SUM(AA29:AL29) -> 0
B30: Deposit | C30: k$
B32: Total | C32: k$ | E32: =SUM(E28:E29,E24,E19,E13) -> 11062145 | F32: =SUM(F28:F29,F24,F19,F13) -> 8152744.7 | G32: =SUM(G28:G29,G24,G19,G13) -> 1676491.8 | H32: =SUM(H28:H29,H24,H19,H13) -> 1872842.3 | I32: =SUM(I28:I29,I24,I19,I13) -> 1801814.9 | J32: =SUM(J28:J29,J24,J19,J13) -> 1806319.4 | K32: =SUM(K28:K29,K24,K19,K13) -> 2503831.7 | L32: =SUM(L28:L29,L24,L19,L13) -> 3591387.2 | ... P32: =SUM(P28:P29,P24,P19,P13) -> 4247689.1 | R32: =SUM(E32:P32) -> 50560640 | AA32: =SUM(AA28:AA29,AA24,AA19,AA13) -> 9464577.5 | AB32: =SUM(AB28:AB29,AB24,AB19,AB13) -> 0 | AC32: =SUM(AC28:AC29,AC24,AC19,AC13) -> 0 | AD32: =SUM(AD28:AD29,AD24,AD19,AD13) -> 0 | AE32: =SUM(AE28:AE29,AE24,AE19,AE13) -> 0 | AF32: =SUM(AF28:AF29,AF24,AF19,AF13) -> 0 | AG32: =SUM(AG28:AG29,AG24,AG19,AG13) -> 0 | AH32: =SUM(AH28:AH29,AH24,AH19,AH13) -> 0 | ... AL32: =SUM(AL28:AL29,AL24,AL19,AL13) -> 0 | AN32: =SUM(AA32:AL32) -> 9464577.5
R33: =R32/12 -> 4213386.7 | AN33: =AN32/12 -> 788714.79
B35: Cash Balance - Abivax LLC
B37: Balance LLC - USD - begining of month | C37: k$ | E37: ='LLC actual'!E37 -> 1.9794316e+08 | F37: =E38 -> 1.8688101e+08 | G37: =F38 -> 1.7872827e+08 | H37: =G38 -> 1.7705178e+08 | I37: =H38 -> 1.7517893e+08 | J37: =I38 -> 1.7337712e+08 | K37: =J38 -> 1.715708e+08 | L37: =K38 -> 1.6906697e+08 | M37: =L38 -> 1.6547558e+08 | ... P37: =O38 -> 1.5163021e+08 | AA37: =E37-'LLC Budget'!E37 -> 0 | AB37: =F37-'LLC Budget'!F37 -> -9464577.5 | AC37: =G37-'LLC Budget'!G37 -> -9464577.5 | AD37: =H37-'LLC Budget'!H37 -> -9464577.5 | AE37: =I37-'LLC Budget'!I37 -> -9464577.5 | AF37: =J37-'LLC Budget'!J37 -> -9464577.5 | AG37: =K37-'LLC Budget'!K37 -> -9464577.5 | AH37: =L37-'LLC Budget'!L37 -> -9464577.5 | ... AL37: =P37-'LLC Budget'!P37 -> -9464577.5
B38: Balance LLC - USD - end of month | C38: k$ | E38: =E37-E32 -> 1.8688101e+08 | F38: =F37-F32 -> 1.7872827e+08 | G38: =G37-G32 -> 1.7705178e+08 | H38: =H37-H32 -> 1.7517893e+08 | I38: =I37-I32 -> 1.7337712e+08 | J38: =J37-J32 -> 1.715708e+08 | K38: =K37-K32 -> 1.6906697e+08 | L38: =L37-L32 -> 1.6547558e+08 | ... P38: =P37-P32 -> 1.4738252e+08 | AA38: =E38-'LLC Budget'!E38 -> -9464577.5 | AB38: =F38-'LLC Budget'!F38 -> -9464577.5 | AC38: =G38-'LLC Budget'!G38 -> -9464577.5 | AD38: =H38-'LLC Budget'!H38 -> -9464577.5 | AE38: =I38-'LLC Budget'!I38 -> -9464577.5 | AF38: =J38-'LLC Budget'!J38 -> -9464577.5 | AG38: =K38-'LLC Budget'!K38 -> -9464577.5 | AH38: =L38-'LLC Budget'!L38 -> -9464577.5 | ... AL38: =P38-'LLC Budget'!P38 -> -9464577.5
B40: EUR-USD m-1 | C40: $ | E40: ='SA Reforecast'!E88 -> 1.175 | F40: ='SA Reforecast'!F88 -> 1.16 | G40: ='SA Reforecast'!G88 -> 1.16 | H40: ='SA Reforecast'!H88 -> 1.16 | I40: ='SA Reforecast'!I88 -> 1.16 | J40: ='SA Reforecast'!J88 -> 1.16 | K40: ='SA Reforecast'!K88 -> 1.16 | L40: ='SA Reforecast'!L88 -> 1.16 | ... P40: ='SA Reforecast'!P88 -> 1.16 | AA40: =E40-'LLC Budget'!E40 -> 0 | AB40: =F40-'LLC Budget'!F40 -> 0 | AC40: =G40-'LLC Budget'!G40 -> 0 | AD40: =H40-'LLC Budget'!H40 -> 0 | AE40: =I40-'LLC Budget'!I40 -> 0 | AF40: =J40-'LLC Budget'!J40 -> 0 | AG40: =K40-'LLC Budget'!K40 -> 0 | AH40: =L40-'LLC Budget'!L40 -> 0 | ... AL40: =P40-'LLC Budget'!P40 -> 0
B41: EUR-USD m | C41: $ | E41: ='SA Reforecast'!E89 -> 1.1919 | F41: ='SA Reforecast'!F89 -> 1.16 | G41: ='SA Reforecast'!G89 -> 1.16 | H41: ='SA Reforecast'!H89 -> 1.16 | I41: ='SA Reforecast'!I89 -> 1.16 | J41: ='SA Reforecast'!J89 -> 1.16 | K41: ='SA Reforecast'!K89 -> 1.16 | L41: ='SA Reforecast'!L89 -> 1.16 | ... P41: ='SA Reforecast'!P89 -> 1.16 | AA41: =E41-'LLC Budget'!E41 -> 0.0319 | AB41: =F41-'LLC Budget'!F41 -> 0 | AC41: =G41-'LLC Budget'!G41 -> 0 | AD41: =H41-'LLC Budget'!H41 -> 0 | AE41: =I41-'LLC Budget'!I41 -> 0 | AF41: =J41-'LLC Budget'!J41 -> 0 | AG41: =K41-'LLC Budget'!K41 -> 0 | AH41: =L41-'LLC Budget'!L41 -> 0 | ... AL41: =P41-'LLC Budget'!P41 -> 0
B43: Cash Balance - Abivax LLC expressed in EUR
B45: Balance SA-USD - begining of month | C45: k€ | E45: =E37/E40 -> 1.6846226e+08 | F45: =F37/F40 -> 1.6110432e+08 | G45: =G37/G40 -> 1.5407609e+08 | H45: =H37/H40 -> 1.5263084e+08 | I45: =I37/I40 -> 1.5101632e+08 | J45: =J37/J40 -> 1.4946303e+08 | K45: =K37/K40 -> 1.4790586e+08 | L45: =L37/L40 -> 1.4574739e+08 | ... P45: =P37/P40 -> 1.3071569e+08 | AA45: =E45-'LLC Budget'!E45 -> 0 | AB45: =F45-'LLC Budget'!F45 -> -8159118.5 | AC45: =G45-'LLC Budget'!G45 -> -8159118.5 | AD45: =H45-'LLC Budget'!H45 -> -8159118.5 | AE45: =I45-'LLC Budget'!I45 -> -8159118.5 | AF45: =J45-'LLC Budget'!J45 -> -8159118.5 | AG45: =K45-'LLC Budget'!K45 -> -8159118.5 | AH45: =L45-'LLC Budget'!L45 -> -8159118.5 | ... AL45: =P45-'LLC Budget'!P45 -> -8159118.5
B46: Balance SA-USD - end of month | C46: k€ | E46: =E38/E41 -> 1.5679253e+08 | F46: =F38/F41 -> 1.5407609e+08 | G46: =G38/G41 -> 1.5263084e+08 | H46: =H38/H41 -> 1.5101632e+08 | I46: =I38/I41 -> 1.4946303e+08 | J46: =J38/J41 -> 1.4790586e+08 | K46: =K38/K41 -> 1.4574739e+08 | L46: =L38/L41 -> 1.4265136e+08 | ... P46: =P38/P41 -> 1.2705389e+08 | AA46: =E46-'LLC Budget'!E46 -> -12470913 | AB46: =F46-'LLC Budget'!F46 -> -8159118.5 | AC46: =G46-'LLC Budget'!G46 -> -8159118.5 | AD46: =H46-'LLC Budget'!H46 -> -8159118.5 | AE46: =I46-'LLC Budget'!I46 -> -8159118.5 | AF46: =J46-'LLC Budget'!J46 -> -8159118.5 | AG46: =K46-'LLC Budget'!K46 -> -8159118.5 | AH46: =L46-'LLC Budget'!L46 -> -8159118.5 | ... AL46: =P46-'LLC Budget'!P46 -> -8159118.5

Sheet Data Reforecast
C1: EURUSD - Budget | D1: =1/1.16 -> 0.86206897
B3: Verification
F4: Budget
C5: Contractors | D5: French + LLC | E5: EUR | F5: =SUM(M39:M41) -> 15068882
C6: ALL Suppliers without IQVIA/Contractors/Jetons | D6: French-EUR | E6: EUR | F6: =J56 -> 57907732 | I6: Explications
C7: IQVIA | D7: French | E7: EUR | F7: 67563871 | G7: ='SA Reforecast'!R20 -> 74115430 | H7: =G7-F7 -> 6551559 | I7: 3m€ extourne FNP, 1 m€ dépenses janvier/dece, +2,4 milestone 105
C8: ALL Suppliers without contractors | D8: French-USD | E8: EUR | F8: =J65*D1 -> 36304410
C9: ALL Suppliers without contractors | D9: LLC | E9: EUR | F9: =J74*D1 -> 18194371
C10: Jetons | D10: French | E10: EUR | F10: 770000 | G10: ='SA Reforecast'!R40 -> 936000 | H10: 905 k€ versus 770 k€, et charges sociales | L10: charges sociales forfait social intégré au budget ?
C11: Non cash | D11: French | E11: N/A | F11: 286677.12
C12: Non cash | D12: LLC | E12: N/A | F12: 34482.759
C14: Total Suppliers | D14: French + LLC | E14: EUR | F14: =SUM(F5:F12) -> 1.9613043e+08
F15: 1.9613043e+08
F16: =F14-F15 -> 0
C17: Budget 2026 FTE - SA | E17: EUR | F17: 10529171 | G17: ='SA Reforecast'!R36 -> 10488428
C18: Budget 2026 FTE - LLC | E18: EUR | F18: 17706421 | G18: ='LLC Reforecast'!R19 -> 20360838
C19: Budget 2026 AGA LLC | D19: EUR | E19: EUR | F19: 9373187.6 | G19: ='LLC Reforecast'!R24 -> 15379696
C20: Budget 2026 AGA SA | E20: EUR | F20: 30886028 | G20: ='SA Reforecast'!R46 -> 17408279
C22: Total budget 2026 (avec ce fichier) | F22: =F14+SUM(F17:F20) -> 2.6462523e+08 | H22: 265 m€
B25: Abivax SA
C26: IQVIA
C27: Source :
C28: IQVIA Vision Summary Reforecast 20260223
C29: Done with Clinical Trial follow-up and budget for CO impact
C30: CO impact :
C31: RD - Clinical_budget 2026-NBE 10.11update
B33: Source : Suppliers SA EUR-USD et LLC-USD - vBudget
B34: Abivax SA & LLC
C36: Contractors
C37: Budget by quarter
B38: Entity | C38: P&L | D38: Devise | E38: Q1 2026 | F38: Q2 2026 | G38: Q3 2026 | H38: Q4 2026 | J38: 2026 | K38: Monthly | M38: en EUR | P38: Source :
B39: LLC | C39: Contractors USD | D39: USD | E39: 336000 | F39: 336000 | G39: 336000 | H39: 336000 | J39: =SUM(E39:H39) -> 1344000 | K39: =J39/12 -> 112000 | M39: =J39*D1 -> 1158620.7 | P39: Suppliers SA EUR-USD et LLC-USD -vBudget 2026
B40: French | C40: Contractors USD | D40: USD | E40: 2523760 | F40: 2584560 | G40: 2558160 | H40: 2549920 | J40: =SUM(E40:H40) -> 10216400 | K40: =J40/12 -> 851366.67 | M40: =J40*D1 -> 8807241.4
B41: French | C41: Contractors EUR | D41: EUR | E41: 1249340 | F41: 1295540 | G41: 1295540 | H41: 1262600 | J41: =SUM(E41:H41) -> 5103020 | K41: =J41/12 -> 425251.67 | M41: =J41 -> 5103020 | N41: =SUM(M39:M41) -> 15068882
C45: monthly | E45: 46023 | F45: =EDATE(E45,1) -> 46054 | G45: =EDATE(F45,1) -> 46082 | H45: =EDATE(G45,1) -> 46113 | I45: =EDATE(H45,1) -> 46143 | J45: =EDATE(I45,1) -> 46174 | K45: =EDATE(J45,1) -> 46204 | L45: =EDATE(K45,1) -> 46235 | M45: =EDATE(L45,1) -> 46266 | ... P45: =EDATE(O45,1) -> 46357 | R45: Total | S45: check (negligeable)
B46: LLC | C46: Contractors USD-LLC | D46: USD | E46: =E39/3 -> 112000 | F46: =E46 -> 112000 | G46: =F46 -> 112000 | H46: =G46 -> 112000 | I46: =F39/3 -> 112000 | J46: =I46 -> 112000 | K46: =J46 -> 112000 | L46: =G39/3 -> 112000 | M46: =L46 -> 112000 | N46: =M46 -> 112000 | O46: =H39/3 -> 112000 | P46: =O46 -> 112000 | R46: =SUM(E46:P46) -> 1344000 | S46: =R46-J39 -> 0
B47: French | C47: Contractors USD-SA | D47: USD | E47: =E40/3 -> 841253.33 | F47: =E47 -> 841253.33 | G47: =F47 -> 841253.33 | H47: =G47 -> 841253.33 | I47: =F40/3 -> 861520 | J47: =I47 -> 861520 | K47: =J47 -> 861520 | L47: =G40/3 -> 852720 | M47: =L47 -> 852720 | N47: =M47 -> 852720 | O47: =H40/3 -> 849973.33 | P47: =O47 -> 849973.33 | R47: =SUM(E47:P47) -> 10207680 | S47: =R47-J40 -> -8720
B48: French | C48: Contractors EUR-SA | D48: EUR | E48: =E41/3 -> 416446.67 | F48: =E48 -> 416446.67 | G48: =F48 -> 416446.67 | H48: =G48 -> 416446.67 | I48: =F41/3 -> 431846.67 | J48: =I48 -> 431846.67 | K48: =J48 -> 431846.67 | L48: =G41/3 -> 431846.67 | M48: =L48 -> 431846.67 | N48: =M48 -> 431846.67 | O48: =H41/3 -> 420866.67 | P48: =O48 -> 420866.67 | R48: =SUM(E48:P48) -> 5098600 | S48: =R48-J41 -> -4420
B51: Abivax SA
C53: Suppliers minus IQVIA & Contractors & Jetons - Abivax SA €
E55: Q1 2026 | F55: Q2 2026 | G55: Q3 2026 | H55: Q4 2026 | J55: Total
C56: ALL Suppliers without IQVIA/Contractors/Jetons | D56: € | E56: 14155071 | F56: 13790286 | G56: 14575851 | H56: 15386525 | J56: =SUM(E56:H56) -> 57907732
C57: monthly | D57: € | E57: 4718356.9 | F57: 4596761.9 | G57: 4858617.1 | H57: 5128841.5 | J57: =SUM(E57:H57) -> 19302577
E60: 46023 | F60: =EDATE(E60,1) -> 46054 | G60: =EDATE(F60,1) -> 46082 | H60: =EDATE(G60,1) -> 46113 | I60: =EDATE(H60,1) -> 46143 | J60: =EDATE(I60,1) -> 46174 | K60: =EDATE(J60,1) -> 46204 | L60: =EDATE(K60,1) -> 46235 | M60: =EDATE(L60,1) -> 46266 | ... P60: =EDATE(O60,1) -> 46357 | R60: Total | S60: check
C61: ALL Suppliers without IQVIA/Contractors with Risk Adj. | D61: € | E61: =E57 -> 4718356.9 | F61: =E61 -> 4718356.9 | G61: =F61 -> 4718356.9 | H61: =G61 -> 4718356.9 | I61: =F57 -> 4596761.9 | J61: =I61 -> 4596761.9 | K61: =J61 -> 4596761.9 | L61: =G57 -> 4858617.1 | M61: =L61 -> 4858617.1 | N61: =M61 -> 4858617.1 | O61: =H57 -> 5128841.5 | P61: =O61 -> 5128841.5 | R61: =SUM(E61:P61) -> 57497248 | S61: =R61-J56 -> -410484.67
B63: Abivax SA | C63: Suppliers minus Contractors - Abivax SA $
E64: Q1 2026 | F64: Q2 2026 | G64: Q3 2026 | H64: Q4 2026 | J64: Total
C65: ALL Suppliers without contractors | D65: $ | E65: 7957968.7 | F65: 8078711.5 | G65: 16198996 | H65: 9877439.5 | J65: =SUM(E65:H65) -> 42113116
C66: monthly | D66: $ | E66: 2652656.2 | F66: 2692903.8 | G66: 5399665.4 | H66: 3292479.8 | J66: =SUM(E66:H66) -> 14037705
E68: 46023 | F68: =EDATE(E68,1) -> 46054 | G68: =EDATE(F68,1) -> 46082 | H68: =EDATE(G68,1) -> 46113 | I68: =EDATE(H68,1) -> 46143 | J68: =EDATE(I68,1) -> 46174 | K68: =EDATE(J68,1) -> 46204 | L68: =EDATE(K68,1) -> 46235 | M68: =EDATE(L68,1) -> 46266 | ... P68: =EDATE(O68,1) -> 46357 | R68: Total | S68: check
C69: ALL Suppliers without contractors with Risk Adj. | D69: $ | E69: =E66 -> 2652656.2 | F69: =E69 -> 2652656.2 | G69: =F69 -> 2652656.2 | H69: =G69 -> 2652656.2 | I69: =F66 -> 2692903.8 | J69: =I69 -> 2692903.8 | K69: =J69 -> 2692903.8 | L69: =G66 -> 5399665.4 | M69: =L69 -> 5399665.4 | N69: =M69 -> 5399665.4 | O69: =H66 -> 3292479.8 | P69: =O69 -> 3292479.8 | R69: =SUM(E69:P69) -> 41473292 | S69: =R69-J65 -> -639823.61
B72: Abivax LLC | C72: Suppliers minus Contractors - Abivax LLC $
E73: Q1 2026 | F73: Q2 2026 | G73: Q3 2026 | H73: Q4 2026 | J73: Total
C74: ALL Suppliers without contractors | D74: $ | E74: 2837755.2 | F74: 2610910.2 | G74: 7657210.2 | H74: 7999594.2 | J74: =SUM(E74:H74) -> 21105470
C75: monthly | D75: $ | E75: 945918.42 | F75: 870303.42 | G75: 2552403.4 | H75: 2666531.4 | J75: =SUM(E75:H75) -> 7035156.7
E78: 46023 | F78: =EDATE(E78,1) -> 46054 | G78: =EDATE(F78,1) -> 46082 | H78: =EDATE(G78,1) -> 46113 | I78: =EDATE(H78,1) -> 46143 | J78: =EDATE(I78,1) -> 46174 | K78: =EDATE(J78,1) -> 46204 | L78: =EDATE(K78,1) -> 46235 | M78: =EDATE(L78,1) -> 46266 | ... P78: =EDATE(O78,1) -> 46357 | R78: Total
C79: ALL Suppliers without contractors with Risk Adj. | D79: $ | E79: =E75 -> 945918.42 | F79: =E79 -> 945918.42 | G79: =F79 -> 945918.42 | H79: =G79 -> 945918.42 | I79: =F75 -> 870303.42 | J79: =I79 -> 870303.42 | K79: =J79 -> 870303.42 | L79: =G75 -> 2552403.4 | M79: =L79 -> 2552403.4 | N79: =M79 -> 2552403.4 | O79: =H75 -> 2666531.4 | P79: =O79 -> 2666531.4 | R79: =SUM(E79:P79) -> 19384857
B83: HR | C83: voir
C84: Cash out Payroll 2026, V Forecast
C85: Suppliers SA EUR-USD et LLC-USD -vBudget 2026
C86: Bonus dispatch 2026 - 20260602
C87: calcul cash out AGA 20260226
C88: jetons : mail FG
B91: Advances for IQVIA
E93: FP&A - accounting | G93: Cash | H93: in m€
C94: TOTAL UC108 | D94: 380000 | E94: 46327 | F94: accounting | G94: Q1 2027
C95: TOTAL UC105 | D95: 3594680.8 | E95: 46082 | F95: FP&A | G95: Q4 2026 | H95: =D95*10^-6 -> 3.5946808
C96: TOTAL UC106 | D96: 4144364.4 | E96: 46082 | F96: FP&A | G96: Q4 2026 | H96: =D96*10^-6 -> 4.1443644 | I96: =H96+H95 -> 7.7390452
C97: TOTAL UC107 | D97: 5538475.8 | E97: 47818 | F97: FP&A | G97: Q4 2031 | H97: =D97*10^-6 -> 5.5384758
C98: TOTAL Orgapharm | D98: 129037.5 | E98: 46327 | F98: accounting | G98: Q1 2027
B100: Capex
C101: ABIVAX SA | D101: 1832000 | E101: EUR
C102: ABIVAX LLC | D102: 22000 | E102: USD | F102: negligable

Sheet Risk & Opp- diff budget-to do 
E5: Novembre | F5: 518978 | G5: récupéré | H5: janvier
E6: Decembre | F6: 1563714 | G6: récupéré | H6: janvier
E7: Janvier | F7: 1078090 | G7: en attente
E9: CIR 2020 | F9: 2380320
E11: Update versus Budget
J13: impact 2026 FY
F14: SP janvuary | J14: m€
E15: AGA Abivax SA | F15: DS | G15: 100% to 30% | J15: if-, less expenses
F16: Mary Mantock | G16: withdraw
F17: Safaa Abbas | G17: withdraw
F19: previous | G19: now
F20: 14030820 | G20: 11294952 | J20: =(G20-F20)*10^-6 -> -2.735868
E23: AGA Abivax LLC
F24: SP janvuary
F25: Social charges | G25: previous | H25: 0.095
G26: now | H26: 0.025
F27: previous | G27: now
F28: 5185807.6 | G28: 1367916.4 | J28: =(G28-F28)*10^-6 -> -3.8178912
E31: Bonus | F31: previous | G31: now
E32: Abivax SA | F32: 3740926.2 | G32: 3059927 | J32: =(G32-F32)*144%*10^-6 -> -0.98063879
E33: Abivax LLC | F33: 1075771 | G33: 1142870 | J33: =(G33-F33)*115.5%*10^-6 -> 0.077499299
F36: previous | G36: now
E37: Board fees | F37: ='Data Budget'!F10 -> 770000 | G37: ='SA Reforecast'!R38 -> 845500 | J37: =(G37-F37)*120%*10^-6 -> 0.0906
F39: previous | G39: now
E40: RTC | F40: 5 | G40: 3 | J40: =-(G40-F40) -> 2
E45: impact FX | J45: 4
J47: =SUM(J20:J40) -> -5.3662987

Sheet Actual   ->

Sheet SA Actual
H2: séparer remboursement MdG
B3: Abivax SA | E3: Cash Forecast - Actual
B6: Abivax SA EUR | E6: Actual
E7: 46023 | F7: =EDATE(E7,1) -> 46054 | G7: =EDATE(F7,1) -> 46082 | H7: =EDATE(G7,1) -> 46113 | I7: =EDATE(H7,1) -> 46143 | J7: =EDATE(I7,1) -> 46174 | K7: =EDATE(J7,1) -> 46204 | L7: =EDATE(K7,1) -> 46235 | M7: =EDATE(L7,1) -> 46266 | ... P7: =EDATE(O7,1) -> 46357 | R7: 2026
B9: Amount are VAT excluded
B10: IQVIA 105 milestone | C10: k€ | E10: 0 | F10: 0 | G10: 0 | H10: 0 | I10: 0 | J10: 0 | K10: 0 | L10: 0 | M10: 0 | N10: 0 | O10: 0 | P10: 0 | R10: =SUM(E10:P10) -> 0
B11: IQVIA 105 PTC & IF & Q2 | C11: k€ | E11: 599166.48 | F11: 0 | G11: 0 | H11: 0 | I11: 0 | J11: 0 | K11: 0 | L11: 0 | M11: 0 | N11: 0 | O11: 0 | P11: 0 | R11: =SUM(E11:P11) -> 599166.48
B12: IQVIA 106 milestone | C12: k€ | E12: 0 | F12: 0 | G12: 0 | H12: 0 | I12: 0 | J12: 0 | K12: 0 | L12: 0 | M12: 0 | N12: 0 | O12: 0 | P12: 0 | R12: =SUM(E12:P12) -> 0
B13: IQVIA 106 PTC & IF & Q2 | C13: k€ | E13: 1246050.2 | F13: 0 | G13: 0 | H13: 0 | I13: 0 | J13: 0 | K13: 0 | L13: 0 | M13: 0 | N13: 0 | O13: 0 | P13: 0 | R13: =SUM(E13:P13) -> 1246050.2
B14: IQVIA 107 milestone | C14: k€ | E14: 4790962 | F14: 0 | G14: 0 | H14: 0 | I14: 0 | J14: 0 | K14: 0 | L14: 0 | M14: 0 | N14: 0 | O14: 0 | P14: 0 | R14: =SUM(E14:P14) -> 4790962
B15: IQVIA 107 PTC & IF & Q2 | C15: k€ | E15: 1814129.3 | F15: 0 | G15: 0 | H15: 0 | I15: 0 | J15: 0 | K15: 0 | L15: 0 | M15: 0 | N15: 0 | O15: 0 | P15: 0 | R15: =SUM(E15:P15) -> 1814129.3
B16: IQVIA Ph3 - CO | C16: k€
B17: IQVIA CD milestone | C17: k€ | E17: 1308382 | F17: 0 | G17: 0 | H17: 0 | I17: 0 | J17: 0 | K17: 0 | L17: 0 | M17: 0 | N17: 0 | O17: 0 | P17: 0 | R17: =SUM(E17:P17) -> 1308382
B18: IQVIA CD PTC & IF & Q2 | C18: k€ | E18: 214041.3 | F18: 0 | G18: 0 | H18: 0 | I18: 0 | J18: 0 | K18: 0 | L18: 0 | M18: 0 | N18: 0 | O18: 0 | P18: 0 | R18: =SUM(E18:P18) -> 214041.3
B19: IQVIA CD -CO | C19: k€ | E19: 0 | F19: 0 | G19: 0 | H19: 0 | I19: 0 | J19: 0 | K19: 0 | L19: 0 | M19: 0 | N19: 0 | O19: 0 | P19: 0 | R19: =SUM(E19:P19) -> 0
B20: Total IQVIA | C20: k€ | E20: =SUM(E10:E19) -> 9972731.3 | F20: =SUM(F10:F19) -> 0 | G20: =SUM(G10:G19) -> 0 | H20: =SUM(H10:H19) -> 0 | I20: =SUM(I10:I19) -> 0 | J20: =SUM(J10:J19) -> 0 | K20: =SUM(K10:K19) -> 0 | L20: =SUM(L10:L19) -> 0 | ... P20: =SUM(P10:P19) -> 0 | R20: =SUM(E20:P20) -> 9972731.3
B22: Other Suppliers € (HT) with 10% R/Adj. | C22: k€ | E22: 5117218.8 | F22: 0 | G22: 0 | H22: 0 | I22: 0 | J22: 0 | K22: 0 | L22: 0 | M22: 0 | N22: 0 | O22: 0 | P22: 0 | R22: =SUM(E22:P22) -> 5117218.8
B23: Contractor (HT) with 10% R/Adj. | C23: k€ | E23: 405647.09 | F23: 0 | G23: 0 | H23: 0 | I23: 0 | J23: 0 | K23: 0 | L23: 0 | M23: 0 | N23: 0 | O23: 0 | P23: 0 | R23: =SUM(E23:P23) -> 405647.09
B24: Bank fees | C24: k€ | E24: 17774.39 | F24: 0 | G24: 0 | H24: 0 | I24: 0 | J24: 0 | K24: 0 | L24: 0 | M24: 0 | N24: 0 | O24: 0 | P24: 0
B25: Suppliers + Contractos | C25: k€ | E25: =SUM(E22:E24) -> 5540640.2 | F25: =SUM(F22:F24) -> 0 | G25: =SUM(G22:G24) -> 0 | H25: =SUM(H22:H24) -> 0 | I25: =SUM(I22:I24) -> 0 | J25: =SUM(J22:J24) -> 0 | K25: =SUM(K22:K24) -> 0 | L25: =SUM(L22:L24) -> 0 | ... P25: =SUM(P22:P24) -> 0 | R25: =SUM(E25:P25) -> 5540640.2
B27: Capex | C27: k€ | R27: =SUM(E27:P27) -> 0
B29: Salaire net aprés PAS | C29: k€ | E29: 309076.43 | F29: 0 | G29: 0 | H29: 0 | I29: 0 | J29: 0 | K29: 0 | L29: 0 | M29: 0 | N29: 0 | O29: 0 | P29: 0 | R29: =SUM(E29:P29) -> 309076.43
B30: Bonus net sans PAS | C30: k€ | E30: 0 | F30: 0 | G30: 0 | H30: 0 | I30: 0 | J30: 0 | K30: 0 | L30: 0 | M30: 0 | N30: 0 | O30: 0 | P30: 0 | R30: =SUM(E30:P30) -> 0
B31: Urssaf | C31: k€ | E31: 175083 | F31: 0 | G31: 0 | H31: 0 | I31: 0 | J31: 0 | K31: 0 | L31: 0 | M31: 0 | N31: 0 | O31: 0 | P31: 0 | R31: =SUM(E31:P31) -> 175083
B32: Retraite | C32: k€ | E32: 70015.02 | F32: 0 | G32: 0 | H32: 0 | I32: 0 | J32: 0 | K32: 0 | L32: 0 | M32: 0 | N32: 0 | O32: 0 | P32: 0 | R32: =SUM(E32:P32) -> 70015.02
B33: Prévoyance | C33: k€ | E33: 0 | F33: 0 | G33: 0 | H33: 0 | I33: 0 | J33: 0 | K33: 0 | L33: 0 | M33: 0 | N33: 0 | O33: 0 | P33: 0 | R33: =SUM(E33:P33) -> 0
B34: Mutuelle | C34: k€ | E34: 6151.49 | F34: 0 | G34: 0 | H34: 0 | I34: 0 | J34: 0 | K34: 0 | L34: 0 | M34: 0 | N34: 0 | O34: 0 | P34: 0 | R34: =SUM(E34:P34) -> 6151.49
B35: Dgfip (PAS) | C35: k€ | E35: 69813 | F35: 0 | G35: 0 | H35: 0 | I35: 0 | J35: 0 | K35: 0 | L35: 0 | M35: 0 | N35: 0 | O35: 0 | P35: 0 | R35: =SUM(E35:P35) -> 69813
B36: Total Salary & Social Charges | C36: k€ | E36: =SUM(E29:E35) -> 630138.94 | F36: =SUM(F29:F35) -> 0 | G36: =SUM(G29:G35) -> 0 | H36: =SUM(H29:H35) -> 0 | I36: =SUM(I29:I35) -> 0 | J36: =SUM(J29:J35) -> 0 | K36: =SUM(K29:K35) -> 0 | L36: =SUM(L29:L35) -> 0 | ... P36: =SUM(P29:P35) -> 0 | R36: =SUM(E36:P36) -> 630138.94
B38: Jetons de présence | C38: k€ | E38: 75500 | F38: 0 | G38: 0 | H38: 0 | I38: 0 | J38: 0 | K38: 0 | L38: 0 | M38: 0 | N38: 0 | O38: 0 | P38: 0 | R38: =SUM(E38:P38) -> 75500
B39: Forfait social jetons de présence (urssaf) | C39: k€ | E39: 0 | F39: 0 | G39: 0 | H39: 0 | I39: 0 | J39: 0 | K39: 0 | L39: 0 | M39: 0 | N39: 0 | O39: 0 | P39: 0 | R39: =SUM(E39:P39) -> 0
B40: Total jetons | C40: k€ | E40: =SUM(E38:E39) -> 75500 | F40: =SUM(F38:F39) -> 0 | G40: =SUM(G38:G39) -> 0 | H40: =SUM(H38:H39) -> 0 | I40: =SUM(I38:I39) -> 0 | J40: =SUM(J38:J39) -> 0 | K40: =SUM(K38:K39) -> 0 | L40: =SUM(L38:L39) -> 0 | ... P40: =SUM(P38:P39) -> 0 | R40: =SUM(E40:P40) -> 75500
B42: AGA MdG - Part patronale | C42: k€ | E42: 0 | F42: 0 | G42: 0 | H42: 0 | I42: 0 | J42: 0 | K42: 0 | L42: 0 | M42: 0 | N42: 0 | O42: 0 | P42: 0 | R42: =SUM(E42:P42) -> 0
B43: AGA MdG - Part patronale | C43: k€ | E43: 0
B44: AGA MdG -Remboursement MdG - Part salariales | C44: k€ | E44: -400704.4
B45: AGA Abivax SA (French employee) | C45: k€ | E45: 353002 | F45: 0 | G45: 0 | H45: 0 | I45: 0 | J45: 0 | K45: 0 | L45: 0 | M45: 0 | N45: 0 | O45: 0 | P45: 0 | R45: =SUM(E45:P45) -> 353002
B46: Total AGA | C46: k€ | E46: =SUM(E42:E45) -> -47702.4 | F46: =SUM(F42:F45) -> 0 | G46: =SUM(G42:G45) -> 0 | H46: =SUM(H42:H45) -> 0 | I46: =SUM(I42:I45) -> 0 | J46: =SUM(J42:J45) -> 0 | K46: =SUM(K42:K45) -> 0 | L46: =SUM(L42:L45) -> 0 | ... P46: =SUM(P42:P45) -> 0 | R46: =SUM(E46:P46) -> -47702.4
B48: Total HR related | C48: k€ | E48: =E46+E40+E36 -> 657936.54 | F48: =F46+F40+F36 -> 0 | G48: =G46+G40+G36 -> 0 | H48: =H46+H40+H36 -> 0 | I48: =I46+I40+I36 -> 0 | J48: =J46+J40+J36 -> 0 | K48: =K46+K40+K36 -> 0 | L48: =L46+L40+L36 -> 0 | ... P48: =P46+P40+P36 -> 0 | R48: =SUM(E48:P48) -> 657936.54
B50: RTC | C50: k€ | E50: 0 | F50: 0 | G50: 0 | H50: 0 | I50: 0 | J50: 0 | K50: 0 | L50: 0 | M50: 0 | N50: 0 | O50: 0 | P50: 0 | R50: =SUM(E50:P50) -> 0
B51: IQVIA advances | C51: k€
B52: BSA/BCE cash in | C52: k€ | E52: -22758.4 | F52: 0 | G52: 0 | H52: 0 | I52: 0 | J52: 0 | K52: 0 | L52: 0 | M52: 0 | N52: 0 | O52: 0 | P52: 0 | R52: =SUM(E52:P52) -> -22758.4
B53: Interets in | C53: k€ | E53: -38317.47 | F53: 0 | G53: 0 | H53: 0 | I53: 0 | J53: 0 | K53: 0 | L53: 0 | M53: 0 | N53: 0 | O53: 0 | P53: 0 | R53: =SUM(E53:P53) -> -38317.47
B54: Codéis interest in | C54: k€ | E54: -111686 | F54: 0 | G54: 0 | H54: 0 | I54: 0 | J54: 0 | K54: 0 | L54: 0 | M54: 0 | N54: 0 | O54: 0 | P54: 0 | R54: =SUM(E54:P54) -> -111686
B55: monthly value variation FCP (Ellipsis) | C55: k€ | E55: -200245.61 | F55: 0 | G55: 0 | H55: 0 | I55: 0 | J55: 0 | K55: 0 | L55: 0 | M55: 0 | N55: 0 | O55: 0 | P55: 0 | R55: =SUM(E55:P55) -> -200245.61
B57: Change USD-> EUR | E57: 0 | F57: 0 | G57: 0 | H57: 0 | I57: 0 | J57: 0 | K57: 0 | L57: 0 | M57: 0 | N57: 0 | O57: 0 | P57: 0 | R57: =SUM(E57:P57) -> 0
B59: Paid VAT | C59: k€ | E59: 3099119.4 | F59: 0 | G59: 0 | H59: 0 | I59: 0 | J59: 0 | K59: 0 | L59: 0 | M59: 0 | N59: 0 | O59: 0 | P59: 0 | R59: =SUM(E59:P59) -> 3099119.4
B60: received VAT | C60: k€ | E60: -2082692 | F60: 0 | G60: 0 | H60: 0 | I60: 0 | J60: 0 | K60: 0 | L60: 0 | M60: 0 | N60: 0 | O60: 0 | P60: 0 | R60: =SUM(E60:P60) -> -2082692
B62: Total | C62: k€ | E62: =+E48+E25+E20+SUM(E50:E55)+SUM(E59:E60)+E27 -> 16814728 | F62: =+F48+F25+F20+SUM(F50:F55)+SUM(F59:F60)+F27 -> 0 | G62: =+G48+G25+G20+SUM(G50:G55)+SUM(G59:G60)+G27 -> 0 | H62: =+H48+H25+H20+SUM(H50:H55)+SUM(H59:H60)+H27 -> 0 | I62: =+I48+I25+I20+SUM(I50:I55)+SUM(I59:I60)+I27 -> 0 | J62: =+J48+J25+J20+SUM(J50:J55)+SUM(J59:J60)+J27 -> 0 | K62: =+K48+K25+K20+SUM(K50:K55)+SUM(K59:K60)+K27 -> 0 | L62: =+L48+L25+L20+SUM(L50:L55)+SUM(L59:L60)+L27 -> 0 | ... P62: =+P48+P25+P20+SUM(P50:P55)+SUM(P59:P60)+P27 -> 0 | R62: =SUM(E62:P62) -> 16814728
R63: =R62/12 -> 1401227.3
B64: Balance SA-EUR - begining of month | C64: k€ | E64: 2.0489846e+08 | F64: =E65 -> 1.8808373e+08 | G64: =F65 -> 1.8808373e+08 | H64: =G65 -> 1.8808373e+08 | I64: =H65 -> 1.8808373e+08 | J64: =I65 -> 1.8808373e+08 | K64: =J65 -> 1.8808373e+08 | L64: =K65 -> 1.8808373e+08 | M64: =L65 -> 1.8808373e+08 | ... P64: =O65 -> 1.8808373e+08
B65: Balance SA-EUR - end of month | C65: k€ | E65: =E64-E62 -> 1.8808373e+08 | F65: =F64-F62 -> 1.8808373e+08 | G65: =G64-G62 -> 1.8808373e+08 | H65: =H64-H62 -> 1.8808373e+08 | I65: =I64-I62 -> 1.8808373e+08 | J65: =J64-J62 -> 1.8808373e+08 | K65: =K64-K62 -> 1.8808373e+08 | L65: =L64-L62 -> 1.8808373e+08 | ... P65: =P64-P62 -> 1.8808373e+08
B70: Abivax SA USD | E70: 46023 | F70: =EDATE(E70,1) -> 46054 | G70: =EDATE(F70,1) -> 46082 | H70: =EDATE(G70,1) -> 46113 | I70: =EDATE(H70,1) -> 46143 | J70: =EDATE(I70,1) -> 46174 | K70: =EDATE(J70,1) -> 46204 | L70: =EDATE(K70,1) -> 46235 | M70: =EDATE(L70,1) -> 46266 | ... P70: =EDATE(O70,1) -> 46357 | R70: 2026
B72: Other Suppliers (HT) | C72: k$ | E72: 1654185 | F72: 0 | G72: 0 | H72: 0 | I72: 0 | J72: 0 | K72: 0 | L72: 0 | M72: 0 | N72: 0 | O72: 0 | P72: 0 | R72: =SUM(E72:P72) -> 1654185
B73: Contractor (HT) | C73: k$ | E73: 462906.43 | F73: 0 | G73: 0 | H73: 0 | I73: 0 | J73: 0 | K73: 0 | L73: 0 | M73: 0 | N73: 0 | O73: 0 | P73: 0 | R73: =SUM(E73:P73) -> 462906.43
B74: Bank fees | C74: k$ | E74: 407.48 | F74: 0 | G74: 0 | H74: 0 | I74: 0 | J74: 0 | K74: 0 | L74: 0 | M74: 0 | N74: 0 | O74: 0 | P74: 0
B75: Citi cash in | C75: k$ | E75: 0 | F75: 0 | G75: 0 | H75: 0 | I75: 0 | J75: 0 | K75: 0 | L75: 0 | M75: 0 | N75: 0 | O75: 0 | P75: 0
B76: interests cash in | C76: k$ | E76: -4307.63 | F76: 0 | G76: 0 | H76: 0 | I76: 0 | J76: 0 | K76: 0 | L76: 0 | M76: 0 | N76: 0 | O76: 0 | P76: 0 | R76: =SUM(E76:P76) -> -4307.63
B77: Codéis interest in | C77: k$ | E77: -490769.4 | F77: 0 | G77: 0 | H77: 0 | I77: 0 | J77: 0 | K77: 0 | L77: 0 | M77: 0 | N77: 0 | O77: 0 | P77: 0
B78: Capital Raised | C78: k$ | E78: 0 | F78: 0 | G78: 0 | H78: 0 | I78: 0 | J78: 0 | K78: 0 | L78: 0 | M78: 0 | N78: 0 | O78: 0 | P78: 0
B79: Internal wire | C79: k$ | E79: 0 | F79: 0 | G79: 0 | H79: 0 | I79: 0 | J79: 0 | K79: 0 | L79: 0 | M79: 0 | N79: 0 | O79: 0 | P79: 0
B80: Change USD -> EUR | C80: k$ | E80: 0 | F80: 0 | G80: 0 | H80: 0 | I80: 0 | J80: 0 | K80: 0 | L80: 0 | M80: 0 | N80: 0 | O80: 0 | P80: 0
E81: =SUM(E72:E80) -> 1622421.9 | F81: =SUM(F72:F80) -> 0 | G81: =SUM(G72:G80) -> 0 | H81: =SUM(H72:H80) -> 0 | I81: =SUM(I72:I80) -> 0 | J81: =SUM(J72:J80) -> 0 | K81: =SUM(K72:K80) -> 0 | L81: =SUM(L72:L80) -> 0 | ... P81: =SUM(P72:P80) -> 0 | R81: =SUM(R72:R72) -> 1654185
B83: Abivax SA USD - Balance
B85: Balance SA-USD - begining of month | C85: k$ | E85: 1.8423633e+08 | F85: =E86 -> 1.8261391e+08 | G85: =F86 -> 1.8261391e+08 | H85: =G86 -> 1.8261391e+08 | I85: =H86 -> 1.8261391e+08 | J85: =I86 -> 1.8261391e+08 | K85: =J86 -> 1.8261391e+08 | L85: =K86 -> 1.8261391e+08 | M85: =L86 -> 1.8261391e+08 | ... P85: =O86 -> 1.8261391e+08
B86: Balance SA-USD - end of month | C86: k$ | E86: =E85-E81 -> 1.8261391e+08 | F86: =F85-F81 -> 1.8261391e+08 | G86: =G85-G81 -> 1.8261391e+08 | H86: =H85-H81 -> 1.8261391e+08 | I86: =I85-I81 -> 1.8261391e+08 | J86: =J85-J81 -> 1.8261391e+08 | K86: =K85-K81 -> 1.8261391e+08 | L86: =L85-L81 -> 1.8261391e+08 | ... P86: =P85-P81 -> 1.8261391e+08
B88: EUR-USD m-1 | C88: k$ | E88: 1.175 | F88: =E89 -> 1.1919 | G88: =F89 -> 1.18 | H88: =G89 -> 1.18 | I88: =H89 -> 1.18 | J88: =I89 -> 1.18 | K88: =J89 -> 1.18 | L88: =K89 -> 1.18 | M88: =L89 -> 1.18 | ... P88: =O89 -> 1.18
B89: EUR-USD m | C89: k$ | E89: 1.1919 | F89: 1.18 | G89: =G88 -> 1.18 | H89: =H88 -> 1.18 | I89: =I88 -> 1.18 | J89: =J88 -> 1.18 | K89: =K88 -> 1.18 | L89: =L88 -> 1.18 | M89: =M88 -> 1.18 | N89: =N88 -> 1.18 | ... P89: =P88 -> 1.18
B91: Balance SA-USD - begining of month | C91: k$ | E91: =E85/E88 -> 1.5679688e+08 | F91: =F85/F88 -> 1.5321244e+08 | G91: =G85/G88 -> 1.5475755e+08 | H91: =H85/H88 -> 1.5475755e+08 | I91: =I85/I88 -> 1.5475755e+08 | J91: =J85/J88 -> 1.5475755e+08 | K91: =K85/K88 -> 1.5475755e+08 | L91: =L85/L88 -> 1.5475755e+08 | ... P91: =P85/P88 -> 1.5475755e+08
B92: Balance SA-USD - end of month | C92: k$ | E92: =E86/E89 -> 1.5321244e+08 | F92: =F86/F89 -> 1.5475755e+08 | G92: =G86/G89 -> 1.5475755e+08 | H92: =H86/H89 -> 1.5475755e+08 | I92: =I86/I89 -> 1.5475755e+08 | J92: =J86/J89 -> 1.5475755e+08 | K92: =K86/K89 -> 1.5475755e+08 | L92: =L86/L89 -> 1.5475755e+08 | ... P92: =P86/P89 -> 1.5475755e+08
B99: Abivax SA EUR + USD
B101: Balance SA EUR-USD begining of month | C101: k€ | E101: =E91+E64 -> 3.6169533e+08 | F101: =F91+F64 -> 3.4129617e+08 | G101: =G91+G64 -> 3.4284128e+08 | H101: =H91+H64 -> 3.4284128e+08 | I101: =I91+I64 -> 3.4284128e+08 | J101: =J91+J64 -> 3.4284128e+08 | K101: =K91+K64 -> 3.4284128e+08 | L101: =L91+L64 -> 3.4284128e+08 | ... P101: =P91+P64 -> 3.4284128e+08
B102: Balance SA EUR-USD end of month | C102: k€ | E102: =E92+E65 -> 3.4129617e+08 | F102: =F92+F65 -> 3.4284128e+08 | G102: =G92+G65 -> 3.4284128e+08 | H102: =H92+H65 -> 3.4284128e+08 | I102: =I92+I65 -> 3.4284128e+08 | J102: =J92+J65 -> 3.4284128e+08 | K102: =K92+K65 -> 3.4284128e+08 | L102: =L92+L65 -> 3.4284128e+08 | ... P102: =P92+P65 -> 3.4284128e+08
B106: check SA €+USD-€ eq
B107: to add
B109: check SA €- € eq | E109: 3.4129617e+08 | F109: 0 | G109: 0 | H109: 0 | I109: 0 | J109: 0 | K109: 0 | L109: 0 | M109: 0 | N109: 0 | O109: 0 | P109: 0
B110: (from "analyse cash out", row 11 | E110: =E102-E109 -> 0.099494874 | F110: =F102-F109 -> 3.4284128e+08 | G110: =G102-G109 -> 3.4284128e+08 | H110: =H102-H109 -> 3.4284128e+08 | I110: =I102-I109 -> 3.4284128e+08 | J110: =J102-J109 -> 3.4284128e+08 | K110: =K102-K109 -> 3.4284128e+08 | L110: =L102-L109 -> 3.4284128e+08 | ... P110: =P102-P109 -> 3.4284128e+08
B112: check SA € - IFRS cash variation | E112: -16814728 | F112: 0 | G112: 0 | H112: 0 | I112: 0 | J112: 0 | K112: 0 | L112: 0 | M112: 0 | N112: 0 | O112: 0 | P112: 0
B113: (from "analyse cash out", row 18 | E113: =E62+E112 -> -0.0010119975 | F113: =F62+F112 -> 0 | G113: =G62+G112 -> 0 | H113: =H62+H112 -> 0 | I113: =I62+I112 -> 0 | J113: =J62+J112 -> 0 | K113: =K62+K112 -> 0 | L113: =L62+L112 -> 0 | ... P113: =P62+P112 -> 0
B115: check
B116: SA € | E116: 1.8808373e+08 | F116: 0 | G116: 0 | H116: 0 | I116: 0 | J116: 0 | K116: 0 | L116: 0 | M116: 0 | N116: 0 | O116: 0 | P116: 0
B117: (from "analyse cash out", row 17 | E117: =E116-E65 -> -0.099494845 | F117: =F116-F65 -> -1.8808373e+08 | G117: =G116-G65 -> -1.8808373e+08 | H117: =H116-H65 -> -1.8808373e+08 | I117: =I116-I65 -> -1.8808373e+08 | J117: =J116-J65 -> -1.8808373e+08 | K117: =K116-K65 -> -1.8808373e+08 | L117: =L116-L65 -> -1.8808373e+08 | ... P117: =P116-P65 -> -1.8808373e+08
B119: check
B120: SA $ | E120: 1.8261391e+08 | F120: 0 | G120: 0 | H120: 0 | I120: 0 | J120: 0 | K120: 0 | L120: 0 | M120: 0 | N120: 0 | O120: 0 | P120: 0
B121: (from "analyse cash out", row 46 | E121: =E120-E86 -> 0 | F121: =F120-F86 -> -1.8261391e+08 | G121: =G120-G86 -> -1.8261391e+08 | H121: =H120-H86 -> -1.8261391e+08 | I121: =I120-I86 -> -1.8261391e+08 | J121: =J120-J86 -> -1.8261391e+08 | K121: =K120-K86 -> -1.8261391e+08 | L121: =L120-L86 -> -1.8261391e+08 | ... P121: =P120-P86 -> -1.8261391e+08
B123: Total Interets (from "analyse cash out", row 66) | E123: 1282414.5 | F123: 0 | G123: 0 | H123: 0 | I123: 0 | J123: 0 | K123: 0 | L123: 0 | M123: 0 | N123: 0 | O123: 0 | P123: 0
B124: Total Interets SA + LLC (This file) | E124: =-(SUM(E53:E55)+SUM(E76:E77,'LLC actual'!E28)/ 'LLC actual'!E40) -> 1282599.6 | F124: =-(SUM(F53:F55)+SUM(F76:F77,'LLC actual'!F28)/ 'LLC actual'!F40) -> 0 | G124: =-(SUM(G53:G55)+SUM(G76:G77,'LLC actual'!G28)/ 'LLC actual'!G40) -> 0 | H124: =-(SUM(H53:H55)+SUM(H76:H77,'LLC actual'!H28)/ 'LLC actual'!H40) -> 0 | I124: =-(SUM(I53:I55)+SUM(I76:I77,'LLC actual'!I28)/ 'LLC actual'!I40) -> 0 | J124: =-(SUM(J53:J55)+SUM(J76:J77,'LLC actual'!J28)/ 'LLC actual'!J40) -> 0 | K124: =-(SUM(K53:K55)+SUM(K76:K77,'LLC actual'!K28)/ 'LLC actual'!K40) -> 0 | L124: =-(SUM(L53:L55)+SUM(L76:L77,'LLC actual'!L28)/ 'LLC actual'!L40) -> 0 | ... P124: =-(SUM(P53:P55)+SUM(P76:P77,'LLC actual'!P28)/ 'LLC actual'!P40) -> 0
B125: check = 0 | E125: =E124-E123 -> 185.02649 | F125: =F124-F123 -> 0 | G125: =G124-G123 -> 0 | H125: =H124-H123 -> 0 | I125: =I124-I123 -> 0 | J125: =J124-J123 -> 0 | K125: =K124-K123 -> 0 | L125: =L124-L123 -> 0 | ... P125: =P124-P123 -> 0
E126: >0 mais NS car en € (interets on deposit) | O126: =O125*O89 -> 0

Sheet LLC actual
E3: Cash Forecast - V budget
B6: Abivax LLC USD
E7: 46023 | F7: =EDATE(E7,1) -> 46054 | G7: =EDATE(F7,1) -> 46082 | H7: =EDATE(G7,1) -> 46113 | I7: =EDATE(H7,1) -> 46143 | J7: =EDATE(I7,1) -> 46174 | K7: =EDATE(J7,1) -> 46204 | L7: =EDATE(K7,1) -> 46235 | M7: =EDATE(L7,1) -> 46266 | ... P7: =EDATE(O7,1) -> 46357 | R7: 2026
B9: Amount are VAT excluded
B10: Other Suppliers € (HT) with 10% R/Adj. | C10: k$ | E10: 615407.3 | F10: 0 | G10: 0 | H10: 0 | I10: 0 | J10: 0 | K10: 0 | L10: 0 | M10: 0 | N10: 0 | O10: 0 | P10: 0 | R10: =SUM(E10:P10) -> 615407.3
B11: Contractor (HT) with 10% R/Adj. | C11: k$ | E11: 0 | F11: 0 | G11: 0 | H11: 0 | I11: 0 | J11: 0 | K11: 0 | L11: 0 | M11: 0 | N11: 0 | O11: 0 | P11: 0 | R11: =SUM(E11:P11) -> 0
B12: Bank fees | C12: k$ | E12: 1825.81 | F12: 0 | G12: 0 | H12: 0 | I12: 0 | J12: 0 | K12: 0 | L12: 0 | M12: 0 | N12: 0 | O12: 0 | P12: 0
B13: Suppliers + Contractos | C13: k$ | E13: =SUM(E10:E12) -> 617233.11 | F13: =SUM(F10:F12) -> 0 | G13: =SUM(G10:G12) -> 0 | H13: =SUM(H10:H12) -> 0 | I13: =SUM(I10:I12) -> 0 | J13: =SUM(J10:J12) -> 0 | K13: =SUM(K10:K12) -> 0 | L13: =SUM(L10:L12) -> 0 | ... P13: =SUM(P10:P12) -> 0 | R13: =SUM(E13:P13) -> 617233.11
B15: Payroll LLC (Salary) | C15: k$ | E15: 853284.16 | F15: 0 | G15: 0 | H15: 0 | I15: 0 | J15: 0 | K15: 0 | L15: 0 | M15: 0 | N15: 0 | O15: 0 | P15: 0 | R15: =SUM(E15:P15) -> 853284.16
B16: Payroll LLC (Charges) | C16: k$
B17: Bonus LLC (Gross) | C17: k$
B18: Bonus LLC (Charges) | C18: k$
B19: Total Salary & Social Charges | C19: k$ | E19: =SUM(E15:E18) -> 853284.16 | F19: =SUM(F15:F18) -> 0 | G19: =SUM(G15:G18) -> 0 | H19: =SUM(H15:H18) -> 0 | I19: =SUM(I15:I18) -> 0 | J19: =SUM(J15:J18) -> 0 | K19: =SUM(K15:K18) -> 0 | L19: =SUM(L15:L18) -> 0 | ... P19: =SUM(P15:P18) -> 0 | R19: =SUM(E19:P19) -> 853284.16
B22: AGA charges LLC | C22: k$ | E22: 10193888 | F22: 0 | G22: 0 | H22: 0 | I22: 0 | J22: 0 | K22: 0 | L22: 0 | M22: 0 | N22: 0 | O22: 0 | P22: 0 | R22: =SUM(E22:P22) -> 10193888
B23: AGA Uptevia STC | C23: k$ | E23: 0 | F23: 0 | G23: 0 | H23: 0 | I23: 0 | J23: 0 | K23: 0 | L23: 0 | M23: 0 | N23: 0 | O23: 0 | P23: 0
B24: Total AGA | C24: k$ | E24: =SUM(E22:E22) -> 10193888 | F24: =SUM(F22:F22) -> 0 | G24: =SUM(G22:G22) -> 0 | H24: =SUM(H22:H22) -> 0 | I24: =SUM(I22:I22) -> 0 | J24: =SUM(J22:J22) -> 0 | K24: =SUM(K22:K22) -> 0 | L24: =SUM(L22:L22) -> 0 | M24: =SUM(M22:M23) -> 0 | N24: =SUM(N22:N23) -> 0 | O24: =SUM(O22:O22) -> 0 | P24: =SUM(P22:P23) -> 0 | R24: =SUM(E24:P24) -> 10193888
B26: Total HR related | C26: k$ | E26: =E24+E19 -> 11047172 | F26: =F24+F19 -> 0 | G26: =G24+G19 -> 0 | H26: =H24+H19 -> 0 | I26: =I24+I19 -> 0 | J26: =J24+J19 -> 0 | K26: =K24+K19 -> 0 | L26: =L24+L19 -> 0 | ... P26: =P24+P19 -> 0 | R26: =SUM(E26:P26) -> 11047172
B28: Interets in | C28: k$ | E28: -600434.79 | F28: 0 | G28: 0 | H28: 0 | I28: 0 | J28: 0 | K28: 0 | L28: 0 | M28: 0 | N28: 0 | O28: 0 | P28: 0 | R28: =SUM(E28:P28) -> -600434.79
B29: Internal wire | C29: k$ | E29: 0 | F29: 0 | G29: 0 | H29: 0 | I29: 0 | J29: 0 | K29: 0 | L29: 0 | M29: 0 | N29: 0 | O29: 0 | P29: 0
B30: Deposit | C30: k$ | E30: 0 | F30: 0 | G30: 0 | H30: 0 | I30: 0 | J30: 0 | K30: 0 | L30: 0 | M30: 0 | N30: 0 | O30: 0 | P30: 0
B32: Total | C32: k$ | E32: =SUM(E28:E29,E24,E19,E13) -> 11063971 | F32: =SUM(F28:F29,F24,F19,F13) -> 0 | G32: =SUM(G28:G29,G24,G19,G13) -> 0 | H32: =SUM(H28:H29,H24,H19,H13) -> 0 | I32: =SUM(I28:I29,I24,I19,I13) -> 0 | J32: =SUM(J28:J29,J24,J19,J13) -> 0 | K32: =SUM(K28:K30,K24,K19,K13) -> 0 | L32: =SUM(L28:L30,L24,L19,L13) -> 0 | M32: =SUM(M28:M29,M24,M19,M13) -> 0 | N32: =SUM(N28:N29,N24,N19,N13) -> 0 | O32: =SUM(O28:O29,O24,O19,O13) -> 0 | P32: =SUM(P28:P29,P24,P19,P13) -> 0 | R32: =SUM(E32:P32) -> 11063971
R33: =R32/12 -> 921997.55
B35: Cash Balance - Abivax LLC - USD
B37: Balance LLC - USD - begining of month | C37: k$ | E37: 1.9794316e+08 | F37: =E38 -> 1.8687919e+08 | G37: =F38 -> 1.8687919e+08 | H37: =G38 -> 1.8687919e+08 | I37: =H38 -> 1.8687919e+08 | J37: =I38 -> 1.8687919e+08 | K37: =J38 -> 1.8687919e+08 | L37: =K38 -> 1.8687919e+08 | M37: =L38 -> 1.8687919e+08 | ... P37: =O38 -> 1.8687919e+08
B38: Balance LLC - USD - end of month | C38: k$ | E38: =E37-E32 -> 1.8687919e+08 | F38: =F37-F32 -> 1.8687919e+08 | G38: =G37-G32 -> 1.8687919e+08 | H38: =H37-H32 -> 1.8687919e+08 | I38: =I37-I32 -> 1.8687919e+08 | J38: =J37-J32 -> 1.8687919e+08 | K38: =K37-K32 -> 1.8687919e+08 | L38: =L37-L32 -> 1.8687919e+08 | ... P38: =P37-P32 -> 1.8687919e+08
B40: EUR-USD m-1 | C40: $ | E40: ='SA Actual'!E88 -> 1.175 | F40: ='SA Actual'!F88 -> 1.1919 | G40: ='SA Actual'!G88 -> 1.18 | H40: ='SA Actual'!H88 -> 1.18 | I40: ='SA Actual'!I88 -> 1.18 | J40: ='SA Actual'!J88 -> 1.18 | K40: ='SA Actual'!K88 -> 1.18 | L40: ='SA Actual'!L88 -> 1.18 | ... P40: ='SA Actual'!P88 -> 1.18
B41: EUR-USD m | C41: $ | E41: ='SA Actual'!E89 -> 1.1919 | F41: ='SA Actual'!F89 -> 1.18 | G41: ='SA Actual'!G89 -> 1.18 | H41: ='SA Actual'!H89 -> 1.18 | I41: ='SA Actual'!I89 -> 1.18 | J41: ='SA Actual'!J89 -> 1.18 | K41: ='SA Actual'!K89 -> 1.18 | L41: ='SA Actual'!L89 -> 1.18 | ... P41: ='SA Actual'!P89 -> 1.18
B45: Balance SA-USD - begining of month | C45: k€ | E45: =E37/E40 -> 1.6846226e+08 | F45: =F37/F40 -> 1.5679099e+08 | G45: =G37/G40 -> 1.5837219e+08 | H45: =H37/H40 -> 1.5837219e+08 | I45: =I37/I40 -> 1.5837219e+08 | J45: =J37/J40 -> 1.5837219e+08 | K45: =K37/K40 -> 1.5837219e+08 | L45: =L37/L40 -> 1.5837219e+08 | ... P45: =P37/P40 -> 1.5837219e+08
B46: Balance SA-USD - end of month | C46: k€ | E46: =E38/E41 -> 1.5679099e+08 | F46: =F38/F41 -> 1.5837219e+08 | G46: =G38/G41 -> 1.5837219e+08 | H46: =H38/H41 -> 1.5837219e+08 | I46: =I38/I41 -> 1.5837219e+08 | J46: =J38/J41 -> 1.5837219e+08 | K46: =K38/K41 -> 1.5837219e+08 | L46: =L38/L41 -> 1.5837219e+08 | ... P46: =P38/P41 -> 1.5837219e+08
B48: Balance SA-USD - begining of month | C48: k€ | E48: =E37/E41 -> 1.6607363e+08
B51: check | E51: 1.8687919e+08 | F51: 0 | G51: 0 | H51: 0 | I51: 0 | J51: 0 | K51: 0 | L51: 0 | M51: 0 | N51: 0 | O51: 0 | P51: 0
E52: =E38-E51 -> 0 | F52: =F38-F51 -> 1.8687919e+08 | G52: =G38-G51 -> 1.8687919e+08 | H52: =H38-H51 -> 1.8687919e+08 | I52: =I38-I51 -> 1.8687919e+08 | J52: =J38-J51 -> 1.8687919e+08 | K52: =K38-K51 -> 1.8687919e+08 | L52: =L38-L51 -> 1.8687919e+08 | ... P52: =P38-P51 -> 1.8687919e+08

Sheet Budget   ->

Sheet Consolidated Budget
B3: Abivax SA & LLC | E3: Cash Forecast - VBudget
B7: Abivax SA + LLC | E7: 46023 | F7: =EDATE(E7,1) -> 46054 | G7: =EDATE(F7,1) -> 46082 | H7: =EDATE(G7,1) -> 46113 | I7: =EDATE(H7,1) -> 46143 | J7: =EDATE(I7,1) -> 46174 | K7: =EDATE(J7,1) -> 46204 | L7: =EDATE(K7,1) -> 46235 | M7: =EDATE(L7,1) -> 46266 | ... P7: =EDATE(O7,1) -> 46357
B8: Balance SA -EUR+USD- begining of month | C8: k€ | E8: =E15+E19 -> 5.3015759e+08 | F8: =F15+F19 -> 5.1424281e+08 | G8: =G15+G19 -> 4.9302873e+08 | H8: =H15+H19 -> 4.8015354e+08 | I8: =I15+I19 -> 4.4716444e+08 | J8: =J15+J19 -> 4.2277816e+08 | K8: =K15+K19 -> 4.1045758e+08 | L8: =L15+L19 -> 3.9128657e+08 | ... P8: =P15+P19 -> 3.0928072e+08
B9: Balance SA -EUR+USD- begining of month | C9: k€ | E9: =E16+E20 -> 5.1424281e+08 | F9: =F16+F20 -> 4.9302873e+08 | G9: =G16+G20 -> 4.8015354e+08 | H9: =H16+H20 -> 4.4716444e+08 | I9: =I16+I20 -> 4.2277816e+08 | J9: =J16+J20 -> 4.1045758e+08 | K9: =K16+K20 -> 3.9128657e+08 | L9: =L16+L20 -> 3.6313273e+08 | ... P9: =P16+P20 -> 3.0454818e+08 | R9: =P9*1.16 -> 3.5327588e+08
B11: Variance | E11: =E9-E8 -> -15914782 | F11: =F9-F8 -> -21214077 | G11: =G9-G8 -> -12875195 | H11: =H9-H8 -> -32989102 | I11: =I9-I8 -> -24386281 | J11: =J9-J8 -> -12320576 | K11: =K9-K8 -> -19171010 | L11: =L9-L8 -> -28153839 | ... P11: =P9-P8 -> -4732544.2
B14: Abivax SA EUR + USD | E14: 46023 | F14: =EDATE(E14,1) -> 46054 | G14: =EDATE(F14,1) -> 46082 | H14: =EDATE(G14,1) -> 46113 | I14: =EDATE(H14,1) -> 46143 | J14: =EDATE(I14,1) -> 46174 | K14: =EDATE(J14,1) -> 46204 | L14: =EDATE(K14,1) -> 46235 | M14: =EDATE(L14,1) -> 46266 | ... P14: =EDATE(O14,1) -> 46357
B15: Balance SA-EUR - begining of month | C15: k€ | E15: ='SA budget'!E101 -> 3.6169533e+08 | F15: ='SA budget'!F101 -> 3.4497937e+08 | G15: ='SA budget'!G101 -> 3.3079352e+08 | H15: ='SA budget'!H101 -> 3.1936358e+08 | I15: ='SA budget'!I101 -> 2.87989e+08 | J15: ='SA budget'!J101 -> 2.65156e+08 | K15: ='SA budget'!K101 -> 2.543926e+08 | L15: ='SA budget'!L101 -> 2.3738007e+08 | ... P15: ='SA budget'!P101 -> 1.7040591e+08
B16: Balance SA-EUR - begining of month | C16: k€ | E16: ='SA budget'!E102 -> 3.4497937e+08 | F16: ='SA budget'!F102 -> 3.3079352e+08 | G16: ='SA budget'!G102 -> 3.1936358e+08 | H16: ='SA budget'!H102 -> 2.87989e+08 | I16: ='SA budget'!I102 -> 2.65156e+08 | J16: ='SA budget'!J102 -> 2.543926e+08 | K16: ='SA budget'!K102 -> 2.3738007e+08 | L16: ='SA budget'!L102 -> 2.1232225e+08 | ... P16: ='SA budget'!P102 -> 1.6933516e+08
B18: Abivax LLC USD expressed in EUR
B19: Balance SA-USD - begining of month | C19: k€ | E19: ='LLC Budget'!E45 -> 1.6846226e+08 | F19: ='LLC Budget'!F45 -> 1.6926344e+08 | G19: ='LLC Budget'!G45 -> 1.6223521e+08 | H19: ='LLC Budget'!H45 -> 1.6078996e+08 | I19: ='LLC Budget'!I45 -> 1.5917544e+08 | J19: ='LLC Budget'!J45 -> 1.5762215e+08 | K19: ='LLC Budget'!K45 -> 1.5606498e+08 | L19: ='LLC Budget'!L45 -> 1.539065e+08 | ... P19: ='LLC Budget'!P45 -> 1.3887481e+08
B20: Balance SA-USD - end of month | C20: k€ | E20: ='LLC Budget'!E46 -> 1.6926344e+08 | F20: ='LLC Budget'!F46 -> 1.6223521e+08 | G20: ='LLC Budget'!G46 -> 1.6078996e+08 | H20: ='LLC Budget'!H46 -> 1.5917544e+08 | I20: ='LLC Budget'!I46 -> 1.5762215e+08 | J20: ='LLC Budget'!J46 -> 1.5606498e+08 | K20: ='LLC Budget'!K46 -> 1.539065e+08 | L20: ='LLC Budget'!L46 -> 1.5081048e+08 | ... P20: ='LLC Budget'!P46 -> 1.3521301e+08
B25: Version présenté au board decembre
B35: Version présenté au board mars 'en cours"
B36: update 2025 : Cash (WCR+ 8 m€), P&L (-2 m€), RTC (-2 m€) -> +4 m€ ou + 4 m$
B46: non updated : 2026 : AGA

Sheet SA budget
B3: Abivax SA | E3: Cash Forecast - V budget
B6: Abivax SA EUR | E6: Forecast-Budget
E7: 46023 | F7: =EDATE(E7,1) -> 46054 | G7: =EDATE(F7,1) -> 46082 | H7: =EDATE(G7,1) -> 46113 | I7: =EDATE(H7,1) -> 46143 | J7: =EDATE(I7,1) -> 46174 | K7: =EDATE(J7,1) -> 46204 | L7: =EDATE(K7,1) -> 46235 | M7: =EDATE(L7,1) -> 46266 | ... P7: =EDATE(O7,1) -> 46357 | R7: 2026
B9: Amount are VAT excluded
B10: IQVIA 105 milestone | C10: k€ | E10: 0 | F10: 0 | G10: 0 | H10: 0 | I10: 0 | J10: 0 | K10: 2363322 | L10: 294998.69 | M10: 0 | N10: 0 | O10: 0 | P10: 0 | R10: =SUM(E10:P10) -> 2658320.7 | T10: 54 en cash versus 51 au budget : +3 m€
B11: IQVIA 105 PTC & IF & Q2 | C11: k€ | E11: 599166.48 | F11: 570621.62 | G11: 612797.98 | H11: 237810 | I11: 0 | J11: 0 | K11: 0 | L11: 0 | M11: 0 | N11: 0 | O11: 0 | P11: 0 | R11: =SUM(E11:P11) -> 2020396.1 | T11: milestone DBL 105 à ajouter au Reforecast : 2,4 m€
B12: IQVIA 106 milestone | C12: k€ | E12: 0 | F12: 0 | G12: 0 | H12: 0 | I12: 0 | J12: 0 | K12: 756326 | L12: 109002.94 | M12: 0 | N12: 0 | O12: 0 | P12: 0 | R12: =SUM(E12:P12) -> 865328.94 | T12: paiement janvier de facture de décembre 2025 + 10 m€ mais -9 m€ pour 107 (65% monitoring et PTC)
B13: IQVIA 106 PTC & IF & Q2 | C13: k€ | E13: 1246050.2 | F13: 467517.53 | G13: 619029.58 | H13: 237306 | I13: 224267 | J13: 0 | K13: 0 | L13: 0 | M13: 0 | N13: 0 | O13: 0 | P13: 0 | R13: =SUM(E13:P13) -> 2794170.4
B14: IQVIA 107 milestone | C14: k€ | E14: 4790962 | F14: 0 | G14: 0 | H14: 0 | I14: 7186443 | J14: 0 | K14: 0 | L14: 9581924 | M14: 0 | N14: 0 | O14: 7186443 | P14: 0 | R14: =SUM(E14:P14) -> 28745772
B15: IQVIA 107 PTC & IF & Q2 | C15: k€ | E15: 1814129.3 | F15: 1542238.5 | G15: 1125311.7 | H15: 978890 | I15: 650000 | J15: 650000 | K15: 0 | L15: 0 | M15: 0 | N15: 0 | O15: 0 | P15: 0 | R15: =SUM(E15:P15) -> 6760569.5
B16: IQVIA Ph3 - CO | C16: k€ | H16: 5000000 | I16: 2000000 | J16: 2000000 | K16: 1000000 | R16: =SUM(E16:P16) -> 10000000 | T16: Budget : 10,5 me CO4 Ph3 sur 2026
B17: IQVIA CD milestone | C17: k€ | E17: 1308382 | F17: 0 | G17: 1308382 | H17: 1308381.9 | I17: 1831734.7 | J17: 0 | K17: 2355087.5 | L17: 1570058.3 | M17: 1046705.6 | N17: 0 | O17: 1046705.6 | P17: 0 | R17: =SUM(E17:P17) -> 11775438 | T17: pourquoi 14 m€ versus 10 m€ au budget et 14 m€ sur couts projets
B18: IQVIA CD PTC & IF & Q2 | C18: k€ | E18: 214041.3 | F18: 301393.22 | G18: 0 | H18: 220000 | I18: 220000 | J18: 220000 | K18: 220000 | L18: 220000 | M18: 220000 | N18: 220000 | O18: 220000 | P18: 220000 | R18: =SUM(E18:P18) -> 2495434.5 | T18: réponse : -3m€ de FNP en janvier; +1 m€ de paiement jnvier et -1m€ factures dec 2026
B19: IQVIA CD -CO | C19: k€ | H19: 3000000 | I19: 375000 | J19: 375000 | K19: 375000 | L19: 375000 | M19: 375000 | N19: 375000 | O19: 375000 | P19: 375000 | R19: =SUM(E19:P19) -> 6000000 | T19: CO2 ! 6 m€ ppour 2026
B20: Total IQVIA | C20: k€ | E20: =SUM(E10:E19) -> 9972731.3 | F20: =SUM(F10:F19) -> 2881770.9 | G20: =SUM(G10:G19) -> 3665521.2 | H20: =SUM(H10:H19) -> 10982388 | I20: =SUM(I10:I19) -> 12487445 | J20: =SUM(J10:J19) -> 3245000 | K20: =SUM(K10:K19) -> 7069735.5 | L20: =SUM(L10:L19) -> 12150984 | ... P20: =SUM(P10:P19) -> 595000 | R20: =SUM(E20:P20) -> 74115430
B22: Other Suppliers € (HT) | C22: k€ | E22: ='Data Budget'!E61 -> 4718356.9 | F22: ='Data Budget'!F61 -> 4718356.9 | G22: ='Data Budget'!G61 -> 4718356.9 | H22: ='Data Budget'!H61 -> 4718356.9 | I22: ='Data Budget'!I61 -> 4596761.9 | J22: ='Data Budget'!J61 -> 4596761.9 | K22: ='Data Budget'!K61 -> 4596761.9 | L22: ='Data Budget'!L61 -> 4858617.1 | ... P22: ='Data Budget'!P61 -> 5128841.5 | R22: =SUM(E22:P22) -> 57497248
B23: Contractor (HT) | C23: k€ | E23: ='Data Budget'!E48 -> 416446.67 | F23: ='Data Budget'!F48 -> 416446.67 | G23: ='Data Budget'!G48 -> 416446.67 | H23: ='Data Budget'!H48 -> 416446.67 | I23: ='Data Budget'!I48 -> 431846.67 | J23: ='Data Budget'!J48 -> 431846.67 | K23: ='Data Budget'!K48 -> 431846.67 | L23: ='Data Budget'!L48 -> 431846.67 | ... P23: ='Data Budget'!P48 -> 420866.67 | R23: =SUM(E23:P23) -> 5098600
B24: Bank fees | C24: k€
B25: Suppliers + Contractos | C25: k€ | E25: =SUM(E22:E24) -> 5134803.5 | F25: =SUM(F22:F24) -> 5134803.5 | G25: =SUM(G22:G24) -> 5134803.5 | H25: =SUM(H22:H24) -> 5134803.5 | I25: =SUM(I22:I24) -> 5028608.5 | J25: =SUM(J22:J24) -> 5028608.5 | K25: =SUM(K22:K24) -> 5028608.5 | L25: =SUM(L22:L24) -> 5290463.8 | ... P25: =SUM(P22:P24) -> 5549708.2 | R25: =SUM(E25:P25) -> 62595848
B27: Capex | C27: k€ | H27: =1800000/9 -> 200000 | I27: =1800000/9 -> 200000 | J27: =1800000/9 -> 200000 | K27: =1800000/9 -> 200000 | L27: =1800000/9 -> 200000 | M27: =1800000/9 -> 200000 | N27: =1800000/9 -> 200000 | O27: =1800000/9 -> 200000 | P27: =1800000/9 -> 200000 | R27: =SUM(E27:P27) -> 1800000
B29: Salaire net aprés PAS | C29: k€ | E29: 296854.81 | F29: 296854.81 | G29: 296854.81 | H29: 296854.81 | I29: 296854.81 | J29: 296854.81 | K29: 296854.81 | L29: 296854.81 | M29: 296854.81 | N29: 296854.81 | O29: 296854.81 | P29: 296854.81 | R29: =SUM(E29:P29) -> 3562257.7
B30: Bonus net sans PAS | C30: k€ | F30: 662352.23 | J30: 277342.06 | R30: =SUM(E30:P30) -> 939694.29
B31: Urssaf | C31: k€ | E31: 213251.39 | F31: 213251.39 | G31: 689064.92 | H31: 213251.39 | I31: 213251.39 | J31: 213251.39 | K31: 412485.43 | L31: 213251.39 | M31: 213251.39 | N31: 213251.39 | O31: 213251.39 | P31: 213251.39 | R31: =SUM(E31:P31) -> 3234064.3
B32: Retraite | C32: k€ | E32: 93053.399 | F32: 93053.399 | G32: 300677.21 | H32: 93053.399 | I32: 93053.399 | J32: 93053.399 | K32: 179990.25 | L32: 93053.399 | M32: 93053.399 | N32: 93053.399 | O32: 93053.399 | P32: 93053.399 | R32: =SUM(E32:P32) -> 1411201.4
B33: Prévoyance | C33: k€ | E33: 25312.453 | H33: 44138.446 | K33: 25312.453 | N33: 25312.453 | R33: =SUM(E33:P33) -> 120075.81
B34: Mutuelle | C34: k€ | E34: 21985.674 | H34: 38337.393 | K34: 21985.674 | N34: 21985.674 | R34: =SUM(E34:P34) -> 104294.41
B35: Dgfip (PAS) | C35: k€ | E35: 80276.637 | F35: 80276.637 | G35: 259392.52 | H35: 80276.637 | I35: 80276.637 | J35: 80276.637 | K35: 155276.56 | L35: 80276.637 | M35: 80276.637 | N35: 80276.637 | O35: 80276.637 | P35: 80276.637 | R35: =SUM(E35:P35) -> 1217435.4
B36: Total Salary & Social Charges | C36: k€ | E36: =SUM(E29:E35) -> 730734.36 | F36: =SUM(F29:F35) -> 1345788.5 | G36: =SUM(G29:G35) -> 1545989.5 | H36: =SUM(H29:H35) -> 765912.07 | I36: =SUM(I29:I35) -> 683436.23 | J36: =SUM(J29:J35) -> 960778.3 | K36: =SUM(K29:K35) -> 1091905.2 | L36: =SUM(L29:L35) -> 683436.23 | ... P36: =SUM(P29:P35) -> 683436.23 | R36: =SUM(E36:P36) -> 10589023
B38: Jetons de présence | C38: k€ | J38: ='Data Budget'!F10/2 -> 385000 | P38: ='Data Budget'!F10/2 -> 385000 | R38: =SUM(E38:P38) -> 770000
B39: Forfait social jetons de présence (urssaf) | C39: k€ | E39: 77000 | K39: 90500 | R39: =SUM(E39:P39) -> 167500
B40: Total jetons | C40: k€ | E40: =SUM(E38:E39) -> 77000 | F40: =SUM(F38:F39) -> 0 | G40: =SUM(G38:G39) -> 0 | H40: =SUM(H38:H39) -> 0 | I40: =SUM(I38:I39) -> 0 | J40: =SUM(J38:J39) -> 385000 | K40: =SUM(K38:K39) -> 90500 | L40: =SUM(L38:L39) -> 0 | ... P40: =SUM(P38:P39) -> 385000 | R40: =SUM(E40:P40) -> 937500
B42: AGA MdG - Part patronales | C42: k€ | E42: 0 | F42: 274324.77 | G42: 0 | H42: 787709.15 | I42: 0 | J42: 0 | K42: 787709.15 | L42: 0 | M42: 0 | N42: 787709.15 | O42: 0 | P42: 787709.15 | R42: =SUM(E42:P42) -> 3425161.4
B43: AGA MdG - Part salariales | C43: k€ | E43: 0 | F43: 274324.77 | G43: 0 | H43: 787709.15 | I43: 0 | J43: 0 | K43: 787709.15 | L43: 0 | M43: 0 | N43: 787709.15 | O43: 0 | P43: 787709.15 | R43: =SUM(E43:P43) -> 3425161.4
B44: AGA MdG -Remboursement MdG - Part salariales | C44: k€ | E44: -400704.4 | F44: 0 | G44: 0 | H44: 0 | I44: 0 | J44: 0 | K44: 0 | L44: 0 | M44: 0 | N44: 0 | O44: 0 | P44: -3425161.4 | R44: =SUM(E44:P44) -> -3825865.8
B45: AGA Abivax SA (French employee) | C45: k€ | E45: 0 | F45: 352350 | G45: 0 | H45: 8715600 | I45: 210600 | J45: 0 | K45: 502200 | L45: 0 | M45: 252720 | N45: 0 | O45: 3997350 | P45: 0 | R45: =SUM(E45:P45) -> 14030820
B46: Total AGA | C46: k€ | E46: =SUM(E42:E45) -> -400704.4 | F46: =SUM(F42:F45) -> 900999.53 | G46: =SUM(G42:G45) -> 0 | H46: =SUM(H42:H45) -> 10291018 | I46: =SUM(I42:I45) -> 210600 | J46: =SUM(J42:J45) -> 0 | K46: =SUM(K42:K45) -> 2077618.3 | L46: =SUM(L42:L45) -> 0 | ... P46: =SUM(P42:P45) -> -1849743.1 | R46: =SUM(E46:P46) -> 17055277
B48: Total HR related | C48: k€ | E48: =E46+E40+E36 -> 407029.96 | F48: =F46+F40+F36 -> 2246788 | G48: =G46+G40+G36 -> 1545989.5 | H48: =H46+H40+H36 -> 11056930 | I48: =I46+I40+I36 -> 894036.23 | J48: =J46+J40+J36 -> 1345778.3 | K48: =K46+K40+K36 -> 3260023.5 | L48: =L46+L40+L36 -> 683436.23 | ... P48: =P46+P40+P36 -> -781306.84 | R48: =SUM(E48:P48) -> 28581800
B50: RTC | C50: k€ | M50: -5000000 | R50: =SUM(E50:P50) -> -5000000
B51: IQVIA advances | C51: k€ | P51: =-'Data Budget'!I101*10^6 -> -7739045.2
B52: BSA/BCE cash in | C52: k€
B53: Interets in | C53: k€ | E53: =-MAX(2%/12*AVERAGE(E64,E64-SUM(E20,E25,E48)),0) -> -328568.62 | F53: =-MAX(2%/12*AVERAGE(F64,F64-SUM(F20,F25,F48)),0) -> -306069.94 | G53: =-MAX(2%/12*AVERAGE(G64,G64-SUM(G20,G25,G48)),0) -> -286733.13 | H53: =-MAX(2%/12*AVERAGE(H64,H64-SUM(H20,H25,H48)),0) -> -258046.4 | I53: =-MAX(2%/12*AVERAGE(I64,I64-SUM(I20,I25,I48)),0) -> -217456.09 | J53: =-MAX(2%/12*AVERAGE(J64,J64-SUM(J20,J25,J48)),0) -> -191222.05 | K53: =-MAX(2%/12*AVERAGE(K64,K64-SUM(K20,K25,K48)),0) -> -173007.15 | L53: =-MAX(2%/12*AVERAGE(L64,L64-SUM(L20,L25,L48)),0) -> -146865.35 | ... P53: =-MAX(2%/12*AVERAGE(P64,P64-SUM(P20,P25,P48)),0) -> -76608.913 | R53: =SUM(E53:P53) -> -2324849.4
B54: Codéis interest in | C54: k€
B55: monthly value variation FCP (Ellipsis) | C55: k€
B59: Paid VAT | C59: k€ | E59: =20%*SUM(E25,E20) -> 3021507 | F59: =20%*SUM(F25,F20) -> 1603314.9 | G59: =20%*SUM(G25,G20) -> 1760065 | H59: =20%*SUM(H25,H20) -> 3223438.3 | I59: =20%*SUM(I25,I20) -> 3503210.7 | J59: =20%*SUM(J25,J20) -> 1654721.7 | K59: =20%*SUM(K25,K20) -> 2419668.8 | L59: =20%*SUM(L25,L20) -> 3488289.5 | ... P59: =20%*SUM(P25,P20) -> 1228941.6 | R59: =SUM(E59:P59) -> 27342255
B60: received VAT | C60: k€ | E60: -2082692 | F60: 0 | G60: =-E59 -> -3021507 | H60: =-F59 -> -1603314.9 | I60: =-G59 -> -1760065 | J60: =-H59 -> -3223438.3 | K60: =-I59 -> -3503210.7 | L60: =-J59 -> -1654721.7 | M60: =-K59 -> -2419668.8 | N60: =-L59 -> -3488289.5 | ... P60: =-N59 -> -1177092.8 | R60: =SUM(E60:P60) -> -25320434
B62: Total | C62: k€ | E62: =+E48+E25+E20+SUM(E50:E55)+SUM(E59:E60)+E27 -> 16124811 | F62: =+F48+F25+F20+SUM(F50:F55)+SUM(F59:F60)+F27 -> 11560607 | G62: =+G48+G25+G20+SUM(G50:G55)+SUM(G59:G60)+G27 -> 8798139.1 | H62: =+H48+H25+H20+SUM(H50:H55)+SUM(H59:H60)+H27 -> 28736199 | I62: =+I48+I25+I20+SUM(I50:I55)+SUM(I59:I60)+I27 -> 20135779 | J62: =+J48+J25+J20+SUM(J50:J55)+SUM(J59:J60)+J27 -> 8059448.2 | K62: =+K48+K25+K20+SUM(K50:K55)+SUM(K59:K60)+K27 -> 14301819 | L62: =+L48+L25+L20+SUM(L50:L55)+SUM(L59:L60)+L27 -> 20011586 | ... P62: =+P48+P25+P20+SUM(P50:P55)+SUM(P59:P60)+P27 -> -2200403.9 | R62: =SUM(E62:P62) -> 1.54051e+08
R63: =R62/12 -> 12837584
B64: Balance SA-EUR - begining of month | C64: k€ | E64: 2.0489846e+08 | F64: =E65 -> 1.8877365e+08 | G64: =F65 -> 1.7721304e+08 | H64: =G65 -> 1.684149e+08 | I64: =H65 -> 1.396787e+08 | J64: =I65 -> 1.1954292e+08 | K64: =J65 -> 1.1148347e+08 | L64: =K65 -> 97181654 | M64: =L65 -> 77170067 | ... P64: =O65 -> 48647048
B65: Balance SA-EUR - end of month | C65: k€ | E65: =E64-E62 -> 1.8877365e+08 | F65: =F64-F62 -> 1.7721304e+08 | G65: =G64-G62 -> 1.684149e+08 | H65: =H64-H62 -> 1.396787e+08 | I65: =I64-I62 -> 1.1954292e+08 | J65: =J64-J62 -> 1.1148347e+08 | K65: =K64-K62 -> 97181654 | L65: =L64-L62 -> 77170067 | ... P65: =P64-P62 -> 50847452
B70: Abivax SA USD | E70: 46023 | F70: =EDATE(E70,1) -> 46054 | G70: =EDATE(F70,1) -> 46082 | H70: =EDATE(G70,1) -> 46113 | I70: =EDATE(H70,1) -> 46143 | J70: =EDATE(I70,1) -> 46174 | K70: =EDATE(J70,1) -> 46204 | L70: =EDATE(K70,1) -> 46235 | M70: =EDATE(L70,1) -> 46266 | ... P70: =EDATE(O70,1) -> 46357 | R70: 2025
B72: Other Suppliers (HT) | C72: k$ | E72: ='Data Budget'!E69 -> 2652656.2 | F72: ='Data Budget'!F69 -> 2652656.2 | G72: ='Data Budget'!G69 -> 2652656.2 | H72: ='Data Budget'!H69 -> 2652656.2 | I72: ='Data Budget'!I69 -> 2692903.8 | J72: ='Data Budget'!J69 -> 2692903.8 | K72: ='Data Budget'!K69 -> 2692903.8 | L72: ='Data Budget'!L69 -> 5399665.4 | ... P72: ='Data Budget'!P69 -> 3292479.8 | R72: =SUM(E72:P72) -> 41473292 | S72: usd
B73: Contractor (HT) | C73: k$ | E73: ='Data Budget'!E47 -> 841253.33 | F73: ='Data Budget'!F47 -> 841253.33 | G73: ='Data Budget'!G47 -> 841253.33 | H73: ='Data Budget'!H47 -> 841253.33 | I73: ='Data Budget'!I47 -> 861520 | J73: ='Data Budget'!J47 -> 861520 | K73: ='Data Budget'!K47 -> 861520 | L73: ='Data Budget'!L47 -> 852720 | ... P73: ='Data Budget'!P47 -> 849973.33 | R73: =SUM(E73:P73) -> 10207680
B74: Bank fees | C74: k$
B75: Citi cash in | C75: k$
B76: interests cash in | C76: k$ | E76: =-MAX(3%/12*AVERAGE(E85,E85-SUM(E72:E73)),0) -> -456223.44 | F76: =-MAX(3%/12*AVERAGE(F85,F85-SUM(F72:F73)),0) -> -448629.22 | G76: =-MAX(3%/12*AVERAGE(G85,G85-SUM(G72:G73)),0) -> -441016.02 | H76: =-MAX(3%/12*AVERAGE(H85,H85-SUM(H72:H73)),0) -> -433383.79 | I76: =-MAX(3%/12*AVERAGE(I85,I85-SUM(I72:I73)),0) -> -425656.83 | J76: =-MAX(3%/12*AVERAGE(J85,J85-SUM(J72:J73)),0) -> -417834.91 | K76: =-MAX(3%/12*AVERAGE(K85,K85-SUM(K72:K73)),0) -> -409993.44 | L76: =-MAX(3%/12*AVERAGE(L85,L85-SUM(L72:L73)),0) -> -398759.91 | ... P76: =-MAX(3%/12*AVERAGE(P85,P85-SUM(P72:P73)),0) -> -347922.62 | R76: =SUM(E76:P76) -> -4890386.5
B77: Codéis interest in | C77: k$
B78: Internal wire | C78: k$
B79: Capital Raised | C79: k$
B80: Change USD -> EUR | C80: k$
E81: =SUM(E72:E76) -> 3037686.1 | F81: =SUM(F72:F76) -> 3045280.3 | G81: =SUM(G72:G76) -> 3052893.5 | H81: =SUM(H72:H76) -> 3060525.8 | I81: =SUM(I72:I76) -> 3128767 | J81: =SUM(J72:J76) -> 3136588.9 | K81: =SUM(K72:K76) -> 3144430.4 | L81: =SUM(L72:L76) -> 5853625.5 | ... P81: =SUM(P72:P76) -> 3794530.6 | R81: =SUM(R72:R72) -> 41473292 | S81: eur
B83: Abivax SA USD- Balance
B85: Balance SA-USD - begining of month | C85: k$ | E85: 1.8423633e+08 | F85: =E86 -> 1.8119864e+08 | G85: =F86 -> 1.7815336e+08 | H85: =G86 -> 1.7510047e+08 | I85: =H86 -> 1.7203994e+08 | J85: =I86 -> 1.6891118e+08 | K85: =J86 -> 1.6577459e+08 | L85: =K86 -> 1.6263016e+08 | M85: =L86 -> 1.5677653e+08 | ... P85: =O86 -> 1.4124028e+08
B86: Balance SA-USD - end of month | C86: k$ | E86: =E85-E81 -> 1.8119864e+08 | F86: =F85-F81 -> 1.7815336e+08 | G86: =G85-G81 -> 1.7510047e+08 | H86: =H85-H81 -> 1.7203994e+08 | I86: =I85-I81 -> 1.6891118e+08 | J86: =J85-J81 -> 1.6577459e+08 | K86: =K85-K81 -> 1.6263016e+08 | L86: =L85-L81 -> 1.5677653e+08 | ... P86: =P85-P81 -> 1.3744574e+08 | R86: =P86+'LLC Budget'!P38 -> 2.9429284e+08
B88: EUR-USD m-1 | C88: k$ | E88: 1.175 | F88: 1.16 | G88: 1.16 | H88: 1.16 | I88: 1.16 | J88: 1.16 | K88: 1.16 | L88: 1.16 | M88: 1.16 | N88: 1.16 | O88: 1.16 | P88: 1.16
B89: EUR-USD m | C89: k$ | E89: 1.16 | F89: 1.16 | G89: 1.16 | H89: 1.16 | I89: 1.16 | J89: 1.16 | K89: 1.16 | L89: 1.16 | M89: 1.16 | N89: 1.16 | O89: 1.16 | P89: 1.16
B91: Balance SA-USD - begining of month | C91: k$ | E91: =E85/E88 -> 1.5679688e+08 | F91: =F85/F88 -> 1.5620573e+08 | G91: =G85/G88 -> 1.5358049e+08 | H91: =H85/H88 -> 1.5094868e+08 | I91: =I85/I88 -> 1.483103e+08 | J91: =J85/J88 -> 1.4561308e+08 | K91: =K85/K88 -> 1.4290913e+08 | L91: =L85/L88 -> 1.4019841e+08 | ... P91: =P85/P88 -> 1.2175886e+08
B92: Balance SA-USD - end of month | C92: k$ | E92: =E86/E89 -> 1.5620573e+08 | F92: =F86/F89 -> 1.5358049e+08 | G92: =G86/G89 -> 1.5094868e+08 | H92: =H86/H89 -> 1.483103e+08 | I92: =I86/I89 -> 1.4561308e+08 | J92: =J86/J89 -> 1.4290913e+08 | K92: =K86/K89 -> 1.4019841e+08 | L92: =L86/L89 -> 1.3515218e+08 | ... P92: =P86/P89 -> 1.1848771e+08
B99: Abivax SA EUR + USD
B101: Balance SA-USD - begining of month | C101: k€ | E101: =E91+E64 -> 3.6169533e+08 | F101: =F91+F64 -> 3.4497937e+08 | G101: =G91+G64 -> 3.3079352e+08 | H101: =H91+H64 -> 3.1936358e+08 | I101: =I91+I64 -> 2.87989e+08 | J101: =J91+J64 -> 2.65156e+08 | K101: =K91+K64 -> 2.543926e+08 | L101: =L91+L64 -> 2.3738007e+08 | ... P101: =P91+P64 -> 1.7040591e+08
B102: Balance SA-USD - end of month | C102: k€ | E102: =E92+E65 -> 3.4497937e+08 | F102: =F92+F65 -> 3.3079352e+08 | G102: =G92+G65 -> 3.1936358e+08 | H102: =H92+H65 -> 2.87989e+08 | I102: =I92+I65 -> 2.65156e+08 | J102: =J92+J65 -> 2.543926e+08 | K102: =K92+K65 -> 2.3738007e+08 | L102: =L92+L65 -> 2.1232225e+08 | ... P102: =P92+P65 -> 1.6933516e+08

Sheet LLC Budget
E3: Cash Forecast - V budget
B6: Abivax LLC USD
E7: 46023 | F7: =EDATE(E7,1) -> 46054 | G7: =EDATE(F7,1) -> 46082 | H7: =EDATE(G7,1) -> 46113 | I7: =EDATE(H7,1) -> 46143 | J7: =EDATE(I7,1) -> 46174 | K7: =EDATE(J7,1) -> 46204 | L7: =EDATE(K7,1) -> 46235 | M7: =EDATE(L7,1) -> 46266 | ... P7: =EDATE(O7,1) -> 46357 | R7: 2026
B9: Amount are VAT excluded
B10: Other Suppliers € (HT) | C10: k$ | E10: ='Data Budget'!E79 -> 945918.42 | F10: ='Data Budget'!F79 -> 945918.42 | G10: ='Data Budget'!G79 -> 945918.42 | H10: ='Data Budget'!H79 -> 945918.42 | I10: ='Data Budget'!I79 -> 870303.42 | J10: ='Data Budget'!J79 -> 870303.42 | K10: ='Data Budget'!K79 -> 870303.42 | L10: ='Data Budget'!L79 -> 2552403.4 | ... P10: ='Data Budget'!P79 -> 2666531.4 | R10: =SUM(E10:P10) -> 19384857
B11: Contractor (HT) | C11: k$ | E11: ='Data Budget'!E46 -> 112000 | F11: ='Data Budget'!F46 -> 112000 | G11: ='Data Budget'!G46 -> 112000 | H11: ='Data Budget'!H46 -> 112000 | I11: ='Data Budget'!I46 -> 112000 | J11: ='Data Budget'!J46 -> 112000 | K11: ='Data Budget'!K46 -> 112000 | L11: ='Data Budget'!L46 -> 112000 | ... P11: ='Data Budget'!P46 -> 112000 | R11: =SUM(E11:P11) -> 1344000
B12: Bank fees | C12: k$
B13: Suppliers + Contractos | C13: k$ | E13: =E11+E10 -> 1057918.4 | F13: =F11+F10 -> 1057918.4 | G13: =G11+G10 -> 1057918.4 | H13: =H11+H10 -> 1057918.4 | I13: =I11+I10 -> 982303.42 | J13: =J11+J10 -> 982303.42 | K13: =K11+K10 -> 982303.42 | L13: =L11+L10 -> 2664403.4 | ... P13: =P11+P10 -> 2778531.4 | R13: =SUM(E13:P13) -> 20728857
B15: Payroll LLC (Salary) | C15: k$ | E15: 893415.14 | F15: 893415.14 | G15: 893415.14 | H15: 1106748.5 | I15: 1106748.5 | J15: 1106748.5 | K15: 1184650.9 | L15: 1184650.9 | M15: 1184650.9 | N15: 1495900.9 | O15: 1495900.9 | P15: 1495900.9 | R15: =SUM(E15:P15) -> 14042146
B16: Payroll LLC (Charges) | C16: k$ | E16: 138479.35 | F16: 138479.35 | G16: 138479.35 | H16: 171546.01 | I16: 171546.01 | J16: 171546.01 | K16: 183620.89 | L16: 183620.89 | M16: 183620.89 | N16: 231864.64 | O16: 231864.64 | P16: 231864.64 | R16: =SUM(E16:P16) -> 2176532.7
B17: Bonus LLC (Gross) | C17: k$ | F17: 3740926.2 | R17: =SUM(E17:P17) -> 3740926.2
B18: Bonus LLC (Charges) | C18: k$ | F18: 579843.56 | R18: =SUM(E18:P18) -> 579843.56
B19: Total Salary & Social Charges | C19: k$ | E19: =SUM(E15:E18) -> 1031894.5 | F19: =SUM(F15:F18) -> 5352664.2 | G19: =SUM(G15:G18) -> 1031894.5 | H19: =SUM(H15:H18) -> 1278294.5 | I19: =SUM(I15:I18) -> 1278294.5 | J19: =SUM(J15:J18) -> 1278294.5 | K19: =SUM(K15:K18) -> 1368271.8 | L19: =SUM(L15:L18) -> 1368271.8 | ... P19: =SUM(P15:P18) -> 1727765.5 | R19: =SUM(E19:P19) -> 20539449
B22: AGA Abivax SA (US employee) | C22: k$ | E22: 0 | F22: 2222235 | G22: 54480.6 | H22: 0 | I22: 0 | J22: 0 | K22: 602154 | L22: 0 | M22: 2168614.6 | N22: 0 | O22: 0 | P22: 138323.38 | R22: =SUM(E22:P22) -> 5185807.6
B23: AGA Uptevia STC | C23: k$
B24: Total AGA | C24: k$ | E24: =SUM(E22:E22) -> 0 | F24: =SUM(F22:F22) -> 2222235 | G24: =SUM(G22:G22) -> 54480.6 | H24: =SUM(H22:H22) -> 0 | I24: =SUM(I22:I22) -> 0 | J24: =SUM(J22:J22) -> 0 | K24: =SUM(K22:K22) -> 602154 | L24: =SUM(L22:L22) -> 0 | ... P24: =SUM(P22:P22) -> 138323.38 | R24: =SUM(E24:P24) -> 5185807.6
B26: Total HR related | C26: k$ | E26: =E24+E19 -> 1031894.5 | F26: =F24+F19 -> 7574899.2 | G26: =G24+G19 -> 1086375.1 | H26: =H24+H19 -> 1278294.5 | I26: =I24+I19 -> 1278294.5 | J26: =J24+J19 -> 1278294.5 | K26: =K24+K19 -> 1970425.8 | L26: =L24+L19 -> 1368271.8 | ... P26: =P24+P19 -> 1866088.9 | R26: =SUM(E26:P26) -> 25725256
B28: Interets in | C28: k$ | E28: =-MAX(3%/12*AVERAGE(E37,E37-SUM(E26,E13)),0) -> -492245.62 | F28: =-MAX(3%/12*AVERAGE(F37,F37-SUM(F26,F13)),0) -> -480072.95 | G28: =-MAX(3%/12*AVERAGE(G37,G37-SUM(G26,G13)),0) -> -467801.74 | H28: =-MAX(3%/12*AVERAGE(H37,H37-SUM(H26,H13)),0) -> -463370.62 | I28: =-MAX(3%/12*AVERAGE(I37,I37-SUM(I26,I13)),0) -> -458783.03 | J28: =-MAX(3%/12*AVERAGE(J37,J37-SUM(J26,J13)),0) -> -454278.49 | K28: =-MAX(3%/12*AVERAGE(K37,K37-SUM(K26,K13)),0) -> -448897.53 | L28: =-MAX(3%/12*AVERAGE(L37,L37-SUM(L26,L13)),0) -> -441288.02 | ... P28: =-MAX(3%/12*AVERAGE(P37,P37-SUM(P26,P13)),0) -> -396931.18 | R28: =SUM(E28:P28) -> -5358050.4
B29: Internal wire | C29: k$ | R29: =SUM(E29:P29) -> 0
B30: Deposit | C30: k$ | R30: =SUM(E30:P30) -> 0
B32: Total | C32: k$ | E32: =SUM(E28:E29,E24,E19,E13) -> 1597567.3 | F32: =SUM(F28:F29,F24,F19,F13) -> 8152744.7 | G32: =SUM(G28:G29,G24,G19,G13) -> 1676491.8 | H32: =SUM(H28:H29,H24,H19,H13) -> 1872842.3 | I32: =SUM(I28:I29,I24,I19,I13) -> 1801814.9 | J32: =SUM(J28:J29,J24,J19,J13) -> 1806319.4 | K32: =SUM(K28:K29,K24,K19,K13) -> 2503831.7 | L32: =SUM(L28:L29,L24,L19,L13) -> 3591387.2 | ... P32: =SUM(P28:P29,P24,P19,P13) -> 4247689.1 | R32: =SUM(E32:P32) -> 41096063
R33: =R32/12 -> 3424671.9
B35: Cash Balance - Abivax LLC
B37: Balance LLC - USD - begining of month | C37: k$ | E37: 1.9794316e+08 | F37: =E38 -> 1.9634559e+08 | G37: =F38 -> 1.8819284e+08 | H37: =G38 -> 1.8651635e+08 | I37: =H38 -> 1.8464351e+08 | J37: =I38 -> 1.828417e+08 | K37: =J38 -> 1.8103538e+08 | L37: =K38 -> 1.7853154e+08 | M37: =L38 -> 1.7494016e+08 | ... P37: =O38 -> 1.6109478e+08
B38: Balance LLC - USD - end of month | C38: k$ | E38: =E37-E32 -> 1.9634559e+08 | F38: =F37-F32 -> 1.8819284e+08 | G38: =G37-G32 -> 1.8651635e+08 | H38: =H37-H32 -> 1.8464351e+08 | I38: =I37-I32 -> 1.828417e+08 | J38: =J37-J32 -> 1.8103538e+08 | K38: =K37-K32 -> 1.7853154e+08 | L38: =L37-L32 -> 1.7494016e+08 | ... P38: =P37-P32 -> 1.5684709e+08
B40: EUR-USD m-1 | C40: $ | E40: ='SA budget'!E88 -> 1.175 | F40: ='SA budget'!F88 -> 1.16 | G40: ='SA budget'!G88 -> 1.16 | H40: ='SA budget'!H88 -> 1.16 | I40: ='SA budget'!I88 -> 1.16 | J40: ='SA budget'!J88 -> 1.16 | K40: ='SA budget'!K88 -> 1.16 | L40: ='SA budget'!L88 -> 1.16 | ... P40: ='SA budget'!P88 -> 1.16
B41: EUR-USD m | C41: $ | E41: ='SA budget'!E89 -> 1.16 | F41: ='SA budget'!F89 -> 1.16 | G41: ='SA budget'!G89 -> 1.16 | H41: ='SA budget'!H89 -> 1.16 | I41: ='SA budget'!I89 -> 1.16 | J41: ='SA budget'!J89 -> 1.16 | K41: ='SA budget'!K89 -> 1.16 | L41: ='SA budget'!L89 -> 1.16 | ... P41: ='SA budget'!P89 -> 1.16
B43: Cash Balance - Abivax LLC expressed in EUR
B45: Balance SA-USD - begining of month | C45: k€ | E45: =E37/E40 -> 1.6846226e+08 | F45: =F37/F40 -> 1.6926344e+08 | G45: =G37/G40 -> 1.6223521e+08 | H45: =H37/H40 -> 1.6078996e+08 | I45: =I37/I40 -> 1.5917544e+08 | J45: =J37/J40 -> 1.5762215e+08 | K45: =K37/K40 -> 1.5606498e+08 | L45: =L37/L40 -> 1.539065e+08 | ... P45: =P37/P40 -> 1.3887481e+08
B46: Balance SA-USD - end of month | C46: k€ | E46: =E38/E41 -> 1.6926344e+08 | F46: =F38/F41 -> 1.6223521e+08 | G46: =G38/G41 -> 1.6078996e+08 | H46: =H38/H41 -> 1.5917544e+08 | I46: =I38/I41 -> 1.5762215e+08 | J46: =J38/J41 -> 1.5606498e+08 | K46: =K38/K41 -> 1.539065e+08 | L46: =L38/L41 -> 1.5081048e+08 | ... P46: =P38/P41 -> 1.3521301e+08

Sheet Data Budget
C1: EURUSD - Budget | D1: =1/1.16 -> 0.86206897
B3: Verification
F4: Budget
C5: Contractors | D5: French + LLC | E5: EUR | F5: =SUM(M39:M41) -> 15068882
C6: ALL Suppliers without IQVIA/Contractors/Jetons | D6: French-EUR | E6: EUR | F6: =J56 -> 57907732 | I6: Explications
C7: IQVIA | D7: French | E7: EUR | F7: 67563871 | G7: ='SA budget'!R20 -> 74115430 | H7: =G7-F7 -> 6551559 | I7: 3m€ extourne FNP, 1 m€ dépenses janvier/dece, +2,4 milestone 105
C8: ALL Suppliers without contractors | D8: French-USD | E8: EUR | F8: =J65*D1 -> 36304410
C9: ALL Suppliers without contractors | D9: LLC | E9: EUR | F9: =J74*D1 -> 18194371
C10: Jetons | D10: French | E10: EUR | F10: 770000 | G10: ='SA budget'!R40 -> 937500 | H10: 905 k€ versus 770 k€, et charges sociales | L10: charges sociales forfait social intégré au budget ?
C11: Non cash | D11: French | E11: N/A | F11: 286677.12
C12: Non cash | D12: LLC | E12: N/A | F12: 34482.759
C14: Total Suppliers | D14: French + LLC | E14: EUR | F14: =SUM(F5:F12) -> 1.9613043e+08
F15: 1.9613043e+08
F16: =F14-F15 -> 0
C17: Budget 2026 FTE - SA | E17: EUR | F17: 10529171 | G17: ='SA budget'!R36 -> 10589023
C18: Budget 2026 FTE - LLC | E18: EUR | F18: 17706421 | G18: ='LLC Budget'!R19 -> 20539449
C19: Budget 2026 AGA LLC | D19: EUR | E19: EUR | F19: 9373187.6 | G19: ='LLC Budget'!R24 -> 5185807.6
C20: Budget 2026 AGA SA | E20: EUR | F20: 30886028 | G20: ='SA budget'!R46 -> 17055277
C22: Total budget 2026 (avec ce fichier) | F22: =F14+SUM(F17:F20) -> 2.6462523e+08 | H22: 265 m€
B25: Abivax SA
C26: IQVIA
C27: Source :
C28: IQVIA Vision Summary Reforecast 20260223
C29: Done with Clinical Trial follow-up and budget for CO impact
C30: CO impact :
C31: RD - Clinical_budget 2026-NBE 10.11update
B33: Source : Suppliers SA EUR-USD et LLC-USD - vBudget
B34: Abivax SA & LLC
C36: Contractors
C37: Budget by quarter
B38: Entity | C38: P&L | D38: Devise | E38: Q1 2026 | F38: Q2 2026 | G38: Q3 2026 | H38: Q4 2026 | J38: 2026 | K38: Monthly | M38: en EUR | P38: Source :
B39: LLC | C39: Contractors USD | D39: USD | E39: 336000 | F39: 336000 | G39: 336000 | H39: 336000 | J39: =SUM(E39:H39) -> 1344000 | K39: =J39/12 -> 112000 | M39: =J39*D1 -> 1158620.7 | P39: Suppliers SA EUR-USD et LLC-USD -vBudget 2026
B40: French | C40: Contractors USD | D40: USD | E40: 2523760 | F40: 2584560 | G40: 2558160 | H40: 2549920 | J40: =SUM(E40:H40) -> 10216400 | K40: =J40/12 -> 851366.67 | M40: =J40*D1 -> 8807241.4
B41: French | C41: Contractors EUR | D41: EUR | E41: 1249340 | F41: 1295540 | G41: 1295540 | H41: 1262600 | J41: =SUM(E41:H41) -> 5103020 | K41: =J41/12 -> 425251.67 | M41: =J41 -> 5103020 | N41: =SUM(M39:M41) -> 15068882
C45: monthly | E45: 46023 | F45: =EDATE(E45,1) -> 46054 | G45: =EDATE(F45,1) -> 46082 | H45: =EDATE(G45,1) -> 46113 | I45: =EDATE(H45,1) -> 46143 | J45: =EDATE(I45,1) -> 46174 | K45: =EDATE(J45,1) -> 46204 | L45: =EDATE(K45,1) -> 46235 | M45: =EDATE(L45,1) -> 46266 | ... P45: =EDATE(O45,1) -> 46357 | R45: Total | S45: check (negligeable)
B46: LLC | C46: Contractors USD-LLC | D46: USD | E46: =E39/3 -> 112000 | F46: =E46 -> 112000 | G46: =F46 -> 112000 | H46: =G46 -> 112000 | I46: =F39/3 -> 112000 | J46: =I46 -> 112000 | K46: =J46 -> 112000 | L46: =G39/3 -> 112000 | M46: =L46 -> 112000 | N46: =M46 -> 112000 | O46: =H39/3 -> 112000 | P46: =O46 -> 112000 | R46: =SUM(E46:P46) -> 1344000 | S46: =R46-J39 -> 0
B47: French | C47: Contractors USD-SA | D47: USD | E47: =E40/3 -> 841253.33 | F47: =E47 -> 841253.33 | G47: =F47 -> 841253.33 | H47: =G47 -> 841253.33 | I47: =F40/3 -> 861520 | J47: =I47 -> 861520 | K47: =J47 -> 861520 | L47: =G40/3 -> 852720 | M47: =L47 -> 852720 | N47: =M47 -> 852720 | O47: =H40/3 -> 849973.33 | P47: =O47 -> 849973.33 | R47: =SUM(E47:P47) -> 10207680 | S47: =R47-J40 -> -8720
B48: French | C48: Contractors EUR-SA | D48: EUR | E48: =E41/3 -> 416446.67 | F48: =E48 -> 416446.67 | G48: =F48 -> 416446.67 | H48: =G48 -> 416446.67 | I48: =F41/3 -> 431846.67 | J48: =I48 -> 431846.67 | K48: =J48 -> 431846.67 | L48: =G41/3 -> 431846.67 | M48: =L48 -> 431846.67 | N48: =M48 -> 431846.67 | O48: =H41/3 -> 420866.67 | P48: =O48 -> 420866.67 | R48: =SUM(E48:P48) -> 5098600 | S48: =R48-J41 -> -4420
B51: Abivax SA
C53: Suppliers minus IQVIA & Contractors & Jetons - Abivax SA €
E55: Q1 2026 | F55: Q2 2026 | G55: Q3 2026 | H55: Q4 2026 | J55: Total
C56: ALL Suppliers without IQVIA/Contractors/Jetons | D56: € | E56: 14155071 | F56: 13790286 | G56: 14575851 | H56: 15386525 | J56: =SUM(E56:H56) -> 57907732
C57: monthly | D57: € | E57: 4718356.9 | F57: 4596761.9 | G57: 4858617.1 | H57: 5128841.5 | J57: =SUM(E57:H57) -> 19302577
E60: 46023 | F60: =EDATE(E60,1) -> 46054 | G60: =EDATE(F60,1) -> 46082 | H60: =EDATE(G60,1) -> 46113 | I60: =EDATE(H60,1) -> 46143 | J60: =EDATE(I60,1) -> 46174 | K60: =EDATE(J60,1) -> 46204 | L60: =EDATE(K60,1) -> 46235 | M60: =EDATE(L60,1) -> 46266 | ... P60: =EDATE(O60,1) -> 46357 | R60: Total | S60: check
C61: ALL Suppliers without IQVIA/Contractors with Risk Adj. | D61: € | E61: =E57 -> 4718356.9 | F61: =E61 -> 4718356.9 | G61: =F61 -> 4718356.9 | H61: =G61 -> 4718356.9 | I61: =F57 -> 4596761.9 | J61: =I61 -> 4596761.9 | K61: =J61 -> 4596761.9 | L61: =G57 -> 4858617.1 | M61: =L61 -> 4858617.1 | N61: =M61 -> 4858617.1 | O61: =H57 -> 5128841.5 | P61: =O61 -> 5128841.5 | R61: =SUM(E61:P61) -> 57497248 | S61: =R61-J56 -> -410484.67
B63: Abivax SA | C63: Suppliers minus Contractors - Abivax SA $
E64: Q1 2026 | F64: Q2 2026 | G64: Q3 2026 | H64: Q4 2026 | J64: Total
C65: ALL Suppliers without contractors | D65: $ | E65: 7957968.7 | F65: 8078711.5 | G65: 16198996 | H65: 9877439.5 | J65: =SUM(E65:H65) -> 42113116
C66: monthly | D66: $ | E66: 2652656.2 | F66: 2692903.8 | G66: 5399665.4 | H66: 3292479.8 | J66: =SUM(E66:H66) -> 14037705
E68: 46023 | F68: =EDATE(E68,1) -> 46054 | G68: =EDATE(F68,1) -> 46082 | H68: =EDATE(G68,1) -> 46113 | I68: =EDATE(H68,1) -> 46143 | J68: =EDATE(I68,1) -> 46174 | K68: =EDATE(J68,1) -> 46204 | L68: =EDATE(K68,1) -> 46235 | M68: =EDATE(L68,1) -> 46266 | ... P68: =EDATE(O68,1) -> 46357 | R68: Total | S68: check
C69: ALL Suppliers without contractors with Risk Adj. | D69: $ | E69: =E66 -> 2652656.2 | F69: =E69 -> 2652656.2 | G69: =F69 -> 2652656.2 | H69: =G69 -> 2652656.2 | I69: =F66 -> 2692903.8 | J69: =I69 -> 2692903.8 | K69: =J69 -> 2692903.8 | L69: =G66 -> 5399665.4 | M69: =L69 -> 5399665.4 | N69: =M69 -> 5399665.4 | O69: =H66 -> 3292479.8 | P69: =O69 -> 3292479.8 | R69: =SUM(E69:P69) -> 41473292 | S69: =R69-J65 -> -639823.61
B72: Abivax LLC | C72: Suppliers minus Contractors - Abivax LLC $
E73: Q1 2026 | F73: Q2 2026 | G73: Q3 2026 | H73: Q4 2026 | J73: Total
C74: ALL Suppliers without contractors | D74: $ | E74: 2837755.2 | F74: 2610910.2 | G74: 7657210.2 | H74: 7999594.2 | J74: =SUM(E74:H74) -> 21105470
C75: monthly | D75: $ | E75: 945918.42 | F75: 870303.42 | G75: 2552403.4 | H75: 2666531.4 | J75: =SUM(E75:H75) -> 7035156.7
E78: 46023 | F78: =EDATE(E78,1) -> 46054 | G78: =EDATE(F78,1) -> 46082 | H78: =EDATE(G78,1) -> 46113 | I78: =EDATE(H78,1) -> 46143 | J78: =EDATE(I78,1) -> 46174 | K78: =EDATE(J78,1) -> 46204 | L78: =EDATE(K78,1) -> 46235 | M78: =EDATE(L78,1) -> 46266 | ... P78: =EDATE(O78,1) -> 46357 | R78: Total
C79: ALL Suppliers without contractors with Risk Adj. | D79: $ | E79: =E75 -> 945918.42 | F79: =E79 -> 945918.42 | G79: =F79 -> 945918.42 | H79: =G79 -> 945918.42 | I79: =F75 -> 870303.42 | J79: =I79 -> 870303.42 | K79: =J79 -> 870303.42 | L79: =G75 -> 2552403.4 | M79: =L79 -> 2552403.4 | N79: =M79 -> 2552403.4 | O79: =H75 -> 2666531.4 | P79: =O79 -> 2666531.4 | R79: =SUM(E79:P79) -> 19384857
B83: HR | C83: Cash out Payroll 2026, V BUDGET
C84: Suppliers SA EUR-USD et LLC-USD -vBudget 2026
C85: Bonus dispatch 2026 - 20260602 pour bonus MdG
C87: AGA
C88: budget (dec 2025)
C89: V Board décembre 2025
C90: O:\Support\Finance\Reporting\2025\1. Board 2025\12- December\Back-Up
C91: Source : calcul cash out AGA 108 € puis +20% 20251203 v3
C93: Jetons : Budget
B96: Advances for IQVIA
E98: FP&A - accounting | G98: Cash | H98: in m€
C99: TOTAL UC108 | D99: 380000 | E99: 46327 | F99: accounting | G99: Q1 2027
C100: TOTAL UC105 | D100: 3594680.8 | E100: 46082 | F100: FP&A | G100: Q4 2026 | H100: =D100*10^-6 -> 3.5946808
C101: TOTAL UC106 | D101: 4144364.4 | E101: 46082 | F101: FP&A | G101: Q4 2026 | H101: =D101*10^-6 -> 4.1443644 | I101: =H101+H100 -> 7.7390452
C102: TOTAL UC107 | D102: 5538475.8 | E102: 47818 | F102: FP&A | G102: Q4 2031 | H102: =D102*10^-6 -> 5.5384758
C103: TOTAL Orgapharm | D103: 129037.5 | E103: 46327 | F103: accounting | G103: Q1 2027
B107: Capex
C108: ABIVAX SA | D108: 1832000 | E108: EUR
C109: ABIVAX LLC | D109: 22000 | E109: USD | F109: negligable

Sheet Copie gardée ->

Sheet Copie Abivax LLC reforecast 
E3: Cash Forecast - V budget
B6: Abivax LLC USD
E7: 45658 | F7: =EDATE(E7,1) -> 45689 | G7: =EDATE(F7,1) -> 45717 | H7: =EDATE(G7,1) -> 45748 | I7: =EDATE(H7,1) -> 45778 | J7: =EDATE(I7,1) -> 45809 | K7: =EDATE(J7,1) -> 45839 | L7: =EDATE(K7,1) -> 45870 | M7: =EDATE(L7,1) -> 45901 | ... P7: =EDATE(O7,1) -> 45992 | R7: 2025
B9: Amount are VAT excluded
B10: Other Suppliers € (HT) with 10% R/Adj. | C10: $ | E10: =#REF! -> #REF! | F10: =#REF! -> #REF! | G10: =#REF! -> #REF! | H10: =#REF! -> #REF! | I10: =#REF! -> #REF! | J10: =#REF! -> #REF! | K10: =#REF! -> #REF! | L10: =#REF! -> #REF! | ... P10: =#REF! -> #REF! | R10: =SUM(E10:P10) -> #REF!
B11: Contractor (HT) with 10% R/Adj. | C11: $ | E11: =#REF! -> #REF! | F11: =#REF! -> #REF! | G11: =#REF! -> #REF! | H11: =#REF! -> #REF! | I11: =#REF! -> #REF! | J11: =#REF! -> #REF! | K11: =#REF! -> #REF! | L11: =#REF! -> #REF! | ... P11: =#REF! -> #REF! | R11: =SUM(E11:P11) -> #REF!
B12: Bank fees | C12: $
B13: Suppliers + Contractos | C13: $ | E13: =SUM(E10:E12) -> #REF! | F13: =SUM(F10:F12) -> #REF! | G13: =SUM(G10:G12) -> #REF! | H13: =SUM(H10:H12) -> #REF! | I13: =SUM(I10:I12) -> #REF! | J13: =SUM(J10:J12) -> #REF! | K13: =SUM(K10:K12) -> #REF! | L13: =SUM(L10:L12) -> #REF! | ... P13: =SUM(P10:P12) -> #REF! | R13: =SUM(E13:P13) -> #REF! | S13: même que Vbudget
B15: Payroll | C15: $ | E15: =#REF! -> #REF! | F15: =#REF! -> #REF! | G15: =#REF! -> #REF! | H15: =#REF! -> #REF! | I15: =#REF! -> #REF! | J15: =#REF! -> #REF! | K15: =#REF! -> #REF! | L15: =#REF! -> #REF! | ... P15: =#REF! -> #REF! | R15: =SUM(E15:P15) -> #REF!
B16: Total Salary & Social Charges | C16: $ | E16: =SUM(E15:E15) -> #REF! | F16: =SUM(F15:F15) -> #REF! | G16: =SUM(G15:G15) -> #REF! | H16: =SUM(H15:H15) -> #REF! | I16: =SUM(I15:I15) -> #REF! | J16: =SUM(J15:J15) -> #REF! | K16: =SUM(K15:K15) -> #REF! | L16: =SUM(L15:L15) -> #REF! | ... P16: =SUM(P15:P15) -> #REF! | R16: =SUM(E16:P16) -> #REF! | S16: retiré le risk adj. Pour salaires
B19: AGA Abivax SA (US employee) | C19: $ | N19: 235657.84 | R19: =SUM(E19:P19) -> 235657.84
B20: Total AGA | C20: $ | E20: =SUM(E19:E19) -> 0 | F20: =SUM(F19:F19) -> 0 | G20: =SUM(G19:G19) -> 0 | H20: =SUM(H19:H19) -> 0 | I20: =SUM(I19:I19) -> 0 | J20: =SUM(J19:J19) -> 0 | K20: =SUM(K19:K19) -> 0 | L20: =SUM(L19:L19) -> 0 | ... P20: =SUM(P19:P19) -> 0 | R20: =SUM(E20:P20) -> 235657.84 | S20: AGA cash forecast (Plan Long terme/previsionnel de trésorerie)
B22: Total HR related | C22: $ | E22: =E20+E16 -> #REF! | F22: =F20+F16 -> #REF! | G22: =G20+G16 -> #REF! | H22: =H20+H16 -> #REF! | I22: =I20+I16 -> #REF! | J22: =J20+J16 -> #REF! | K22: =K20+K16 -> #REF! | L22: =L20+L16 -> #REF! | ... P22: =P20+P16 -> #REF! | R22: =SUM(E22:P22) -> #REF!
B24: Interets in | C24: $ | E24: =-MAX(3%/4*AVERAGE(E33,E33-SUM(E13,E16,E20)),0) -> #REF! | F24: =-MAX(3%/4*AVERAGE(F33,F33-SUM(F13,F16,F20)),0) -> #REF! | G24: =-MAX(3%/4*AVERAGE(G33,G33-SUM(G13,G16,G20)),0) -> #REF! | H24: =-MAX(3%/4*AVERAGE(H33,H33-SUM(H13,H16,H20)),0) -> #REF! | I24: =-MAX(3%/4*AVERAGE(I33,I33-SUM(I13,I16,I20)),0) -> #REF! | J24: =-MAX(3%/4*AVERAGE(J33,J33-SUM(J13,J16,J20)),0) -> #REF! | K24: =-MAX(3%/4*AVERAGE(K33,K33-SUM(K13,K16,K20)),0) -> #REF! | L24: =-MAX(3%/4*AVERAGE(L33,L33-SUM(L13,L16,L20)),0) -> #REF! | ... P24: =-MAX(3%/4*AVERAGE(P33,P33-SUM(P13,P16,P20)),0) -> #REF! | R24: =SUM(E24:P24) -> #REF!
B26: TVA à payer | C26: $ | R26: =SUM(E26:P26) -> 0
B27: TVA à recevoir | C27: $ | R27: =SUM(E27:P27) -> 0
B29: Total | C29: $ | E29: =SUM(E26:E27,E24,E20,E16,E13) -> #REF! | F29: =SUM(F26:F27,F24,F20,F16,F13) -> #REF! | G29: =SUM(G26:G27,G24,G20,G16,G13) -> #REF! | H29: =SUM(H26:H27,H24,H20,H16,H13) -> #REF! | I29: =SUM(I26:I27,I24,I20,I16,I13) -> #REF! | J29: =SUM(J26:J27,J24,J20,J16,J13) -> #REF! | K29: =SUM(K26:K27,K24,K20,K16,K13) -> #REF! | L29: =SUM(L26:L27,L24,L20,L16,L13) -> #REF! | ... P29: =SUM(P26:P27,P24,P20,P16,P13) -> #REF! | R29: =SUM(E29:P29) -> #REF!
R30: =R29/12 -> #REF!
B31: Cash Balance - Abivax LLC
B33: Balance LLC - USD - begining of month | C33: $ | E33: 12656163 | F33: =E34 -> #REF! | G33: =F34 -> #REF! | H33: =G34 -> #REF! | I33: =H34 -> #REF! | J33: =I34 -> #REF! | K33: =J34 -> #REF! | L33: =K34 -> #REF! | M33: =L34 -> #REF! | ... P33: =O34 -> #REF!
B34: Balance LLC - USD - end of month | C34: $ | E34: =E33-E29 -> #REF! | F34: =F33-F29 -> #REF! | G34: =G33-G29 -> #REF! | H34: =H33-H29 -> #REF! | I34: =I33-I29 -> #REF! | J34: =J33-J29 -> #REF! | K34: =K33-K29 -> #REF! | L34: =L33-L29 -> #REF! | ... P34: =P33-P29 -> #REF!
B36: EUR-USD m-1 | C36: $ | E36: =#REF! -> #REF! | F36: =#REF! -> #REF! | G36: =#REF! -> #REF! | H36: =#REF! -> #REF! | I36: =#REF! -> #REF! | J36: =#REF! -> #REF! | K36: =#REF! -> #REF! | L36: =#REF! -> #REF! | ... P36: =#REF! -> #REF!
B37: EUR-USD m | C37: $ | E37: =#REF! -> #REF! | F37: =#REF! -> #REF! | G37: =#REF! -> #REF! | H37: =#REF! -> #REF! | I37: =#REF! -> #REF! | J37: =#REF! -> #REF! | K37: =#REF! -> #REF! | L37: =#REF! -> #REF! | ... P37: =#REF! -> #REF!
B39: Balance SA-USD - begining of month | C39: € | E39: =E33/E36 -> #REF! | F39: =F33/F36 -> #REF! | G39: =G33/G36 -> #REF! | H39: =H33/H36 -> #REF! | I39: =I33/I36 -> #REF! | J39: =J33/J36 -> #REF! | K39: =K33/K36 -> #REF! | L39: =L33/L36 -> #REF! | ... P39: =P33/P36 -> #REF!
B40: Balance SA-USD - end of month | C40: € | E40: =E34/E37 -> #REF! | F40: =F34/F37 -> #REF! | G40: =G34/G37 -> #REF! | H40: =H34/H37 -> #REF! | I40: =I34/I37 -> #REF! | J40: =J34/J37 -> #REF! | K40: =K34/K37 -> #REF! | L40: =L34/L37 -> #REF! | ... P40: =P34/P37 -> #REF!
B42: Balance SA-USD - begining of month | C42: € | E42: =E33/E37 -> #REF!
B43: avec taux budget ---> perte : | E43: =E42-E39 -> #REF!

Sheet Copie -Abivax SA Reforecast
B3: Abivax SA | E3: Cash Forecast - V budget | AB3: Comparison with Budget
B6: Abivax SA EUR | E6: Forecast-Budget | AB6: Forecast-Budget
E7: 45658 | F7: =EDATE(E7,1) -> 45689 | G7: =EDATE(F7,1) -> 45717 | H7: =EDATE(G7,1) -> 45748 | I7: =EDATE(H7,1) -> 45778 | J7: =EDATE(I7,1) -> 45809 | K7: =EDATE(J7,1) -> 45839 | L7: =EDATE(K7,1) -> 45870 | M7: =EDATE(L7,1) -> 45901 | ... P7: =EDATE(O7,1) -> 45992 | R7: 2025 | AB7: 45658 | AC7: =EDATE(AB7,1) -> 45689 | AD7: =EDATE(AC7,1) -> 45717 | AE7: =EDATE(AD7,1) -> 45748 | AF7: =EDATE(AE7,1) -> 45778 | AG7: =EDATE(AF7,1) -> 45809 | AH7: =EDATE(AG7,1) -> 45839 | AI7: =EDATE(AH7,1) -> 45870 | AJ7: =EDATE(AI7,1) -> 45901 | ... AM7: =EDATE(AL7,1) -> 45992 | AO7: 2025
V8: Source :
B9: Amount are VAT excluded | V9: IQVIA Vision Summary Budget, total pour cash forecast-: 79,7m€
B10: IQVIA 104 milestone | C10: € | E10: 0 | F10: 0 | G10: 0 | H10: 0 | I10: 0 | J10: 0 | K10: 0 | L10: 0 | M10: 0 | N10: 0 | O10: 0 | P10: 0 | R10: =SUM(E10:P10) -> 0 | V10: IQVIA Phase 3 & CD forecast BUDGET MAJ2002025 pour ajustment CD : -4,3 m€ | AO10: =SUM(AB10:AM10) -> 0
B11: IQVIA 104 PTC & IF & Q2 | C11: € | E11: 9730 | F11: 0 | G11: 0 | H11: 0 | I11: 0 | J11: 0 | K11: 0 | L11: 0 | M11: 0 | N11: 0 | O11: 0 | P11: 0 | R11: =SUM(E11:P11) -> 9730 | AO11: =SUM(AB11:AM11) -> 0
B12: IQVIA 105 milestone | C12: € | E12: 2017976 | F12: 0 | G12: 0 | H12: 2017976 | I12: 0 | J12: 3531459 | K12: 0 | L12: 0 | M12: 3531459 | N12: 0 | O12: 0 | P12: 0 | R12: =SUM(E12:P12) -> 11098870 | V12: =SUM(R10:R19) -> 94124874 | AO12: =SUM(AB12:AM12) -> 0
B13: IQVIA 105 PTC & IF & Q2 | C13: € | E13: 2296110.1 | F13: 0 | G13: 0 | H13: 3348209.9 | I13: 1080000 | J13: 1162081 | K13: 780000 | L13: 780000 | M13: 650000 | N13: 650000 | O13: 483562 | P13: 350000 | R13: =SUM(E13:P13) -> 11579963 | V13: =R20 -> -3344444.4 | W13: Budget | X13: Diff | AO13: =SUM(AB13:AM13) -> 0
B14: IQVIA 106 milestone | C14: € | E14: 2450977 | F14: 0 | G14: 0 | H14: 2450977 | I14: 0 | J14: 2941173 | K14: 0 | L14: 0 | M14: 3921564 | N14: 0 | O14: 0 | P14: 0 | R14: =SUM(E14:P14) -> 11764691 | V14: =V12+V13 -> 90780429 | W14: 75689579 | X14: =V14-W14 -> 15090850 | AO14: =SUM(AB14:AM14) -> 0
B15: IQVIA 106 PTC & IF & Q2 | C15: € | E15: 2246164.8 | F15: 0 | G15: 0 | H15: 3394710.3 | I15: 1230000 | J15: 1230000 | K15: 1230000 | L15: 730000 | M15: 730000 | N15: 730000 | O15: 683049 | P15: 0 | R15: =SUM(E15:P15) -> 12203924 | V15: car notamment : factures novembre (notament milestone 70%) payées en janvier 25 | AO15: =SUM(AB15:AM15) -> 0
B16: IQVIA 107 milestone | C16: € | E16: 0 | F16: 0 | G16: 0 | H16: 4652021 | I16: 0 | J16: 9304042 | K16: 0 | L16: 0 | M16: 0 | N16: 0 | O16: 0 | P16: 6978032 | R16: =SUM(E16:P16) -> 20934095 | V16: bcp plus de paiement en janvier (budget 2024) que décembre 2025 (passera en cash 2026) : 5,6 m€ en plus | AO16: =SUM(AB16:AM16) -> 0
B17: IQVIA 107 PTC & IF & Q2 | C17: € | E17: 1875058.2 | F17: 0 | G17: 0 | H17: 3155209.9 | I17: 1100000 | J17: 1100000 | K17: 1100000 | L17: 1100000 | M17: 950000 | N17: 950000 | O17: 950000 | P17: 950000 | R17: =SUM(E17:P17) -> 13230268 | AO17: =SUM(AB17:AM17) -> 0
B18: IQVIA CD milestone | C18: € | E18: 0 | F18: 0 | G18: 0 | H18: 1831734.7 | I18: 1308381.9 | J18: 0 | K18: 2616763.9 | L18: 1308381.9 | M18: 1308381.9 | N18: 1308381.9 | O18: 1308381.9 | P18: 0 | R18: =SUM(E18:P18) -> 10990408 | AO18: =SUM(AB18:AM18) -> 0
B19: IQVIA CD PTC & IF & Q2 | C19: € | E19: 241072.55 | F19: 0 | G19: 0 | H19: 407851.3 | I19: 208000 | J19: 208000 | K19: 208000 | L19: 208000 | M19: 208000 | N19: 208000 | O19: 208000 | P19: 208000 | R19: =SUM(E19:P19) -> 2312923.9 | AO19: =SUM(AB19:AM19) -> 0
B20: IQVIA CD ajustment budget | C20: € | E20: 0 | F20: 0 | G20: 0 | H20: 0 | I20: -477777.78 | J20: -477777.78 | K20: -477777.78 | L20: -477777.78 | M20: -477777.78 | N20: -477777.78 | O20: -477777.78 | P20: 0 | R20: =SUM(E20:P20) -> -3344444.4 | AO20: =SUM(AB20:AM20) -> 0
B21: IQVIA CD ajustment 10% | C21: € | E21: 0 | F21: 0 | G21: 0 | H21: 0 | I21: -103860.42 | J21: 26977.778 | K21: -234698.61 | L21: -103860.42 | M21: -103860.42 | N21: -103860.42 | O21: -103860.42 | P21: -20800 | R21: =SUM(E21:P21) -> -747822.92 | V21: Source : | AO21: =SUM(AB21:AM21) -> 0
B22: Total IQVIA | C22: € | E22: =SUM(E10:E21) -> 11137089 | F22: =SUM(F10:F21) -> 0 | G22: =SUM(G10:G21) -> 0 | H22: =SUM(H10:H21) -> 21258690 | I22: =SUM(I10:I21) -> 4344743.8 | J22: =SUM(J10:J21) -> 19025955 | K22: =SUM(K10:K21) -> 5222287.5 | L22: =SUM(L10:L21) -> 3544743.8 | ... P22: =SUM(P10:P21) -> 8465232 | R22: =SUM(E22:P22) -> 90032606 | S22: update 20/03/2025 | V22: Suppliers SA EUR-USD et LLC-USD - vBudget (en ligne avec Abivax Financials) | AB22: =SUM(AB10:AB21) -> 0 | AC22: =SUM(AC10:AC21) -> 0 | AD22: =SUM(AD10:AD21) -> 0 | AE22: =SUM(AE10:AE21) -> 0 | AF22: =SUM(AF10:AF21) -> 0 | AG22: =SUM(AG10:AG21) -> 0 | AH22: =SUM(AH10:AH21) -> 0 | AI22: =SUM(AI10:AI21) -> 0 | ... AM22: =SUM(AM10:AM21) -> 0 | AO22: =SUM(AB22:AM22) -> 0
B24: Other Suppliers € (HT) with 10% R/Adj. | C24: € | E24: =#REF! -> #REF! | F24: =#REF! -> #REF! | G24: =#REF! -> #REF! | H24: =#REF! -> #REF! | I24: =#REF! -> #REF! | J24: =#REF! -> #REF! | K24: =#REF! -> #REF! | L24: =#REF! -> #REF! | ... P24: =#REF! -> #REF! | R24: =SUM(E24:P24) -> #REF! | AO24: =SUM(AB24:AM24) -> 0
B25: Contractor (HT) with 10% R/Adj. | C25: € | E25: =#REF! -> #REF! | F25: =#REF! -> #REF! | G25: =#REF! -> #REF! | H25: =#REF! -> #REF! | I25: =#REF! -> #REF! | J25: =#REF! -> #REF! | K25: =#REF! -> #REF! | L25: =#REF! -> #REF! | ... P25: =#REF! -> #REF! | R25: =SUM(E25:P25) -> #REF! | AO25: =SUM(AB25:AM25) -> 0
B26: Bank fees | C26: € | V26: Cash | W26: Budget | X26: Diff
B27: Suppliers + Contractos | C27: € | E27: =SUM(E24:E26) -> #REF! | F27: =SUM(F24:F26) -> #REF! | G27: =SUM(G24:G26) -> #REF! | H27: =SUM(H24:H26) -> #REF! | I27: =SUM(I24:I26) -> #REF! | J27: =SUM(J24:J26) -> #REF! | K27: =SUM(K24:K26) -> #REF! | L27: =SUM(L24:L26) -> #REF! | ... P27: =SUM(P24:P26) -> #REF! | R27: =SUM(E27:P27) -> #REF! | S27: update mais tjrs chiffres budget | V27: =R27+R38+R21 -> #REF! | W27: =(120367048.146484-75689579.43)*0.9+R21 -> 39461899 | X27: =V27-W27 -> #REF! | AB27: =SUM(AB24:AB26) -> 0 | AC27: =SUM(AC24:AC26) -> 0 | AD27: =SUM(AD24:AD26) -> 0 | AE27: =SUM(AE24:AE26) -> 0 | AF27: =SUM(AF24:AF26) -> 0 | AG27: =SUM(AG24:AG26) -> 0 | AH27: =SUM(AH24:AH26) -> 0 | AI27: =SUM(AI24:AI26) -> 0 | ... AM27: =SUM(AM24:AM26) -> 0 | AO27: =SUM(AB27:AM27) -> 0
X28: car Q1>Q4
B29: Salaire net aprés PAS | C29: € | E29: 291635.4 | F29: 291635.4 | G29: 291635.4 | H29: 291635.4 | I29: 291635.4 | J29: 291635.4 | K29: 291635.4 | L29: 291635.4 | M29: 291635.4 | N29: 291635.4 | O29: 291635.4 | P29: 291635.4 | R29: =SUM(E29:P29) -> 3499624.8 | X29: 1,3 m€ en plus par mois janvier par rapport à décembre | AO29: =SUM(AB29:AM29) -> 0
B30: Bonus net sans PAS | C30: € | G30: 543314.85 | J30: 0 | R30: =SUM(E30:P30) -> 543314.85 | X30: 1,3 en moins car DAP … | AO30: =SUM(AB30:AM30) -> 0
B31: Urssaf | C31: € | E31: 211432.5 | F31: 216131 | G31: 216131 | H31: 618781.64 | I31: 216131 | J31: 216131 | K31: 216131 | L31: 216131 | M31: 216131 | N31: 216131 | O31: 216131 | P31: 216131 | R31: =SUM(E31:P31) -> 2991524.1 | AO31: =SUM(AB31:AM31) -> 0
B32: Retraite | C32: € | E32: 86130 | F32: 88044 | G32: 88044 | H32: 252069.4 | I32: 88044 | J32: 88044 | K32: 88044 | L32: 88044 | M32: 88044 | N32: 88044 | O32: 88044 | P32: 88044 | R32: =SUM(E32:P32) -> 1218639.4 | AO32: =SUM(AB32:AM32) -> 0
B33: Prévoyance | C33: € | E33: 23625 | H33: 39147.098 | K33: 24150 | N33: 24150 | R33: =SUM(E33:P33) -> 111072.1 | AO33: =SUM(AB33:AM33) -> 0
B34: Mutuelle | C34: € | E34: 23841 | H34: 39505.014 | K34: 24370.8 | N34: 24370.8 | R34: =SUM(E34:P34) -> 112087.61 | AO34: =SUM(AB34:AM34) -> 0
B35: Dgfip (PAS) | C35: € | E35: 67207.5 | F35: 68701 | G35: 68701 | H35: 196690.51 | I35: 68701 | J35: 68701 | K35: 68701 | L35: 68701 | M35: 68701 | N35: 68701 | O35: 68701 | P35: 68701 | R35: =SUM(E35:P35) -> 950908.01 | V35: Cash | W35: Budget | AO35: =SUM(AB35:AM35) -> 0
B36: Total Salary & Social Charges | C36: € | E36: =SUM(E29:E35) -> 703871.4 | F36: =SUM(F29:F35) -> 664511.4 | G36: =SUM(G29:G35) -> 1207826.2 | H36: =SUM(H29:H35) -> 1437829.1 | I36: =SUM(I29:I35) -> 664511.4 | J36: =SUM(J29:J35) -> 664511.4 | K36: =SUM(K29:K35) -> 713032.2 | L36: =SUM(L29:L35) -> 664511.4 | ... P36: =SUM(P29:P35) -> 664511.4 | R36: =SUM(E36:P36) -> 9427170.9 | S36: update Bonus et pas de R/Adj. Sur salaire | V36: =R36+R39 -> 9539541.6 | W36: =10045099.705716*0.9 -> 9040589.7 | X36: =V36-W36 -> 498951.91 | AB36: =SUM(AB29:AB35) -> 0 | AC36: =SUM(AC29:AC35) -> 0 | AD36: =SUM(AD29:AD35) -> 0 | AE36: =SUM(AE29:AE35) -> 0 | AF36: =SUM(AF29:AF35) -> 0 | AG36: =SUM(AG29:AG35) -> 0 | AH36: =SUM(AH29:AH35) -> 0 | AI36: =SUM(AI29:AI35) -> 0 | ... AM36: =SUM(AM29:AM35) -> 0 | AO36: =SUM(AB36:AM36) -> 0
B38: Jetons de présence | C38: € | J38: 326666.66 | P38: 326666.66 | R38: =SUM(E38:P38) -> 653333.33 | AM38: 294000 | AO38: =SUM(AB38:AM38) -> 294000
B39: Forfait social jetons de présence (urssaf) | C39: € | E39: 47037.4 | K39: 65333.333 | R39: =SUM(E39:P39) -> 112370.73 | AM39: 0 | AO39: =SUM(AB39:AM39) -> 0
B40: Total jetons | C40: € | E40: =SUM(E38:E39) -> 47037.4 | F40: =SUM(F38:F39) -> 0 | G40: =SUM(G38:G39) -> 0 | H40: =SUM(H38:H39) -> 0 | I40: =SUM(I38:I39) -> 0 | J40: =SUM(J38:J39) -> 326666.66 | K40: =SUM(K38:K39) -> 65333.333 | L40: =SUM(L38:L39) -> 0 | ... P40: =SUM(P38:P39) -> 326666.66 | R40: =SUM(E40:P40) -> 765704.06 | S40: update, pas de risk adj. Sur jetons | AB40: =SUM(AB38:AB39) -> 0 | AC40: =SUM(AC38:AC39) -> 0 | AD40: =SUM(AD38:AD39) -> 0 | AE40: =SUM(AE38:AE39) -> 0 | AF40: =SUM(AF38:AF39) -> 0 | AG40: =SUM(AG38:AG39) -> 0 | AH40: =SUM(AH38:AH39) -> 0 | AI40: =SUM(AI38:AI39) -> 0 | ... AM40: =SUM(AM38:AM39) -> 294000 | AO40: =SUM(AB40:AM40) -> 294000
B42: AGA MdG | C42: € | E42: 0 | F42: 0 | G42: 620596.26 | H42: 37228.8 | I42: 0 | J42: 0 | K42: 37228.8 | L42: 0 | M42: 0 | N42: 96794.88 | O42: 0 | P42: 0 | R42: =SUM(E42:P42) -> 791848.74 | AO42: =SUM(AB42:AM42) -> 0
B43: AGA Abivax SA (French employee) | C43: € | E43: 0 | F43: 0 | G43: 0 | H43: 62700 | I43: 0 | J43: 0 | K43: 0 | L43: 407550 | M43: 0 | N43: 714455.99 | O43: 0 | P43: 0 | R43: =SUM(E43:P43) -> 1184706 | AB43: =64194.53125*0.9 -> 57775.078 | AC43: =64194.53125*0.9 -> 57775.078 | AD43: =64194.53125*0.9 -> 57775.078 | AE43: =64194.53125*0.9 -> 57775.078 | AF43: =64194.53125*0.9 -> 57775.078 | AG43: =64194.53125*0.9 -> 57775.078 | AH43: =64194.53125*0.9 -> 57775.078 | AI43: =64194.53125*0.9 -> 57775.078 | ... AM43: =64194.53125*0.9 -> 57775.078 | AO43: =SUM(AB43:AM43) -> 693300.94
B44: AGA Abivax SA (US employee) | C44: € | R44: =SUM(E44:P44) -> 0 | V44: Cash | W44: Budget | AO44: =SUM(AB44:AM44) -> 0
B45: Total AGA | C45: € | E45: =SUM(E42:E44) -> 0 | F45: =SUM(F42:F44) -> 0 | G45: =SUM(G42:G44) -> 620596.26 | H45: =SUM(H42:H44) -> 99928.8 | I45: =SUM(I42:I44) -> 0 | J45: =SUM(J42:J44) -> 0 | K45: =SUM(K42:K44) -> 37228.8 | L45: =SUM(L42:L44) -> 407550 | ... P45: =SUM(P42:P44) -> 0 | R45: =SUM(E45:P45) -> 1976554.7 | S45: update, pas de risk adj. | V45: =R45 -> 1976554.7 | W45: =770334.375*0.9 -> 693300.94 | X45: =V45-W45 -> 1283253.8 | AB45: =SUM(AB42:AB44) -> 57775.078 | AC45: =SUM(AC42:AC44) -> 57775.078 | AD45: =SUM(AD42:AD44) -> 57775.078 | AE45: =SUM(AE42:AE44) -> 57775.078 | AF45: =SUM(AF42:AF44) -> 57775.078 | AG45: =SUM(AG42:AG44) -> 57775.078 | AH45: =SUM(AH42:AH44) -> 57775.078 | AI45: =SUM(AI42:AI44) -> 57775.078 | ... AM45: =SUM(AM42:AM44) -> 57775.078 | AO45: =SUM(AB45:AM45) -> 693300.94
B47: Total HR related | C47: € | E47: =E45+E40+E36 -> 750908.8 | F47: =F45+F40+F36 -> 664511.4 | G47: =G45+G40+G36 -> 1828422.5 | H47: =H45+H40+H36 -> 1537757.9 | I47: =I45+I40+I36 -> 664511.4 | J47: =J45+J40+J36 -> 991178.06 | K47: =K45+K40+K36 -> 815594.33 | L47: =L45+L40+L36 -> 1072061.4 | ... P47: =P45+P40+P36 -> 991178.06 | R47: =SUM(E47:P47) -> 12169430 | AB47: =AB45+AB40+AB36 -> 57775.078 | AC47: =AC45+AC40+AC36 -> 57775.078 | AD47: =AD45+AD40+AD36 -> 57775.078 | AE47: =AE45+AE40+AE36 -> 57775.078 | AF47: =AF45+AF40+AF36 -> 57775.078 | AG47: =AG45+AG40+AG36 -> 57775.078 | AH47: =AH45+AH40+AH36 -> 57775.078 | AI47: =AI45+AI40+AI36 -> 57775.078 | ... AM47: =AM45+AM40+AM36 -> 351775.08 | AO47: =SUM(AB47:AM47) -> 987300.94
B49: Financial debt
B50: Kreos Tranche A | C50: € | E50: 375000 | H50: 375000 | K50: 375000 | N50: 375000 | R50: =SUM(E50:P50) -> 1500000 | AB50: 375000 | AE50: 375000 | AH50: 375000 | AK50: 375000 | AO50: =SUM(AB50:AM50) -> 1500000
B51: Kreos Tranche B | C51: € | E51: 147916.67 | F51: 714314.08 | G51: 712465.63 | H51: 710688.31 | I51: 710688.31 | J51: 710688.31 | K51: 710688.31 | L51: 710688.31 | M51: 710688.31 | N51: 710688.31 | O51: 710688.31 | P51: 710688.31 | R51: =SUM(E51:P51) -> 7970891.1 | AB51: 151388.89 | AC51: 716085.82 | AD51: 716085.82 | AE51: 716085.82 | AF51: 716085.82 | AG51: 716085.82 | AH51: 716085.82 | AI51: 716085.82 | AJ51: 716085.82 | AK51: 716085.82 | AL51: 716085.82 | AM51: 716085.82 | AO51: =SUM(AB51:AM51) -> 8028332.9
B52: Kreos Tranche C | C52: € | E52: 147916.67 | F52: 714314.08 | G52: 712465.63 | H52: 710688.31 | I52: 710688.31 | J52: 710688.31 | K52: 710688.31 | L52: 710688.31 | M52: 710688.31 | N52: 710688.31 | O52: 710688.31 | P52: 710688.31 | R52: =SUM(E52:P52) -> 7970891.1 | AB52: 151388.89 | AC52: 716085.82 | AD52: 716085.82 | AE52: 716085.82 | AF52: 716085.82 | AG52: 716085.82 | AH52: 716085.82 | AI52: 716085.82 | AJ52: 716085.82 | AK52: 716085.82 | AL52: 716085.82 | AM52: 716085.82 | AO52: =SUM(AB52:AM52) -> 8028332.9
B53: Claret Tranche A | C53: € | E53: 187499.99 | H53: 187499.99 | K53: 187499.99 | N53: 187499.99 | R53: =SUM(E53:P53) -> 749999.97 | AB53: 187499.99 | AE53: 187499.99 | AH53: 187499.99 | AK53: 187499.99 | AO53: =SUM(AB53:AM53) -> 749999.97
B54: Claret Tranche B | C54: € | E54: 73958.33 | F54: 357157.02 | G54: 356232.8 | H54: 355344.14 | I54: 355344.14 | J54: 355344.14 | K54: 355344.14 | L54: 355344.14 | M54: 355344.14 | N54: 355344.14 | O54: 355344.14 | P54: 355344.14 | R54: =SUM(E54:P54) -> 3985445.4 | AB54: 75694.441 | AC54: 358042.89 | AD54: 358042.89 | AE54: 358042.89 | AF54: 358042.89 | AG54: 358042.89 | AH54: 358042.89 | AI54: 358042.89 | AJ54: 358042.89 | AK54: 358042.89 | AL54: 358042.89 | AM54: 358042.89 | AO54: =SUM(AB54:AM54) -> 4014166.3
B55: Claret Tranche C | C55: € | E55: 73958.33 | F55: 357157.02 | G55: 356232.8 | H55: 355344.14 | I55: 355344.14 | J55: 355344.14 | K55: 355344.14 | L55: 355344.14 | M55: 355344.14 | N55: 355344.14 | O55: 355344.14 | P55: 355344.14 | R55: =SUM(E55:P55) -> 3985445.4 | S55: update baisse taux pour Kreos & Claret | AB55: 75694.441 | AC55: 358042.89 | AD55: 358042.89 | AE55: 358042.89 | AF55: 358042.89 | AG55: 358042.89 | AH55: 358042.89 | AI55: 358042.89 | AJ55: 358042.89 | AK55: 358042.89 | AL55: 358042.89 | AM55: 358042.89 | AO55: =SUM(AB55:AM55) -> 4014166.3
B56: Heights | C56: € | F56: 2548437.5 | I56: 328125 | L56: 328125 | O56: 328125 | R56: =SUM(E56:P56) -> 3532812.5 | S56: update car paiement intérêts pour Heights car cours action trop bas | AC56: 2548437.5 | AO56: =SUM(AB56:AM56) -> 2548437.5
B57: PGE | C57: € | J57: 1293249.7 | R57: =SUM(E57:P57) -> 1293249.7 | V57: Cash | W57: Board | AG57: 1293249.7 | AO57: =SUM(AB57:AM57) -> 1293249.7
B58: Total debt | C58: € | E58: =SUM(E50:E57) -> 1006250 | F58: =SUM(F50:F57) -> 4691379.7 | G58: =SUM(G50:G57) -> 2137396.9 | H58: =SUM(H50:H57) -> 2694564.9 | I58: =SUM(I50:I57) -> 2460189.9 | J58: =SUM(J50:J57) -> 3425314.6 | K58: =SUM(K50:K57) -> 2694564.9 | L58: =SUM(L50:L57) -> 2460189.9 | ... P58: =SUM(P50:P57) -> 2132064.9 | R58: =SUM(E58:P58) -> 30988735 | V58: =R58 -> 30988735 | W58: =30.1766857390578*10^6 -> 30176686 | X58: =V58-W58 -> 812049.48 | AB58: =SUM(AB50:AB57) -> 1016666.7 | AC58: =SUM(AC50:AC57) -> 4696694.9 | AD58: =SUM(AD50:AD57) -> 2148257.4 | AE58: =SUM(AE50:AE57) -> 2710757.4 | AF58: =SUM(AF50:AF57) -> 2148257.4 | AG58: =SUM(AG50:AG57) -> 3441507.1 | AH58: =SUM(AH50:AH57) -> 2710757.4 | AI58: =SUM(AI50:AI57) -> 2148257.4 | ... AM58: =SUM(AM50:AM57) -> 2148257.4 | AO58: =SUM(AB58:AM58) -> 30176685
B60: RTC | C60: € | N60: 5667591.4 | R60: =SUM(E60:P60) -> 5667591.4 | V60: =R60 -> 5667591.4 | W60: =-5*10^6 -> -5000000 | X60: =V60-W60 -> 10667591 | AJ60: -5000000 | AO60: =SUM(AB60:AM60) -> -5000000
B61: BSA cash in
B62: Interets in | C62: € | E62: =-MAX(3%/12*AVERAGE(E69,E69-SUM(E22,E27,E47,E58)+SUM(E60,E61)),0) -> #REF! | F62: =-MAX(3%/12*AVERAGE(F69,F69-SUM(F22,F27,F47,F58)+SUM(F60,F61)),0) -> #REF! | G62: =-MAX(3%/12*AVERAGE(G69,G69-SUM(G22,G27,G47,G58)+SUM(G60,G61)),0) -> #REF! | H62: =-MAX(3%/12*AVERAGE(H69,H69-SUM(H22,H27,H47,H58)+SUM(H60,H61)),0) -> #REF! | I62: =-MAX(3%/12*AVERAGE(I69,I69-SUM(I22,I27,I47,I58)+SUM(I60,I61)),0) -> #REF! | J62: =-MAX(3%/12*AVERAGE(J69,J69-SUM(J22,J27,J47,J58)+SUM(J60,J61)),0) -> #REF! | K62: =-MAX(3%/12*AVERAGE(K69,K69-SUM(K22,K27,K47,K58)+SUM(K60,K61)),0) -> #REF! | L62: =-MAX(3%/12*AVERAGE(L69,L69-SUM(L22,L27,L47,L58)+SUM(L60,L61)),0) -> #REF! | ... P62: =-MAX(3%/12*AVERAGE(P69,P69-SUM(P22,P27,P47,P58)+SUM(P60,P61)),0) -> #REF! | R62: =SUM(E62:P62) -> #REF! | AB62: =-MAX(3%/12*AVERAGE(AB69,AB69-SUM(AB22,AB27,AB47,AB58)+SUM(AB60,AB61)),0) -> -284918.75 | AC62: =-MAX(3%/12*AVERAGE(AC69,AC69-SUM(AC22,AC27,AC47,AC58)+SUM(AC60,AC61)),0) -> -278344.91 | AD62: =-MAX(3%/12*AVERAGE(AD69,AD69-SUM(AD22,AD27,AD47,AD58)+SUM(AD60,AD61)),0) -> -270340.14 | AE62: =-MAX(3%/12*AVERAGE(AE69,AE69-SUM(AE22,AE27,AE47,AE58)+SUM(AE60,AE61)),0) -> -264797.79 | AF62: =-MAX(3%/12*AVERAGE(AF69,AF69-SUM(AF22,AF27,AF47,AF58)+SUM(AF60,AF61)),0) -> -259241.58 | AG62: =-MAX(3%/12*AVERAGE(AG69,AG69-SUM(AG22,AG27,AG47,AG58)+SUM(AG60,AG61)),0) -> -252758.04 | AH62: =-MAX(3%/12*AVERAGE(AH69,AH69-SUM(AH22,AH27,AH47,AH58)+SUM(AH60,AH61)),0) -> -245555.16 | AI62: =-MAX(3%/12*AVERAGE(AI69,AI69-SUM(AI22,AI27,AI47,AI58)+SUM(AI60,AI61)),0) -> -239950.84 | ... AM62: =-MAX(3%/12*AVERAGE(AM69,AM69-SUM(AM22,AM27,AM47,AM58)+SUM(AM60,AM61)),0) -> -230984.02 | AO62: =SUM(AB62:AM62) -> -3033842.2
B64: TVA à payer | C64: € | R64: =SUM(E64:P64) -> 0 | AO64: =SUM(AB64:AM64) -> 0
B65: TVA à recevoir | C65: € | R65: =SUM(E65:P65) -> 0 | AO65: =SUM(AB65:AM65) -> 0
B67: Total | C67: € | E67: =E58+E47+E27+E22+SUM(E60:E62)+SUM(E64:E65) -> #REF! | F67: =F58+F47+F27+F22+SUM(F60:F62)+SUM(F64:F65) -> #REF! | G67: =G58+G47+G27+G22+SUM(G60:G62)+SUM(G64:G65) -> #REF! | H67: =H58+H47+H27+H22+SUM(H60:H62)+SUM(H64:H65) -> #REF! | I67: =I58+I47+I27+I22+SUM(I60:I62)+SUM(I64:I65) -> #REF! | J67: =J58+J47+J27+J22+SUM(J60:J62)+SUM(J64:J65) -> #REF! | K67: =K58+K47+K27+K22+SUM(K60:K62)+SUM(K64:K65) -> #REF! | L67: =L58+L47+L27+L22+SUM(L60:L62)+SUM(L64:L65) -> #REF! | ... P67: =P58+P47+P27+P22+SUM(P60:P62)+SUM(P64:P65) -> #REF! | R67: =SUM(E67:P67) -> #REF! | AB67: =AB58+AB47+AB27+AB22+SUM(AB60:AB62)+SUM(AB64:AB65) -> 789522.98 | AC67: =AC58+AC47+AC27+AC22+SUM(AC60:AC62)+SUM(AC64:AC65) -> 4476125.1 | AD67: =AD58+AD47+AD27+AD22+SUM(AD60:AD62)+SUM(AD64:AD65) -> 1935692.4 | AE67: =AE58+AE47+AE27+AE22+SUM(AE60:AE62)+SUM(AE64:AE65) -> 2503734.7 | AF67: =AF58+AF47+AF27+AF22+SUM(AF60:AF62)+SUM(AF64:AF65) -> 1946790.9 | AG67: =AG58+AG47+AG27+AG22+SUM(AG60:AG62)+SUM(AG64:AG65) -> 3246524.2 | AH67: =AH58+AH47+AH27+AH22+SUM(AH60:AH62)+SUM(AH64:AH65) -> 2522977.3 | AI67: =AI58+AI47+AI27+AI22+SUM(AI60:AI62)+SUM(AI64:AI65) -> 1966081.7 | ... AM67: =AM58+AM47+AM27+AM22+SUM(AM60:AM62)+SUM(AM64:AM65) -> 2269048.5 | AO67: =SUM(AB67:AM67) -> 23130144
R68: =R67/12 -> #REF! | AO68: =AO67/12 -> 1927512
B69: Balance SA-EUR - begining of month | C69: € | E69: =118571222.46 -> 1.1857122e+08 | F69: =E70 -> #REF! | G69: =F70 -> #REF! | H69: =G70 -> #REF! | I69: =H70 -> #REF! | J69: =I70 -> #REF! | K69: =J70 -> #REF! | L69: =K70 -> #REF! | M69: =L70 -> #REF! | ... P69: =O70 -> #REF! | AB69: =118571222.46-4066500.86023101 -> 1.1450472e+08 | AC69: =AB70 -> 1.137152e+08 | AD69: =AC70 -> 1.0923907e+08 | AE69: =AD70 -> 1.0730338e+08 | AF69: =AE70 -> 1.0479965e+08 | AG69: =AF70 -> 1.0285286e+08 | AH69: =AG70 -> 99606331 | AI69: =AH70 -> 97083354 | AJ69: =AI70 -> 95117272 | ... AM69: =AL70 -> 93643626
B70: Balance SA-EUR - end of month | C70: € | E70: =E69-E67 -> #REF! | F70: =F69-F67 -> #REF! | G70: =G69-G67 -> #REF! | H70: =H69-H67 -> #REF! | I70: =I69-I67 -> #REF! | J70: =J69-J67 -> #REF! | K70: =K69-K67 -> #REF! | L70: =L69-L67 -> #REF! | ... P70: =P69-P67 -> #REF! | AB70: =AB69-AB67 -> 1.137152e+08 | AC70: =AC69-AC67 -> 1.0923907e+08 | AD70: =AD69-AD67 -> 1.0730338e+08 | AE70: =AE69-AE67 -> 1.0479965e+08 | AF70: =AF69-AF67 -> 1.0285286e+08 | AG70: =AG69-AG67 -> 99606331 | AH70: =AH69-AH67 -> 97083354 | AI70: =AI69-AI67 -> 95117272 | ... AM70: =AM69-AM67 -> 91374577
B74: Abivax SA USD | E74: 45658 | F74: =EDATE(E74,1) -> 45689 | G74: =EDATE(F74,1) -> 45717 | H74: =EDATE(G74,1) -> 45748 | I74: =EDATE(H74,1) -> 45778 | J74: =EDATE(I74,1) -> 45809 | K74: =EDATE(J74,1) -> 45839 | L74: =EDATE(K74,1) -> 45870 | M74: =EDATE(L74,1) -> 45901 | ... P74: =EDATE(O74,1) -> 45992 | R74: 2025 | AB74: 45658 | AC74: =EDATE(AB74,1) -> 45689 | AD74: =EDATE(AC74,1) -> 45717 | AE74: =EDATE(AD74,1) -> 45748 | AF74: =EDATE(AE74,1) -> 45778 | AG74: =EDATE(AF74,1) -> 45809 | AH74: =EDATE(AG74,1) -> 45839 | AI74: =EDATE(AH74,1) -> 45870 | AJ74: =EDATE(AI74,1) -> 45901 | ... AM74: =EDATE(AL74,1) -> 45992 | AO74: 2025
B76: Other Suppliers (HT) with 10% Risk Adj. | C76: $ | E76: =#REF! -> #REF! | F76: =#REF! -> #REF! | G76: =#REF! -> #REF! | H76: =#REF! -> #REF! | I76: =#REF! -> #REF! | J76: =#REF! -> #REF! | K76: =#REF! -> #REF! | L76: =#REF! -> #REF! | ... P76: =#REF! -> #REF! | R76: =SUM(E76:P76) -> #REF! | S76: usd | V76: =R77+R76 -> #REF! | AB76: =#REF! -> #REF! | AC76: =#REF! -> #REF! | AD76: =#REF! -> #REF! | AE76: =#REF! -> #REF! | AF76: =#REF! -> #REF! | AG76: =#REF! -> #REF! | AH76: =#REF! -> #REF! | AI76: =#REF! -> #REF! | ... AM76: =#REF! -> #REF! | AO76: =SUM(AB76:AM76) -> #REF!
B77: Contractor (HT) with 10% Risk Adj. | C77: $ | E77: =#REF! -> #REF! | F77: =#REF! -> #REF! | G77: =#REF! -> #REF! | H77: =#REF! -> #REF! | I77: =#REF! -> #REF! | J77: =#REF! -> #REF! | K77: =#REF! -> #REF! | L77: =#REF! -> #REF! | ... P77: =#REF! -> #REF! | R77: =SUM(E77:P77) -> #REF! | V77: Cash | W77: Budget | X77: Diff | AB77: =#REF! -> #REF! | AC77: =#REF! -> #REF! | AD77: =#REF! -> #REF! | AE77: =#REF! -> #REF! | AF77: =#REF! -> #REF! | AG77: =#REF! -> #REF! | AH77: =#REF! -> #REF! | AI77: =#REF! -> #REF! | ... AM77: =#REF! -> #REF! | AO77: =SUM(AB77:AM77) -> #REF!
B78: interests cash in | C78: $ | E78: =-MAX(3%/12*AVERAGE(E84,E84-SUM(E76:E76)),0) -> #REF! | F78: =-MAX(3%/12*AVERAGE(F84,F84-SUM(F76:F76)),0) -> #REF! | G78: =-MAX(3%/12*AVERAGE(G84,G84-SUM(G76:G76)),0) -> #REF! | H78: =-MAX(3%/12*AVERAGE(H84,H84-SUM(H76:H76)),0) -> #REF! | I78: =-MAX(3%/12*AVERAGE(I84,I84-SUM(I76:I76)),0) -> #REF! | J78: =-MAX(3%/12*AVERAGE(J84,J84-SUM(J76:J76)),0) -> #REF! | K78: =-MAX(3%/12*AVERAGE(K84,K84-SUM(K76:K76)),0) -> #REF! | L78: =-MAX(3%/12*AVERAGE(L84,L84-SUM(L76:L76)),0) -> #REF! | ... P78: =-MAX(3%/12*AVERAGE(P84,P84-SUM(P76:P76)),0) -> #REF! | R78: =SUM(E78:P78) -> #REF! | AB78: =-MAX(3%/12*AVERAGE(AB84,AB84-SUM(AB76:AB76)),0) -> #REF! | AC78: =-MAX(3%/12*AVERAGE(AC84,AC84-SUM(AC76:AC76)),0) -> #REF! | AD78: =-MAX(3%/12*AVERAGE(AD84,AD84-SUM(AD76:AD76)),0) -> #REF! | AE78: =-MAX(3%/12*AVERAGE(AE84,AE84-SUM(AE76:AE76)),0) -> #REF! | AF78: =-MAX(3%/12*AVERAGE(AF84,AF84-SUM(AF76:AF76)),0) -> #REF! | AG78: =-MAX(3%/12*AVERAGE(AG84,AG84-SUM(AG76:AG76)),0) -> #REF! | AH78: =-MAX(3%/12*AVERAGE(AH84,AH84-SUM(AH76:AH76)),0) -> #REF! | AI78: =-MAX(3%/12*AVERAGE(AI84,AI84-SUM(AI76:AI76)),0) -> #REF! | ... AM78: =-MAX(3%/12*AVERAGE(AM84,AM84-SUM(AM76:AM76)),0) -> #REF! | AO78: =SUM(AB78:AM78) -> #REF!
B79: Bank fees | C79: $
E80: =SUM(E76:E76) -> #REF! | F80: =SUM(F76:F76) -> #REF! | G80: =SUM(G76:G76) -> #REF! | H80: =SUM(H76:H76) -> #REF! | I80: =SUM(I76:I76) -> #REF! | J80: =SUM(J76:J76) -> #REF! | K80: =SUM(K76:K76) -> #REF! | L80: =SUM(L76:L76) -> #REF! | ... P80: =SUM(P76:P76) -> #REF! | R80: =SUM(R76:R76) -> #REF! | S80: eur | V80: =V76*0.92 -> #REF! | W80: =21793918.379759*0.92*0.9 -> 18045364 | X80: =V80-W80 -> #REF! | Y80: Q4 >Q1 | AB80: =SUM(AB76:AB76) -> #REF! | AC80: =SUM(AC76:AC76) -> #REF! | AD80: =SUM(AD76:AD76) -> #REF! | AE80: =SUM(AE76:AE76) -> #REF! | AF80: =SUM(AF76:AF76) -> #REF! | AG80: =SUM(AG76:AG76) -> #REF! | AH80: =SUM(AH76:AH76) -> #REF! | AI80: =SUM(AI76:AI76) -> #REF! | ... AM80: =SUM(AM76:AM76) -> #REF! | AO80: =SUM(AO76:AO76) -> #REF!
B82: Abivax SA- Balance
B84: Balance SA-USD - begining of month | C84: $ | E84: 13830882 | F84: =E85 -> #REF! | G84: =F85 -> #REF! | H84: =G85 -> #REF! | I84: =H85 -> #REF! | J84: =I85 -> #REF! | K84: =J85 -> #REF! | L84: =K85 -> #REF! | M84: =L85 -> #REF! | ... P84: =O85 -> #REF! | AB84: 13830882 | AC84: =AB85 -> #REF! | AD84: =AC85 -> #REF! | AE84: =AD85 -> #REF! | AF84: =AE85 -> #REF! | AG84: =AF85 -> #REF! | AH84: =AG85 -> #REF! | AI84: =AH85 -> #REF! | AJ84: =AI85 -> #REF! | ... AM84: =AL85 -> #REF!
B85: Balance SA-USD - end of month | C85: $ | E85: =E84-E80 -> #REF! | F85: =F84-F80 -> #REF! | G85: =G84-G80 -> #REF! | H85: =H84-H80 -> #REF! | I85: =I84-I80 -> #REF! | J85: =J84-J80 -> #REF! | K85: =K84-K80 -> #REF! | L85: =L84-L80 -> #REF! | ... P85: =P84-P80 -> #REF! | AB85: =AB84-AB80 -> #REF! | AC85: =AC84-AC80 -> #REF! | AD85: =AD84-AD80 -> #REF! | AE85: =AE84-AE80 -> #REF! | AF85: =AF84-AF80 -> #REF! | AG85: =AG84-AG80 -> #REF! | AH85: =AH84-AH80 -> #REF! | AI85: =AI84-AI80 -> #REF! | ... AM85: =AM84-AM80 -> #REF!
B87: EUR-USD m-1 | C87: $ | E87: 1.0389 | F87: =1/0.92 -> 1.0869565 | G87: =1/0.92 -> 1.0869565 | H87: =1/0.92 -> 1.0869565 | I87: =1/0.92 -> 1.0869565 | J87: =1/0.92 -> 1.0869565 | K87: =1/0.92 -> 1.0869565 | L87: =1/0.92 -> 1.0869565 | M87: =1/0.92 -> 1.0869565 | ... P87: =1/0.92 -> 1.0869565 | AB87: 1.0389 | AC87: =1/0.92 -> 1.0869565 | AD87: =1/0.92 -> 1.0869565 | AE87: =1/0.92 -> 1.0869565 | AF87: =1/0.92 -> 1.0869565 | AG87: =1/0.92 -> 1.0869565 | AH87: =1/0.92 -> 1.0869565 | AI87: =1/0.92 -> 1.0869565 | AJ87: =1/0.92 -> 1.0869565 | ... AM87: =1/0.92 -> 1.0869565
B88: EUR-USD m | C88: $ | E88: =1/0.92 -> 1.0869565 | F88: =1/0.92 -> 1.0869565 | G88: =1/0.92 -> 1.0869565 | H88: =1/0.92 -> 1.0869565 | I88: =1/0.92 -> 1.0869565 | J88: =1/0.92 -> 1.0869565 | K88: =1/0.92 -> 1.0869565 | L88: =1/0.92 -> 1.0869565 | ... P88: =1/0.92 -> 1.0869565 | AB88: =1/0.92 -> 1.0869565 | AC88: =1/0.92 -> 1.0869565 | AD88: =1/0.92 -> 1.0869565 | AE88: =1/0.92 -> 1.0869565 | AF88: =1/0.92 -> 1.0869565 | AG88: =1/0.92 -> 1.0869565 | AH88: =1/0.92 -> 1.0869565 | AI88: =1/0.92 -> 1.0869565 | ... AM88: =1/0.92 -> 1.0869565
B90: Balance SA-USD - begining of month | C90: € | E90: =E84/E87 -> 13313006 | F90: =F84/F87 -> #REF! | G90: =G84/G87 -> #REF! | H90: =H84/H87 -> #REF! | I90: =I84/I87 -> #REF! | J90: =J84/J87 -> #REF! | K90: =K84/K87 -> #REF! | L90: =L84/L87 -> #REF! | ... P90: =P84/P87 -> #REF! | AB90: =AB84/AB87 -> 13313006 | AC90: =AC84/AC87 -> #REF! | AD90: =AD84/AD87 -> #REF! | AE90: =AE84/AE87 -> #REF! | AF90: =AF84/AF87 -> #REF! | AG90: =AG84/AG87 -> #REF! | AH90: =AH84/AH87 -> #REF! | AI90: =AI84/AI87 -> #REF! | ... AM90: =AM84/AM87 -> #REF!
B91: Balance SA-USD - end of month | C91: € | E91: =E85/E88 -> #REF! | F91: =F85/F88 -> #REF! | G91: =G85/G88 -> #REF! | H91: =H85/H88 -> #REF! | I91: =I85/I88 -> #REF! | J91: =J85/J88 -> #REF! | K91: =K85/K88 -> #REF! | L91: =L85/L88 -> #REF! | ... P91: =P85/P88 -> #REF! | AB91: =AB85/AB88 -> #REF! | AC91: =AC85/AC88 -> #REF! | AD91: =AD85/AD88 -> #REF! | AE91: =AE85/AE88 -> #REF! | AF91: =AF85/AF88 -> #REF! | AG91: =AG85/AG88 -> #REF! | AH91: =AH85/AH88 -> #REF! | AI91: =AI85/AI88 -> #REF! | ... AM91: =AM85/AM88 -> #REF!
B93: Balance SA-USD - begining of month | C93: € | E93: =E84/E88 -> 12724411 | AB93: =AB84/AB88 -> 12724411
B94: avec taux budget ---> perte : | E94: =E93-E90 -> -588594.62 | AB94: =AB93-AB90 -> -588594.62
S97: Vérification par rapport à la version Budget/Board (Abivax Fianncials)
B98: Abivax SA EUR + USD
V99: Total
B100: Balance SA-USD - begining of month | C100: € | E100: =E90+E69 -> 1.3188423e+08 | F100: =F90+F69 -> #REF! | G100: =G90+G69 -> #REF! | H100: =H90+H69 -> #REF! | I100: =I90+I69 -> #REF! | J100: =J90+J69 -> #REF! | K100: =K90+K69 -> #REF! | L100: =L90+L69 -> #REF! | ... P100: =P90+P69 -> #REF! | V100: Cash | W100: Cas Vboard | X100: Diff | AB100: =AB90+AB69 -> 1.2781773e+08 | AC100: =AC90+AC69 -> #REF! | AD100: =AD90+AD69 -> #REF! | AE100: =AE90+AE69 -> #REF! | AF100: =AF90+AF69 -> #REF! | AG100: =AG90+AG69 -> #REF! | AH100: =AH90+AH69 -> #REF! | AI100: =AI90+AI69 -> #REF! | ... AM100: =AM90+AM69 -> #REF!
A101: ICI | B101: Balance SA-USD - end of month | C101: € | E101: =E91+E70 -> #REF! | F101: =F91+F70 -> #REF! | G101: =G91+G70 -> #REF! | H101: =H91+H70 -> #REF! | I101: =I91+I70 -> #REF! | J101: =J91+J70 -> #REF! | K101: =K91+K70 -> #REF! | L101: =L91+L70 -> #REF! | ... P101: =P91+P70 -> #REF! | V101: =V27+V36+V45+V58+V60+V80+V14 -> #REF! | W101: =W27+W36+W45+W58+W60+W80+W14 -> 1.6810742e+08 | X101: =X27+X36+X45+X58+X60+X80+X14+X38 -> #REF! | AB101: =AB91+AB70 -> #REF! | AC101: =AC91+AC70 -> #REF! | AD101: =AD91+AD70 -> #REF! | AE101: =AE91+AE70 -> #REF! | AF101: =AF91+AF70 -> #REF! | AG101: =AG91+AG70 -> #REF! | AH101: =AH91+AH70 -> #REF! | AI101: =AI91+AI70 -> #REF! | ... AM101: =AM91+AM70 -> #REF!
X102: =V101-W101 -> #REF!
V104: Total Budget en euros
S105: SA EUR | V105: =R22+R27+R36+R40+R45 -> #REF! | W105: =W14+W27+W36+W45 -> 1.2488537e+08 | X105: =V105-W105 -> #REF!
S106: SA USD | V106: =V80 -> #REF! | W106: =W80 -> 18045364 | X106: =V106-W106 -> #REF!
X107: =X105+X106 -> #REF! | Y107: OK
V108: Total Budget en euros
S109: LLC | V109: =(#REF!+#REF!+#REF!)*0.92 -> #REF! | W109: =(#REF!+#REF!+#REF!)*0.92 -> #REF! | X109: =V109-W109 -> #REF!
S110: SA + LLC | V110: =V109+V106+V105 -> #REF! | W110: =W109+W106+W105 -> #REF! | X110: =X107+X109 -> #REF!
R113: Vérification par rapport à la version Budget du Board janvier | AO113: Vérification par rapport à la version Budget du Board janvier
B114: Total eq-Budget SA | C114: € | E114: =E22+E27+E36+E40+E45+E80/E88 -> #REF! | F114: =F22+F27+F36+F40+F45+F80/F88 -> #REF! | G114: =G22+G27+G36+G40+G45+G80/G88 -> #REF! | H114: =H22+H27+H36+H40+H45+H80/H88 -> #REF! | I114: =I22+I27+I36+I40+I45+I80/I88 -> #REF! | J114: =J22+J27+J36+J40+J45+J80/J88 -> #REF! | K114: =K22+K27+K36+K40+K45+K80/K88 -> #REF! | L114: =L22+L27+L36+L40+L45+L80/L88 -> #REF! | ... P114: =P22+P27+P36+P40+P45+P80/P88 -> #REF! | R114: =SUM(E114:P114) -> #REF! | AB114: =AB22+AB27+AB36+AB40+AB45+AB80/AB88 -> #REF! | AC114: =AC22+AC27+AC36+AC40+AC45+AC80/AC88 -> #REF! | AD114: =AD22+AD27+AD36+AD40+AD45+AD80/AD88 -> #REF! | AE114: =AE22+AE27+AE36+AE40+AE45+AE80/AE88 -> #REF! | AF114: =AF22+AF27+AF36+AF40+AF45+AF80/AF88 -> #REF! | AG114: =AG22+AG27+AG36+AG40+AG45+AG80/AG88 -> #REF! | AH114: =AH22+AH27+AH36+AH40+AH45+AH80/AH88 -> #REF! | AI114: =AI22+AI27+AI36+AI40+AI45+AI80/AI88 -> #REF! | ... AM114: =AM22+AM27+AM36+AM40+AM45+AM80/AM88 -> #REF! | AO114: =SUM(AB114:AM114) -> #REF!
B115: Total eq-Budget LLC | C115: € | E115: =#REF!*0.92 -> #REF! | F115: =#REF!*0.92 -> #REF! | G115: =#REF!*0.92 -> #REF! | H115: =#REF!*0.92 -> #REF! | I115: =#REF!*0.92 -> #REF! | J115: =#REF!*0.92 -> #REF! | K115: =#REF!*0.92 -> #REF! | L115: =#REF!*0.92 -> #REF! | ... P115: =#REF!*0.92 -> #REF! | R115: =#REF!*0.92 -> #REF! | S115: budget | V115: différence | AB115: =#REF!*0.92 -> #REF! | AC115: =#REF!*0.92 -> #REF! | AD115: =#REF!*0.92 -> #REF! | AE115: =#REF!*0.92 -> #REF! | AF115: =#REF!*0.92 -> #REF! | AG115: =#REF!*0.92 -> #REF! | AH115: =#REF!*0.92 -> #REF! | AI115: =#REF!*0.92 -> #REF! | ... AM115: =#REF!*0.92 -> #REF! | AO115: =#REF!*0.92 -> #REF!
R116: =R115+R114 -> #REF! | S116: =155.203431765471*10^6 -> 1.5520343e+08 | V116: =R116-S116 -> #REF! | AO116: =AO115+AO114 -> #REF!
